Workbook

Sheet 前提
A1: SuguDesk 事業計画 前提条件
A3: 【価格前提】
A4: SuguDesk ARPA（月額） | B4: 11500 | C4: チャットボット基本（ライトとスタンダードの平均）
A5: SuguDesk 導入費（初期） | B5: 225000 | C5: 1院あたり（ライトとスタンダードの平均）
A6: BPO事務長代行 ARPA（月額） | B6: 150000 | C6: 算定業務＋事務長代行
A7: BPO採用/集患 ARPA（月額） | B7: 50000 | C7: BPO#2。M13以降
A8: SuguDeskチャーン率（月次） | B8: 0.02
A9: BPOチャーン率（月次） | B9: 0.01 | C9: 粘着性高い
A10: BPOアップセル率（月次） | B10: 0.05 | C10: SuguDesk→BPO転換率。M7以降
A12: 【営業前提：月間新規SuguDesk契約数】
A13: Phase1（M1-M6） | B13: 2 | C13: 直販
A14: Phase2（M7-M12） | B14: 5 | C14: v2リリース後 ギミックとの提携加速
A15: Phase3（M13-M18） | B15: 5
A16: Phase4（M19-M24） | B16: 6 | C16: Series A前
A17: Phase5（M25-M36） | B17: 8 | C17: Series A後
A18: Phase6（M37-M48） | B18: 10 | C18: スケール期
A19: Phase7（M49-M60） | B19: 12 | C19: 成熟期
A21: 【コスト前提：人件費（月額）】
A22: CEO報酬 | B22: 300000
A23: エンジニア時給 | B23: 5000 | C23: 業務委託
A24: エンジニア月間稼働h（Phase1） | B24: 64.5 | C24: 3h/日×5日×4.3週
A25: エンジニア月間稼働h（Phase2+） | B25: 40 | C25: メンテナンスモード
A26: エンジニア正社員 単価/人（月額） | B26: 700000
A27: BPO事務長 単価/人（月額） | B27: 400000
A28: BPOオペ 単価/人（月額） | B28: 200000
A29: 営業サポート 単価/人（月額） | B29: 200000 | C29: 業務委託
A30: CS 単価/人（月額） | B30: 350000 | C30: 業務委託
A31: 営業/GTM費（月額基準） | B31: 100000
A32: その他固定費 | B32: 200000 | C32: 法務・会計・雑費
A34: 【コスト前提：インフラ（実績ベース）】
A35: LLM API変動費/院（月額） | B35: 12 | C35: Vertex AI Gemini Flash実績
A36: Cloud SQL 基本料金（月額） | B36: 8000 | C36: 〜50院
A37: Cloud SQL 拡張料金（月額） | B37: 15000 | C37: 50〜200院
A38: Cloud SQL 大規模料金（月額） | B38: 25000 | C38: 200院超
A39: Cloud Run 基本料金（月額） | B39: 2000 | C39: 〜50院
A40: Cloud Run 拡張料金（月額） | B40: 5000 | C40: 50〜200院
A41: Cloud Run 大規模料金（月額） | B41: 15000 | C41: 200院超
A43: 【人員スケーリング前提】
A44: CS 1人あたり担当SuguDesk院数上限 | B44: 30
A46: 【エンジニア人員計画（人数）】 | B46: エンジニア
A47: Phase1（M1-M6） | C47: 直接入力
A48: Phase2（M7-M12） | C48: 直接入力
A49: Phase3（M13-M18） | B49: 1
A50: Phase4（M19-M24） | B50: 1
A51: Phase5（M25-M36） | B51: 2
A52: Phase6（M37-M48） | B52: 2
A53: Phase7（M49-M60） | B53: 2
A55: 【BPO人員計画（人数）】 | B55: 事務長 | C55: オペレーター
A56: Phase1（M1-M6） | B56: 0 | C56: 0
A57: Phase2（M7-M12） | B57: 1 | C57: 2
A58: Phase3（M13-M18） | B58: 2 | C58: 4
A59: Phase4（M19-M24） | B59: 3 | C59: 5
A60: Phase5（M25-M36） | B60: 4 | C60: 7
A61: Phase6（M37-M48） | B61: 5 | C61: 9
A62: Phase7（M49-M60） | B62: 6 | C62: 10
A64: 【営業サポート人員計画（人数）】
A65: Phase1（M1-M6） | B65: 1
A66: Phase2（M7-M12） | B66: 1
A67: Phase3（M13-M18） | B67: 1
A68: Phase4（M19-M24） | B68: 1
A69: Phase5（M25-M36） | B69: 2
A70: Phase6（M37-M48） | B70: 2
A71: Phase7（M49-M60） | B71: 3
A73: 【資本政策前提】
A74: 設立時株数 | B74: 1000000
A75: 設立時資本金 | B75: 1000000 | C75: 1株1円
A76: シードプレバリュー | B76: 170000000 | C76: 1.7億
A77: VC出資額（Oikaze） | B77: 30000000
A78: 佐藤さん出資額 | B78: 2000000
A79: 洋介さん出資額 | B79: 500000
A80: デッド | B80: 5000000
A81: 公庫金利（年率） | B81: 0.015
A82: 公庫据置期間（月） | B82: 24
A83: 公庫返済期間（月） | B83: 60
A84: Series Aプレバリュー | B84: 500000000
A85: Series A調達額 | B85: 100000000
A86: SOPプール比率 | B86: 0.067
A87: Series A調達月 | B87: 24

Sheet 月次事業計画
A1: 月次事業計画（5年）
A2: フェーズ | B2: =IF(1<=6,"P1",IF(1<=12,"P2",IF(1<=18,"P3",IF(1<=24,"P4",IF(1<=36,"P5",IF(1<=48,"P6","P7")))))) -> P1 | C2: =IF(2<=6,"P1",IF(2<=12,"P2",IF(2<=18,"P3",IF(2<=24,"P4",IF(2<=36,"P5",IF(2<=48,"P6","P7")))))) -> P1 | D2: =IF(3<=6,"P1",IF(3<=12,"P2",IF(3<=18,"P3",IF(3<=24,"P4",IF(3<=36,"P5",IF(3<=48,"P6","P7")))))) -> P1 | E2: =IF(4<=6,"P1",IF(4<=12,"P2",IF(4<=18,"P3",IF(4<=24,"P4",IF(4<=36,"P5",IF(4<=48,"P6","P7")))))) -> P1 | F2: =IF(5<=6,"P1",IF(5<=12,"P2",IF(5<=18,"P3",IF(5<=24,"P4",IF(5<=36,"P5",IF(5<=48,"P6","P7")))))) -> P1 | G2: =IF(6<=6,"P1",IF(6<=12,"P2",IF(6<=18,"P3",IF(6<=24,"P4",IF(6<=36,"P5",IF(6<=48,"P6","P7")))))) -> P1 | H2: =IF(7<=6,"P1",IF(7<=12,"P2",IF(7<=18,"P3",IF(7<=24,"P4",IF(7<=36,"P5",IF(7<=48,"P6","P7")))))) -> P2 | I2: =IF(8<=6,"P1",IF(8<=12,"P2",IF(8<=18,"P3",IF(8<=24,"P4",IF(8<=36,"P5",IF(8<=48,"P6","P7")))))) -> P2 | J2: =IF(9<=6,"P1",IF(9<=12,"P2",IF(9<=18,"P3",IF(9<=24,"P4",IF(9<=36,"P5",IF(9<=48,"P6","P7")))))) -> P2 | K2: =IF(10<=6,"P1",IF(10<=12,"P2",IF(10<=18,"P3",IF(10<=24,"P4",IF(10<=36,"P5",IF(10<=48,"P6","P7")))))) -> P2 | L2: =IF(11<=6,"P1",IF(11<=12,"P2",IF(11<=18,"P3",IF(11<=24,"P4",IF(11<=36,"P5",IF(11<=48,"P6","P7")))))) -> P2 | M2: =IF(12<=6,"P1",IF(12<=12,"P2",IF(12<=18,"P3",IF(12<=24,"P4",IF(12<=36,"P5",IF(12<=48,"P6","P7")))))) -> P2 | N2: =IF(13<=6,"P1",IF(13<=12,"P2",IF(13<=18,"P3",IF(13<=24,"P4",IF(13<=36,"P5",IF(13<=48,"P6","P7")))))) -> P3 | O2: =IF(14<=6,"P1",IF(14<=12,"P2",IF(14<=18,"P3",IF(14<=24,"P4",IF(14<=36,"P5",IF(14<=48,"P6","P7")))))) -> P3 | P2: =IF(15<=6,"P1",IF(15<=12,"P2",IF(15<=18,"P3",IF(15<=24,"P4",IF(15<=36,"P5",IF(15<=48,"P6","P7")))))) -> P3 | Q2: =IF(16<=6,"P1",IF(16<=12,"P2",IF(16<=18,"P3",IF(16<=24,"P4",IF(16<=36,"P5",IF(16<=48,"P6","P7")))))) -> P3 | R2: =IF(17<=6,"P1",IF(17<=12,"P2",IF(17<=18,"P3",IF(17<=24,"P4",IF(17<=36,"P5",IF(17<=48,"P6","P7")))))) -> P3 | S2: =IF(18<=6,"P1",IF(18<=12,"P2",IF(18<=18,"P3",IF(18<=24,"P4",IF(18<=36,"P5",IF(18<=48,"P6","P7")))))) -> P3 | T2: =IF(19<=6,"P1",IF(19<=12,"P2",IF(19<=18,"P3",IF(19<=24,"P4",IF(19<=36,"P5",IF(19<=48,"P6","P7")))))) -> P4 | U2: =IF(20<=6,"P1",IF(20<=12,"P2",IF(20<=18,"P3",IF(20<=24,"P4",IF(20<=36,"P5",IF(20<=48,"P6","P7")))))) -> P4 | V2: =IF(21<=6,"P1",IF(21<=12,"P2",IF(21<=18,"P3",IF(21<=24,"P4",IF(21<=36,"P5",IF(21<=48,"P6","P7")))))) -> P4 | W2: =IF(22<=6,"P1",IF(22<=12,"P2",IF(22<=18,"P3",IF(22<=24,"P4",IF(22<=36,"P5",IF(22<=48,"P6","P7")))))) -> P4 | X2: =IF(23<=6,"P1",IF(23<=12,"P2",IF(23<=18,"P3",IF(23<=24,"P4",IF(23<=36,"P5",IF(23<=48,"P6","P7")))))) -> P4 | Y2: =IF(24<=6,"P1",IF(24<=12,"P2",IF(24<=18,"P3",IF(24<=24,"P4",IF(24<=36,"P5",IF(24<=48,"P6","P7")))))) -> P4 | Z2: =IF(25<=6,"P1",IF(25<=12,"P2",IF(25<=18,"P3",IF(25<=24,"P4",IF(25<=36,"P5",IF(25<=48,"P6","P7")))))) -> P5 | AA2: =IF(26<=6,"P1",IF(26<=12,"P2",IF(26<=18,"P3",IF(26<=24,"P4",IF(26<=36,"P5",IF(26<=48,"P6","P7")))))) -> P5 | AB2: =IF(27<=6,"P1",IF(27<=12,"P2",IF(27<=18,"P3",IF(27<=24,"P4",IF(27<=36,"P5",IF(27<=48,"P6","P7")))))) -> P5 | AC2: =IF(28<=6,"P1",IF(28<=12,"P2",IF(28<=18,"P3",IF(28<=24,"P4",IF(28<=36,"P5",IF(28<=48,"P6","P7")))))) -> P5 | AD2: =IF(29<=6,"P1",IF(29<=12,"P2",IF(29<=18,"P3",IF(29<=24,"P4",IF(29<=36,"P5",IF(29<=48,"P6","P7")))))) -> P5 | AE2: =IF(30<=6,"P1",IF(30<=12,"P2",IF(30<=18,"P3",IF(30<=24,"P4",IF(30<=36,"P5",IF(30<=48,"P6","P7")))))) -> P5 | AF2: =IF(31<=6,"P1",IF(31<=12,"P2",IF(31<=18,"P3",IF(31<=24,"P4",IF(31<=36,"P5",IF(31<=48,"P6","P7")))))) -> P5 | AG2: =IF(32<=6,"P1",IF(32<=12,"P2",IF(32<=18,"P3",IF(32<=24,"P4",IF(32<=36,"P5",IF(32<=48,"P6","P7")))))) -> P5 | AH2: =IF(33<=6,"P1",IF(33<=12,"P2",IF(33<=18,"P3",IF(33<=24,"P4",IF(33<=36,"P5",IF(33<=48,"P6","P7")))))) -> P5 | AI2: =IF(34<=6,"P1",IF(34<=12,"P2",IF(34<=18,"P3",IF(34<=24,"P4",IF(34<=36,"P5",IF(34<=48,"P6","P7")))))) -> P5 | AJ2: =IF(35<=6,"P1",IF(35<=12,"P2",IF(35<=18,"P3",IF(35<=24,"P4",IF(35<=36,"P5",IF(35<=48,"P6","P7")))))) -> P5 | AK2: =IF(36<=6,"P1",IF(36<=12,"P2",IF(36<=18,"P3",IF(36<=24,"P4",IF(36<=36,"P5",IF(36<=48,"P6","P7")))))) -> P5 | AL2: =IF(37<=6,"P1",IF(37<=12,"P2",IF(37<=18,"P3",IF(37<=24,"P4",IF(37<=36,"P5",IF(37<=48,"P6","P7")))))) -> P6 | AM2: =IF(38<=6,"P1",IF(38<=12,"P2",IF(38<=18,"P3",IF(38<=24,"P4",IF(38<=36,"P5",IF(38<=48,"P6","P7")))))) -> P6 | AN2: =IF(39<=6,"P1",IF(39<=12,"P2",IF(39<=18,"P3",IF(39<=24,"P4",IF(39<=36,"P5",IF(39<=48,"P6","P7")))))) -> P6 | AO2: =IF(40<=6,"P1",IF(40<=12,"P2",IF(40<=18,"P3",IF(40<=24,"P4",IF(40<=36,"P5",IF(40<=48,"P6","P7")))))) -> P6 | AP2: =IF(41<=6,"P1",IF(41<=12,"P2",IF(41<=18,"P3",IF(41<=24,"P4",IF(41<=36,"P5",IF(41<=48,"P6","P7")))))) -> P6 | AQ2: =IF(42<=6,"P1",IF(42<=12,"P2",IF(42<=18,"P3",IF(42<=24,"P4",IF(42<=36,"P5",IF(42<=48,"P6","P7")))))) -> P6 | AR2: =IF(43<=6,"P1",IF(43<=12,"P2",IF(43<=18,"P3",IF(43<=24,"P4",IF(43<=36,"P5",IF(43<=48,"P6","P7")))))) -> P6 | AS2: =IF(44<=6,"P1",IF(44<=12,"P2",IF(44<=18,"P3",IF(44<=24,"P4",IF(44<=36,"P5",IF(44<=48,"P6","P7")))))) -> P6 | AT2: =IF(45<=6,"P1",IF(45<=12,"P2",IF(45<=18,"P3",IF(45<=24,"P4",IF(45<=36,"P5",IF(45<=48,"P6","P7")))))) -> P6 | AU2: =IF(46<=6,"P1",IF(46<=12,"P2",IF(46<=18,"P3",IF(46<=24,"P4",IF(46<=36,"P5",IF(46<=48,"P6","P7")))))) -> P6 | AV2: =IF(47<=6,"P1",IF(47<=12,"P2",IF(47<=18,"P3",IF(47<=24,"P4",IF(47<=36,"P5",IF(47<=48,"P6","P7")))))) -> P6 | AW2: =IF(48<=6,"P1",IF(48<=12,"P2",IF(48<=18,"P3",IF(48<=24,"P4",IF(48<=36,"P5",IF(48<=48,"P6","P7")))))) -> P6 | AX2: =IF(49<=6,"P1",IF(49<=12,"P2",IF(49<=18,"P3",IF(49<=24,"P4",IF(49<=36,"P5",IF(49<=48,"P6","P7")))))) -> P7 | AY2: =IF(50<=6,"P1",IF(50<=12,"P2",IF(50<=18,"P3",IF(50<=24,"P4",IF(50<=36,"P5",IF(50<=48,"P6","P7")))))) -> P7 | AZ2: =IF(51<=6,"P1",IF(51<=12,"P2",IF(51<=18,"P3",IF(51<=24,"P4",IF(51<=36,"P5",IF(51<=48,"P6","P7")))))) -> P7 | BA2: =IF(52<=6,"P1",IF(52<=12,"P2",IF(52<=18,"P3",IF(52<=24,"P4",IF(52<=36,"P5",IF(52<=48,"P6","P7")))))) -> P7 | BB2: =IF(53<=6,"P1",IF(53<=12,"P2",IF(53<=18,"P3",IF(53<=24,"P4",IF(53<=36,"P5",IF(53<=48,"P6","P7")))))) -> P7 | BC2: =IF(54<=6,"P1",IF(54<=12,"P2",IF(54<=18,"P3",IF(54<=24,"P4",IF(54<=36,"P5",IF(54<=48,"P6","P7")))))) -> P7 | BD2: =IF(55<=6,"P1",IF(55<=12,"P2",IF(55<=18,"P3",IF(55<=24,"P4",IF(55<=36,"P5",IF(55<=48,"P6","P7")))))) -> P7 | BE2: =IF(56<=6,"P1",IF(56<=12,"P2",IF(56<=18,"P3",IF(56<=24,"P4",IF(56<=36,"P5",IF(56<=48,"P6","P7")))))) -> P7 | BF2: =IF(57<=6,"P1",IF(57<=12,"P2",IF(57<=18,"P3",IF(57<=24,"P4",IF(57<=36,"P5",IF(57<=48,"P6","P7")))))) -> P7 | BG2: =IF(58<=6,"P1",IF(58<=12,"P2",IF(58<=18,"P3",IF(58<=24,"P4",IF(58<=36,"P5",IF(58<=48,"P6","P7")))))) -> P7 | BH2: =IF(59<=6,"P1",IF(59<=12,"P2",IF(59<=18,"P3",IF(59<=24,"P4",IF(59<=36,"P5",IF(59<=48,"P6","P7")))))) -> P7 | BI2: =IF(60<=6,"P1",IF(60<=12,"P2",IF(60<=18,"P3",IF(60<=24,"P4",IF(60<=36,"P5",IF(60<=48,"P6","P7")))))) -> P7
A3: 月 | B3: M1 | C3: M2 | D3: M3 | E3: M4 | F3: M5 | G3: M6 | H3: M7 | I3: M8 | J3: M9 | K3: M10 | L3: M11 | M3: M12 | N3: M13 | O3: M14 | P3: M15 | Q3: M16 | R3: M17 | S3: M18 | T3: M19 | U3: M20 | V3: M21 | W3: M22 | X3: M23 | Y3: M24 | Z3: M25 | AA3: M26 | AB3: M27 | AC3: M28 | AD3: M29 | AE3: M30 | AF3: M31 | AG3: M32 | AH3: M33 | AI3: M34 | AJ3: M35 | AK3: M36 | AL3: M37 | AM3: M38 | AN3: M39 | AO3: M40 | AP3: M41 | AQ3: M42 | AR3: M43 | AS3: M44 | AT3: M45 | AU3: M46 | AV3: M47 | AW3: M48 | AX3: M49 | AY3: M50 | AZ3: M51 | BA3: M52 | BB3: M53 | BC3: M54 | BD3: M55 | BE3: M56 | BF3: M57 | BG3: M58 | BH3: M59 | BI3: M60
A4: 【営業活動】
A5: 月間新規SuguDesk契約数 | B5: 0 | C5: =IF(2<=6,'前提'!$B$13,IF(2<=12,'前提'!$B$14,IF(2<=18,'前提'!$B$15,IF(2<=24,'前提'!$B$16,IF(2<=36,'前提'!$B$17,IF(2<=48,'前提'!$B$18,'前提'!$B$19)))))) -> 2 | D5: =IF(3<=6,'前提'!$B$13,IF(3<=12,'前提'!$B$14,IF(3<=18,'前提'!$B$15,IF(3<=24,'前提'!$B$16,IF(3<=36,'前提'!$B$17,IF(3<=48,'前提'!$B$18,'前提'!$B$19)))))) -> 2 | E5: =IF(4<=6,'前提'!$B$13,IF(4<=12,'前提'!$B$14,IF(4<=18,'前提'!$B$15,IF(4<=24,'前提'!$B$16,IF(4<=36,'前提'!$B$17,IF(4<=48,'前提'!$B$18,'前提'!$B$19)))))) -> 2 | F5: =IF(5<=6,'前提'!$B$13,IF(5<=12,'前提'!$B$14,IF(5<=18,'前提'!$B$15,IF(5<=24,'前提'!$B$16,IF(5<=36,'前提'!$B$17,IF(5<=48,'前提'!$B$18,'前提'!$B$19)))))) -> 2 | G5: =IF(6<=6,'前提'!$B$13,IF(6<=12,'前提'!$B$14,IF(6<=18,'前提'!$B$15,IF(6<=24,'前提'!$B$16,IF(6<=36,'前提'!$B$17,IF(6<=48,'前提'!$B$18,'前提'!$B$19)))))) -> 2 | H5: =IF(7<=6,'前提'!$B$13,IF(7<=12,'前提'!$B$14,IF(7<=18,'前提'!$B$15,IF(7<=24,'前提'!$B$16,IF(7<=36,'前提'!$B$17,IF(7<=48,'前提'!$B$18,'前提'!$B$19)))))) -> 5 | I5: =IF(8<=6,'前提'!$B$13,IF(8<=12,'前提'!$B$14,IF(8<=18,'前提'!$B$15,IF(8<=24,'前提'!$B$16,IF(8<=36,'前提'!$B$17,IF(8<=48,'前提'!$B$18,'前提'!$B$19)))))) -> 5 | J5: =IF(9<=6,'前提'!$B$13,IF(9<=12,'前提'!$B$14,IF(9<=18,'前提'!$B$15,IF(9<=24,'前提'!$B$16,IF(9<=36,'前提'!$B$17,IF(9<=48,'前提'!$B$18,'前提'!$B$19)))))) -> 5 | K5: =IF(10<=6,'前提'!$B$13,IF(10<=12,'前提'!$B$14,IF(10<=18,'前提'!$B$15,IF(10<=24,'前提'!$B$16,IF(10<=36,'前提'!$B$17,IF(10<=48,'前提'!$B$18,'前提'!$B$19)))))) -> 5 | L5: =IF(11<=6,'前提'!$B$13,IF(11<=12,'前提'!$B$14,IF(11<=18,'前提'!$B$15,IF(11<=24,'前提'!$B$16,IF(11<=36,'前提'!$B$17,IF(11<=48,'前提'!$B$18,'前提'!$B$19)))))) -> 5 | M5: =IF(12<=6,'前提'!$B$13,IF(12<=12,'前提'!$B$14,IF(12<=18,'前提'!$B$15,IF(12<=24,'前提'!$B$16,IF(12<=36,'前提'!$B$17,IF(12<=48,'前提'!$B$18,'前提'!$B$19)))))) -> 5 | N5: =IF(13<=6,'前提'!$B$13,IF(13<=12,'前提'!$B$14,IF(13<=18,'前提'!$B$15,IF(13<=24,'前提'!$B$16,IF(13<=36,'前提'!$B$17,IF(13<=48,'前提'!$B$18,'前提'!$B$19)))))) -> 5 | O5: =IF(14<=6,'前提'!$B$13,IF(14<=12,'前提'!$B$14,IF(14<=18,'前提'!$B$15,IF(14<=24,'前提'!$B$16,IF(14<=36,'前提'!$B$17,IF(14<=48,'前提'!$B$18,'前提'!$B$19)))))) -> 5 | P5: =IF(15<=6,'前提'!$B$13,IF(15<=12,'前提'!$B$14,IF(15<=18,'前提'!$B$15,IF(15<=24,'前提'!$B$16,IF(15<=36,'前提'!$B$17,IF(15<=48,'前提'!$B$18,'前提'!$B$19)))))) -> 5 | Q5: =IF(16<=6,'前提'!$B$13,IF(16<=12,'前提'!$B$14,IF(16<=18,'前提'!$B$15,IF(16<=24,'前提'!$B$16,IF(16<=36,'前提'!$B$17,IF(16<=48,'前提'!$B$18,'前提'!$B$19)))))) -> 5 | R5: =IF(17<=6,'前提'!$B$13,IF(17<=12,'前提'!$B$14,IF(17<=18,'前提'!$B$15,IF(17<=24,'前提'!$B$16,IF(17<=36,'前提'!$B$17,IF(17<=48,'前提'!$B$18,'前提'!$B$19)))))) -> 5 | S5: =IF(18<=6,'前提'!$B$13,IF(18<=12,'前提'!$B$14,IF(18<=18,'前提'!$B$15,IF(18<=24,'前提'!$B$16,IF(18<=36,'前提'!$B$17,IF(18<=48,'前提'!$B$18,'前提'!$B$19)))))) -> 5 | T5: =IF(19<=6,'前提'!$B$13,IF(19<=12,'前提'!$B$14,IF(19<=18,'前提'!$B$15,IF(19<=24,'前提'!$B$16,IF(19<=36,'前提'!$B$17,IF(19<=48,'前提'!$B$18,'前提'!$B$19)))))) -> 6 | U5: =IF(20<=6,'前提'!$B$13,IF(20<=12,'前提'!$B$14,IF(20<=18,'前提'!$B$15,IF(20<=24,'前提'!$B$16,IF(20<=36,'前提'!$B$17,IF(20<=48,'前提'!$B$18,'前提'!$B$19)))))) -> 6 | V5: =IF(21<=6,'前提'!$B$13,IF(21<=12,'前提'!$B$14,IF(21<=18,'前提'!$B$15,IF(21<=24,'前提'!$B$16,IF(21<=36,'前提'!$B$17,IF(21<=48,'前提'!$B$18,'前提'!$B$19)))))) -> 6 | W5: =IF(22<=6,'前提'!$B$13,IF(22<=12,'前提'!$B$14,IF(22<=18,'前提'!$B$15,IF(22<=24,'前提'!$B$16,IF(22<=36,'前提'!$B$17,IF(22<=48,'前提'!$B$18,'前提'!$B$19)))))) -> 6 | X5: =IF(23<=6,'前提'!$B$13,IF(23<=12,'前提'!$B$14,IF(23<=18,'前提'!$B$15,IF(23<=24,'前提'!$B$16,IF(23<=36,'前提'!$B$17,IF(23<=48,'前提'!$B$18,'前提'!$B$19)))))) -> 6 | Y5: =IF(24<=6,'前提'!$B$13,IF(24<=12,'前提'!$B$14,IF(24<=18,'前提'!$B$15,IF(24<=24,'前提'!$B$16,IF(24<=36,'前提'!$B$17,IF(24<=48,'前提'!$B$18,'前提'!$B$19)))))) -> 6 | Z5: =IF(25<=6,'前提'!$B$13,IF(25<=12,'前提'!$B$14,IF(25<=18,'前提'!$B$15,IF(25<=24,'前提'!$B$16,IF(25<=36,'前提'!$B$17,IF(25<=48,'前提'!$B$18,'前提'!$B$19)))))) -> 8 | AA5: =IF(26<=6,'前提'!$B$13,IF(26<=12,'前提'!$B$14,IF(26<=18,'前提'!$B$15,IF(26<=24,'前提'!$B$16,IF(26<=36,'前提'!$B$17,IF(26<=48,'前提'!$B$18,'前提'!$B$19)))))) -> 8 | AB5: =IF(27<=6,'前提'!$B$13,IF(27<=12,'前提'!$B$14,IF(27<=18,'前提'!$B$15,IF(27<=24,'前提'!$B$16,IF(27<=36,'前提'!$B$17,IF(27<=48,'前提'!$B$18,'前提'!$B$19)))))) -> 8 | AC5: =IF(28<=6,'前提'!$B$13,IF(28<=12,'前提'!$B$14,IF(28<=18,'前提'!$B$15,IF(28<=24,'前提'!$B$16,IF(28<=36,'前提'!$B$17,IF(28<=48,'前提'!$B$18,'前提'!$B$19)))))) -> 8 | AD5: =IF(29<=6,'前提'!$B$13,IF(29<=12,'前提'!$B$14,IF(29<=18,'前提'!$B$15,IF(29<=24,'前提'!$B$16,IF(29<=36,'前提'!$B$17,IF(29<=48,'前提'!$B$18,'前提'!$B$19)))))) -> 8 | AE5: =IF(30<=6,'前提'!$B$13,IF(30<=12,'前提'!$B$14,IF(30<=18,'前提'!$B$15,IF(30<=24,'前提'!$B$16,IF(30<=36,'前提'!$B$17,IF(30<=48,'前提'!$B$18,'前提'!$B$19)))))) -> 8 | AF5: =IF(31<=6,'前提'!$B$13,IF(31<=12,'前提'!$B$14,IF(31<=18,'前提'!$B$15,IF(31<=24,'前提'!$B$16,IF(31<=36,'前提'!$B$17,IF(31<=48,'前提'!$B$18,'前提'!$B$19)))))) -> 8 | AG5: =IF(32<=6,'前提'!$B$13,IF(32<=12,'前提'!$B$14,IF(32<=18,'前提'!$B$15,IF(32<=24,'前提'!$B$16,IF(32<=36,'前提'!$B$17,IF(32<=48,'前提'!$B$18,'前提'!$B$19)))))) -> 8 | AH5: =IF(33<=6,'前提'!$B$13,IF(33<=12,'前提'!$B$14,IF(33<=18,'前提'!$B$15,IF(33<=24,'前提'!$B$16,IF(33<=36,'前提'!$B$17,IF(33<=48,'前提'!$B$18,'前提'!$B$19)))))) -> 8 | AI5: =IF(34<=6,'前提'!$B$13,IF(34<=12,'前提'!$B$14,IF(34<=18,'前提'!$B$15,IF(34<=24,'前提'!$B$16,IF(34<=36,'前提'!$B$17,IF(34<=48,'前提'!$B$18,'前提'!$B$19)))))) -> 8 | AJ5: =IF(35<=6,'前提'!$B$13,IF(35<=12,'前提'!$B$14,IF(35<=18,'前提'!$B$15,IF(35<=24,'前提'!$B$16,IF(35<=36,'前提'!$B$17,IF(35<=48,'前提'!$B$18,'前提'!$B$19)))))) -> 8 | AK5: =IF(36<=6,'前提'!$B$13,IF(36<=12,'前提'!$B$14,IF(36<=18,'前提'!$B$15,IF(36<=24,'前提'!$B$16,IF(36<=36,'前提'!$B$17,IF(36<=48,'前提'!$B$18,'前提'!$B$19)))))) -> 8 | AL5: =IF(37<=6,'前提'!$B$13,IF(37<=12,'前提'!$B$14,IF(37<=18,'前提'!$B$15,IF(37<=24,'前提'!$B$16,IF(37<=36,'前提'!$B$17,IF(37<=48,'前提'!$B$18,'前提'!$B$19)))))) -> 10 | AM5: =IF(38<=6,'前提'!$B$13,IF(38<=12,'前提'!$B$14,IF(38<=18,'前提'!$B$15,IF(38<=24,'前提'!$B$16,IF(38<=36,'前提'!$B$17,IF(38<=48,'前提'!$B$18,'前提'!$B$19)))))) -> 10 | AN5: =IF(39<=6,'前提'!$B$13,IF(39<=12,'前提'!$B$14,IF(39<=18,'前提'!$B$15,IF(39<=24,'前提'!$B$16,IF(39<=36,'前提'!$B$17,IF(39<=48,'前提'!$B$18,'前提'!$B$19)))))) -> 10 | AO5: =IF(40<=6,'前提'!$B$13,IF(40<=12,'前提'!$B$14,IF(40<=18,'前提'!$B$15,IF(40<=24,'前提'!$B$16,IF(40<=36,'前提'!$B$17,IF(40<=48,'前提'!$B$18,'前提'!$B$19)))))) -> 10 | AP5: =IF(41<=6,'前提'!$B$13,IF(41<=12,'前提'!$B$14,IF(41<=18,'前提'!$B$15,IF(41<=24,'前提'!$B$16,IF(41<=36,'前提'!$B$17,IF(41<=48,'前提'!$B$18,'前提'!$B$19)))))) -> 10 | AQ5: =IF(42<=6,'前提'!$B$13,IF(42<=12,'前提'!$B$14,IF(42<=18,'前提'!$B$15,IF(42<=24,'前提'!$B$16,IF(42<=36,'前提'!$B$17,IF(42<=48,'前提'!$B$18,'前提'!$B$19)))))) -> 10 | AR5: =IF(43<=6,'前提'!$B$13,IF(43<=12,'前提'!$B$14,IF(43<=18,'前提'!$B$15,IF(43<=24,'前提'!$B$16,IF(43<=36,'前提'!$B$17,IF(43<=48,'前提'!$B$18,'前提'!$B$19)))))) -> 10 | AS5: =IF(44<=6,'前提'!$B$13,IF(44<=12,'前提'!$B$14,IF(44<=18,'前提'!$B$15,IF(44<=24,'前提'!$B$16,IF(44<=36,'前提'!$B$17,IF(44<=48,'前提'!$B$18,'前提'!$B$19)))))) -> 10 | AT5: =IF(45<=6,'前提'!$B$13,IF(45<=12,'前提'!$B$14,IF(45<=18,'前提'!$B$15,IF(45<=24,'前提'!$B$16,IF(45<=36,'前提'!$B$17,IF(45<=48,'前提'!$B$18,'前提'!$B$19)))))) -> 10 | AU5: =IF(46<=6,'前提'!$B$13,IF(46<=12,'前提'!$B$14,IF(46<=18,'前提'!$B$15,IF(46<=24,'前提'!$B$16,IF(46<=36,'前提'!$B$17,IF(46<=48,'前提'!$B$18,'前提'!$B$19)))))) -> 10 | AV5: =IF(47<=6,'前提'!$B$13,IF(47<=12,'前提'!$B$14,IF(47<=18,'前提'!$B$15,IF(47<=24,'前提'!$B$16,IF(47<=36,'前提'!$B$17,IF(47<=48,'前提'!$B$18,'前提'!$B$19)))))) -> 10 | AW5: =IF(48<=6,'前提'!$B$13,IF(48<=12,'前提'!$B$14,IF(48<=18,'前提'!$B$15,IF(48<=24,'前提'!$B$16,IF(48<=36,'前提'!$B$17,IF(48<=48,'前提'!$B$18,'前提'!$B$19)))))) -> 10 | AX5: =IF(49<=6,'前提'!$B$13,IF(49<=12,'前提'!$B$14,IF(49<=18,'前提'!$B$15,IF(49<=24,'前提'!$B$16,IF(49<=36,'前提'!$B$17,IF(49<=48,'前提'!$B$18,'前提'!$B$19)))))) -> 12 | AY5: =IF(50<=6,'前提'!$B$13,IF(50<=12,'前提'!$B$14,IF(50<=18,'前提'!$B$15,IF(50<=24,'前提'!$B$16,IF(50<=36,'前提'!$B$17,IF(50<=48,'前提'!$B$18,'前提'!$B$19)))))) -> 12 | AZ5: =IF(51<=6,'前提'!$B$13,IF(51<=12,'前提'!$B$14,IF(51<=18,'前提'!$B$15,IF(51<=24,'前提'!$B$16,IF(51<=36,'前提'!$B$17,IF(51<=48,'前提'!$B$18,'前提'!$B$19)))))) -> 12 | BA5: =IF(52<=6,'前提'!$B$13,IF(52<=12,'前提'!$B$14,IF(52<=18,'前提'!$B$15,IF(52<=24,'前提'!$B$16,IF(52<=36,'前提'!$B$17,IF(52<=48,'前提'!$B$18,'前提'!$B$19)))))) -> 12 | BB5: =IF(53<=6,'前提'!$B$13,IF(53<=12,'前提'!$B$14,IF(53<=18,'前提'!$B$15,IF(53<=24,'前提'!$B$16,IF(53<=36,'前提'!$B$17,IF(53<=48,'前提'!$B$18,'前提'!$B$19)))))) -> 12 | BC5: =IF(54<=6,'前提'!$B$13,IF(54<=12,'前提'!$B$14,IF(54<=18,'前提'!$B$15,IF(54<=24,'前提'!$B$16,IF(54<=36,'前提'!$B$17,IF(54<=48,'前提'!$B$18,'前提'!$B$19)))))) -> 12 | BD5: =IF(55<=6,'前提'!$B$13,IF(55<=12,'前提'!$B$14,IF(55<=18,'前提'!$B$15,IF(55<=24,'前提'!$B$16,IF(55<=36,'前提'!$B$17,IF(55<=48,'前提'!$B$18,'前提'!$B$19)))))) -> 12 | BE5: =IF(56<=6,'前提'!$B$13,IF(56<=12,'前提'!$B$14,IF(56<=18,'前提'!$B$15,IF(56<=24,'前提'!$B$16,IF(56<=36,'前提'!$B$17,IF(56<=48,'前提'!$B$18,'前提'!$B$19)))))) -> 12 | BF5: =IF(57<=6,'前提'!$B$13,IF(57<=12,'前提'!$B$14,IF(57<=18,'前提'!$B$15,IF(57<=24,'前提'!$B$16,IF(57<=36,'前提'!$B$17,IF(57<=48,'前提'!$B$18,'前提'!$B$19)))))) -> 12 | BG5: =IF(58<=6,'前提'!$B$13,IF(58<=12,'前提'!$B$14,IF(58<=18,'前提'!$B$15,IF(58<=24,'前提'!$B$16,IF(58<=36,'前提'!$B$17,IF(58<=48,'前提'!$B$18,'前提'!$B$19)))))) -> 12 | BH5: =IF(59<=6,'前提'!$B$13,IF(59<=12,'前提'!$B$14,IF(59<=18,'前提'!$B$15,IF(59<=24,'前提'!$B$16,IF(59<=36,'前提'!$B$17,IF(59<=48,'前提'!$B$18,'前提'!$B$19)))))) -> 12 | BI5: =IF(60<=6,'前提'!$B$13,IF(60<=12,'前提'!$B$14,IF(60<=18,'前提'!$B$15,IF(60<=24,'前提'!$B$16,IF(60<=36,'前提'!$B$17,IF(60<=48,'前提'!$B$18,'前提'!$B$19)))))) -> 12
A7: 【顧客数】
A8: SuguDesk期首顧客数 | B8: 1 | C8: =B10 -> 1 | D8: =C10 -> 3 | E8: =D10 -> 5 | F8: =E10 -> 7 | G8: =F10 -> 9 | H8: =G10 -> 11 | I8: =H10 -> 16 | J8: =I10 -> 21 | ... BI8: =BH10 -> 319
A9: SuguDesk解約数 | B9: =ROUNDDOWN(B8*'前提'!$B$8,0) -> 0 | C9: =ROUNDDOWN(C8*'前提'!$B$8,0) -> 0 | D9: =ROUNDDOWN(D8*'前提'!$B$8,0) -> 0 | E9: =ROUNDDOWN(E8*'前提'!$B$8,0) -> 0 | F9: =ROUNDDOWN(F8*'前提'!$B$8,0) -> 0 | G9: =ROUNDDOWN(G8*'前提'!$B$8,0) -> 0 | H9: =ROUNDDOWN(H8*'前提'!$B$8,0) -> 0 | I9: =ROUNDDOWN(I8*'前提'!$B$8,0) -> 0 | ... BI9: =ROUNDDOWN(BI8*'前提'!$B$8,0) -> 6
A10: SuguDesk期末顧客数 | B10: =B8+B5-B9 -> 1 | C10: =C8+C5-C9 -> 3 | D10: =D8+D5-D9 -> 5 | E10: =E8+E5-E9 -> 7 | F10: =F8+F5-F9 -> 9 | G10: =G8+G5-G9 -> 11 | H10: =H8+H5-H9 -> 16 | I10: =I8+I5-I9 -> 21 | ... BI10: =BI8+BI5-BI9 -> 325
A11: BPO新規転換数 | B11: =IF(1>=7,ROUNDDOWN(B10*'前提'!$B$10,0),0) -> 0 | C11: =IF(2>=7,ROUNDDOWN(C10*'前提'!$B$10,0),0) -> 0 | D11: =IF(3>=7,ROUNDDOWN(D10*'前提'!$B$10,0),0) -> 0 | E11: =IF(4>=7,ROUNDDOWN(E10*'前提'!$B$10,0),0) -> 0 | F11: =IF(5>=7,ROUNDDOWN(F10*'前提'!$B$10,0),0) -> 0 | G11: =IF(6>=7,ROUNDDOWN(G10*'前提'!$B$10,0),0) -> 0 | H11: =IF(7>=7,ROUNDDOWN(H10*'前提'!$B$10,0),0) -> 0 | I11: =IF(8>=7,ROUNDDOWN(I10*'前提'!$B$10,0),0) -> 1 | J11: =IF(9>=7,ROUNDDOWN(J10*'前提'!$B$10,0),0) -> 1 | K11: =IF(10>=7,ROUNDDOWN(K10*'前提'!$B$10,0),0) -> 1 | L11: =IF(11>=7,ROUNDDOWN(L10*'前提'!$B$10,0),0) -> 1 | M11: =IF(12>=7,ROUNDDOWN(M10*'前提'!$B$10,0),0) -> 2 | N11: =IF(13>=7,ROUNDDOWN(N10*'前提'!$B$10,0),0) -> 2 | O11: =IF(14>=7,ROUNDDOWN(O10*'前提'!$B$10,0),0) -> 2 | P11: =IF(15>=7,ROUNDDOWN(P10*'前提'!$B$10,0),0) -> 2 | Q11: =IF(16>=7,ROUNDDOWN(Q10*'前提'!$B$10,0),0) -> 2 | R11: =IF(17>=7,ROUNDDOWN(R10*'前提'!$B$10,0),0) -> 3 | S11: =IF(18>=7,ROUNDDOWN(S10*'前提'!$B$10,0),0) -> 3 | T11: =IF(19>=7,ROUNDDOWN(T10*'前提'!$B$10,0),0) -> 3 | U11: =IF(20>=7,ROUNDDOWN(U10*'前提'!$B$10,0),0) -> 3 | V11: =IF(21>=7,ROUNDDOWN(V10*'前提'!$B$10,0),0) -> 4 | W11: =IF(22>=7,ROUNDDOWN(W10*'前提'!$B$10,0),0) -> 4 | X11: =IF(23>=7,ROUNDDOWN(X10*'前提'!$B$10,0),0) -> 4 | Y11: =IF(24>=7,ROUNDDOWN(Y10*'前提'!$B$10,0),0) -> 4 | Z11: =IF(25>=7,ROUNDDOWN(Z10*'前提'!$B$10,0),0) -> 5 | AA11: =IF(26>=7,ROUNDDOWN(AA10*'前提'!$B$10,0),0) -> 5 | AB11: =IF(27>=7,ROUNDDOWN(AB10*'前提'!$B$10,0),0) -> 5 | AC11: =IF(28>=7,ROUNDDOWN(AC10*'前提'!$B$10,0),0) -> 6 | AD11: =IF(29>=7,ROUNDDOWN(AD10*'前提'!$B$10,0),0) -> 6 | AE11: =IF(30>=7,ROUNDDOWN(AE10*'前提'!$B$10,0),0) -> 6 | AF11: =IF(31>=7,ROUNDDOWN(AF10*'前提'!$B$10,0),0) -> 7 | AG11: =IF(32>=7,ROUNDDOWN(AG10*'前提'!$B$10,0),0) -> 7 | AH11: =IF(33>=7,ROUNDDOWN(AH10*'前提'!$B$10,0),0) -> 7 | AI11: =IF(34>=7,ROUNDDOWN(AI10*'前提'!$B$10,0),0) -> 7 | AJ11: =IF(35>=7,ROUNDDOWN(AJ10*'前提'!$B$10,0),0) -> 8 | AK11: =IF(36>=7,ROUNDDOWN(AK10*'前提'!$B$10,0),0) -> 8 | AL11: =IF(37>=7,ROUNDDOWN(AL10*'前提'!$B$10,0),0) -> 8 | AM11: =IF(38>=7,ROUNDDOWN(AM10*'前提'!$B$10,0),0) -> 9 | AN11: =IF(39>=7,ROUNDDOWN(AN10*'前提'!$B$10,0),0) -> 9 | AO11: =IF(40>=7,ROUNDDOWN(AO10*'前提'!$B$10,0),0) -> 9 | AP11: =IF(41>=7,ROUNDDOWN(AP10*'前提'!$B$10,0),0) -> 10 | AQ11: =IF(42>=7,ROUNDDOWN(AQ10*'前提'!$B$10,0),0) -> 10 | AR11: =IF(43>=7,ROUNDDOWN(AR10*'前提'!$B$10,0),0) -> 10 | AS11: =IF(44>=7,ROUNDDOWN(AS10*'前提'!$B$10,0),0) -> 11 | AT11: =IF(45>=7,ROUNDDOWN(AT10*'前提'!$B$10,0),0) -> 11 | AU11: =IF(46>=7,ROUNDDOWN(AU10*'前提'!$B$10,0),0) -> 11 | AV11: =IF(47>=7,ROUNDDOWN(AV10*'前提'!$B$10,0),0) -> 11 | AW11: =IF(48>=7,ROUNDDOWN(AW10*'前提'!$B$10,0),0) -> 12 | AX11: =IF(49>=7,ROUNDDOWN(AX10*'前提'!$B$10,0),0) -> 12 | AY11: =IF(50>=7,ROUNDDOWN(AY10*'前提'!$B$10,0),0) -> 12 | AZ11: =IF(51>=7,ROUNDDOWN(AZ10*'前提'!$B$10,0),0) -> 13 | BA11: =IF(52>=7,ROUNDDOWN(BA10*'前提'!$B$10,0),0) -> 13 | BB11: =IF(53>=7,ROUNDDOWN(BB10*'前提'!$B$10,0),0) -> 14 | BC11: =IF(54>=7,ROUNDDOWN(BC10*'前提'!$B$10,0),0) -> 14 | BD11: =IF(55>=7,ROUNDDOWN(BD10*'前提'!$B$10,0),0) -> 14 | BE11: =IF(56>=7,ROUNDDOWN(BE10*'前提'!$B$10,0),0) -> 15 | BF11: =IF(57>=7,ROUNDDOWN(BF10*'前提'!$B$10,0),0) -> 15 | BG11: =IF(58>=7,ROUNDDOWN(BG10*'前提'!$B$10,0),0) -> 15 | BH11: =IF(59>=7,ROUNDDOWN(BH10*'前提'!$B$10,0),0) -> 15 | BI11: =IF(60>=7,ROUNDDOWN(BI10*'前提'!$B$10,0),0) -> 16
A12: BPO解約数 | B12: =ROUNDDOWN(B13*'前提'!$B$9,0) -> 0 | C12: =ROUNDDOWN(C13*'前提'!$B$9,0) -> 0 | D12: =ROUNDDOWN(D13*'前提'!$B$9,0) -> 0 | E12: =ROUNDDOWN(E13*'前提'!$B$9,0) -> 0 | F12: =ROUNDDOWN(F13*'前提'!$B$9,0) -> 0 | G12: =ROUNDDOWN(G13*'前提'!$B$9,0) -> 0 | H12: =ROUNDDOWN(H13*'前提'!$B$9,0) -> 0 | I12: =ROUNDDOWN(I13*'前提'!$B$9,0) -> 0 | ... BI12: =ROUNDDOWN(BI13*'前提'!$B$9,0) -> 3
A13: BPO期首顧客数 | B13: 0 | C13: =B14 -> 0 | D13: =C14 -> 0 | E13: =D14 -> 0 | F13: =E14 -> 0 | G13: =F14 -> 0 | H13: =G14 -> 0 | I13: =H14 -> 0 | J13: =I14 -> 1 | ... BI13: =BH14 -> 350
A14: BPO期末顧客数 | B14: =B13+B11-B12 -> 0 | C14: =C13+C11-C12 -> 0 | D14: =D13+D11-D12 -> 0 | E14: =E13+E11-E12 -> 0 | F14: =F13+F11-F12 -> 0 | G14: =G13+G11-G12 -> 0 | H14: =H13+H11-H12 -> 0 | I14: =I13+I11-I12 -> 1 | ... BI14: =BI13+BI11-BI12 -> 363
A16: 【売上】
A17: SuguDesk月額売上 | B17: =B10*'前提'!$B$4 -> 11500 | C17: =C10*'前提'!$B$4 -> 34500 | D17: =D10*'前提'!$B$4 -> 57500 | E17: =E10*'前提'!$B$4 -> 80500 | F17: =F10*'前提'!$B$4 -> 103500 | G17: =G10*'前提'!$B$4 -> 126500 | H17: =H10*'前提'!$B$4 -> 184000 | I17: =I10*'前提'!$B$4 -> 241500 | ... BI17: =BI10*'前提'!$B$4 -> 3737500
A18: BPO事務長代行売上 | B18: =B14*'前提'!$B$6 -> 0 | C18: =C14*'前提'!$B$6 -> 0 | D18: =D14*'前提'!$B$6 -> 0 | E18: =E14*'前提'!$B$6 -> 0 | F18: =F14*'前提'!$B$6 -> 0 | G18: =G14*'前提'!$B$6 -> 0 | H18: =H14*'前提'!$B$6 -> 0 | I18: =I14*'前提'!$B$6 -> 150000 | ... BI18: =BI14*'前提'!$B$6 -> 54450000
A19: BPO採用/集患売上 | B19: =IF(1>=13,B14*'前提'!$B$7,0) -> 0 | C19: =IF(2>=13,C14*'前提'!$B$7,0) -> 0 | D19: =IF(3>=13,D14*'前提'!$B$7,0) -> 0 | E19: =IF(4>=13,E14*'前提'!$B$7,0) -> 0 | F19: =IF(5>=13,F14*'前提'!$B$7,0) -> 0 | G19: =IF(6>=13,G14*'前提'!$B$7,0) -> 0 | H19: =IF(7>=13,H14*'前提'!$B$7,0) -> 0 | I19: =IF(8>=13,I14*'前提'!$B$7,0) -> 0 | J19: =IF(9>=13,J14*'前提'!$B$7,0) -> 0 | K19: =IF(10>=13,K14*'前提'!$B$7,0) -> 0 | L19: =IF(11>=13,L14*'前提'!$B$7,0) -> 0 | M19: =IF(12>=13,M14*'前提'!$B$7,0) -> 0 | N19: =IF(13>=13,N14*'前提'!$B$7,0) -> 400000 | O19: =IF(14>=13,O14*'前提'!$B$7,0) -> 500000 | P19: =IF(15>=13,P14*'前提'!$B$7,0) -> 600000 | Q19: =IF(16>=13,Q14*'前提'!$B$7,0) -> 700000 | R19: =IF(17>=13,R14*'前提'!$B$7,0) -> 850000 | S19: =IF(18>=13,S14*'前提'!$B$7,0) -> 1000000 | T19: =IF(19>=13,T14*'前提'!$B$7,0) -> 1150000 | U19: =IF(20>=13,U14*'前提'!$B$7,0) -> 1300000 | V19: =IF(21>=13,V14*'前提'!$B$7,0) -> 1500000 | W19: =IF(22>=13,W14*'前提'!$B$7,0) -> 1700000 | X19: =IF(23>=13,X14*'前提'!$B$7,0) -> 1900000 | Y19: =IF(24>=13,Y14*'前提'!$B$7,0) -> 2100000 | Z19: =IF(25>=13,Z14*'前提'!$B$7,0) -> 2350000 | AA19: =IF(26>=13,AA14*'前提'!$B$7,0) -> 2600000 | AB19: =IF(27>=13,AB14*'前提'!$B$7,0) -> 2850000 | AC19: =IF(28>=13,AC14*'前提'!$B$7,0) -> 3150000 | AD19: =IF(29>=13,AD14*'前提'!$B$7,0) -> 3450000 | AE19: =IF(30>=13,AE14*'前提'!$B$7,0) -> 3750000 | AF19: =IF(31>=13,AF14*'前提'!$B$7,0) -> 4100000 | AG19: =IF(32>=13,AG14*'前提'!$B$7,0) -> 4450000 | AH19: =IF(33>=13,AH14*'前提'!$B$7,0) -> 4800000 | AI19: =IF(34>=13,AI14*'前提'!$B$7,0) -> 5150000 | AJ19: =IF(35>=13,AJ14*'前提'!$B$7,0) -> 5500000 | AK19: =IF(36>=13,AK14*'前提'!$B$7,0) -> 5850000 | AL19: =IF(37>=13,AL14*'前提'!$B$7,0) -> 6200000 | AM19: =IF(38>=13,AM14*'前提'!$B$7,0) -> 6600000 | AN19: =IF(39>=13,AN14*'前提'!$B$7,0) -> 7000000 | AO19: =IF(40>=13,AO14*'前提'!$B$7,0) -> 7400000 | AP19: =IF(41>=13,AP14*'前提'!$B$7,0) -> 7850000 | AQ19: =IF(42>=13,AQ14*'前提'!$B$7,0) -> 8300000 | AR19: =IF(43>=13,AR14*'前提'!$B$7,0) -> 8750000 | AS19: =IF(44>=13,AS14*'前提'!$B$7,0) -> 9250000 | AT19: =IF(45>=13,AT14*'前提'!$B$7,0) -> 9750000 | AU19: =IF(46>=13,AU14*'前提'!$B$7,0) -> 10250000 | AV19: =IF(47>=13,AV14*'前提'!$B$7,0) -> 10700000 | AW19: =IF(48>=13,AW14*'前提'!$B$7,0) -> 11200000 | AX19: =IF(49>=13,AX14*'前提'!$B$7,0) -> 11700000 | AY19: =IF(50>=13,AY14*'前提'!$B$7,0) -> 12200000 | AZ19: =IF(51>=13,AZ14*'前提'!$B$7,0) -> 12750000 | BA19: =IF(52>=13,BA14*'前提'!$B$7,0) -> 13300000 | BB19: =IF(53>=13,BB14*'前提'!$B$7,0) -> 13900000 | BC19: =IF(54>=13,BC14*'前提'!$B$7,0) -> 14500000 | BD19: =IF(55>=13,BD14*'前提'!$B$7,0) -> 15100000 | BE19: =IF(56>=13,BE14*'前提'!$B$7,0) -> 15700000 | BF19: =IF(57>=13,BF14*'前提'!$B$7,0) -> 16300000 | BG19: =IF(58>=13,BG14*'前提'!$B$7,0) -> 16900000 | BH19: =IF(59>=13,BH14*'前提'!$B$7,0) -> 17500000 | BI19: =IF(60>=13,BI14*'前提'!$B$7,0) -> 18150000
A20: 導入費用 | B20: =B5*'前提'!$B$5 -> 0 | C20: =C5*'前提'!$B$5 -> 450000 | D20: =D5*'前提'!$B$5 -> 450000 | E20: =E5*'前提'!$B$5 -> 450000 | F20: =F5*'前提'!$B$5 -> 450000 | G20: =G5*'前提'!$B$5 -> 450000 | H20: =H5*'前提'!$B$5 -> 1125000 | I20: =I5*'前提'!$B$5 -> 1125000 | ... BI20: =BI5*'前提'!$B$5 -> 2700000
A21: MRR | B21: =B17+B18+B19 -> 11500 | C21: =C17+C18+C19 -> 34500 | D21: =D17+D18+D19 -> 57500 | E21: =E17+E18+E19 -> 80500 | F21: =F17+F18+F19 -> 103500 | G21: =G17+G18+G19 -> 126500 | H21: =H17+H18+H19 -> 184000 | I21: =I17+I18+I19 -> 391500 | ... BI21: =BI17+BI18+BI19 -> 76337500
A22: 売上合計 | B22: =B21+B20 -> 11500 | C22: =C21+C20 -> 484500 | D22: =D21+D20 -> 507500 | E22: =E21+E20 -> 530500 | F22: =F21+F20 -> 553500 | G22: =G21+G20 -> 576500 | H22: =H21+H20 -> 1309000 | I22: =I21+I20 -> 1516500 | ... BI22: =BI21+BI20 -> 79037500
A24: 【コスト】
A25: CEO報酬 | B25: ='前提'!$B$22 -> 300000 | C25: ='前提'!$B$22 -> 300000 | D25: ='前提'!$B$22 -> 300000 | E25: ='前提'!$B$22 -> 300000 | F25: ='前提'!$B$22 -> 300000 | G25: ='前提'!$B$22 -> 300000 | H25: ='前提'!$B$22 -> 300000 | I25: ='前提'!$B$22 -> 300000 | ... BI25: ='前提'!$B$22 -> 300000
A26: エンジニア | B26: =IF(1<=6,'前提'!$B$23*'前提'!$B$24,IF(1<=12,'前提'!$B$23*'前提'!$B$25,'前提'!$B$26*IF(1<=18,'前提'!$B$49,IF(1<=24,'前提'!$B$50,IF(1<=36,'前提'!$B$51,IF(1<=48,'前提'!$B$52,'前提'!$B$53)))))) -> 322500 | C26: =IF(2<=6,'前提'!$B$23*'前提'!$B$24,IF(2<=12,'前提'!$B$23*'前提'!$B$25,'前提'!$B$26*IF(2<=18,'前提'!$B$49,IF(2<=24,'前提'!$B$50,IF(2<=36,'前提'!$B$51,IF(2<=48,'前提'!$B$52,'前提'!$B$53)))))) -> 322500 | D26: =IF(3<=6,'前提'!$B$23*'前提'!$B$24,IF(3<=12,'前提'!$B$23*'前提'!$B$25,'前提'!$B$26*IF(3<=18,'前提'!$B$49,IF(3<=24,'前提'!$B$50,IF(3<=36,'前提'!$B$51,IF(3<=48,'前提'!$B$52,'前提'!$B$53)))))) -> 322500 | E26: =IF(4<=6,'前提'!$B$23*'前提'!$B$24,IF(4<=12,'前提'!$B$23*'前提'!$B$25,'前提'!$B$26*IF(4<=18,'前提'!$B$49,IF(4<=24,'前提'!$B$50,IF(4<=36,'前提'!$B$51,IF(4<=48,'前提'!$B$52,'前提'!$B$53)))))) -> 322500 | F26: =IF(5<=6,'前提'!$B$23*'前提'!$B$24,IF(5<=12,'前提'!$B$23*'前提'!$B$25,'前提'!$B$26*IF(5<=18,'前提'!$B$49,IF(5<=24,'前提'!$B$50,IF(5<=36,'前提'!$B$51,IF(5<=48,'前提'!$B$52,'前提'!$B$53)))))) -> 322500 | G26: =IF(6<=6,'前提'!$B$23*'前提'!$B$24,IF(6<=12,'前提'!$B$23*'前提'!$B$25,'前提'!$B$26*IF(6<=18,'前提'!$B$49,IF(6<=24,'前提'!$B$50,IF(6<=36,'前提'!$B$51,IF(6<=48,'前提'!$B$52,'前提'!$B$53)))))) -> 322500 | H26: =IF(7<=6,'前提'!$B$23*'前提'!$B$24,IF(7<=12,'前提'!$B$23*'前提'!$B$25,'前提'!$B$26*IF(7<=18,'前提'!$B$49,IF(7<=24,'前提'!$B$50,IF(7<=36,'前提'!$B$51,IF(7<=48,'前提'!$B$52,'前提'!$B$53)))))) -> 200000 | I26: =IF(8<=6,'前提'!$B$23*'前提'!$B$24,IF(8<=12,'前提'!$B$23*'前提'!$B$25,'前提'!$B$26*IF(8<=18,'前提'!$B$49,IF(8<=24,'前提'!$B$50,IF(8<=36,'前提'!$B$51,IF(8<=48,'前提'!$B$52,'前提'!$B$53)))))) -> 200000 | J26: =IF(9<=6,'前提'!$B$23*'前提'!$B$24,IF(9<=12,'前提'!$B$23*'前提'!$B$25,'前提'!$B$26*IF(9<=18,'前提'!$B$49,IF(9<=24,'前提'!$B$50,IF(9<=36,'前提'!$B$51,IF(9<=48,'前提'!$B$52,'前提'!$B$53)))))) -> 200000 | K26: =IF(10<=6,'前提'!$B$23*'前提'!$B$24,IF(10<=12,'前提'!$B$23*'前提'!$B$25,'前提'!$B$26*IF(10<=18,'前提'!$B$49,IF(10<=24,'前提'!$B$50,IF(10<=36,'前提'!$B$51,IF(10<=48,'前提'!$B$52,'前提'!$B$53)))))) -> 200000 | L26: =IF(11<=6,'前提'!$B$23*'前提'!$B$24,IF(11<=12,'前提'!$B$23*'前提'!$B$25,'前提'!$B$26*IF(11<=18,'前提'!$B$49,IF(11<=24,'前提'!$B$50,IF(11<=36,'前提'!$B$51,IF(11<=48,'前提'!$B$52,'前提'!$B$53)))))) -> 200000 | M26: =IF(12<=6,'前提'!$B$23*'前提'!$B$24,IF(12<=12,'前提'!$B$23*'前提'!$B$25,'前提'!$B$26*IF(12<=18,'前提'!$B$49,IF(12<=24,'前提'!$B$50,IF(12<=36,'前提'!$B$51,IF(12<=48,'前提'!$B$52,'前提'!$B$53)))))) -> 200000 | N26: =IF(13<=6,'前提'!$B$23*'前提'!$B$24,IF(13<=12,'前提'!$B$23*'前提'!$B$25,'前提'!$B$26*IF(13<=18,'前提'!$B$49,IF(13<=24,'前提'!$B$50,IF(13<=36,'前提'!$B$51,IF(13<=48,'前提'!$B$52,'前提'!$B$53)))))) -> 700000 | O26: =IF(14<=6,'前提'!$B$23*'前提'!$B$24,IF(14<=12,'前提'!$B$23*'前提'!$B$25,'前提'!$B$26*IF(14<=18,'前提'!$B$49,IF(14<=24,'前提'!$B$50,IF(14<=36,'前提'!$B$51,IF(14<=48,'前提'!$B$52,'前提'!$B$53)))))) -> 700000 | P26: =IF(15<=6,'前提'!$B$23*'前提'!$B$24,IF(15<=12,'前提'!$B$23*'前提'!$B$25,'前提'!$B$26*IF(15<=18,'前提'!$B$49,IF(15<=24,'前提'!$B$50,IF(15<=36,'前提'!$B$51,IF(15<=48,'前提'!$B$52,'前提'!$B$53)))))) -> 700000 | Q26: =IF(16<=6,'前提'!$B$23*'前提'!$B$24,IF(16<=12,'前提'!$B$23*'前提'!$B$25,'前提'!$B$26*IF(16<=18,'前提'!$B$49,IF(16<=24,'前提'!$B$50,IF(16<=36,'前提'!$B$51,IF(16<=48,'前提'!$B$52,'前提'!$B$53)))))) -> 700000 | R26: =IF(17<=6,'前提'!$B$23*'前提'!$B$24,IF(17<=12,'前提'!$B$23*'前提'!$B$25,'前提'!$B$26*IF(17<=18,'前提'!$B$49,IF(17<=24,'前提'!$B$50,IF(17<=36,'前提'!$B$51,IF(17<=48,'前提'!$B$52,'前提'!$B$53)))))) -> 700000 | S26: =IF(18<=6,'前提'!$B$23*'前提'!$B$24,IF(18<=12,'前提'!$B$23*'前提'!$B$25,'前提'!$B$26*IF(18<=18,'前提'!$B$49,IF(18<=24,'前提'!$B$50,IF(18<=36,'前提'!$B$51,IF(18<=48,'前提'!$B$52,'前提'!$B$53)))))) -> 700000 | T26: =IF(19<=6,'前提'!$B$23*'前提'!$B$24,IF(19<=12,'前提'!$B$23*'前提'!$B$25,'前提'!$B$26*IF(19<=18,'前提'!$B$49,IF(19<=24,'前提'!$B$50,IF(19<=36,'前提'!$B$51,IF(19<=48,'前提'!$B$52,'前提'!$B$53)))))) -> 700000 | U26: =IF(20<=6,'前提'!$B$23*'前提'!$B$24,IF(20<=12,'前提'!$B$23*'前提'!$B$25,'前提'!$B$26*IF(20<=18,'前提'!$B$49,IF(20<=24,'前提'!$B$50,IF(20<=36,'前提'!$B$51,IF(20<=48,'前提'!$B$52,'前提'!$B$53)))))) -> 700000 | V26: =IF(21<=6,'前提'!$B$23*'前提'!$B$24,IF(21<=12,'前提'!$B$23*'前提'!$B$25,'前提'!$B$26*IF(21<=18,'前提'!$B$49,IF(21<=24,'前提'!$B$50,IF(21<=36,'前提'!$B$51,IF(21<=48,'前提'!$B$52,'前提'!$B$53)))))) -> 700000 | W26: =IF(22<=6,'前提'!$B$23*'前提'!$B$24,IF(22<=12,'前提'!$B$23*'前提'!$B$25,'前提'!$B$26*IF(22<=18,'前提'!$B$49,IF(22<=24,'前提'!$B$50,IF(22<=36,'前提'!$B$51,IF(22<=48,'前提'!$B$52,'前提'!$B$53)))))) -> 700000 | X26: =IF(23<=6,'前提'!$B$23*'前提'!$B$24,IF(23<=12,'前提'!$B$23*'前提'!$B$25,'前提'!$B$26*IF(23<=18,'前提'!$B$49,IF(23<=24,'前提'!$B$50,IF(23<=36,'前提'!$B$51,IF(23<=48,'前提'!$B$52,'前提'!$B$53)))))) -> 700000 | Y26: =IF(24<=6,'前提'!$B$23*'前提'!$B$24,IF(24<=12,'前提'!$B$23*'前提'!$B$25,'前提'!$B$26*IF(24<=18,'前提'!$B$49,IF(24<=24,'前提'!$B$50,IF(24<=36,'前提'!$B$51,IF(24<=48,'前提'!$B$52,'前提'!$B$53)))))) -> 700000 | Z26: =IF(25<=6,'前提'!$B$23*'前提'!$B$24,IF(25<=12,'前提'!$B$23*'前提'!$B$25,'前提'!$B$26*IF(25<=18,'前提'!$B$49,IF(25<=24,'前提'!$B$50,IF(25<=36,'前提'!$B$51,IF(25<=48,'前提'!$B$52,'前提'!$B$53)))))) -> 1400000 | AA26: =IF(26<=6,'前提'!$B$23*'前提'!$B$24,IF(26<=12,'前提'!$B$23*'前提'!$B$25,'前提'!$B$26*IF(26<=18,'前提'!$B$49,IF(26<=24,'前提'!$B$50,IF(26<=36,'前提'!$B$51,IF(26<=48,'前提'!$B$52,'前提'!$B$53)))))) -> 1400000 | AB26: =IF(27<=6,'前提'!$B$23*'前提'!$B$24,IF(27<=12,'前提'!$B$23*'前提'!$B$25,'前提'!$B$26*IF(27<=18,'前提'!$B$49,IF(27<=24,'前提'!$B$50,IF(27<=36,'前提'!$B$51,IF(27<=48,'前提'!$B$52,'前提'!$B$53)))))) -> 1400000 | AC26: =IF(28<=6,'前提'!$B$23*'前提'!$B$24,IF(28<=12,'前提'!$B$23*'前提'!$B$25,'前提'!$B$26*IF(28<=18,'前提'!$B$49,IF(28<=24,'前提'!$B$50,IF(28<=36,'前提'!$B$51,IF(28<=48,'前提'!$B$52,'前提'!$B$53)))))) -> 1400000 | AD26: =IF(29<=6,'前提'!$B$23*'前提'!$B$24,IF(29<=12,'前提'!$B$23*'前提'!$B$25,'前提'!$B$26*IF(29<=18,'前提'!$B$49,IF(29<=24,'前提'!$B$50,IF(29<=36,'前提'!$B$51,IF(29<=48,'前提'!$B$52,'前提'!$B$53)))))) -> 1400000 | AE26: =IF(30<=6,'前提'!$B$23*'前提'!$B$24,IF(30<=12,'前提'!$B$23*'前提'!$B$25,'前提'!$B$26*IF(30<=18,'前提'!$B$49,IF(30<=24,'前提'!$B$50,IF(30<=36,'前提'!$B$51,IF(30<=48,'前提'!$B$52,'前提'!$B$53)))))) -> 1400000 | AF26: =IF(31<=6,'前提'!$B$23*'前提'!$B$24,IF(31<=12,'前提'!$B$23*'前提'!$B$25,'前提'!$B$26*IF(31<=18,'前提'!$B$49,IF(31<=24,'前提'!$B$50,IF(31<=36,'前提'!$B$51,IF(31<=48,'前提'!$B$52,'前提'!$B$53)))))) -> 1400000 | AG26: =IF(32<=6,'前提'!$B$23*'前提'!$B$24,IF(32<=12,'前提'!$B$23*'前提'!$B$25,'前提'!$B$26*IF(32<=18,'前提'!$B$49,IF(32<=24,'前提'!$B$50,IF(32<=36,'前提'!$B$51,IF(32<=48,'前提'!$B$52,'前提'!$B$53)))))) -> 1400000 | AH26: =IF(33<=6,'前提'!$B$23*'前提'!$B$24,IF(33<=12,'前提'!$B$23*'前提'!$B$25,'前提'!$B$26*IF(33<=18,'前提'!$B$49,IF(33<=24,'前提'!$B$50,IF(33<=36,'前提'!$B$51,IF(33<=48,'前提'!$B$52,'前提'!$B$53)))))) -> 1400000 | AI26: =IF(34<=6,'前提'!$B$23*'前提'!$B$24,IF(34<=12,'前提'!$B$23*'前提'!$B$25,'前提'!$B$26*IF(34<=18,'前提'!$B$49,IF(34<=24,'前提'!$B$50,IF(34<=36,'前提'!$B$51,IF(34<=48,'前提'!$B$52,'前提'!$B$53)))))) -> 1400000 | AJ26: =IF(35<=6,'前提'!$B$23*'前提'!$B$24,IF(35<=12,'前提'!$B$23*'前提'!$B$25,'前提'!$B$26*IF(35<=18,'前提'!$B$49,IF(35<=24,'前提'!$B$50,IF(35<=36,'前提'!$B$51,IF(35<=48,'前提'!$B$52,'前提'!$B$53)))))) -> 1400000 | AK26: =IF(36<=6,'前提'!$B$23*'前提'!$B$24,IF(36<=12,'前提'!$B$23*'前提'!$B$25,'前提'!$B$26*IF(36<=18,'前提'!$B$49,IF(36<=24,'前提'!$B$50,IF(36<=36,'前提'!$B$51,IF(36<=48,'前提'!$B$52,'前提'!$B$53)))))) -> 1400000 | AL26: =IF(37<=6,'前提'!$B$23*'前提'!$B$24,IF(37<=12,'前提'!$B$23*'前提'!$B$25,'前提'!$B$26*IF(37<=18,'前提'!$B$49,IF(37<=24,'前提'!$B$50,IF(37<=36,'前提'!$B$51,IF(37<=48,'前提'!$B$52,'前提'!$B$53)))))) -> 1400000 | AM26: =IF(38<=6,'前提'!$B$23*'前提'!$B$24,IF(38<=12,'前提'!$B$23*'前提'!$B$25,'前提'!$B$26*IF(38<=18,'前提'!$B$49,IF(38<=24,'前提'!$B$50,IF(38<=36,'前提'!$B$51,IF(38<=48,'前提'!$B$52,'前提'!$B$53)))))) -> 1400000 | AN26: =IF(39<=6,'前提'!$B$23*'前提'!$B$24,IF(39<=12,'前提'!$B$23*'前提'!$B$25,'前提'!$B$26*IF(39<=18,'前提'!$B$49,IF(39<=24,'前提'!$B$50,IF(39<=36,'前提'!$B$51,IF(39<=48,'前提'!$B$52,'前提'!$B$53)))))) -> 1400000 | AO26: =IF(40<=6,'前提'!$B$23*'前提'!$B$24,IF(40<=12,'前提'!$B$23*'前提'!$B$25,'前提'!$B$26*IF(40<=18,'前提'!$B$49,IF(40<=24,'前提'!$B$50,IF(40<=36,'前提'!$B$51,IF(40<=48,'前提'!$B$52,'前提'!$B$53)))))) -> 1400000 | AP26: =IF(41<=6,'前提'!$B$23*'前提'!$B$24,IF(41<=12,'前提'!$B$23*'前提'!$B$25,'前提'!$B$26*IF(41<=18,'前提'!$B$49,IF(41<=24,'前提'!$B$50,IF(41<=36,'前提'!$B$51,IF(41<=48,'前提'!$B$52,'前提'!$B$53)))))) -> 1400000 | AQ26: =IF(42<=6,'前提'!$B$23*'前提'!$B$24,IF(42<=12,'前提'!$B$23*'前提'!$B$25,'前提'!$B$26*IF(42<=18,'前提'!$B$49,IF(42<=24,'前提'!$B$50,IF(42<=36,'前提'!$B$51,IF(42<=48,'前提'!$B$52,'前提'!$B$53)))))) -> 1400000 | AR26: =IF(43<=6,'前提'!$B$23*'前提'!$B$24,IF(43<=12,'前提'!$B$23*'前提'!$B$25,'前提'!$B$26*IF(43<=18,'前提'!$B$49,IF(43<=24,'前提'!$B$50,IF(43<=36,'前提'!$B$51,IF(43<=48,'前提'!$B$52,'前提'!$B$53)))))) -> 1400000 | AS26: =IF(44<=6,'前提'!$B$23*'前提'!$B$24,IF(44<=12,'前提'!$B$23*'前提'!$B$25,'前提'!$B$26*IF(44<=18,'前提'!$B$49,IF(44<=24,'前提'!$B$50,IF(44<=36,'前提'!$B$51,IF(44<=48,'前提'!$B$52,'前提'!$B$53)))))) -> 1400000 | AT26: =IF(45<=6,'前提'!$B$23*'前提'!$B$24,IF(45<=12,'前提'!$B$23*'前提'!$B$25,'前提'!$B$26*IF(45<=18,'前提'!$B$49,IF(45<=24,'前提'!$B$50,IF(45<=36,'前提'!$B$51,IF(45<=48,'前提'!$B$52,'前提'!$B$53)))))) -> 1400000 | AU26: =IF(46<=6,'前提'!$B$23*'前提'!$B$24,IF(46<=12,'前提'!$B$23*'前提'!$B$25,'前提'!$B$26*IF(46<=18,'前提'!$B$49,IF(46<=24,'前提'!$B$50,IF(46<=36,'前提'!$B$51,IF(46<=48,'前提'!$B$52,'前提'!$B$53)))))) -> 1400000 | AV26: =IF(47<=6,'前提'!$B$23*'前提'!$B$24,IF(47<=12,'前提'!$B$23*'前提'!$B$25,'前提'!$B$26*IF(47<=18,'前提'!$B$49,IF(47<=24,'前提'!$B$50,IF(47<=36,'前提'!$B$51,IF(47<=48,'前提'!$B$52,'前提'!$B$53)))))) -> 1400000 | AW26: =IF(48<=6,'前提'!$B$23*'前提'!$B$24,IF(48<=12,'前提'!$B$23*'前提'!$B$25,'前提'!$B$26*IF(48<=18,'前提'!$B$49,IF(48<=24,'前提'!$B$50,IF(48<=36,'前提'!$B$51,IF(48<=48,'前提'!$B$52,'前提'!$B$53)))))) -> 1400000 | AX26: =IF(49<=6,'前提'!$B$23*'前提'!$B$24,IF(49<=12,'前提'!$B$23*'前提'!$B$25,'前提'!$B$26*IF(49<=18,'前提'!$B$49,IF(49<=24,'前提'!$B$50,IF(49<=36,'前提'!$B$51,IF(49<=48,'前提'!$B$52,'前提'!$B$53)))))) -> 1400000 | AY26: =IF(50<=6,'前提'!$B$23*'前提'!$B$24,IF(50<=12,'前提'!$B$23*'前提'!$B$25,'前提'!$B$26*IF(50<=18,'前提'!$B$49,IF(50<=24,'前提'!$B$50,IF(50<=36,'前提'!$B$51,IF(50<=48,'前提'!$B$52,'前提'!$B$53)))))) -> 1400000 | AZ26: =IF(51<=6,'前提'!$B$23*'前提'!$B$24,IF(51<=12,'前提'!$B$23*'前提'!$B$25,'前提'!$B$26*IF(51<=18,'前提'!$B$49,IF(51<=24,'前提'!$B$50,IF(51<=36,'前提'!$B$51,IF(51<=48,'前提'!$B$52,'前提'!$B$53)))))) -> 1400000 | BA26: =IF(52<=6,'前提'!$B$23*'前提'!$B$24,IF(52<=12,'前提'!$B$23*'前提'!$B$25,'前提'!$B$26*IF(52<=18,'前提'!$B$49,IF(52<=24,'前提'!$B$50,IF(52<=36,'前提'!$B$51,IF(52<=48,'前提'!$B$52,'前提'!$B$53)))))) -> 1400000 | BB26: =IF(53<=6,'前提'!$B$23*'前提'!$B$24,IF(53<=12,'前提'!$B$23*'前提'!$B$25,'前提'!$B$26*IF(53<=18,'前提'!$B$49,IF(53<=24,'前提'!$B$50,IF(53<=36,'前提'!$B$51,IF(53<=48,'前提'!$B$52,'前提'!$B$53)))))) -> 1400000 | BC26: =IF(54<=6,'前提'!$B$23*'前提'!$B$24,IF(54<=12,'前提'!$B$23*'前提'!$B$25,'前提'!$B$26*IF(54<=18,'前提'!$B$49,IF(54<=24,'前提'!$B$50,IF(54<=36,'前提'!$B$51,IF(54<=48,'前提'!$B$52,'前提'!$B$53)))))) -> 1400000 | BD26: =IF(55<=6,'前提'!$B$23*'前提'!$B$24,IF(55<=12,'前提'!$B$23*'前提'!$B$25,'前提'!$B$26*IF(55<=18,'前提'!$B$49,IF(55<=24,'前提'!$B$50,IF(55<=36,'前提'!$B$51,IF(55<=48,'前提'!$B$52,'前提'!$B$53)))))) -> 1400000 | BE26: =IF(56<=6,'前提'!$B$23*'前提'!$B$24,IF(56<=12,'前提'!$B$23*'前提'!$B$25,'前提'!$B$26*IF(56<=18,'前提'!$B$49,IF(56<=24,'前提'!$B$50,IF(56<=36,'前提'!$B$51,IF(56<=48,'前提'!$B$52,'前提'!$B$53)))))) -> 1400000 | BF26: =IF(57<=6,'前提'!$B$23*'前提'!$B$24,IF(57<=12,'前提'!$B$23*'前提'!$B$25,'前提'!$B$26*IF(57<=18,'前提'!$B$49,IF(57<=24,'前提'!$B$50,IF(57<=36,'前提'!$B$51,IF(57<=48,'前提'!$B$52,'前提'!$B$53)))))) -> 1400000 | BG26: =IF(58<=6,'前提'!$B$23*'前提'!$B$24,IF(58<=12,'前提'!$B$23*'前提'!$B$25,'前提'!$B$26*IF(58<=18,'前提'!$B$49,IF(58<=24,'前提'!$B$50,IF(58<=36,'前提'!$B$51,IF(58<=48,'前提'!$B$52,'前提'!$B$53)))))) -> 1400000 | BH26: =IF(59<=6,'前提'!$B$23*'前提'!$B$24,IF(59<=12,'前提'!$B$23*'前提'!$B$25,'前提'!$B$26*IF(59<=18,'前提'!$B$49,IF(59<=24,'前提'!$B$50,IF(59<=36,'前提'!$B$51,IF(59<=48,'前提'!$B$52,'前提'!$B$53)))))) -> 1400000 | BI26: =IF(60<=6,'前提'!$B$23*'前提'!$B$24,IF(60<=12,'前提'!$B$23*'前提'!$B$25,'前提'!$B$26*IF(60<=18,'前提'!$B$49,IF(60<=24,'前提'!$B$50,IF(60<=36,'前提'!$B$51,IF(60<=48,'前提'!$B$52,'前提'!$B$53)))))) -> 1400000
A27: CS人件費 | B27: =IF(1<=6,0,CEILING(B10/'前提'!$B$44,1)*'前提'!$B$30) -> 0 | C27: =IF(2<=6,0,CEILING(C10/'前提'!$B$44,1)*'前提'!$B$30) -> 0 | D27: =IF(3<=6,0,CEILING(D10/'前提'!$B$44,1)*'前提'!$B$30) -> 0 | E27: =IF(4<=6,0,CEILING(E10/'前提'!$B$44,1)*'前提'!$B$30) -> 0 | F27: =IF(5<=6,0,CEILING(F10/'前提'!$B$44,1)*'前提'!$B$30) -> 0 | G27: =IF(6<=6,0,CEILING(G10/'前提'!$B$44,1)*'前提'!$B$30) -> 0 | H27: =IF(7<=6,0,CEILING(H10/'前提'!$B$44,1)*'前提'!$B$30) -> 350000 | I27: =IF(8<=6,0,CEILING(I10/'前提'!$B$44,1)*'前提'!$B$30) -> 350000 | J27: =IF(9<=6,0,CEILING(J10/'前提'!$B$44,1)*'前提'!$B$30) -> 350000 | K27: =IF(10<=6,0,CEILING(K10/'前提'!$B$44,1)*'前提'!$B$30) -> 700000 | L27: =IF(11<=6,0,CEILING(L10/'前提'!$B$44,1)*'前提'!$B$30) -> 700000 | M27: =IF(12<=6,0,CEILING(M10/'前提'!$B$44,1)*'前提'!$B$30) -> 700000 | N27: =IF(13<=6,0,CEILING(N10/'前提'!$B$44,1)*'前提'!$B$30) -> 700000 | O27: =IF(14<=6,0,CEILING(O10/'前提'!$B$44,1)*'前提'!$B$30) -> 700000 | P27: =IF(15<=6,0,CEILING(P10/'前提'!$B$44,1)*'前提'!$B$30) -> 700000 | Q27: =IF(16<=6,0,CEILING(Q10/'前提'!$B$44,1)*'前提'!$B$30) -> 700000 | R27: =IF(17<=6,0,CEILING(R10/'前提'!$B$44,1)*'前提'!$B$30) -> 1050000 | S27: =IF(18<=6,0,CEILING(S10/'前提'!$B$44,1)*'前提'!$B$30) -> 1050000 | T27: =IF(19<=6,0,CEILING(T10/'前提'!$B$44,1)*'前提'!$B$30) -> 1050000 | U27: =IF(20<=6,0,CEILING(U10/'前提'!$B$44,1)*'前提'!$B$30) -> 1050000 | V27: =IF(21<=6,0,CEILING(V10/'前提'!$B$44,1)*'前提'!$B$30) -> 1050000 | W27: =IF(22<=6,0,CEILING(W10/'前提'!$B$44,1)*'前提'!$B$30) -> 1050000 | X27: =IF(23<=6,0,CEILING(X10/'前提'!$B$44,1)*'前提'!$B$30) -> 1400000 | Y27: =IF(24<=6,0,CEILING(Y10/'前提'!$B$44,1)*'前提'!$B$30) -> 1400000 | Z27: =IF(25<=6,0,CEILING(Z10/'前提'!$B$44,1)*'前提'!$B$30) -> 1400000 | AA27: =IF(26<=6,0,CEILING(AA10/'前提'!$B$44,1)*'前提'!$B$30) -> 1400000 | AB27: =IF(27<=6,0,CEILING(AB10/'前提'!$B$44,1)*'前提'!$B$30) -> 1400000 | AC27: =IF(28<=6,0,CEILING(AC10/'前提'!$B$44,1)*'前提'!$B$30) -> 1750000 | AD27: =IF(29<=6,0,CEILING(AD10/'前提'!$B$44,1)*'前提'!$B$30) -> 1750000 | AE27: =IF(30<=6,0,CEILING(AE10/'前提'!$B$44,1)*'前提'!$B$30) -> 1750000 | AF27: =IF(31<=6,0,CEILING(AF10/'前提'!$B$44,1)*'前提'!$B$30) -> 1750000 | AG27: =IF(32<=6,0,CEILING(AG10/'前提'!$B$44,1)*'前提'!$B$30) -> 1750000 | AH27: =IF(33<=6,0,CEILING(AH10/'前提'!$B$44,1)*'前提'!$B$30) -> 2100000 | AI27: =IF(34<=6,0,CEILING(AI10/'前提'!$B$44,1)*'前提'!$B$30) -> 2100000 | AJ27: =IF(35<=6,0,CEILING(AJ10/'前提'!$B$44,1)*'前提'!$B$30) -> 2100000 | AK27: =IF(36<=6,0,CEILING(AK10/'前提'!$B$44,1)*'前提'!$B$30) -> 2100000 | AL27: =IF(37<=6,0,CEILING(AL10/'前提'!$B$44,1)*'前提'!$B$30) -> 2100000 | AM27: =IF(38<=6,0,CEILING(AM10/'前提'!$B$44,1)*'前提'!$B$30) -> 2450000 | AN27: =IF(39<=6,0,CEILING(AN10/'前提'!$B$44,1)*'前提'!$B$30) -> 2450000 | AO27: =IF(40<=6,0,CEILING(AO10/'前提'!$B$44,1)*'前提'!$B$30) -> 2450000 | AP27: =IF(41<=6,0,CEILING(AP10/'前提'!$B$44,1)*'前提'!$B$30) -> 2450000 | AQ27: =IF(42<=6,0,CEILING(AQ10/'前提'!$B$44,1)*'前提'!$B$30) -> 2450000 | AR27: =IF(43<=6,0,CEILING(AR10/'前提'!$B$44,1)*'前提'!$B$30) -> 2800000 | AS27: =IF(44<=6,0,CEILING(AS10/'前提'!$B$44,1)*'前提'!$B$30) -> 2800000 | AT27: =IF(45<=6,0,CEILING(AT10/'前提'!$B$44,1)*'前提'!$B$30) -> 2800000 | AU27: =IF(46<=6,0,CEILING(AU10/'前提'!$B$44,1)*'前提'!$B$30) -> 2800000 | AV27: =IF(47<=6,0,CEILING(AV10/'前提'!$B$44,1)*'前提'!$B$30) -> 2800000 | AW27: =IF(48<=6,0,CEILING(AW10/'前提'!$B$44,1)*'前提'!$B$30) -> 3150000 | AX27: =IF(49<=6,0,CEILING(AX10/'前提'!$B$44,1)*'前提'!$B$30) -> 3150000 | AY27: =IF(50<=6,0,CEILING(AY10/'前提'!$B$44,1)*'前提'!$B$30) -> 3150000 | AZ27: =IF(51<=6,0,CEILING(AZ10/'前提'!$B$44,1)*'前提'!$B$30) -> 3150000 | BA27: =IF(52<=6,0,CEILING(BA10/'前提'!$B$44,1)*'前提'!$B$30) -> 3500000 | BB27: =IF(53<=6,0,CEILING(BB10/'前提'!$B$44,1)*'前提'!$B$30) -> 3500000 | BC27: =IF(54<=6,0,CEILING(BC10/'前提'!$B$44,1)*'前提'!$B$30) -> 3500000 | BD27: =IF(55<=6,0,CEILING(BD10/'前提'!$B$44,1)*'前提'!$B$30) -> 3500000 | BE27: =IF(56<=6,0,CEILING(BE10/'前提'!$B$44,1)*'前提'!$B$30) -> 3850000 | BF27: =IF(57<=6,0,CEILING(BF10/'前提'!$B$44,1)*'前提'!$B$30) -> 3850000 | BG27: =IF(58<=6,0,CEILING(BG10/'前提'!$B$44,1)*'前提'!$B$30) -> 3850000 | BH27: =IF(59<=6,0,CEILING(BH10/'前提'!$B$44,1)*'前提'!$B$30) -> 3850000 | BI27: =IF(60<=6,0,CEILING(BI10/'前提'!$B$44,1)*'前提'!$B$30) -> 3850000
A28: 営業サポート | B28: ='前提'!$B$29*IF(1<=6,'前提'!$B$65,IF(1<=12,'前提'!$B$66,IF(1<=18,'前提'!$B$67,IF(1<=24,'前提'!$B$68,IF(1<=36,'前提'!$B$69,IF(1<=48,'前提'!$B$70,'前提'!$B$71)))))) -> 200000 | C28: ='前提'!$B$29*IF(2<=6,'前提'!$B$65,IF(2<=12,'前提'!$B$66,IF(2<=18,'前提'!$B$67,IF(2<=24,'前提'!$B$68,IF(2<=36,'前提'!$B$69,IF(2<=48,'前提'!$B$70,'前提'!$B$71)))))) -> 200000 | D28: ='前提'!$B$29*IF(3<=6,'前提'!$B$65,IF(3<=12,'前提'!$B$66,IF(3<=18,'前提'!$B$67,IF(3<=24,'前提'!$B$68,IF(3<=36,'前提'!$B$69,IF(3<=48,'前提'!$B$70,'前提'!$B$71)))))) -> 200000 | E28: ='前提'!$B$29*IF(4<=6,'前提'!$B$65,IF(4<=12,'前提'!$B$66,IF(4<=18,'前提'!$B$67,IF(4<=24,'前提'!$B$68,IF(4<=36,'前提'!$B$69,IF(4<=48,'前提'!$B$70,'前提'!$B$71)))))) -> 200000 | F28: ='前提'!$B$29*IF(5<=6,'前提'!$B$65,IF(5<=12,'前提'!$B$66,IF(5<=18,'前提'!$B$67,IF(5<=24,'前提'!$B$68,IF(5<=36,'前提'!$B$69,IF(5<=48,'前提'!$B$70,'前提'!$B$71)))))) -> 200000 | G28: ='前提'!$B$29*IF(6<=6,'前提'!$B$65,IF(6<=12,'前提'!$B$66,IF(6<=18,'前提'!$B$67,IF(6<=24,'前提'!$B$68,IF(6<=36,'前提'!$B$69,IF(6<=48,'前提'!$B$70,'前提'!$B$71)))))) -> 200000 | H28: ='前提'!$B$29*IF(7<=6,'前提'!$B$65,IF(7<=12,'前提'!$B$66,IF(7<=18,'前提'!$B$67,IF(7<=24,'前提'!$B$68,IF(7<=36,'前提'!$B$69,IF(7<=48,'前提'!$B$70,'前提'!$B$71)))))) -> 200000 | I28: ='前提'!$B$29*IF(8<=6,'前提'!$B$65,IF(8<=12,'前提'!$B$66,IF(8<=18,'前提'!$B$67,IF(8<=24,'前提'!$B$68,IF(8<=36,'前提'!$B$69,IF(8<=48,'前提'!$B$70,'前提'!$B$71)))))) -> 200000 | J28: ='前提'!$B$29*IF(9<=6,'前提'!$B$65,IF(9<=12,'前提'!$B$66,IF(9<=18,'前提'!$B$67,IF(9<=24,'前提'!$B$68,IF(9<=36,'前提'!$B$69,IF(9<=48,'前提'!$B$70,'前提'!$B$71)))))) -> 200000 | K28: ='前提'!$B$29*IF(10<=6,'前提'!$B$65,IF(10<=12,'前提'!$B$66,IF(10<=18,'前提'!$B$67,IF(10<=24,'前提'!$B$68,IF(10<=36,'前提'!$B$69,IF(10<=48,'前提'!$B$70,'前提'!$B$71)))))) -> 200000 | L28: ='前提'!$B$29*IF(11<=6,'前提'!$B$65,IF(11<=12,'前提'!$B$66,IF(11<=18,'前提'!$B$67,IF(11<=24,'前提'!$B$68,IF(11<=36,'前提'!$B$69,IF(11<=48,'前提'!$B$70,'前提'!$B$71)))))) -> 200000 | M28: ='前提'!$B$29*IF(12<=6,'前提'!$B$65,IF(12<=12,'前提'!$B$66,IF(12<=18,'前提'!$B$67,IF(12<=24,'前提'!$B$68,IF(12<=36,'前提'!$B$69,IF(12<=48,'前提'!$B$70,'前提'!$B$71)))))) -> 200000 | N28: ='前提'!$B$29*IF(13<=6,'前提'!$B$65,IF(13<=12,'前提'!$B$66,IF(13<=18,'前提'!$B$67,IF(13<=24,'前提'!$B$68,IF(13<=36,'前提'!$B$69,IF(13<=48,'前提'!$B$70,'前提'!$B$71)))))) -> 200000 | O28: ='前提'!$B$29*IF(14<=6,'前提'!$B$65,IF(14<=12,'前提'!$B$66,IF(14<=18,'前提'!$B$67,IF(14<=24,'前提'!$B$68,IF(14<=36,'前提'!$B$69,IF(14<=48,'前提'!$B$70,'前提'!$B$71)))))) -> 200000 | P28: ='前提'!$B$29*IF(15<=6,'前提'!$B$65,IF(15<=12,'前提'!$B$66,IF(15<=18,'前提'!$B$67,IF(15<=24,'前提'!$B$68,IF(15<=36,'前提'!$B$69,IF(15<=48,'前提'!$B$70,'前提'!$B$71)))))) -> 200000 | Q28: ='前提'!$B$29*IF(16<=6,'前提'!$B$65,IF(16<=12,'前提'!$B$66,IF(16<=18,'前提'!$B$67,IF(16<=24,'前提'!$B$68,IF(16<=36,'前提'!$B$69,IF(16<=48,'前提'!$B$70,'前提'!$B$71)))))) -> 200000 | R28: ='前提'!$B$29*IF(17<=6,'前提'!$B$65,IF(17<=12,'前提'!$B$66,IF(17<=18,'前提'!$B$67,IF(17<=24,'前提'!$B$68,IF(17<=36,'前提'!$B$69,IF(17<=48,'前提'!$B$70,'前提'!$B$71)))))) -> 200000 | S28: ='前提'!$B$29*IF(18<=6,'前提'!$B$65,IF(18<=12,'前提'!$B$66,IF(18<=18,'前提'!$B$67,IF(18<=24,'前提'!$B$68,IF(18<=36,'前提'!$B$69,IF(18<=48,'前提'!$B$70,'前提'!$B$71)))))) -> 200000 | T28: ='前提'!$B$29*IF(19<=6,'前提'!$B$65,IF(19<=12,'前提'!$B$66,IF(19<=18,'前提'!$B$67,IF(19<=24,'前提'!$B$68,IF(19<=36,'前提'!$B$69,IF(19<=48,'前提'!$B$70,'前提'!$B$71)))))) -> 200000 | U28: ='前提'!$B$29*IF(20<=6,'前提'!$B$65,IF(20<=12,'前提'!$B$66,IF(20<=18,'前提'!$B$67,IF(20<=24,'前提'!$B$68,IF(20<=36,'前提'!$B$69,IF(20<=48,'前提'!$B$70,'前提'!$B$71)))))) -> 200000 | V28: ='前提'!$B$29*IF(21<=6,'前提'!$B$65,IF(21<=12,'前提'!$B$66,IF(21<=18,'前提'!$B$67,IF(21<=24,'前提'!$B$68,IF(21<=36,'前提'!$B$69,IF(21<=48,'前提'!$B$70,'前提'!$B$71)))))) -> 200000 | W28: ='前提'!$B$29*IF(22<=6,'前提'!$B$65,IF(22<=12,'前提'!$B$66,IF(22<=18,'前提'!$B$67,IF(22<=24,'前提'!$B$68,IF(22<=36,'前提'!$B$69,IF(22<=48,'前提'!$B$70,'前提'!$B$71)))))) -> 200000 | X28: ='前提'!$B$29*IF(23<=6,'前提'!$B$65,IF(23<=12,'前提'!$B$66,IF(23<=18,'前提'!$B$67,IF(23<=24,'前提'!$B$68,IF(23<=36,'前提'!$B$69,IF(23<=48,'前提'!$B$70,'前提'!$B$71)))))) -> 200000 | Y28: ='前提'!$B$29*IF(24<=6,'前提'!$B$65,IF(24<=12,'前提'!$B$66,IF(24<=18,'前提'!$B$67,IF(24<=24,'前提'!$B$68,IF(24<=36,'前提'!$B$69,IF(24<=48,'前提'!$B$70,'前提'!$B$71)))))) -> 200000 | Z28: ='前提'!$B$29*IF(25<=6,'前提'!$B$65,IF(25<=12,'前提'!$B$66,IF(25<=18,'前提'!$B$67,IF(25<=24,'前提'!$B$68,IF(25<=36,'前提'!$B$69,IF(25<=48,'前提'!$B$70,'前提'!$B$71)))))) -> 400000 | AA28: ='前提'!$B$29*IF(26<=6,'前提'!$B$65,IF(26<=12,'前提'!$B$66,IF(26<=18,'前提'!$B$67,IF(26<=24,'前提'!$B$68,IF(26<=36,'前提'!$B$69,IF(26<=48,'前提'!$B$70,'前提'!$B$71)))))) -> 400000 | AB28: ='前提'!$B$29*IF(27<=6,'前提'!$B$65,IF(27<=12,'前提'!$B$66,IF(27<=18,'前提'!$B$67,IF(27<=24,'前提'!$B$68,IF(27<=36,'前提'!$B$69,IF(27<=48,'前提'!$B$70,'前提'!$B$71)))))) -> 400000 | AC28: ='前提'!$B$29*IF(28<=6,'前提'!$B$65,IF(28<=12,'前提'!$B$66,IF(28<=18,'前提'!$B$67,IF(28<=24,'前提'!$B$68,IF(28<=36,'前提'!$B$69,IF(28<=48,'前提'!$B$70,'前提'!$B$71)))))) -> 400000 | AD28: ='前提'!$B$29*IF(29<=6,'前提'!$B$65,IF(29<=12,'前提'!$B$66,IF(29<=18,'前提'!$B$67,IF(29<=24,'前提'!$B$68,IF(29<=36,'前提'!$B$69,IF(29<=48,'前提'!$B$70,'前提'!$B$71)))))) -> 400000 | AE28: ='前提'!$B$29*IF(30<=6,'前提'!$B$65,IF(30<=12,'前提'!$B$66,IF(30<=18,'前提'!$B$67,IF(30<=24,'前提'!$B$68,IF(30<=36,'前提'!$B$69,IF(30<=48,'前提'!$B$70,'前提'!$B$71)))))) -> 400000 | AF28: ='前提'!$B$29*IF(31<=6,'前提'!$B$65,IF(31<=12,'前提'!$B$66,IF(31<=18,'前提'!$B$67,IF(31<=24,'前提'!$B$68,IF(31<=36,'前提'!$B$69,IF(31<=48,'前提'!$B$70,'前提'!$B$71)))))) -> 400000 | AG28: ='前提'!$B$29*IF(32<=6,'前提'!$B$65,IF(32<=12,'前提'!$B$66,IF(32<=18,'前提'!$B$67,IF(32<=24,'前提'!$B$68,IF(32<=36,'前提'!$B$69,IF(32<=48,'前提'!$B$70,'前提'!$B$71)))))) -> 400000 | AH28: ='前提'!$B$29*IF(33<=6,'前提'!$B$65,IF(33<=12,'前提'!$B$66,IF(33<=18,'前提'!$B$67,IF(33<=24,'前提'!$B$68,IF(33<=36,'前提'!$B$69,IF(33<=48,'前提'!$B$70,'前提'!$B$71)))))) -> 400000 | AI28: ='前提'!$B$29*IF(34<=6,'前提'!$B$65,IF(34<=12,'前提'!$B$66,IF(34<=18,'前提'!$B$67,IF(34<=24,'前提'!$B$68,IF(34<=36,'前提'!$B$69,IF(34<=48,'前提'!$B$70,'前提'!$B$71)))))) -> 400000 | AJ28: ='前提'!$B$29*IF(35<=6,'前提'!$B$65,IF(35<=12,'前提'!$B$66,IF(35<=18,'前提'!$B$67,IF(35<=24,'前提'!$B$68,IF(35<=36,'前提'!$B$69,IF(35<=48,'前提'!$B$70,'前提'!$B$71)))))) -> 400000 | AK28: ='前提'!$B$29*IF(36<=6,'前提'!$B$65,IF(36<=12,'前提'!$B$66,IF(36<=18,'前提'!$B$67,IF(36<=24,'前提'!$B$68,IF(36<=36,'前提'!$B$69,IF(36<=48,'前提'!$B$70,'前提'!$B$71)))))) -> 400000 | AL28: ='前提'!$B$29*IF(37<=6,'前提'!$B$65,IF(37<=12,'前提'!$B$66,IF(37<=18,'前提'!$B$67,IF(37<=24,'前提'!$B$68,IF(37<=36,'前提'!$B$69,IF(37<=48,'前提'!$B$70,'前提'!$B$71)))))) -> 400000 | AM28: ='前提'!$B$29*IF(38<=6,'前提'!$B$65,IF(38<=12,'前提'!$B$66,IF(38<=18,'前提'!$B$67,IF(38<=24,'前提'!$B$68,IF(38<=36,'前提'!$B$69,IF(38<=48,'前提'!$B$70,'前提'!$B$71)))))) -> 400000 | AN28: ='前提'!$B$29*IF(39<=6,'前提'!$B$65,IF(39<=12,'前提'!$B$66,IF(39<=18,'前提'!$B$67,IF(39<=24,'前提'!$B$68,IF(39<=36,'前提'!$B$69,IF(39<=48,'前提'!$B$70,'前提'!$B$71)))))) -> 400000 | AO28: ='前提'!$B$29*IF(40<=6,'前提'!$B$65,IF(40<=12,'前提'!$B$66,IF(40<=18,'前提'!$B$67,IF(40<=24,'前提'!$B$68,IF(40<=36,'前提'!$B$69,IF(40<=48,'前提'!$B$70,'前提'!$B$71)))))) -> 400000 | AP28: ='前提'!$B$29*IF(41<=6,'前提'!$B$65,IF(41<=12,'前提'!$B$66,IF(41<=18,'前提'!$B$67,IF(41<=24,'前提'!$B$68,IF(41<=36,'前提'!$B$69,IF(41<=48,'前提'!$B$70,'前提'!$B$71)))))) -> 400000 | AQ28: ='前提'!$B$29*IF(42<=6,'前提'!$B$65,IF(42<=12,'前提'!$B$66,IF(42<=18,'前提'!$B$67,IF(42<=24,'前提'!$B$68,IF(42<=36,'前提'!$B$69,IF(42<=48,'前提'!$B$70,'前提'!$B$71)))))) -> 400000 | AR28: ='前提'!$B$29*IF(43<=6,'前提'!$B$65,IF(43<=12,'前提'!$B$66,IF(43<=18,'前提'!$B$67,IF(43<=24,'前提'!$B$68,IF(43<=36,'前提'!$B$69,IF(43<=48,'前提'!$B$70,'前提'!$B$71)))))) -> 400000 | AS28: ='前提'!$B$29*IF(44<=6,'前提'!$B$65,IF(44<=12,'前提'!$B$66,IF(44<=18,'前提'!$B$67,IF(44<=24,'前提'!$B$68,IF(44<=36,'前提'!$B$69,IF(44<=48,'前提'!$B$70,'前提'!$B$71)))))) -> 400000 | AT28: ='前提'!$B$29*IF(45<=6,'前提'!$B$65,IF(45<=12,'前提'!$B$66,IF(45<=18,'前提'!$B$67,IF(45<=24,'前提'!$B$68,IF(45<=36,'前提'!$B$69,IF(45<=48,'前提'!$B$70,'前提'!$B$71)))))) -> 400000 | AU28: ='前提'!$B$29*IF(46<=6,'前提'!$B$65,IF(46<=12,'前提'!$B$66,IF(46<=18,'前提'!$B$67,IF(46<=24,'前提'!$B$68,IF(46<=36,'前提'!$B$69,IF(46<=48,'前提'!$B$70,'前提'!$B$71)))))) -> 400000 | AV28: ='前提'!$B$29*IF(47<=6,'前提'!$B$65,IF(47<=12,'前提'!$B$66,IF(47<=18,'前提'!$B$67,IF(47<=24,'前提'!$B$68,IF(47<=36,'前提'!$B$69,IF(47<=48,'前提'!$B$70,'前提'!$B$71)))))) -> 400000 | AW28: ='前提'!$B$29*IF(48<=6,'前提'!$B$65,IF(48<=12,'前提'!$B$66,IF(48<=18,'前提'!$B$67,IF(48<=24,'前提'!$B$68,IF(48<=36,'前提'!$B$69,IF(48<=48,'前提'!$B$70,'前提'!$B$71)))))) -> 400000 | AX28: ='前提'!$B$29*IF(49<=6,'前提'!$B$65,IF(49<=12,'前提'!$B$66,IF(49<=18,'前提'!$B$67,IF(49<=24,'前提'!$B$68,IF(49<=36,'前提'!$B$69,IF(49<=48,'前提'!$B$70,'前提'!$B$71)))))) -> 600000 | AY28: ='前提'!$B$29*IF(50<=6,'前提'!$B$65,IF(50<=12,'前提'!$B$66,IF(50<=18,'前提'!$B$67,IF(50<=24,'前提'!$B$68,IF(50<=36,'前提'!$B$69,IF(50<=48,'前提'!$B$70,'前提'!$B$71)))))) -> 600000 | AZ28: ='前提'!$B$29*IF(51<=6,'前提'!$B$65,IF(51<=12,'前提'!$B$66,IF(51<=18,'前提'!$B$67,IF(51<=24,'前提'!$B$68,IF(51<=36,'前提'!$B$69,IF(51<=48,'前提'!$B$70,'前提'!$B$71)))))) -> 600000 | BA28: ='前提'!$B$29*IF(52<=6,'前提'!$B$65,IF(52<=12,'前提'!$B$66,IF(52<=18,'前提'!$B$67,IF(52<=24,'前提'!$B$68,IF(52<=36,'前提'!$B$69,IF(52<=48,'前提'!$B$70,'前提'!$B$71)))))) -> 600000 | BB28: ='前提'!$B$29*IF(53<=6,'前提'!$B$65,IF(53<=12,'前提'!$B$66,IF(53<=18,'前提'!$B$67,IF(53<=24,'前提'!$B$68,IF(53<=36,'前提'!$B$69,IF(53<=48,'前提'!$B$70,'前提'!$B$71)))))) -> 600000 | BC28: ='前提'!$B$29*IF(54<=6,'前提'!$B$65,IF(54<=12,'前提'!$B$66,IF(54<=18,'前提'!$B$67,IF(54<=24,'前提'!$B$68,IF(54<=36,'前提'!$B$69,IF(54<=48,'前提'!$B$70,'前提'!$B$71)))))) -> 600000 | BD28: ='前提'!$B$29*IF(55<=6,'前提'!$B$65,IF(55<=12,'前提'!$B$66,IF(55<=18,'前提'!$B$67,IF(55<=24,'前提'!$B$68,IF(55<=36,'前提'!$B$69,IF(55<=48,'前提'!$B$70,'前提'!$B$71)))))) -> 600000 | BE28: ='前提'!$B$29*IF(56<=6,'前提'!$B$65,IF(56<=12,'前提'!$B$66,IF(56<=18,'前提'!$B$67,IF(56<=24,'前提'!$B$68,IF(56<=36,'前提'!$B$69,IF(56<=48,'前提'!$B$70,'前提'!$B$71)))))) -> 600000 | BF28: ='前提'!$B$29*IF(57<=6,'前提'!$B$65,IF(57<=12,'前提'!$B$66,IF(57<=18,'前提'!$B$67,IF(57<=24,'前提'!$B$68,IF(57<=36,'前提'!$B$69,IF(57<=48,'前提'!$B$70,'前提'!$B$71)))))) -> 600000 | BG28: ='前提'!$B$29*IF(58<=6,'前提'!$B$65,IF(58<=12,'前提'!$B$66,IF(58<=18,'前提'!$B$67,IF(58<=24,'前提'!$B$68,IF(58<=36,'前提'!$B$69,IF(58<=48,'前提'!$B$70,'前提'!$B$71)))))) -> 600000 | BH28: ='前提'!$B$29*IF(59<=6,'前提'!$B$65,IF(59<=12,'前提'!$B$66,IF(59<=18,'前提'!$B$67,IF(59<=24,'前提'!$B$68,IF(59<=36,'前提'!$B$69,IF(59<=48,'前提'!$B$70,'前提'!$B$71)))))) -> 600000 | BI28: ='前提'!$B$29*IF(60<=6,'前提'!$B$65,IF(60<=12,'前提'!$B$66,IF(60<=18,'前提'!$B$67,IF(60<=24,'前提'!$B$68,IF(60<=36,'前提'!$B$69,IF(60<=48,'前提'!$B$70,'前提'!$B$71)))))) -> 600000
A29: BPO事務長 | B29: ='前提'!$B$27*IF(1<=6,'前提'!$B$56,IF(1<=12,'前提'!$B$57,IF(1<=18,'前提'!$B$58,IF(1<=24,'前提'!$B$59,IF(1<=36,'前提'!$B$60,IF(1<=48,'前提'!$B$61,'前提'!$B$62)))))) -> 0 | C29: ='前提'!$B$27*IF(2<=6,'前提'!$B$56,IF(2<=12,'前提'!$B$57,IF(2<=18,'前提'!$B$58,IF(2<=24,'前提'!$B$59,IF(2<=36,'前提'!$B$60,IF(2<=48,'前提'!$B$61,'前提'!$B$62)))))) -> 0 | D29: ='前提'!$B$27*IF(3<=6,'前提'!$B$56,IF(3<=12,'前提'!$B$57,IF(3<=18,'前提'!$B$58,IF(3<=24,'前提'!$B$59,IF(3<=36,'前提'!$B$60,IF(3<=48,'前提'!$B$61,'前提'!$B$62)))))) -> 0 | E29: ='前提'!$B$27*IF(4<=6,'前提'!$B$56,IF(4<=12,'前提'!$B$57,IF(4<=18,'前提'!$B$58,IF(4<=24,'前提'!$B$59,IF(4<=36,'前提'!$B$60,IF(4<=48,'前提'!$B$61,'前提'!$B$62)))))) -> 0 | F29: ='前提'!$B$27*IF(5<=6,'前提'!$B$56,IF(5<=12,'前提'!$B$57,IF(5<=18,'前提'!$B$58,IF(5<=24,'前提'!$B$59,IF(5<=36,'前提'!$B$60,IF(5<=48,'前提'!$B$61,'前提'!$B$62)))))) -> 0 | G29: ='前提'!$B$27*IF(6<=6,'前提'!$B$56,IF(6<=12,'前提'!$B$57,IF(6<=18,'前提'!$B$58,IF(6<=24,'前提'!$B$59,IF(6<=36,'前提'!$B$60,IF(6<=48,'前提'!$B$61,'前提'!$B$62)))))) -> 0 | H29: ='前提'!$B$27*IF(7<=6,'前提'!$B$56,IF(7<=12,'前提'!$B$57,IF(7<=18,'前提'!$B$58,IF(7<=24,'前提'!$B$59,IF(7<=36,'前提'!$B$60,IF(7<=48,'前提'!$B$61,'前提'!$B$62)))))) -> 400000 | I29: ='前提'!$B$27*IF(8<=6,'前提'!$B$56,IF(8<=12,'前提'!$B$57,IF(8<=18,'前提'!$B$58,IF(8<=24,'前提'!$B$59,IF(8<=36,'前提'!$B$60,IF(8<=48,'前提'!$B$61,'前提'!$B$62)))))) -> 400000 | J29: ='前提'!$B$27*IF(9<=6,'前提'!$B$56,IF(9<=12,'前提'!$B$57,IF(9<=18,'前提'!$B$58,IF(9<=24,'前提'!$B$59,IF(9<=36,'前提'!$B$60,IF(9<=48,'前提'!$B$61,'前提'!$B$62)))))) -> 400000 | K29: ='前提'!$B$27*IF(10<=6,'前提'!$B$56,IF(10<=12,'前提'!$B$57,IF(10<=18,'前提'!$B$58,IF(10<=24,'前提'!$B$59,IF(10<=36,'前提'!$B$60,IF(10<=48,'前提'!$B$61,'前提'!$B$62)))))) -> 400000 | L29: ='前提'!$B$27*IF(11<=6,'前提'!$B$56,IF(11<=12,'前提'!$B$57,IF(11<=18,'前提'!$B$58,IF(11<=24,'前提'!$B$59,IF(11<=36,'前提'!$B$60,IF(11<=48,'前提'!$B$61,'前提'!$B$62)))))) -> 400000 | M29: ='前提'!$B$27*IF(12<=6,'前提'!$B$56,IF(12<=12,'前提'!$B$57,IF(12<=18,'前提'!$B$58,IF(12<=24,'前提'!$B$59,IF(12<=36,'前提'!$B$60,IF(12<=48,'前提'!$B$61,'前提'!$B$62)))))) -> 400000 | N29: ='前提'!$B$27*IF(13<=6,'前提'!$B$56,IF(13<=12,'前提'!$B$57,IF(13<=18,'前提'!$B$58,IF(13<=24,'前提'!$B$59,IF(13<=36,'前提'!$B$60,IF(13<=48,'前提'!$B$61,'前提'!$B$62)))))) -> 800000 | O29: ='前提'!$B$27*IF(14<=6,'前提'!$B$56,IF(14<=12,'前提'!$B$57,IF(14<=18,'前提'!$B$58,IF(14<=24,'前提'!$B$59,IF(14<=36,'前提'!$B$60,IF(14<=48,'前提'!$B$61,'前提'!$B$62)))))) -> 800000 | P29: ='前提'!$B$27*IF(15<=6,'前提'!$B$56,IF(15<=12,'前提'!$B$57,IF(15<=18,'前提'!$B$58,IF(15<=24,'前提'!$B$59,IF(15<=36,'前提'!$B$60,IF(15<=48,'前提'!$B$61,'前提'!$B$62)))))) -> 800000 | Q29: ='前提'!$B$27*IF(16<=6,'前提'!$B$56,IF(16<=12,'前提'!$B$57,IF(16<=18,'前提'!$B$58,IF(16<=24,'前提'!$B$59,IF(16<=36,'前提'!$B$60,IF(16<=48,'前提'!$B$61,'前提'!$B$62)))))) -> 800000 | R29: ='前提'!$B$27*IF(17<=6,'前提'!$B$56,IF(17<=12,'前提'!$B$57,IF(17<=18,'前提'!$B$58,IF(17<=24,'前提'!$B$59,IF(17<=36,'前提'!$B$60,IF(17<=48,'前提'!$B$61,'前提'!$B$62)))))) -> 800000 | S29: ='前提'!$B$27*IF(18<=6,'前提'!$B$56,IF(18<=12,'前提'!$B$57,IF(18<=18,'前提'!$B$58,IF(18<=24,'前提'!$B$59,IF(18<=36,'前提'!$B$60,IF(18<=48,'前提'!$B$61,'前提'!$B$62)))))) -> 800000 | T29: ='前提'!$B$27*IF(19<=6,'前提'!$B$56,IF(19<=12,'前提'!$B$57,IF(19<=18,'前提'!$B$58,IF(19<=24,'前提'!$B$59,IF(19<=36,'前提'!$B$60,IF(19<=48,'前提'!$B$61,'前提'!$B$62)))))) -> 1200000 | U29: ='前提'!$B$27*IF(20<=6,'前提'!$B$56,IF(20<=12,'前提'!$B$57,IF(20<=18,'前提'!$B$58,IF(20<=24,'前提'!$B$59,IF(20<=36,'前提'!$B$60,IF(20<=48,'前提'!$B$61,'前提'!$B$62)))))) -> 1200000 | V29: ='前提'!$B$27*IF(21<=6,'前提'!$B$56,IF(21<=12,'前提'!$B$57,IF(21<=18,'前提'!$B$58,IF(21<=24,'前提'!$B$59,IF(21<=36,'前提'!$B$60,IF(21<=48,'前提'!$B$61,'前提'!$B$62)))))) -> 1200000 | W29: ='前提'!$B$27*IF(22<=6,'前提'!$B$56,IF(22<=12,'前提'!$B$57,IF(22<=18,'前提'!$B$58,IF(22<=24,'前提'!$B$59,IF(22<=36,'前提'!$B$60,IF(22<=48,'前提'!$B$61,'前提'!$B$62)))))) -> 1200000 | X29: ='前提'!$B$27*IF(23<=6,'前提'!$B$56,IF(23<=12,'前提'!$B$57,IF(23<=18,'前提'!$B$58,IF(23<=24,'前提'!$B$59,IF(23<=36,'前提'!$B$60,IF(23<=48,'前提'!$B$61,'前提'!$B$62)))))) -> 1200000 | Y29: ='前提'!$B$27*IF(24<=6,'前提'!$B$56,IF(24<=12,'前提'!$B$57,IF(24<=18,'前提'!$B$58,IF(24<=24,'前提'!$B$59,IF(24<=36,'前提'!$B$60,IF(24<=48,'前提'!$B$61,'前提'!$B$62)))))) -> 1200000 | Z29: ='前提'!$B$27*IF(25<=6,'前提'!$B$56,IF(25<=12,'前提'!$B$57,IF(25<=18,'前提'!$B$58,IF(25<=24,'前提'!$B$59,IF(25<=36,'前提'!$B$60,IF(25<=48,'前提'!$B$61,'前提'!$B$62)))))) -> 1600000 | AA29: ='前提'!$B$27*IF(26<=6,'前提'!$B$56,IF(26<=12,'前提'!$B$57,IF(26<=18,'前提'!$B$58,IF(26<=24,'前提'!$B$59,IF(26<=36,'前提'!$B$60,IF(26<=48,'前提'!$B$61,'前提'!$B$62)))))) -> 1600000 | AB29: ='前提'!$B$27*IF(27<=6,'前提'!$B$56,IF(27<=12,'前提'!$B$57,IF(27<=18,'前提'!$B$58,IF(27<=24,'前提'!$B$59,IF(27<=36,'前提'!$B$60,IF(27<=48,'前提'!$B$61,'前提'!$B$62)))))) -> 1600000 | AC29: ='前提'!$B$27*IF(28<=6,'前提'!$B$56,IF(28<=12,'前提'!$B$57,IF(28<=18,'前提'!$B$58,IF(28<=24,'前提'!$B$59,IF(28<=36,'前提'!$B$60,IF(28<=48,'前提'!$B$61,'前提'!$B$62)))))) -> 1600000 | AD29: ='前提'!$B$27*IF(29<=6,'前提'!$B$56,IF(29<=12,'前提'!$B$57,IF(29<=18,'前提'!$B$58,IF(29<=24,'前提'!$B$59,IF(29<=36,'前提'!$B$60,IF(29<=48,'前提'!$B$61,'前提'!$B$62)))))) -> 1600000 | AE29: ='前提'!$B$27*IF(30<=6,'前提'!$B$56,IF(30<=12,'前提'!$B$57,IF(30<=18,'前提'!$B$58,IF(30<=24,'前提'!$B$59,IF(30<=36,'前提'!$B$60,IF(30<=48,'前提'!$B$61,'前提'!$B$62)))))) -> 1600000 | AF29: ='前提'!$B$27*IF(31<=6,'前提'!$B$56,IF(31<=12,'前提'!$B$57,IF(31<=18,'前提'!$B$58,IF(31<=24,'前提'!$B$59,IF(31<=36,'前提'!$B$60,IF(31<=48,'前提'!$B$61,'前提'!$B$62)))))) -> 1600000 | AG29: ='前提'!$B$27*IF(32<=6,'前提'!$B$56,IF(32<=12,'前提'!$B$57,IF(32<=18,'前提'!$B$58,IF(32<=24,'前提'!$B$59,IF(32<=36,'前提'!$B$60,IF(32<=48,'前提'!$B$61,'前提'!$B$62)))))) -> 1600000 | AH29: ='前提'!$B$27*IF(33<=6,'前提'!$B$56,IF(33<=12,'前提'!$B$57,IF(33<=18,'前提'!$B$58,IF(33<=24,'前提'!$B$59,IF(33<=36,'前提'!$B$60,IF(33<=48,'前提'!$B$61,'前提'!$B$62)))))) -> 1600000 | AI29: ='前提'!$B$27*IF(34<=6,'前提'!$B$56,IF(34<=12,'前提'!$B$57,IF(34<=18,'前提'!$B$58,IF(34<=24,'前提'!$B$59,IF(34<=36,'前提'!$B$60,IF(34<=48,'前提'!$B$61,'前提'!$B$62)))))) -> 1600000 | AJ29: ='前提'!$B$27*IF(35<=6,'前提'!$B$56,IF(35<=12,'前提'!$B$57,IF(35<=18,'前提'!$B$58,IF(35<=24,'前提'!$B$59,IF(35<=36,'前提'!$B$60,IF(35<=48,'前提'!$B$61,'前提'!$B$62)))))) -> 1600000 | AK29: ='前提'!$B$27*IF(36<=6,'前提'!$B$56,IF(36<=12,'前提'!$B$57,IF(36<=18,'前提'!$B$58,IF(36<=24,'前提'!$B$59,IF(36<=36,'前提'!$B$60,IF(36<=48,'前提'!$B$61,'前提'!$B$62)))))) -> 1600000 | AL29: ='前提'!$B$27*IF(37<=6,'前提'!$B$56,IF(37<=12,'前提'!$B$57,IF(37<=18,'前提'!$B$58,IF(37<=24,'前提'!$B$59,IF(37<=36,'前提'!$B$60,IF(37<=48,'前提'!$B$61,'前提'!$B$62)))))) -> 2000000 | AM29: ='前提'!$B$27*IF(38<=6,'前提'!$B$56,IF(38<=12,'前提'!$B$57,IF(38<=18,'前提'!$B$58,IF(38<=24,'前提'!$B$59,IF(38<=36,'前提'!$B$60,IF(38<=48,'前提'!$B$61,'前提'!$B$62)))))) -> 2000000 | AN29: ='前提'!$B$27*IF(39<=6,'前提'!$B$56,IF(39<=12,'前提'!$B$57,IF(39<=18,'前提'!$B$58,IF(39<=24,'前提'!$B$59,IF(39<=36,'前提'!$B$60,IF(39<=48,'前提'!$B$61,'前提'!$B$62)))))) -> 2000000 | AO29: ='前提'!$B$27*IF(40<=6,'前提'!$B$56,IF(40<=12,'前提'!$B$57,IF(40<=18,'前提'!$B$58,IF(40<=24,'前提'!$B$59,IF(40<=36,'前提'!$B$60,IF(40<=48,'前提'!$B$61,'前提'!$B$62)))))) -> 2000000 | AP29: ='前提'!$B$27*IF(41<=6,'前提'!$B$56,IF(41<=12,'前提'!$B$57,IF(41<=18,'前提'!$B$58,IF(41<=24,'前提'!$B$59,IF(41<=36,'前提'!$B$60,IF(41<=48,'前提'!$B$61,'前提'!$B$62)))))) -> 2000000 | AQ29: ='前提'!$B$27*IF(42<=6,'前提'!$B$56,IF(42<=12,'前提'!$B$57,IF(42<=18,'前提'!$B$58,IF(42<=24,'前提'!$B$59,IF(42<=36,'前提'!$B$60,IF(42<=48,'前提'!$B$61,'前提'!$B$62)))))) -> 2000000 | AR29: ='前提'!$B$27*IF(43<=6,'前提'!$B$56,IF(43<=12,'前提'!$B$57,IF(43<=18,'前提'!$B$58,IF(43<=24,'前提'!$B$59,IF(43<=36,'前提'!$B$60,IF(43<=48,'前提'!$B$61,'前提'!$B$62)))))) -> 2000000 | AS29: ='前提'!$B$27*IF(44<=6,'前提'!$B$56,IF(44<=12,'前提'!$B$57,IF(44<=18,'前提'!$B$58,IF(44<=24,'前提'!$B$59,IF(44<=36,'前提'!$B$60,IF(44<=48,'前提'!$B$61,'前提'!$B$62)))))) -> 2000000 | AT29: ='前提'!$B$27*IF(45<=6,'前提'!$B$56,IF(45<=12,'前提'!$B$57,IF(45<=18,'前提'!$B$58,IF(45<=24,'前提'!$B$59,IF(45<=36,'前提'!$B$60,IF(45<=48,'前提'!$B$61,'前提'!$B$62)))))) -> 2000000 | AU29: ='前提'!$B$27*IF(46<=6,'前提'!$B$56,IF(46<=12,'前提'!$B$57,IF(46<=18,'前提'!$B$58,IF(46<=24,'前提'!$B$59,IF(46<=36,'前提'!$B$60,IF(46<=48,'前提'!$B$61,'前提'!$B$62)))))) -> 2000000 | AV29: ='前提'!$B$27*IF(47<=6,'前提'!$B$56,IF(47<=12,'前提'!$B$57,IF(47<=18,'前提'!$B$58,IF(47<=24,'前提'!$B$59,IF(47<=36,'前提'!$B$60,IF(47<=48,'前提'!$B$61,'前提'!$B$62)))))) -> 2000000 | AW29: ='前提'!$B$27*IF(48<=6,'前提'!$B$56,IF(48<=12,'前提'!$B$57,IF(48<=18,'前提'!$B$58,IF(48<=24,'前提'!$B$59,IF(48<=36,'前提'!$B$60,IF(48<=48,'前提'!$B$61,'前提'!$B$62)))))) -> 2000000 | AX29: ='前提'!$B$27*IF(49<=6,'前提'!$B$56,IF(49<=12,'前提'!$B$57,IF(49<=18,'前提'!$B$58,IF(49<=24,'前提'!$B$59,IF(49<=36,'前提'!$B$60,IF(49<=48,'前提'!$B$61,'前提'!$B$62)))))) -> 2400000 | AY29: ='前提'!$B$27*IF(50<=6,'前提'!$B$56,IF(50<=12,'前提'!$B$57,IF(50<=18,'前提'!$B$58,IF(50<=24,'前提'!$B$59,IF(50<=36,'前提'!$B$60,IF(50<=48,'前提'!$B$61,'前提'!$B$62)))))) -> 2400000 | AZ29: ='前提'!$B$27*IF(51<=6,'前提'!$B$56,IF(51<=12,'前提'!$B$57,IF(51<=18,'前提'!$B$58,IF(51<=24,'前提'!$B$59,IF(51<=36,'前提'!$B$60,IF(51<=48,'前提'!$B$61,'前提'!$B$62)))))) -> 2400000 | BA29: ='前提'!$B$27*IF(52<=6,'前提'!$B$56,IF(52<=12,'前提'!$B$57,IF(52<=18,'前提'!$B$58,IF(52<=24,'前提'!$B$59,IF(52<=36,'前提'!$B$60,IF(52<=48,'前提'!$B$61,'前提'!$B$62)))))) -> 2400000 | BB29: ='前提'!$B$27*IF(53<=6,'前提'!$B$56,IF(53<=12,'前提'!$B$57,IF(53<=18,'前提'!$B$58,IF(53<=24,'前提'!$B$59,IF(53<=36,'前提'!$B$60,IF(53<=48,'前提'!$B$61,'前提'!$B$62)))))) -> 2400000 | BC29: ='前提'!$B$27*IF(54<=6,'前提'!$B$56,IF(54<=12,'前提'!$B$57,IF(54<=18,'前提'!$B$58,IF(54<=24,'前提'!$B$59,IF(54<=36,'前提'!$B$60,IF(54<=48,'前提'!$B$61,'前提'!$B$62)))))) -> 2400000 | BD29: ='前提'!$B$27*IF(55<=6,'前提'!$B$56,IF(55<=12,'前提'!$B$57,IF(55<=18,'前提'!$B$58,IF(55<=24,'前提'!$B$59,IF(55<=36,'前提'!$B$60,IF(55<=48,'前提'!$B$61,'前提'!$B$62)))))) -> 2400000 | BE29: ='前提'!$B$27*IF(56<=6,'前提'!$B$56,IF(56<=12,'前提'!$B$57,IF(56<=18,'前提'!$B$58,IF(56<=24,'前提'!$B$59,IF(56<=36,'前提'!$B$60,IF(56<=48,'前提'!$B$61,'前提'!$B$62)))))) -> 2400000 | BF29: ='前提'!$B$27*IF(57<=6,'前提'!$B$56,IF(57<=12,'前提'!$B$57,IF(57<=18,'前提'!$B$58,IF(57<=24,'前提'!$B$59,IF(57<=36,'前提'!$B$60,IF(57<=48,'前提'!$B$61,'前提'!$B$62)))))) -> 2400000 | BG29: ='前提'!$B$27*IF(58<=6,'前提'!$B$56,IF(58<=12,'前提'!$B$57,IF(58<=18,'前提'!$B$58,IF(58<=24,'前提'!$B$59,IF(58<=36,'前提'!$B$60,IF(58<=48,'前提'!$B$61,'前提'!$B$62)))))) -> 2400000 | BH29: ='前提'!$B$27*IF(59<=6,'前提'!$B$56,IF(59<=12,'前提'!$B$57,IF(59<=18,'前提'!$B$58,IF(59<=24,'前提'!$B$59,IF(59<=36,'前提'!$B$60,IF(59<=48,'前提'!$B$61,'前提'!$B$62)))))) -> 2400000 | BI29: ='前提'!$B$27*IF(60<=6,'前提'!$B$56,IF(60<=12,'前提'!$B$57,IF(60<=18,'前提'!$B$58,IF(60<=24,'前提'!$B$59,IF(60<=36,'前提'!$B$60,IF(60<=48,'前提'!$B$61,'前提'!$B$62)))))) -> 2400000
A30: BPOオペレーター | B30: ='前提'!$B$28*IF(1<=6,'前提'!$C$56,IF(1<=12,'前提'!$C$57,IF(1<=18,'前提'!$C$58,IF(1<=24,'前提'!$C$59,IF(1<=36,'前提'!$C$60,IF(1<=48,'前提'!$C$61,'前提'!$C$62)))))) -> 0 | C30: ='前提'!$B$28*IF(2<=6,'前提'!$C$56,IF(2<=12,'前提'!$C$57,IF(2<=18,'前提'!$C$58,IF(2<=24,'前提'!$C$59,IF(2<=36,'前提'!$C$60,IF(2<=48,'前提'!$C$61,'前提'!$C$62)))))) -> 0 | D30: ='前提'!$B$28*IF(3<=6,'前提'!$C$56,IF(3<=12,'前提'!$C$57,IF(3<=18,'前提'!$C$58,IF(3<=24,'前提'!$C$59,IF(3<=36,'前提'!$C$60,IF(3<=48,'前提'!$C$61,'前提'!$C$62)))))) -> 0 | E30: ='前提'!$B$28*IF(4<=6,'前提'!$C$56,IF(4<=12,'前提'!$C$57,IF(4<=18,'前提'!$C$58,IF(4<=24,'前提'!$C$59,IF(4<=36,'前提'!$C$60,IF(4<=48,'前提'!$C$61,'前提'!$C$62)))))) -> 0 | F30: ='前提'!$B$28*IF(5<=6,'前提'!$C$56,IF(5<=12,'前提'!$C$57,IF(5<=18,'前提'!$C$58,IF(5<=24,'前提'!$C$59,IF(5<=36,'前提'!$C$60,IF(5<=48,'前提'!$C$61,'前提'!$C$62)))))) -> 0 | G30: ='前提'!$B$28*IF(6<=6,'前提'!$C$56,IF(6<=12,'前提'!$C$57,IF(6<=18,'前提'!$C$58,IF(6<=24,'前提'!$C$59,IF(6<=36,'前提'!$C$60,IF(6<=48,'前提'!$C$61,'前提'!$C$62)))))) -> 0 | H30: ='前提'!$B$28*IF(7<=6,'前提'!$C$56,IF(7<=12,'前提'!$C$57,IF(7<=18,'前提'!$C$58,IF(7<=24,'前提'!$C$59,IF(7<=36,'前提'!$C$60,IF(7<=48,'前提'!$C$61,'前提'!$C$62)))))) -> 400000 | I30: ='前提'!$B$28*IF(8<=6,'前提'!$C$56,IF(8<=12,'前提'!$C$57,IF(8<=18,'前提'!$C$58,IF(8<=24,'前提'!$C$59,IF(8<=36,'前提'!$C$60,IF(8<=48,'前提'!$C$61,'前提'!$C$62)))))) -> 400000 | J30: ='前提'!$B$28*IF(9<=6,'前提'!$C$56,IF(9<=12,'前提'!$C$57,IF(9<=18,'前提'!$C$58,IF(9<=24,'前提'!$C$59,IF(9<=36,'前提'!$C$60,IF(9<=48,'前提'!$C$61,'前提'!$C$62)))))) -> 400000 | K30: ='前提'!$B$28*IF(10<=6,'前提'!$C$56,IF(10<=12,'前提'!$C$57,IF(10<=18,'前提'!$C$58,IF(10<=24,'前提'!$C$59,IF(10<=36,'前提'!$C$60,IF(10<=48,'前提'!$C$61,'前提'!$C$62)))))) -> 400000 | L30: ='前提'!$B$28*IF(11<=6,'前提'!$C$56,IF(11<=12,'前提'!$C$57,IF(11<=18,'前提'!$C$58,IF(11<=24,'前提'!$C$59,IF(11<=36,'前提'!$C$60,IF(11<=48,'前提'!$C$61,'前提'!$C$62)))))) -> 400000 | M30: ='前提'!$B$28*IF(12<=6,'前提'!$C$56,IF(12<=12,'前提'!$C$57,IF(12<=18,'前提'!$C$58,IF(12<=24,'前提'!$C$59,IF(12<=36,'前提'!$C$60,IF(12<=48,'前提'!$C$61,'前提'!$C$62)))))) -> 400000 | N30: ='前提'!$B$28*IF(13<=6,'前提'!$C$56,IF(13<=12,'前提'!$C$57,IF(13<=18,'前提'!$C$58,IF(13<=24,'前提'!$C$59,IF(13<=36,'前提'!$C$60,IF(13<=48,'前提'!$C$61,'前提'!$C$62)))))) -> 800000 | O30: ='前提'!$B$28*IF(14<=6,'前提'!$C$56,IF(14<=12,'前提'!$C$57,IF(14<=18,'前提'!$C$58,IF(14<=24,'前提'!$C$59,IF(14<=36,'前提'!$C$60,IF(14<=48,'前提'!$C$61,'前提'!$C$62)))))) -> 800000 | P30: ='前提'!$B$28*IF(15<=6,'前提'!$C$56,IF(15<=12,'前提'!$C$57,IF(15<=18,'前提'!$C$58,IF(15<=24,'前提'!$C$59,IF(15<=36,'前提'!$C$60,IF(15<=48,'前提'!$C$61,'前提'!$C$62)))))) -> 800000 | Q30: ='前提'!$B$28*IF(16<=6,'前提'!$C$56,IF(16<=12,'前提'!$C$57,IF(16<=18,'前提'!$C$58,IF(16<=24,'前提'!$C$59,IF(16<=36,'前提'!$C$60,IF(16<=48,'前提'!$C$61,'前提'!$C$62)))))) -> 800000 | R30: ='前提'!$B$28*IF(17<=6,'前提'!$C$56,IF(17<=12,'前提'!$C$57,IF(17<=18,'前提'!$C$58,IF(17<=24,'前提'!$C$59,IF(17<=36,'前提'!$C$60,IF(17<=48,'前提'!$C$61,'前提'!$C$62)))))) -> 800000 | S30: ='前提'!$B$28*IF(18<=6,'前提'!$C$56,IF(18<=12,'前提'!$C$57,IF(18<=18,'前提'!$C$58,IF(18<=24,'前提'!$C$59,IF(18<=36,'前提'!$C$60,IF(18<=48,'前提'!$C$61,'前提'!$C$62)))))) -> 800000 | T30: ='前提'!$B$28*IF(19<=6,'前提'!$C$56,IF(19<=12,'前提'!$C$57,IF(19<=18,'前提'!$C$58,IF(19<=24,'前提'!$C$59,IF(19<=36,'前提'!$C$60,IF(19<=48,'前提'!$C$61,'前提'!$C$62)))))) -> 1000000 | U30: ='前提'!$B$28*IF(20<=6,'前提'!$C$56,IF(20<=12,'前提'!$C$57,IF(20<=18,'前提'!$C$58,IF(20<=24,'前提'!$C$59,IF(20<=36,'前提'!$C$60,IF(20<=48,'前提'!$C$61,'前提'!$C$62)))))) -> 1000000 | V30: ='前提'!$B$28*IF(21<=6,'前提'!$C$56,IF(21<=12,'前提'!$C$57,IF(21<=18,'前提'!$C$58,IF(21<=24,'前提'!$C$59,IF(21<=36,'前提'!$C$60,IF(21<=48,'前提'!$C$61,'前提'!$C$62)))))) -> 1000000 | W30: ='前提'!$B$28*IF(22<=6,'前提'!$C$56,IF(22<=12,'前提'!$C$57,IF(22<=18,'前提'!$C$58,IF(22<=24,'前提'!$C$59,IF(22<=36,'前提'!$C$60,IF(22<=48,'前提'!$C$61,'前提'!$C$62)))))) -> 1000000 | X30: ='前提'!$B$28*IF(23<=6,'前提'!$C$56,IF(23<=12,'前提'!$C$57,IF(23<=18,'前提'!$C$58,IF(23<=24,'前提'!$C$59,IF(23<=36,'前提'!$C$60,IF(23<=48,'前提'!$C$61,'前提'!$C$62)))))) -> 1000000 | Y30: ='前提'!$B$28*IF(24<=6,'前提'!$C$56,IF(24<=12,'前提'!$C$57,IF(24<=18,'前提'!$C$58,IF(24<=24,'前提'!$C$59,IF(24<=36,'前提'!$C$60,IF(24<=48,'前提'!$C$61,'前提'!$C$62)))))) -> 1000000 | Z30: ='前提'!$B$28*IF(25<=6,'前提'!$C$56,IF(25<=12,'前提'!$C$57,IF(25<=18,'前提'!$C$58,IF(25<=24,'前提'!$C$59,IF(25<=36,'前提'!$C$60,IF(25<=48,'前提'!$C$61,'前提'!$C$62)))))) -> 1400000 | AA30: ='前提'!$B$28*IF(26<=6,'前提'!$C$56,IF(26<=12,'前提'!$C$57,IF(26<=18,'前提'!$C$58,IF(26<=24,'前提'!$C$59,IF(26<=36,'前提'!$C$60,IF(26<=48,'前提'!$C$61,'前提'!$C$62)))))) -> 1400000 | AB30: ='前提'!$B$28*IF(27<=6,'前提'!$C$56,IF(27<=12,'前提'!$C$57,IF(27<=18,'前提'!$C$58,IF(27<=24,'前提'!$C$59,IF(27<=36,'前提'!$C$60,IF(27<=48,'前提'!$C$61,'前提'!$C$62)))))) -> 1400000 | AC30: ='前提'!$B$28*IF(28<=6,'前提'!$C$56,IF(28<=12,'前提'!$C$57,IF(28<=18,'前提'!$C$58,IF(28<=24,'前提'!$C$59,IF(28<=36,'前提'!$C$60,IF(28<=48,'前提'!$C$61,'前提'!$C$62)))))) -> 1400000 | AD30: ='前提'!$B$28*IF(29<=6,'前提'!$C$56,IF(29<=12,'前提'!$C$57,IF(29<=18,'前提'!$C$58,IF(29<=24,'前提'!$C$59,IF(29<=36,'前提'!$C$60,IF(29<=48,'前提'!$C$61,'前提'!$C$62)))))) -> 1400000 | AE30: ='前提'!$B$28*IF(30<=6,'前提'!$C$56,IF(30<=12,'前提'!$C$57,IF(30<=18,'前提'!$C$58,IF(30<=24,'前提'!$C$59,IF(30<=36,'前提'!$C$60,IF(30<=48,'前提'!$C$61,'前提'!$C$62)))))) -> 1400000 | AF30: ='前提'!$B$28*IF(31<=6,'前提'!$C$56,IF(31<=12,'前提'!$C$57,IF(31<=18,'前提'!$C$58,IF(31<=24,'前提'!$C$59,IF(31<=36,'前提'!$C$60,IF(31<=48,'前提'!$C$61,'前提'!$C$62)))))) -> 1400000 | AG30: ='前提'!$B$28*IF(32<=6,'前提'!$C$56,IF(32<=12,'前提'!$C$57,IF(32<=18,'前提'!$C$58,IF(32<=24,'前提'!$C$59,IF(32<=36,'前提'!$C$60,IF(32<=48,'前提'!$C$61,'前提'!$C$62)))))) -> 1400000 | AH30: ='前提'!$B$28*IF(33<=6,'前提'!$C$56,IF(33<=12,'前提'!$C$57,IF(33<=18,'前提'!$C$58,IF(33<=24,'前提'!$C$59,IF(33<=36,'前提'!$C$60,IF(33<=48,'前提'!$C$61,'前提'!$C$62)))))) -> 1400000 | AI30: ='前提'!$B$28*IF(34<=6,'前提'!$C$56,IF(34<=12,'前提'!$C$57,IF(34<=18,'前提'!$C$58,IF(34<=24,'前提'!$C$59,IF(34<=36,'前提'!$C$60,IF(34<=48,'前提'!$C$61,'前提'!$C$62)))))) -> 1400000 | AJ30: ='前提'!$B$28*IF(35<=6,'前提'!$C$56,IF(35<=12,'前提'!$C$57,IF(35<=18,'前提'!$C$58,IF(35<=24,'前提'!$C$59,IF(35<=36,'前提'!$C$60,IF(35<=48,'前提'!$C$61,'前提'!$C$62)))))) -> 1400000 | AK30: ='前提'!$B$28*IF(36<=6,'前提'!$C$56,IF(36<=12,'前提'!$C$57,IF(36<=18,'前提'!$C$58,IF(36<=24,'前提'!$C$59,IF(36<=36,'前提'!$C$60,IF(36<=48,'前提'!$C$61,'前提'!$C$62)))))) -> 1400000 | AL30: ='前提'!$B$28*IF(37<=6,'前提'!$C$56,IF(37<=12,'前提'!$C$57,IF(37<=18,'前提'!$C$58,IF(37<=24,'前提'!$C$59,IF(37<=36,'前提'!$C$60,IF(37<=48,'前提'!$C$61,'前提'!$C$62)))))) -> 1800000 | AM30: ='前提'!$B$28*IF(38<=6,'前提'!$C$56,IF(38<=12,'前提'!$C$57,IF(38<=18,'前提'!$C$58,IF(38<=24,'前提'!$C$59,IF(38<=36,'前提'!$C$60,IF(38<=48,'前提'!$C$61,'前提'!$C$62)))))) -> 1800000 | AN30: ='前提'!$B$28*IF(39<=6,'前提'!$C$56,IF(39<=12,'前提'!$C$57,IF(39<=18,'前提'!$C$58,IF(39<=24,'前提'!$C$59,IF(39<=36,'前提'!$C$60,IF(39<=48,'前提'!$C$61,'前提'!$C$62)))))) -> 1800000 | AO30: ='前提'!$B$28*IF(40<=6,'前提'!$C$56,IF(40<=12,'前提'!$C$57,IF(40<=18,'前提'!$C$58,IF(40<=24,'前提'!$C$59,IF(40<=36,'前提'!$C$60,IF(40<=48,'前提'!$C$61,'前提'!$C$62)))))) -> 1800000 | AP30: ='前提'!$B$28*IF(41<=6,'前提'!$C$56,IF(41<=12,'前提'!$C$57,IF(41<=18,'前提'!$C$58,IF(41<=24,'前提'!$C$59,IF(41<=36,'前提'!$C$60,IF(41<=48,'前提'!$C$61,'前提'!$C$62)))))) -> 1800000 | AQ30: ='前提'!$B$28*IF(42<=6,'前提'!$C$56,IF(42<=12,'前提'!$C$57,IF(42<=18,'前提'!$C$58,IF(42<=24,'前提'!$C$59,IF(42<=36,'前提'!$C$60,IF(42<=48,'前提'!$C$61,'前提'!$C$62)))))) -> 1800000 | AR30: ='前提'!$B$28*IF(43<=6,'前提'!$C$56,IF(43<=12,'前提'!$C$57,IF(43<=18,'前提'!$C$58,IF(43<=24,'前提'!$C$59,IF(43<=36,'前提'!$C$60,IF(43<=48,'前提'!$C$61,'前提'!$C$62)))))) -> 1800000 | AS30: ='前提'!$B$28*IF(44<=6,'前提'!$C$56,IF(44<=12,'前提'!$C$57,IF(44<=18,'前提'!$C$58,IF(44<=24,'前提'!$C$59,IF(44<=36,'前提'!$C$60,IF(44<=48,'前提'!$C$61,'前提'!$C$62)))))) -> 1800000 | AT30: ='前提'!$B$28*IF(45<=6,'前提'!$C$56,IF(45<=12,'前提'!$C$57,IF(45<=18,'前提'!$C$58,IF(45<=24,'前提'!$C$59,IF(45<=36,'前提'!$C$60,IF(45<=48,'前提'!$C$61,'前提'!$C$62)))))) -> 1800000 | AU30: ='前提'!$B$28*IF(46<=6,'前提'!$C$56,IF(46<=12,'前提'!$C$57,IF(46<=18,'前提'!$C$58,IF(46<=24,'前提'!$C$59,IF(46<=36,'前提'!$C$60,IF(46<=48,'前提'!$C$61,'前提'!$C$62)))))) -> 1800000 | AV30: ='前提'!$B$28*IF(47<=6,'前提'!$C$56,IF(47<=12,'前提'!$C$57,IF(47<=18,'前提'!$C$58,IF(47<=24,'前提'!$C$59,IF(47<=36,'前提'!$C$60,IF(47<=48,'前提'!$C$61,'前提'!$C$62)))))) -> 1800000 | AW30: ='前提'!$B$28*IF(48<=6,'前提'!$C$56,IF(48<=12,'前提'!$C$57,IF(48<=18,'前提'!$C$58,IF(48<=24,'前提'!$C$59,IF(48<=36,'前提'!$C$60,IF(48<=48,'前提'!$C$61,'前提'!$C$62)))))) -> 1800000 | AX30: ='前提'!$B$28*IF(49<=6,'前提'!$C$56,IF(49<=12,'前提'!$C$57,IF(49<=18,'前提'!$C$58,IF(49<=24,'前提'!$C$59,IF(49<=36,'前提'!$C$60,IF(49<=48,'前提'!$C$61,'前提'!$C$62)))))) -> 2000000 | AY30: ='前提'!$B$28*IF(50<=6,'前提'!$C$56,IF(50<=12,'前提'!$C$57,IF(50<=18,'前提'!$C$58,IF(50<=24,'前提'!$C$59,IF(50<=36,'前提'!$C$60,IF(50<=48,'前提'!$C$61,'前提'!$C$62)))))) -> 2000000 | AZ30: ='前提'!$B$28*IF(51<=6,'前提'!$C$56,IF(51<=12,'前提'!$C$57,IF(51<=18,'前提'!$C$58,IF(51<=24,'前提'!$C$59,IF(51<=36,'前提'!$C$60,IF(51<=48,'前提'!$C$61,'前提'!$C$62)))))) -> 2000000 | BA30: ='前提'!$B$28*IF(52<=6,'前提'!$C$56,IF(52<=12,'前提'!$C$57,IF(52<=18,'前提'!$C$58,IF(52<=24,'前提'!$C$59,IF(52<=36,'前提'!$C$60,IF(52<=48,'前提'!$C$61,'前提'!$C$62)))))) -> 2000000 | BB30: ='前提'!$B$28*IF(53<=6,'前提'!$C$56,IF(53<=12,'前提'!$C$57,IF(53<=18,'前提'!$C$58,IF(53<=24,'前提'!$C$59,IF(53<=36,'前提'!$C$60,IF(53<=48,'前提'!$C$61,'前提'!$C$62)))))) -> 2000000 | BC30: ='前提'!$B$28*IF(54<=6,'前提'!$C$56,IF(54<=12,'前提'!$C$57,IF(54<=18,'前提'!$C$58,IF(54<=24,'前提'!$C$59,IF(54<=36,'前提'!$C$60,IF(54<=48,'前提'!$C$61,'前提'!$C$62)))))) -> 2000000 | BD30: ='前提'!$B$28*IF(55<=6,'前提'!$C$56,IF(55<=12,'前提'!$C$57,IF(55<=18,'前提'!$C$58,IF(55<=24,'前提'!$C$59,IF(55<=36,'前提'!$C$60,IF(55<=48,'前提'!$C$61,'前提'!$C$62)))))) -> 2000000 | BE30: ='前提'!$B$28*IF(56<=6,'前提'!$C$56,IF(56<=12,'前提'!$C$57,IF(56<=18,'前提'!$C$58,IF(56<=24,'前提'!$C$59,IF(56<=36,'前提'!$C$60,IF(56<=48,'前提'!$C$61,'前提'!$C$62)))))) -> 2000000 | BF30: ='前提'!$B$28*IF(57<=6,'前提'!$C$56,IF(57<=12,'前提'!$C$57,IF(57<=18,'前提'!$C$58,IF(57<=24,'前提'!$C$59,IF(57<=36,'前提'!$C$60,IF(57<=48,'前提'!$C$61,'前提'!$C$62)))))) -> 2000000 | BG30: ='前提'!$B$28*IF(58<=6,'前提'!$C$56,IF(58<=12,'前提'!$C$57,IF(58<=18,'前提'!$C$58,IF(58<=24,'前提'!$C$59,IF(58<=36,'前提'!$C$60,IF(58<=48,'前提'!$C$61,'前提'!$C$62)))))) -> 2000000 | BH30: ='前提'!$B$28*IF(59<=6,'前提'!$C$56,IF(59<=12,'前提'!$C$57,IF(59<=18,'前提'!$C$58,IF(59<=24,'前提'!$C$59,IF(59<=36,'前提'!$C$60,IF(59<=48,'前提'!$C$61,'前提'!$C$62)))))) -> 2000000 | BI30: ='前提'!$B$28*IF(60<=6,'前提'!$C$56,IF(60<=12,'前提'!$C$57,IF(60<=18,'前提'!$C$58,IF(60<=24,'前提'!$C$59,IF(60<=36,'前提'!$C$60,IF(60<=48,'前提'!$C$61,'前提'!$C$62)))))) -> 2000000
A31: LLM API変動費 | B31: =(B10+B14)*'前提'!$B$35 -> 12 | C31: =(C10+C14)*'前提'!$B$35 -> 36 | D31: =(D10+D14)*'前提'!$B$35 -> 60 | E31: =(E10+E14)*'前提'!$B$35 -> 84 | F31: =(F10+F14)*'前提'!$B$35 -> 108 | G31: =(G10+G14)*'前提'!$B$35 -> 132 | H31: =(H10+H14)*'前提'!$B$35 -> 192 | I31: =(I10+I14)*'前提'!$B$35 -> 264 | ... BI31: =(BI10+BI14)*'前提'!$B$35 -> 8256
A32: インフラ（Cloud SQL+Run） | B32: =IF((B10+B14)<=50,'前提'!$B$36,IF((B10+B14)<=200,'前提'!$B$37,'前提'!$B$38))+IF((B10+B14)<=50,'前提'!$B$39,IF((B10+B14)<=200,'前提'!$B$40,'前提'!$B$41)) -> 10000 | C32: =IF((C10+C14)<=50,'前提'!$B$36,IF((C10+C14)<=200,'前提'!$B$37,'前提'!$B$38))+IF((C10+C14)<=50,'前提'!$B$39,IF((C10+C14)<=200,'前提'!$B$40,'前提'!$B$41)) -> 10000 | D32: =IF((D10+D14)<=50,'前提'!$B$36,IF((D10+D14)<=200,'前提'!$B$37,'前提'!$B$38))+IF((D10+D14)<=50,'前提'!$B$39,IF((D10+D14)<=200,'前提'!$B$40,'前提'!$B$41)) -> 10000 | E32: =IF((E10+E14)<=50,'前提'!$B$36,IF((E10+E14)<=200,'前提'!$B$37,'前提'!$B$38))+IF((E10+E14)<=50,'前提'!$B$39,IF((E10+E14)<=200,'前提'!$B$40,'前提'!$B$41)) -> 10000 | F32: =IF((F10+F14)<=50,'前提'!$B$36,IF((F10+F14)<=200,'前提'!$B$37,'前提'!$B$38))+IF((F10+F14)<=50,'前提'!$B$39,IF((F10+F14)<=200,'前提'!$B$40,'前提'!$B$41)) -> 10000 | G32: =IF((G10+G14)<=50,'前提'!$B$36,IF((G10+G14)<=200,'前提'!$B$37,'前提'!$B$38))+IF((G10+G14)<=50,'前提'!$B$39,IF((G10+G14)<=200,'前提'!$B$40,'前提'!$B$41)) -> 10000 | H32: =IF((H10+H14)<=50,'前提'!$B$36,IF((H10+H14)<=200,'前提'!$B$37,'前提'!$B$38))+IF((H10+H14)<=50,'前提'!$B$39,IF((H10+H14)<=200,'前提'!$B$40,'前提'!$B$41)) -> 10000 | I32: =IF((I10+I14)<=50,'前提'!$B$36,IF((I10+I14)<=200,'前提'!$B$37,'前提'!$B$38))+IF((I10+I14)<=50,'前提'!$B$39,IF((I10+I14)<=200,'前提'!$B$40,'前提'!$B$41)) -> 10000 | ... BI32: =IF((BI10+BI14)<=50,'前提'!$B$36,IF((BI10+BI14)<=200,'前提'!$B$37,'前提'!$B$38))+IF((BI10+BI14)<=50,'前提'!$B$39,IF((BI10+BI14)<=200,'前提'!$B$40,'前提'!$B$41)) -> 40000
A33: 営業/GTM | B33: ='前提'!$B$31 -> 100000 | C33: ='前提'!$B$31 -> 100000 | D33: ='前提'!$B$31 -> 100000 | E33: ='前提'!$B$31 -> 100000 | F33: ='前提'!$B$31 -> 100000 | G33: ='前提'!$B$31 -> 100000 | H33: ='前提'!$B$31 -> 100000 | I33: ='前提'!$B$31 -> 100000 | ... BI33: ='前提'!$B$31 -> 100000
A34: その他固定費 | B34: ='前提'!$B$32 -> 200000 | C34: ='前提'!$B$32 -> 200000 | D34: ='前提'!$B$32 -> 200000 | E34: ='前提'!$B$32 -> 200000 | F34: ='前提'!$B$32 -> 200000 | G34: ='前提'!$B$32 -> 200000 | H34: ='前提'!$B$32 -> 200000 | I34: ='前提'!$B$32 -> 200000 | ... BI34: ='前提'!$B$32 -> 200000
A35: コスト合計 | B35: =SUM(B25:B34) -> 1132512 | C35: =SUM(C25:C34) -> 1132536 | D35: =SUM(D25:D34) -> 1132560 | E35: =SUM(E25:E34) -> 1132584 | F35: =SUM(F25:F34) -> 1132608 | G35: =SUM(G25:G34) -> 1132632 | H35: =SUM(H25:H34) -> 2160192 | I35: =SUM(I25:I34) -> 2160264 | ... BI35: =SUM(BI25:BI34) -> 10898256
A37: 【損益】
A38: 営業利益 | B38: =B22-B35 -> -1121012 | C38: =C22-C35 -> -648036 | D38: =D22-D35 -> -625060 | E38: =E22-E35 -> -602084 | F38: =F22-F35 -> -579108 | G38: =G22-G35 -> -556132 | H38: =H22-H35 -> -851192 | I38: =I22-I35 -> -643764 | ... BI38: =BI22-BI35 -> 68139244
A39: 営業利益率 | B39: =IF(B22<>0,B38/B22,0) -> -97.479304 | C39: =IF(C22<>0,C38/C22,0) -> -1.3375356 | D39: =IF(D22<>0,D38/D22,0) -> -1.2316453 | E39: =IF(E22<>0,E38/E22,0) -> -1.1349369 | F39: =IF(F22<>0,F38/F22,0) -> -1.0462656 | G39: =IF(G22<>0,G38/G22,0) -> -0.96466956 | H39: =IF(H22<>0,H38/H22,0) -> -0.65026127 | I39: =IF(I22<>0,I38/I22,0) -> -0.42450643 | ... BI39: =IF(BI22<>0,BI38/BI22,0) -> 0.86211285
A40: 累積損益 | B40: =B38 -> -1121012 | C40: =B40+C38 -> -1769048 | D40: =C40+D38 -> -2394108 | E40: =D40+E38 -> -2996192 | F40: =E40+F38 -> -3575300 | G40: =F40+G38 -> -4131432 | H40: =G40+H38 -> -4982624 | I40: =H40+I38 -> -5626388 | J40: =I40+J38 -> -6062724 | ... BI40: =BH40+BI38 -> 1184974708
A41: MRRベース損益 | B41: =B21-B35 -> -1121012 | C41: =C21-C35 -> -1098036 | D41: =D21-D35 -> -1075060 | E41: =E21-E35 -> -1052084 | F41: =F21-F35 -> -1029108 | G41: =G21-G35 -> -1006132 | H41: =H21-H35 -> -1976192 | I41: =I21-I35 -> -1768764 | ... BI41: =BI21-BI35 -> 65439244
A43: 【キャッシュフロー】
A44: 調達資金 | B44: ='前提'!B77+'前提'!B78+'前提'!B79+'前提'!B80 -> 37500000 | C44: 0 | D44: 0 | E44: 0 | F44: 0 | G44: 0 | H44: 0 | I44: 0 | J44: 0 | K44: 0 | L44: 0 | M44: 0 | N44: 0 | O44: 0 | P44: 0 | Q44: 0 | R44: 0 | S44: 0 | T44: 0 | U44: 0 | V44: 0 | W44: 0 | X44: 0 | Y44: 0 | Z44: 0 | AA44: 0 | AB44: 0 | AC44: 0 | AD44: 0 | AE44: 0 | AF44: 0 | AG44: 0 | AH44: 0 | AI44: 0 | AJ44: 0 | AK44: 0 | AL44: 0 | AM44: 0 | AN44: 0 | AO44: 0 | AP44: 0 | AQ44: 0 | AR44: 0 | AS44: 0 | AT44: 0 | AU44: 0 | AV44: 0 | AW44: 0 | AX44: 0 | AY44: 0 | AZ44: 0 | BA44: 0 | BB44: 0 | BC44: 0 | BD44: 0 | BE44: 0 | BF44: 0 | BG44: 0 | BH44: 0 | BI44: 0
A45: Series A入金 | B45: =IF(1='前提'!$B$87,'前提'!$B$85,0) -> 0 | C45: =IF(2='前提'!$B$87,'前提'!$B$85,0) -> 0 | D45: =IF(3='前提'!$B$87,'前提'!$B$85,0) -> 0 | E45: =IF(4='前提'!$B$87,'前提'!$B$85,0) -> 0 | F45: =IF(5='前提'!$B$87,'前提'!$B$85,0) -> 0 | G45: =IF(6='前提'!$B$87,'前提'!$B$85,0) -> 0 | H45: =IF(7='前提'!$B$87,'前提'!$B$85,0) -> 0 | I45: =IF(8='前提'!$B$87,'前提'!$B$85,0) -> 0 | J45: =IF(9='前提'!$B$87,'前提'!$B$85,0) -> 0 | K45: =IF(10='前提'!$B$87,'前提'!$B$85,0) -> 0 | L45: =IF(11='前提'!$B$87,'前提'!$B$85,0) -> 0 | M45: =IF(12='前提'!$B$87,'前提'!$B$85,0) -> 0 | N45: =IF(13='前提'!$B$87,'前提'!$B$85,0) -> 0 | O45: =IF(14='前提'!$B$87,'前提'!$B$85,0) -> 0 | P45: =IF(15='前提'!$B$87,'前提'!$B$85,0) -> 0 | Q45: =IF(16='前提'!$B$87,'前提'!$B$85,0) -> 0 | R45: =IF(17='前提'!$B$87,'前提'!$B$85,0) -> 0 | S45: =IF(18='前提'!$B$87,'前提'!$B$85,0) -> 0 | T45: =IF(19='前提'!$B$87,'前提'!$B$85,0) -> 0 | U45: =IF(20='前提'!$B$87,'前提'!$B$85,0) -> 0 | V45: =IF(21='前提'!$B$87,'前提'!$B$85,0) -> 0 | W45: =IF(22='前提'!$B$87,'前提'!$B$85,0) -> 0 | X45: =IF(23='前提'!$B$87,'前提'!$B$85,0) -> 0 | Y45: =IF(24='前提'!$B$87,'前提'!$B$85,0) -> 100000000 | Z45: =IF(25='前提'!$B$87,'前提'!$B$85,0) -> 0 | AA45: =IF(26='前提'!$B$87,'前提'!$B$85,0) -> 0 | AB45: =IF(27='前提'!$B$87,'前提'!$B$85,0) -> 0 | AC45: =IF(28='前提'!$B$87,'前提'!$B$85,0) -> 0 | AD45: =IF(29='前提'!$B$87,'前提'!$B$85,0) -> 0 | AE45: =IF(30='前提'!$B$87,'前提'!$B$85,0) -> 0 | AF45: =IF(31='前提'!$B$87,'前提'!$B$85,0) -> 0 | AG45: =IF(32='前提'!$B$87,'前提'!$B$85,0) -> 0 | AH45: =IF(33='前提'!$B$87,'前提'!$B$85,0) -> 0 | AI45: =IF(34='前提'!$B$87,'前提'!$B$85,0) -> 0 | AJ45: =IF(35='前提'!$B$87,'前提'!$B$85,0) -> 0 | AK45: =IF(36='前提'!$B$87,'前提'!$B$85,0) -> 0 | AL45: =IF(37='前提'!$B$87,'前提'!$B$85,0) -> 0 | AM45: =IF(38='前提'!$B$87,'前提'!$B$85,0) -> 0 | AN45: =IF(39='前提'!$B$87,'前提'!$B$85,0) -> 0 | AO45: =IF(40='前提'!$B$87,'前提'!$B$85,0) -> 0 | AP45: =IF(41='前提'!$B$87,'前提'!$B$85,0) -> 0 | AQ45: =IF(42='前提'!$B$87,'前提'!$B$85,0) -> 0 | AR45: =IF(43='前提'!$B$87,'前提'!$B$85,0) -> 0 | AS45: =IF(44='前提'!$B$87,'前提'!$B$85,0) -> 0 | AT45: =IF(45='前提'!$B$87,'前提'!$B$85,0) -> 0 | AU45: =IF(46='前提'!$B$87,'前提'!$B$85,0) -> 0 | AV45: =IF(47='前提'!$B$87,'前提'!$B$85,0) -> 0 | AW45: =IF(48='前提'!$B$87,'前提'!$B$85,0) -> 0 | AX45: =IF(49='前提'!$B$87,'前提'!$B$85,0) -> 0 | AY45: =IF(50='前提'!$B$87,'前提'!$B$85,0) -> 0 | AZ45: =IF(51='前提'!$B$87,'前提'!$B$85,0) -> 0 | BA45: =IF(52='前提'!$B$87,'前提'!$B$85,0) -> 0 | BB45: =IF(53='前提'!$B$87,'前提'!$B$85,0) -> 0 | BC45: =IF(54='前提'!$B$87,'前提'!$B$85,0) -> 0 | BD45: =IF(55='前提'!$B$87,'前提'!$B$85,0) -> 0 | BE45: =IF(56='前提'!$B$87,'前提'!$B$85,0) -> 0 | BF45: =IF(57='前提'!$B$87,'前提'!$B$85,0) -> 0 | BG45: =IF(58='前提'!$B$87,'前提'!$B$85,0) -> 0 | BH45: =IF(59='前提'!$B$87,'前提'!$B$85,0) -> 0 | BI45: =IF(60='前提'!$B$87,'前提'!$B$85,0) -> 0
A46: 公庫利息 | B46: ='前提'!$B$80*'前提'!$B$81/12 -> 6250 | C46: ='前提'!$B$80*'前提'!$B$81/12 -> 6250 | D46: ='前提'!$B$80*'前提'!$B$81/12 -> 6250 | E46: ='前提'!$B$80*'前提'!$B$81/12 -> 6250 | F46: ='前提'!$B$80*'前提'!$B$81/12 -> 6250 | G46: ='前提'!$B$80*'前提'!$B$81/12 -> 6250 | H46: ='前提'!$B$80*'前提'!$B$81/12 -> 6250 | I46: ='前提'!$B$80*'前提'!$B$81/12 -> 6250 | ... BI46: ='前提'!$B$80*'前提'!$B$81/12 -> 6250
A47: キャッシュ残高 | B47: =B44+B45+B22-B35-B46 -> 36372738 | C47: =B47+C44+C45+C22-C35-C46 -> 35718452 | D47: =C47+D44+D45+D22-D35-D46 -> 35087142 | E47: =D47+E44+E45+E22-E35-E46 -> 34478808 | F47: =E47+F44+F45+F22-F35-F46 -> 33893450 | G47: =F47+G44+G45+G22-G35-G46 -> 33331068 | H47: =G47+H44+H45+H22-H35-H46 -> 32473626 | I47: =H47+I44+I45+I22-I35-I46 -> 31823612 | J47: =I47+J44+J45+J22-J35-J46 -> 31381026 | ... BI47: =BH47+BI44+BI45+BI22-BI35-BI46 -> 1322099708
A48: ランウェイ（月） | B48: =IF(B47>0,IF(B35>0,B47/B35,999),0) -> 32.116868 | C48: =IF(C47>0,IF(C35>0,C47/C35,999),0) -> 31.538469 | D48: =IF(D47>0,IF(D35>0,D47/D35,999),0) -> 30.980383 | E48: =IF(E47>0,IF(E35>0,E47/E35,999),0) -> 30.442606 | F48: =IF(F47>0,IF(F35>0,F47/F35,999),0) -> 29.925137 | G48: =IF(G47>0,IF(G35>0,G47/G35,999),0) -> 29.427977 | H48: =IF(H47>0,IF(H35>0,H47/H35,999),0) -> 15.03275 | I48: =IF(I47>0,IF(I35>0,I47/I35,999),0) -> 14.731353 | ... BI48: =IF(BI47>0,IF(BI35>0,BI47/BI35,999),0) -> 121.31296
A50: 【人員数】
A51: CEO | B51: 1 | C51: 1 | D51: 1 | E51: 1 | F51: 1 | G51: 1 | H51: 1 | I51: 1 | J51: 1 | K51: 1 | L51: 1 | M51: 1 | N51: 1 | O51: 1 | P51: 1 | Q51: 1 | R51: 1 | S51: 1 | T51: 1 | U51: 1 | V51: 1 | W51: 1 | X51: 1 | Y51: 1 | Z51: 1 | AA51: 1 | AB51: 1 | AC51: 1 | AD51: 1 | AE51: 1 | AF51: 1 | AG51: 1 | AH51: 1 | AI51: 1 | AJ51: 1 | AK51: 1 | AL51: 1 | AM51: 1 | AN51: 1 | AO51: 1 | AP51: 1 | AQ51: 1 | AR51: 1 | AS51: 1 | AT51: 1 | AU51: 1 | AV51: 1 | AW51: 1 | AX51: 1 | AY51: 1 | AZ51: 1 | BA51: 1 | BB51: 1 | BC51: 1 | BD51: 1 | BE51: 1 | BF51: 1 | BG51: 1 | BH51: 1 | BI51: 1
A52: エンジニア（換算） | B52: =IF(1<=6,'前提'!$B$24/160,IF(1<=12,'前提'!$B$25/160,IF(1<=18,'前提'!$B$49,IF(1<=24,'前提'!$B$50,IF(1<=36,'前提'!$B$51,IF(1<=48,'前提'!$B$52,'前提'!$B$53)))))) -> 0.403125 | C52: =IF(2<=6,'前提'!$B$24/160,IF(2<=12,'前提'!$B$25/160,IF(2<=18,'前提'!$B$49,IF(2<=24,'前提'!$B$50,IF(2<=36,'前提'!$B$51,IF(2<=48,'前提'!$B$52,'前提'!$B$53)))))) -> 0.403125 | D52: =IF(3<=6,'前提'!$B$24/160,IF(3<=12,'前提'!$B$25/160,IF(3<=18,'前提'!$B$49,IF(3<=24,'前提'!$B$50,IF(3<=36,'前提'!$B$51,IF(3<=48,'前提'!$B$52,'前提'!$B$53)))))) -> 0.403125 | E52: =IF(4<=6,'前提'!$B$24/160,IF(4<=12,'前提'!$B$25/160,IF(4<=18,'前提'!$B$49,IF(4<=24,'前提'!$B$50,IF(4<=36,'前提'!$B$51,IF(4<=48,'前提'!$B$52,'前提'!$B$53)))))) -> 0.403125 | F52: =IF(5<=6,'前提'!$B$24/160,IF(5<=12,'前提'!$B$25/160,IF(5<=18,'前提'!$B$49,IF(5<=24,'前提'!$B$50,IF(5<=36,'前提'!$B$51,IF(5<=48,'前提'!$B$52,'前提'!$B$53)))))) -> 0.403125 | G52: =IF(6<=6,'前提'!$B$24/160,IF(6<=12,'前提'!$B$25/160,IF(6<=18,'前提'!$B$49,IF(6<=24,'前提'!$B$50,IF(6<=36,'前提'!$B$51,IF(6<=48,'前提'!$B$52,'前提'!$B$53)))))) -> 0.403125 | H52: =IF(7<=6,'前提'!$B$24/160,IF(7<=12,'前提'!$B$25/160,IF(7<=18,'前提'!$B$49,IF(7<=24,'前提'!$B$50,IF(7<=36,'前提'!$B$51,IF(7<=48,'前提'!$B$52,'前提'!$B$53)))))) -> 0.25 | I52: =IF(8<=6,'前提'!$B$24/160,IF(8<=12,'前提'!$B$25/160,IF(8<=18,'前提'!$B$49,IF(8<=24,'前提'!$B$50,IF(8<=36,'前提'!$B$51,IF(8<=48,'前提'!$B$52,'前提'!$B$53)))))) -> 0.25 | J52: =IF(9<=6,'前提'!$B$24/160,IF(9<=12,'前提'!$B$25/160,IF(9<=18,'前提'!$B$49,IF(9<=24,'前提'!$B$50,IF(9<=36,'前提'!$B$51,IF(9<=48,'前提'!$B$52,'前提'!$B$53)))))) -> 0.25 | K52: =IF(10<=6,'前提'!$B$24/160,IF(10<=12,'前提'!$B$25/160,IF(10<=18,'前提'!$B$49,IF(10<=24,'前提'!$B$50,IF(10<=36,'前提'!$B$51,IF(10<=48,'前提'!$B$52,'前提'!$B$53)))))) -> 0.25 | L52: =IF(11<=6,'前提'!$B$24/160,IF(11<=12,'前提'!$B$25/160,IF(11<=18,'前提'!$B$49,IF(11<=24,'前提'!$B$50,IF(11<=36,'前提'!$B$51,IF(11<=48,'前提'!$B$52,'前提'!$B$53)))))) -> 0.25 | M52: =IF(12<=6,'前提'!$B$24/160,IF(12<=12,'前提'!$B$25/160,IF(12<=18,'前提'!$B$49,IF(12<=24,'前提'!$B$50,IF(12<=36,'前提'!$B$51,IF(12<=48,'前提'!$B$52,'前提'!$B$53)))))) -> 0.25 | N52: =IF(13<=6,'前提'!$B$24/160,IF(13<=12,'前提'!$B$25/160,IF(13<=18,'前提'!$B$49,IF(13<=24,'前提'!$B$50,IF(13<=36,'前提'!$B$51,IF(13<=48,'前提'!$B$52,'前提'!$B$53)))))) -> 1 | O52: =IF(14<=6,'前提'!$B$24/160,IF(14<=12,'前提'!$B$25/160,IF(14<=18,'前提'!$B$49,IF(14<=24,'前提'!$B$50,IF(14<=36,'前提'!$B$51,IF(14<=48,'前提'!$B$52,'前提'!$B$53)))))) -> 1 | P52: =IF(15<=6,'前提'!$B$24/160,IF(15<=12,'前提'!$B$25/160,IF(15<=18,'前提'!$B$49,IF(15<=24,'前提'!$B$50,IF(15<=36,'前提'!$B$51,IF(15<=48,'前提'!$B$52,'前提'!$B$53)))))) -> 1 | Q52: =IF(16<=6,'前提'!$B$24/160,IF(16<=12,'前提'!$B$25/160,IF(16<=18,'前提'!$B$49,IF(16<=24,'前提'!$B$50,IF(16<=36,'前提'!$B$51,IF(16<=48,'前提'!$B$52,'前提'!$B$53)))))) -> 1 | R52: =IF(17<=6,'前提'!$B$24/160,IF(17<=12,'前提'!$B$25/160,IF(17<=18,'前提'!$B$49,IF(17<=24,'前提'!$B$50,IF(17<=36,'前提'!$B$51,IF(17<=48,'前提'!$B$52,'前提'!$B$53)))))) -> 1 | S52: =IF(18<=6,'前提'!$B$24/160,IF(18<=12,'前提'!$B$25/160,IF(18<=18,'前提'!$B$49,IF(18<=24,'前提'!$B$50,IF(18<=36,'前提'!$B$51,IF(18<=48,'前提'!$B$52,'前提'!$B$53)))))) -> 1 | T52: =IF(19<=6,'前提'!$B$24/160,IF(19<=12,'前提'!$B$25/160,IF(19<=18,'前提'!$B$49,IF(19<=24,'前提'!$B$50,IF(19<=36,'前提'!$B$51,IF(19<=48,'前提'!$B$52,'前提'!$B$53)))))) -> 1 | U52: =IF(20<=6,'前提'!$B$24/160,IF(20<=12,'前提'!$B$25/160,IF(20<=18,'前提'!$B$49,IF(20<=24,'前提'!$B$50,IF(20<=36,'前提'!$B$51,IF(20<=48,'前提'!$B$52,'前提'!$B$53)))))) -> 1 | V52: =IF(21<=6,'前提'!$B$24/160,IF(21<=12,'前提'!$B$25/160,IF(21<=18,'前提'!$B$49,IF(21<=24,'前提'!$B$50,IF(21<=36,'前提'!$B$51,IF(21<=48,'前提'!$B$52,'前提'!$B$53)))))) -> 1 | W52: =IF(22<=6,'前提'!$B$24/160,IF(22<=12,'前提'!$B$25/160,IF(22<=18,'前提'!$B$49,IF(22<=24,'前提'!$B$50,IF(22<=36,'前提'!$B$51,IF(22<=48,'前提'!$B$52,'前提'!$B$53)))))) -> 1 | X52: =IF(23<=6,'前提'!$B$24/160,IF(23<=12,'前提'!$B$25/160,IF(23<=18,'前提'!$B$49,IF(23<=24,'前提'!$B$50,IF(23<=36,'前提'!$B$51,IF(23<=48,'前提'!$B$52,'前提'!$B$53)))))) -> 1 | Y52: =IF(24<=6,'前提'!$B$24/160,IF(24<=12,'前提'!$B$25/160,IF(24<=18,'前提'!$B$49,IF(24<=24,'前提'!$B$50,IF(24<=36,'前提'!$B$51,IF(24<=48,'前提'!$B$52,'前提'!$B$53)))))) -> 1 | Z52: =IF(25<=6,'前提'!$B$24/160,IF(25<=12,'前提'!$B$25/160,IF(25<=18,'前提'!$B$49,IF(25<=24,'前提'!$B$50,IF(25<=36,'前提'!$B$51,IF(25<=48,'前提'!$B$52,'前提'!$B$53)))))) -> 2 | AA52: =IF(26<=6,'前提'!$B$24/160,IF(26<=12,'前提'!$B$25/160,IF(26<=18,'前提'!$B$49,IF(26<=24,'前提'!$B$50,IF(26<=36,'前提'!$B$51,IF(26<=48,'前提'!$B$52,'前提'!$B$53)))))) -> 2 | AB52: =IF(27<=6,'前提'!$B$24/160,IF(27<=12,'前提'!$B$25/160,IF(27<=18,'前提'!$B$49,IF(27<=24,'前提'!$B$50,IF(27<=36,'前提'!$B$51,IF(27<=48,'前提'!$B$52,'前提'!$B$53)))))) -> 2 | AC52: =IF(28<=6,'前提'!$B$24/160,IF(28<=12,'前提'!$B$25/160,IF(28<=18,'前提'!$B$49,IF(28<=24,'前提'!$B$50,IF(28<=36,'前提'!$B$51,IF(28<=48,'前提'!$B$52,'前提'!$B$53)))))) -> 2 | AD52: =IF(29<=6,'前提'!$B$24/160,IF(29<=12,'前提'!$B$25/160,IF(29<=18,'前提'!$B$49,IF(29<=24,'前提'!$B$50,IF(29<=36,'前提'!$B$51,IF(29<=48,'前提'!$B$52,'前提'!$B$53)))))) -> 2 | AE52: =IF(30<=6,'前提'!$B$24/160,IF(30<=12,'前提'!$B$25/160,IF(30<=18,'前提'!$B$49,IF(30<=24,'前提'!$B$50,IF(30<=36,'前提'!$B$51,IF(30<=48,'前提'!$B$52,'前提'!$B$53)))))) -> 2 | AF52: =IF(31<=6,'前提'!$B$24/160,IF(31<=12,'前提'!$B$25/160,IF(31<=18,'前提'!$B$49,IF(31<=24,'前提'!$B$50,IF(31<=36,'前提'!$B$51,IF(31<=48,'前提'!$B$52,'前提'!$B$53)))))) -> 2 | AG52: =IF(32<=6,'前提'!$B$24/160,IF(32<=12,'前提'!$B$25/160,IF(32<=18,'前提'!$B$49,IF(32<=24,'前提'!$B$50,IF(32<=36,'前提'!$B$51,IF(32<=48,'前提'!$B$52,'前提'!$B$53)))))) -> 2 | AH52: =IF(33<=6,'前提'!$B$24/160,IF(33<=12,'前提'!$B$25/160,IF(33<=18,'前提'!$B$49,IF(33<=24,'前提'!$B$50,IF(33<=36,'前提'!$B$51,IF(33<=48,'前提'!$B$52,'前提'!$B$53)))))) -> 2 | AI52: =IF(34<=6,'前提'!$B$24/160,IF(34<=12,'前提'!$B$25/160,IF(34<=18,'前提'!$B$49,IF(34<=24,'前提'!$B$50,IF(34<=36,'前提'!$B$51,IF(34<=48,'前提'!$B$52,'前提'!$B$53)))))) -> 2 | AJ52: =IF(35<=6,'前提'!$B$24/160,IF(35<=12,'前提'!$B$25/160,IF(35<=18,'前提'!$B$49,IF(35<=24,'前提'!$B$50,IF(35<=36,'前提'!$B$51,IF(35<=48,'前提'!$B$52,'前提'!$B$53)))))) -> 2 | AK52: =IF(36<=6,'前提'!$B$24/160,IF(36<=12,'前提'!$B$25/160,IF(36<=18,'前提'!$B$49,IF(36<=24,'前提'!$B$50,IF(36<=36,'前提'!$B$51,IF(36<=48,'前提'!$B$52,'前提'!$B$53)))))) -> 2 | AL52: =IF(37<=6,'前提'!$B$24/160,IF(37<=12,'前提'!$B$25/160,IF(37<=18,'前提'!$B$49,IF(37<=24,'前提'!$B$50,IF(37<=36,'前提'!$B$51,IF(37<=48,'前提'!$B$52,'前提'!$B$53)))))) -> 2 | AM52: =IF(38<=6,'前提'!$B$24/160,IF(38<=12,'前提'!$B$25/160,IF(38<=18,'前提'!$B$49,IF(38<=24,'前提'!$B$50,IF(38<=36,'前提'!$B$51,IF(38<=48,'前提'!$B$52,'前提'!$B$53)))))) -> 2 | AN52: =IF(39<=6,'前提'!$B$24/160,IF(39<=12,'前提'!$B$25/160,IF(39<=18,'前提'!$B$49,IF(39<=24,'前提'!$B$50,IF(39<=36,'前提'!$B$51,IF(39<=48,'前提'!$B$52,'前提'!$B$53)))))) -> 2 | AO52: =IF(40<=6,'前提'!$B$24/160,IF(40<=12,'前提'!$B$25/160,IF(40<=18,'前提'!$B$49,IF(40<=24,'前提'!$B$50,IF(40<=36,'前提'!$B$51,IF(40<=48,'前提'!$B$52,'前提'!$B$53)))))) -> 2 | AP52: =IF(41<=6,'前提'!$B$24/160,IF(41<=12,'前提'!$B$25/160,IF(41<=18,'前提'!$B$49,IF(41<=24,'前提'!$B$50,IF(41<=36,'前提'!$B$51,IF(41<=48,'前提'!$B$52,'前提'!$B$53)))))) -> 2 | AQ52: =IF(42<=6,'前提'!$B$24/160,IF(42<=12,'前提'!$B$25/160,IF(42<=18,'前提'!$B$49,IF(42<=24,'前提'!$B$50,IF(42<=36,'前提'!$B$51,IF(42<=48,'前提'!$B$52,'前提'!$B$53)))))) -> 2 | AR52: =IF(43<=6,'前提'!$B$24/160,IF(43<=12,'前提'!$B$25/160,IF(43<=18,'前提'!$B$49,IF(43<=24,'前提'!$B$50,IF(43<=36,'前提'!$B$51,IF(43<=48,'前提'!$B$52,'前提'!$B$53)))))) -> 2 | AS52: =IF(44<=6,'前提'!$B$24/160,IF(44<=12,'前提'!$B$25/160,IF(44<=18,'前提'!$B$49,IF(44<=24,'前提'!$B$50,IF(44<=36,'前提'!$B$51,IF(44<=48,'前提'!$B$52,'前提'!$B$53)))))) -> 2 | AT52: =IF(45<=6,'前提'!$B$24/160,IF(45<=12,'前提'!$B$25/160,IF(45<=18,'前提'!$B$49,IF(45<=24,'前提'!$B$50,IF(45<=36,'前提'!$B$51,IF(45<=48,'前提'!$B$52,'前提'!$B$53)))))) -> 2 | AU52: =IF(46<=6,'前提'!$B$24/160,IF(46<=12,'前提'!$B$25/160,IF(46<=18,'前提'!$B$49,IF(46<=24,'前提'!$B$50,IF(46<=36,'前提'!$B$51,IF(46<=48,'前提'!$B$52,'前提'!$B$53)))))) -> 2 | AV52: =IF(47<=6,'前提'!$B$24/160,IF(47<=12,'前提'!$B$25/160,IF(47<=18,'前提'!$B$49,IF(47<=24,'前提'!$B$50,IF(47<=36,'前提'!$B$51,IF(47<=48,'前提'!$B$52,'前提'!$B$53)))))) -> 2 | AW52: =IF(48<=6,'前提'!$B$24/160,IF(48<=12,'前提'!$B$25/160,IF(48<=18,'前提'!$B$49,IF(48<=24,'前提'!$B$50,IF(48<=36,'前提'!$B$51,IF(48<=48,'前提'!$B$52,'前提'!$B$53)))))) -> 2 | AX52: =IF(49<=6,'前提'!$B$24/160,IF(49<=12,'前提'!$B$25/160,IF(49<=18,'前提'!$B$49,IF(49<=24,'前提'!$B$50,IF(49<=36,'前提'!$B$51,IF(49<=48,'前提'!$B$52,'前提'!$B$53)))))) -> 2 | AY52: =IF(50<=6,'前提'!$B$24/160,IF(50<=12,'前提'!$B$25/160,IF(50<=18,'前提'!$B$49,IF(50<=24,'前提'!$B$50,IF(50<=36,'前提'!$B$51,IF(50<=48,'前提'!$B$52,'前提'!$B$53)))))) -> 2 | AZ52: =IF(51<=6,'前提'!$B$24/160,IF(51<=12,'前提'!$B$25/160,IF(51<=18,'前提'!$B$49,IF(51<=24,'前提'!$B$50,IF(51<=36,'前提'!$B$51,IF(51<=48,'前提'!$B$52,'前提'!$B$53)))))) -> 2 | BA52: =IF(52<=6,'前提'!$B$24/160,IF(52<=12,'前提'!$B$25/160,IF(52<=18,'前提'!$B$49,IF(52<=24,'前提'!$B$50,IF(52<=36,'前提'!$B$51,IF(52<=48,'前提'!$B$52,'前提'!$B$53)))))) -> 2 | BB52: =IF(53<=6,'前提'!$B$24/160,IF(53<=12,'前提'!$B$25/160,IF(53<=18,'前提'!$B$49,IF(53<=24,'前提'!$B$50,IF(53<=36,'前提'!$B$51,IF(53<=48,'前提'!$B$52,'前提'!$B$53)))))) -> 2 | BC52: =IF(54<=6,'前提'!$B$24/160,IF(54<=12,'前提'!$B$25/160,IF(54<=18,'前提'!$B$49,IF(54<=24,'前提'!$B$50,IF(54<=36,'前提'!$B$51,IF(54<=48,'前提'!$B$52,'前提'!$B$53)))))) -> 2 | BD52: =IF(55<=6,'前提'!$B$24/160,IF(55<=12,'前提'!$B$25/160,IF(55<=18,'前提'!$B$49,IF(55<=24,'前提'!$B$50,IF(55<=36,'前提'!$B$51,IF(55<=48,'前提'!$B$52,'前提'!$B$53)))))) -> 2 | BE52: =IF(56<=6,'前提'!$B$24/160,IF(56<=12,'前提'!$B$25/160,IF(56<=18,'前提'!$B$49,IF(56<=24,'前提'!$B$50,IF(56<=36,'前提'!$B$51,IF(56<=48,'前提'!$B$52,'前提'!$B$53)))))) -> 2 | BF52: =IF(57<=6,'前提'!$B$24/160,IF(57<=12,'前提'!$B$25/160,IF(57<=18,'前提'!$B$49,IF(57<=24,'前提'!$B$50,IF(57<=36,'前提'!$B$51,IF(57<=48,'前提'!$B$52,'前提'!$B$53)))))) -> 2 | BG52: =IF(58<=6,'前提'!$B$24/160,IF(58<=12,'前提'!$B$25/160,IF(58<=18,'前提'!$B$49,IF(58<=24,'前提'!$B$50,IF(58<=36,'前提'!$B$51,IF(58<=48,'前提'!$B$52,'前提'!$B$53)))))) -> 2 | BH52: =IF(59<=6,'前提'!$B$24/160,IF(59<=12,'前提'!$B$25/160,IF(59<=18,'前提'!$B$49,IF(59<=24,'前提'!$B$50,IF(59<=36,'前提'!$B$51,IF(59<=48,'前提'!$B$52,'前提'!$B$53)))))) -> 2 | BI52: =IF(60<=6,'前提'!$B$24/160,IF(60<=12,'前提'!$B$25/160,IF(60<=18,'前提'!$B$49,IF(60<=24,'前提'!$B$50,IF(60<=36,'前提'!$B$51,IF(60<=48,'前提'!$B$52,'前提'!$B$53)))))) -> 2
A53: CS人数 | B53: =IF(1<=6,0,CEILING(B10/'前提'!$B$44,1)) -> 0 | C53: =IF(2<=6,0,CEILING(C10/'前提'!$B$44,1)) -> 0 | D53: =IF(3<=6,0,CEILING(D10/'前提'!$B$44,1)) -> 0 | E53: =IF(4<=6,0,CEILING(E10/'前提'!$B$44,1)) -> 0 | F53: =IF(5<=6,0,CEILING(F10/'前提'!$B$44,1)) -> 0 | G53: =IF(6<=6,0,CEILING(G10/'前提'!$B$44,1)) -> 0 | H53: =IF(7<=6,0,CEILING(H10/'前提'!$B$44,1)) -> 1 | I53: =IF(8<=6,0,CEILING(I10/'前提'!$B$44,1)) -> 1 | J53: =IF(9<=6,0,CEILING(J10/'前提'!$B$44,1)) -> 1 | K53: =IF(10<=6,0,CEILING(K10/'前提'!$B$44,1)) -> 2 | L53: =IF(11<=6,0,CEILING(L10/'前提'!$B$44,1)) -> 2 | M53: =IF(12<=6,0,CEILING(M10/'前提'!$B$44,1)) -> 2 | N53: =IF(13<=6,0,CEILING(N10/'前提'!$B$44,1)) -> 2 | O53: =IF(14<=6,0,CEILING(O10/'前提'!$B$44,1)) -> 2 | P53: =IF(15<=6,0,CEILING(P10/'前提'!$B$44,1)) -> 2 | Q53: =IF(16<=6,0,CEILING(Q10/'前提'!$B$44,1)) -> 2 | R53: =IF(17<=6,0,CEILING(R10/'前提'!$B$44,1)) -> 3 | S53: =IF(18<=6,0,CEILING(S10/'前提'!$B$44,1)) -> 3 | T53: =IF(19<=6,0,CEILING(T10/'前提'!$B$44,1)) -> 3 | U53: =IF(20<=6,0,CEILING(U10/'前提'!$B$44,1)) -> 3 | V53: =IF(21<=6,0,CEILING(V10/'前提'!$B$44,1)) -> 3 | W53: =IF(22<=6,0,CEILING(W10/'前提'!$B$44,1)) -> 3 | X53: =IF(23<=6,0,CEILING(X10/'前提'!$B$44,1)) -> 4 | Y53: =IF(24<=6,0,CEILING(Y10/'前提'!$B$44,1)) -> 4 | Z53: =IF(25<=6,0,CEILING(Z10/'前提'!$B$44,1)) -> 4 | AA53: =IF(26<=6,0,CEILING(AA10/'前提'!$B$44,1)) -> 4 | AB53: =IF(27<=6,0,CEILING(AB10/'前提'!$B$44,1)) -> 4 | AC53: =IF(28<=6,0,CEILING(AC10/'前提'!$B$44,1)) -> 5 | AD53: =IF(29<=6,0,CEILING(AD10/'前提'!$B$44,1)) -> 5 | AE53: =IF(30<=6,0,CEILING(AE10/'前提'!$B$44,1)) -> 5 | AF53: =IF(31<=6,0,CEILING(AF10/'前提'!$B$44,1)) -> 5 | AG53: =IF(32<=6,0,CEILING(AG10/'前提'!$B$44,1)) -> 5 | AH53: =IF(33<=6,0,CEILING(AH10/'前提'!$B$44,1)) -> 6 | AI53: =IF(34<=6,0,CEILING(AI10/'前提'!$B$44,1)) -> 6 | AJ53: =IF(35<=6,0,CEILING(AJ10/'前提'!$B$44,1)) -> 6 | AK53: =IF(36<=6,0,CEILING(AK10/'前提'!$B$44,1)) -> 6 | AL53: =IF(37<=6,0,CEILING(AL10/'前提'!$B$44,1)) -> 6 | AM53: =IF(38<=6,0,CEILING(AM10/'前提'!$B$44,1)) -> 7 | AN53: =IF(39<=6,0,CEILING(AN10/'前提'!$B$44,1)) -> 7 | AO53: =IF(40<=6,0,CEILING(AO10/'前提'!$B$44,1)) -> 7 | AP53: =IF(41<=6,0,CEILING(AP10/'前提'!$B$44,1)) -> 7 | AQ53: =IF(42<=6,0,CEILING(AQ10/'前提'!$B$44,1)) -> 7 | AR53: =IF(43<=6,0,CEILING(AR10/'前提'!$B$44,1)) -> 8 | AS53: =IF(44<=6,0,CEILING(AS10/'前提'!$B$44,1)) -> 8 | AT53: =IF(45<=6,0,CEILING(AT10/'前提'!$B$44,1)) -> 8 | AU53: =IF(46<=6,0,CEILING(AU10/'前提'!$B$44,1)) -> 8 | AV53: =IF(47<=6,0,CEILING(AV10/'前提'!$B$44,1)) -> 8 | AW53: =IF(48<=6,0,CEILING(AW10/'前提'!$B$44,1)) -> 9 | AX53: =IF(49<=6,0,CEILING(AX10/'前提'!$B$44,1)) -> 9 | AY53: =IF(50<=6,0,CEILING(AY10/'前提'!$B$44,1)) -> 9 | AZ53: =IF(51<=6,0,CEILING(AZ10/'前提'!$B$44,1)) -> 9 | BA53: =IF(52<=6,0,CEILING(BA10/'前提'!$B$44,1)) -> 10 | BB53: =IF(53<=6,0,CEILING(BB10/'前提'!$B$44,1)) -> 10 | BC53: =IF(54<=6,0,CEILING(BC10/'前提'!$B$44,1)) -> 10 | BD53: =IF(55<=6,0,CEILING(BD10/'前提'!$B$44,1)) -> 10 | BE53: =IF(56<=6,0,CEILING(BE10/'前提'!$B$44,1)) -> 11 | BF53: =IF(57<=6,0,CEILING(BF10/'前提'!$B$44,1)) -> 11 | BG53: =IF(58<=6,0,CEILING(BG10/'前提'!$B$44,1)) -> 11 | BH53: =IF(59<=6,0,CEILING(BH10/'前提'!$B$44,1)) -> 11 | BI53: =IF(60<=6,0,CEILING(BI10/'前提'!$B$44,1)) -> 11
A54: 営業サポート | B54: =IF(1<=6,'前提'!$B$65,IF(1<=12,'前提'!$B$66,IF(1<=18,'前提'!$B$67,IF(1<=24,'前提'!$B$68,IF(1<=36,'前提'!$B$69,IF(1<=48,'前提'!$B$70,'前提'!$B$71)))))) -> 1 | C54: =IF(2<=6,'前提'!$B$65,IF(2<=12,'前提'!$B$66,IF(2<=18,'前提'!$B$67,IF(2<=24,'前提'!$B$68,IF(2<=36,'前提'!$B$69,IF(2<=48,'前提'!$B$70,'前提'!$B$71)))))) -> 1 | D54: =IF(3<=6,'前提'!$B$65,IF(3<=12,'前提'!$B$66,IF(3<=18,'前提'!$B$67,IF(3<=24,'前提'!$B$68,IF(3<=36,'前提'!$B$69,IF(3<=48,'前提'!$B$70,'前提'!$B$71)))))) -> 1 | E54: =IF(4<=6,'前提'!$B$65,IF(4<=12,'前提'!$B$66,IF(4<=18,'前提'!$B$67,IF(4<=24,'前提'!$B$68,IF(4<=36,'前提'!$B$69,IF(4<=48,'前提'!$B$70,'前提'!$B$71)))))) -> 1 | F54: =IF(5<=6,'前提'!$B$65,IF(5<=12,'前提'!$B$66,IF(5<=18,'前提'!$B$67,IF(5<=24,'前提'!$B$68,IF(5<=36,'前提'!$B$69,IF(5<=48,'前提'!$B$70,'前提'!$B$71)))))) -> 1 | G54: =IF(6<=6,'前提'!$B$65,IF(6<=12,'前提'!$B$66,IF(6<=18,'前提'!$B$67,IF(6<=24,'前提'!$B$68,IF(6<=36,'前提'!$B$69,IF(6<=48,'前提'!$B$70,'前提'!$B$71)))))) -> 1 | H54: =IF(7<=6,'前提'!$B$65,IF(7<=12,'前提'!$B$66,IF(7<=18,'前提'!$B$67,IF(7<=24,'前提'!$B$68,IF(7<=36,'前提'!$B$69,IF(7<=48,'前提'!$B$70,'前提'!$B$71)))))) -> 1 | I54: =IF(8<=6,'前提'!$B$65,IF(8<=12,'前提'!$B$66,IF(8<=18,'前提'!$B$67,IF(8<=24,'前提'!$B$68,IF(8<=36,'前提'!$B$69,IF(8<=48,'前提'!$B$70,'前提'!$B$71)))))) -> 1 | J54: =IF(9<=6,'前提'!$B$65,IF(9<=12,'前提'!$B$66,IF(9<=18,'前提'!$B$67,IF(9<=24,'前提'!$B$68,IF(9<=36,'前提'!$B$69,IF(9<=48,'前提'!$B$70,'前提'!$B$71)))))) -> 1 | K54: =IF(10<=6,'前提'!$B$65,IF(10<=12,'前提'!$B$66,IF(10<=18,'前提'!$B$67,IF(10<=24,'前提'!$B$68,IF(10<=36,'前提'!$B$69,IF(10<=48,'前提'!$B$70,'前提'!$B$71)))))) -> 1 | L54: =IF(11<=6,'前提'!$B$65,IF(11<=12,'前提'!$B$66,IF(11<=18,'前提'!$B$67,IF(11<=24,'前提'!$B$68,IF(11<=36,'前提'!$B$69,IF(11<=48,'前提'!$B$70,'前提'!$B$71)))))) -> 1 | M54: =IF(12<=6,'前提'!$B$65,IF(12<=12,'前提'!$B$66,IF(12<=18,'前提'!$B$67,IF(12<=24,'前提'!$B$68,IF(12<=36,'前提'!$B$69,IF(12<=48,'前提'!$B$70,'前提'!$B$71)))))) -> 1 | N54: =IF(13<=6,'前提'!$B$65,IF(13<=12,'前提'!$B$66,IF(13<=18,'前提'!$B$67,IF(13<=24,'前提'!$B$68,IF(13<=36,'前提'!$B$69,IF(13<=48,'前提'!$B$70,'前提'!$B$71)))))) -> 1 | O54: =IF(14<=6,'前提'!$B$65,IF(14<=12,'前提'!$B$66,IF(14<=18,'前提'!$B$67,IF(14<=24,'前提'!$B$68,IF(14<=36,'前提'!$B$69,IF(14<=48,'前提'!$B$70,'前提'!$B$71)))))) -> 1 | P54: =IF(15<=6,'前提'!$B$65,IF(15<=12,'前提'!$B$66,IF(15<=18,'前提'!$B$67,IF(15<=24,'前提'!$B$68,IF(15<=36,'前提'!$B$69,IF(15<=48,'前提'!$B$70,'前提'!$B$71)))))) -> 1 | Q54: =IF(16<=6,'前提'!$B$65,IF(16<=12,'前提'!$B$66,IF(16<=18,'前提'!$B$67,IF(16<=24,'前提'!$B$68,IF(16<=36,'前提'!$B$69,IF(16<=48,'前提'!$B$70,'前提'!$B$71)))))) -> 1 | R54: =IF(17<=6,'前提'!$B$65,IF(17<=12,'前提'!$B$66,IF(17<=18,'前提'!$B$67,IF(17<=24,'前提'!$B$68,IF(17<=36,'前提'!$B$69,IF(17<=48,'前提'!$B$70,'前提'!$B$71)))))) -> 1 | S54: =IF(18<=6,'前提'!$B$65,IF(18<=12,'前提'!$B$66,IF(18<=18,'前提'!$B$67,IF(18<=24,'前提'!$B$68,IF(18<=36,'前提'!$B$69,IF(18<=48,'前提'!$B$70,'前提'!$B$71)))))) -> 1 | T54: =IF(19<=6,'前提'!$B$65,IF(19<=12,'前提'!$B$66,IF(19<=18,'前提'!$B$67,IF(19<=24,'前提'!$B$68,IF(19<=36,'前提'!$B$69,IF(19<=48,'前提'!$B$70,'前提'!$B$71)))))) -> 1 | U54: =IF(20<=6,'前提'!$B$65,IF(20<=12,'前提'!$B$66,IF(20<=18,'前提'!$B$67,IF(20<=24,'前提'!$B$68,IF(20<=36,'前提'!$B$69,IF(20<=48,'前提'!$B$70,'前提'!$B$71)))))) -> 1 | V54: =IF(21<=6,'前提'!$B$65,IF(21<=12,'前提'!$B$66,IF(21<=18,'前提'!$B$67,IF(21<=24,'前提'!$B$68,IF(21<=36,'前提'!$B$69,IF(21<=48,'前提'!$B$70,'前提'!$B$71)))))) -> 1 | W54: =IF(22<=6,'前提'!$B$65,IF(22<=12,'前提'!$B$66,IF(22<=18,'前提'!$B$67,IF(22<=24,'前提'!$B$68,IF(22<=36,'前提'!$B$69,IF(22<=48,'前提'!$B$70,'前提'!$B$71)))))) -> 1 | X54: =IF(23<=6,'前提'!$B$65,IF(23<=12,'前提'!$B$66,IF(23<=18,'前提'!$B$67,IF(23<=24,'前提'!$B$68,IF(23<=36,'前提'!$B$69,IF(23<=48,'前提'!$B$70,'前提'!$B$71)))))) -> 1 | Y54: =IF(24<=6,'前提'!$B$65,IF(24<=12,'前提'!$B$66,IF(24<=18,'前提'!$B$67,IF(24<=24,'前提'!$B$68,IF(24<=36,'前提'!$B$69,IF(24<=48,'前提'!$B$70,'前提'!$B$71)))))) -> 1 | Z54: =IF(25<=6,'前提'!$B$65,IF(25<=12,'前提'!$B$66,IF(25<=18,'前提'!$B$67,IF(25<=24,'前提'!$B$68,IF(25<=36,'前提'!$B$69,IF(25<=48,'前提'!$B$70,'前提'!$B$71)))))) -> 2 | AA54: =IF(26<=6,'前提'!$B$65,IF(26<=12,'前提'!$B$66,IF(26<=18,'前提'!$B$67,IF(26<=24,'前提'!$B$68,IF(26<=36,'前提'!$B$69,IF(26<=48,'前提'!$B$70,'前提'!$B$71)))))) -> 2 | AB54: =IF(27<=6,'前提'!$B$65,IF(27<=12,'前提'!$B$66,IF(27<=18,'前提'!$B$67,IF(27<=24,'前提'!$B$68,IF(27<=36,'前提'!$B$69,IF(27<=48,'前提'!$B$70,'前提'!$B$71)))))) -> 2 | AC54: =IF(28<=6,'前提'!$B$65,IF(28<=12,'前提'!$B$66,IF(28<=18,'前提'!$B$67,IF(28<=24,'前提'!$B$68,IF(28<=36,'前提'!$B$69,IF(28<=48,'前提'!$B$70,'前提'!$B$71)))))) -> 2 | AD54: =IF(29<=6,'前提'!$B$65,IF(29<=12,'前提'!$B$66,IF(29<=18,'前提'!$B$67,IF(29<=24,'前提'!$B$68,IF(29<=36,'前提'!$B$69,IF(29<=48,'前提'!$B$70,'前提'!$B$71)))))) -> 2 | AE54: =IF(30<=6,'前提'!$B$65,IF(30<=12,'前提'!$B$66,IF(30<=18,'前提'!$B$67,IF(30<=24,'前提'!$B$68,IF(30<=36,'前提'!$B$69,IF(30<=48,'前提'!$B$70,'前提'!$B$71)))))) -> 2 | AF54: =IF(31<=6,'前提'!$B$65,IF(31<=12,'前提'!$B$66,IF(31<=18,'前提'!$B$67,IF(31<=24,'前提'!$B$68,IF(31<=36,'前提'!$B$69,IF(31<=48,'前提'!$B$70,'前提'!$B$71)))))) -> 2 | AG54: =IF(32<=6,'前提'!$B$65,IF(32<=12,'前提'!$B$66,IF(32<=18,'前提'!$B$67,IF(32<=24,'前提'!$B$68,IF(32<=36,'前提'!$B$69,IF(32<=48,'前提'!$B$70,'前提'!$B$71)))))) -> 2 | AH54: =IF(33<=6,'前提'!$B$65,IF(33<=12,'前提'!$B$66,IF(33<=18,'前提'!$B$67,IF(33<=24,'前提'!$B$68,IF(33<=36,'前提'!$B$69,IF(33<=48,'前提'!$B$70,'前提'!$B$71)))))) -> 2 | AI54: =IF(34<=6,'前提'!$B$65,IF(34<=12,'前提'!$B$66,IF(34<=18,'前提'!$B$67,IF(34<=24,'前提'!$B$68,IF(34<=36,'前提'!$B$69,IF(34<=48,'前提'!$B$70,'前提'!$B$71)))))) -> 2 | AJ54: =IF(35<=6,'前提'!$B$65,IF(35<=12,'前提'!$B$66,IF(35<=18,'前提'!$B$67,IF(35<=24,'前提'!$B$68,IF(35<=36,'前提'!$B$69,IF(35<=48,'前提'!$B$70,'前提'!$B$71)))))) -> 2 | AK54: =IF(36<=6,'前提'!$B$65,IF(36<=12,'前提'!$B$66,IF(36<=18,'前提'!$B$67,IF(36<=24,'前提'!$B$68,IF(36<=36,'前提'!$B$69,IF(36<=48,'前提'!$B$70,'前提'!$B$71)))))) -> 2 | AL54: =IF(37<=6,'前提'!$B$65,IF(37<=12,'前提'!$B$66,IF(37<=18,'前提'!$B$67,IF(37<=24,'前提'!$B$68,IF(37<=36,'前提'!$B$69,IF(37<=48,'前提'!$B$70,'前提'!$B$71)))))) -> 2 | AM54: =IF(38<=6,'前提'!$B$65,IF(38<=12,'前提'!$B$66,IF(38<=18,'前提'!$B$67,IF(38<=24,'前提'!$B$68,IF(38<=36,'前提'!$B$69,IF(38<=48,'前提'!$B$70,'前提'!$B$71)))))) -> 2 | AN54: =IF(39<=6,'前提'!$B$65,IF(39<=12,'前提'!$B$66,IF(39<=18,'前提'!$B$67,IF(39<=24,'前提'!$B$68,IF(39<=36,'前提'!$B$69,IF(39<=48,'前提'!$B$70,'前提'!$B$71)))))) -> 2 | AO54: =IF(40<=6,'前提'!$B$65,IF(40<=12,'前提'!$B$66,IF(40<=18,'前提'!$B$67,IF(40<=24,'前提'!$B$68,IF(40<=36,'前提'!$B$69,IF(40<=48,'前提'!$B$70,'前提'!$B$71)))))) -> 2 | AP54: =IF(41<=6,'前提'!$B$65,IF(41<=12,'前提'!$B$66,IF(41<=18,'前提'!$B$67,IF(41<=24,'前提'!$B$68,IF(41<=36,'前提'!$B$69,IF(41<=48,'前提'!$B$70,'前提'!$B$71)))))) -> 2 | AQ54: =IF(42<=6,'前提'!$B$65,IF(42<=12,'前提'!$B$66,IF(42<=18,'前提'!$B$67,IF(42<=24,'前提'!$B$68,IF(42<=36,'前提'!$B$69,IF(42<=48,'前提'!$B$70,'前提'!$B$71)))))) -> 2 | AR54: =IF(43<=6,'前提'!$B$65,IF(43<=12,'前提'!$B$66,IF(43<=18,'前提'!$B$67,IF(43<=24,'前提'!$B$68,IF(43<=36,'前提'!$B$69,IF(43<=48,'前提'!$B$70,'前提'!$B$71)))))) -> 2 | AS54: =IF(44<=6,'前提'!$B$65,IF(44<=12,'前提'!$B$66,IF(44<=18,'前提'!$B$67,IF(44<=24,'前提'!$B$68,IF(44<=36,'前提'!$B$69,IF(44<=48,'前提'!$B$70,'前提'!$B$71)))))) -> 2 | AT54: =IF(45<=6,'前提'!$B$65,IF(45<=12,'前提'!$B$66,IF(45<=18,'前提'!$B$67,IF(45<=24,'前提'!$B$68,IF(45<=36,'前提'!$B$69,IF(45<=48,'前提'!$B$70,'前提'!$B$71)))))) -> 2 | AU54: =IF(46<=6,'前提'!$B$65,IF(46<=12,'前提'!$B$66,IF(46<=18,'前提'!$B$67,IF(46<=24,'前提'!$B$68,IF(46<=36,'前提'!$B$69,IF(46<=48,'前提'!$B$70,'前提'!$B$71)))))) -> 2 | AV54: =IF(47<=6,'前提'!$B$65,IF(47<=12,'前提'!$B$66,IF(47<=18,'前提'!$B$67,IF(47<=24,'前提'!$B$68,IF(47<=36,'前提'!$B$69,IF(47<=48,'前提'!$B$70,'前提'!$B$71)))))) -> 2 | AW54: =IF(48<=6,'前提'!$B$65,IF(48<=12,'前提'!$B$66,IF(48<=18,'前提'!$B$67,IF(48<=24,'前提'!$B$68,IF(48<=36,'前提'!$B$69,IF(48<=48,'前提'!$B$70,'前提'!$B$71)))))) -> 2 | AX54: =IF(49<=6,'前提'!$B$65,IF(49<=12,'前提'!$B$66,IF(49<=18,'前提'!$B$67,IF(49<=24,'前提'!$B$68,IF(49<=36,'前提'!$B$69,IF(49<=48,'前提'!$B$70,'前提'!$B$71)))))) -> 3 | AY54: =IF(50<=6,'前提'!$B$65,IF(50<=12,'前提'!$B$66,IF(50<=18,'前提'!$B$67,IF(50<=24,'前提'!$B$68,IF(50<=36,'前提'!$B$69,IF(50<=48,'前提'!$B$70,'前提'!$B$71)))))) -> 3 | AZ54: =IF(51<=6,'前提'!$B$65,IF(51<=12,'前提'!$B$66,IF(51<=18,'前提'!$B$67,IF(51<=24,'前提'!$B$68,IF(51<=36,'前提'!$B$69,IF(51<=48,'前提'!$B$70,'前提'!$B$71)))))) -> 3 | BA54: =IF(52<=6,'前提'!$B$65,IF(52<=12,'前提'!$B$66,IF(52<=18,'前提'!$B$67,IF(52<=24,'前提'!$B$68,IF(52<=36,'前提'!$B$69,IF(52<=48,'前提'!$B$70,'前提'!$B$71)))))) -> 3 | BB54: =IF(53<=6,'前提'!$B$65,IF(53<=12,'前提'!$B$66,IF(53<=18,'前提'!$B$67,IF(53<=24,'前提'!$B$68,IF(53<=36,'前提'!$B$69,IF(53<=48,'前提'!$B$70,'前提'!$B$71)))))) -> 3 | BC54: =IF(54<=6,'前提'!$B$65,IF(54<=12,'前提'!$B$66,IF(54<=18,'前提'!$B$67,IF(54<=24,'前提'!$B$68,IF(54<=36,'前提'!$B$69,IF(54<=48,'前提'!$B$70,'前提'!$B$71)))))) -> 3 | BD54: =IF(55<=6,'前提'!$B$65,IF(55<=12,'前提'!$B$66,IF(55<=18,'前提'!$B$67,IF(55<=24,'前提'!$B$68,IF(55<=36,'前提'!$B$69,IF(55<=48,'前提'!$B$70,'前提'!$B$71)))))) -> 3 | BE54: =IF(56<=6,'前提'!$B$65,IF(56<=12,'前提'!$B$66,IF(56<=18,'前提'!$B$67,IF(56<=24,'前提'!$B$68,IF(56<=36,'前提'!$B$69,IF(56<=48,'前提'!$B$70,'前提'!$B$71)))))) -> 3 | BF54: =IF(57<=6,'前提'!$B$65,IF(57<=12,'前提'!$B$66,IF(57<=18,'前提'!$B$67,IF(57<=24,'前提'!$B$68,IF(57<=36,'前提'!$B$69,IF(57<=48,'前提'!$B$70,'前提'!$B$71)))))) -> 3 | BG54: =IF(58<=6,'前提'!$B$65,IF(58<=12,'前提'!$B$66,IF(58<=18,'前提'!$B$67,IF(58<=24,'前提'!$B$68,IF(58<=36,'前提'!$B$69,IF(58<=48,'前提'!$B$70,'前提'!$B$71)))))) -> 3 | BH54: =IF(59<=6,'前提'!$B$65,IF(59<=12,'前提'!$B$66,IF(59<=18,'前提'!$B$67,IF(59<=24,'前提'!$B$68,IF(59<=36,'前提'!$B$69,IF(59<=48,'前提'!$B$70,'前提'!$B$71)))))) -> 3 | BI54: =IF(60<=6,'前提'!$B$65,IF(60<=12,'前提'!$B$66,IF(60<=18,'前提'!$B$67,IF(60<=24,'前提'!$B$68,IF(60<=36,'前提'!$B$69,IF(60<=48,'前提'!$B$70,'前提'!$B$71)))))) -> 3
A55: BPO事務長 | B55: =IF(1<=6,'前提'!$B$56,IF(1<=12,'前提'!$B$57,IF(1<=18,'前提'!$B$58,IF(1<=24,'前提'!$B$59,IF(1<=36,'前提'!$B$60,IF(1<=48,'前提'!$B$61,'前提'!$B$62)))))) -> 0 | C55: =IF(2<=6,'前提'!$B$56,IF(2<=12,'前提'!$B$57,IF(2<=18,'前提'!$B$58,IF(2<=24,'前提'!$B$59,IF(2<=36,'前提'!$B$60,IF(2<=48,'前提'!$B$61,'前提'!$B$62)))))) -> 0 | D55: =IF(3<=6,'前提'!$B$56,IF(3<=12,'前提'!$B$57,IF(3<=18,'前提'!$B$58,IF(3<=24,'前提'!$B$59,IF(3<=36,'前提'!$B$60,IF(3<=48,'前提'!$B$61,'前提'!$B$62)))))) -> 0 | E55: =IF(4<=6,'前提'!$B$56,IF(4<=12,'前提'!$B$57,IF(4<=18,'前提'!$B$58,IF(4<=24,'前提'!$B$59,IF(4<=36,'前提'!$B$60,IF(4<=48,'前提'!$B$61,'前提'!$B$62)))))) -> 0 | F55: =IF(5<=6,'前提'!$B$56,IF(5<=12,'前提'!$B$57,IF(5<=18,'前提'!$B$58,IF(5<=24,'前提'!$B$59,IF(5<=36,'前提'!$B$60,IF(5<=48,'前提'!$B$61,'前提'!$B$62)))))) -> 0 | G55: =IF(6<=6,'前提'!$B$56,IF(6<=12,'前提'!$B$57,IF(6<=18,'前提'!$B$58,IF(6<=24,'前提'!$B$59,IF(6<=36,'前提'!$B$60,IF(6<=48,'前提'!$B$61,'前提'!$B$62)))))) -> 0 | H55: =IF(7<=6,'前提'!$B$56,IF(7<=12,'前提'!$B$57,IF(7<=18,'前提'!$B$58,IF(7<=24,'前提'!$B$59,IF(7<=36,'前提'!$B$60,IF(7<=48,'前提'!$B$61,'前提'!$B$62)))))) -> 1 | I55: =IF(8<=6,'前提'!$B$56,IF(8<=12,'前提'!$B$57,IF(8<=18,'前提'!$B$58,IF(8<=24,'前提'!$B$59,IF(8<=36,'前提'!$B$60,IF(8<=48,'前提'!$B$61,'前提'!$B$62)))))) -> 1 | J55: =IF(9<=6,'前提'!$B$56,IF(9<=12,'前提'!$B$57,IF(9<=18,'前提'!$B$58,IF(9<=24,'前提'!$B$59,IF(9<=36,'前提'!$B$60,IF(9<=48,'前提'!$B$61,'前提'!$B$62)))))) -> 1 | K55: =IF(10<=6,'前提'!$B$56,IF(10<=12,'前提'!$B$57,IF(10<=18,'前提'!$B$58,IF(10<=24,'前提'!$B$59,IF(10<=36,'前提'!$B$60,IF(10<=48,'前提'!$B$61,'前提'!$B$62)))))) -> 1 | L55: =IF(11<=6,'前提'!$B$56,IF(11<=12,'前提'!$B$57,IF(11<=18,'前提'!$B$58,IF(11<=24,'前提'!$B$59,IF(11<=36,'前提'!$B$60,IF(11<=48,'前提'!$B$61,'前提'!$B$62)))))) -> 1 | M55: =IF(12<=6,'前提'!$B$56,IF(12<=12,'前提'!$B$57,IF(12<=18,'前提'!$B$58,IF(12<=24,'前提'!$B$59,IF(12<=36,'前提'!$B$60,IF(12<=48,'前提'!$B$61,'前提'!$B$62)))))) -> 1 | N55: =IF(13<=6,'前提'!$B$56,IF(13<=12,'前提'!$B$57,IF(13<=18,'前提'!$B$58,IF(13<=24,'前提'!$B$59,IF(13<=36,'前提'!$B$60,IF(13<=48,'前提'!$B$61,'前提'!$B$62)))))) -> 2 | O55: =IF(14<=6,'前提'!$B$56,IF(14<=12,'前提'!$B$57,IF(14<=18,'前提'!$B$58,IF(14<=24,'前提'!$B$59,IF(14<=36,'前提'!$B$60,IF(14<=48,'前提'!$B$61,'前提'!$B$62)))))) -> 2 | P55: =IF(15<=6,'前提'!$B$56,IF(15<=12,'前提'!$B$57,IF(15<=18,'前提'!$B$58,IF(15<=24,'前提'!$B$59,IF(15<=36,'前提'!$B$60,IF(15<=48,'前提'!$B$61,'前提'!$B$62)))))) -> 2 | Q55: =IF(16<=6,'前提'!$B$56,IF(16<=12,'前提'!$B$57,IF(16<=18,'前提'!$B$58,IF(16<=24,'前提'!$B$59,IF(16<=36,'前提'!$B$60,IF(16<=48,'前提'!$B$61,'前提'!$B$62)))))) -> 2 | R55: =IF(17<=6,'前提'!$B$56,IF(17<=12,'前提'!$B$57,IF(17<=18,'前提'!$B$58,IF(17<=24,'前提'!$B$59,IF(17<=36,'前提'!$B$60,IF(17<=48,'前提'!$B$61,'前提'!$B$62)))))) -> 2 | S55: =IF(18<=6,'前提'!$B$56,IF(18<=12,'前提'!$B$57,IF(18<=18,'前提'!$B$58,IF(18<=24,'前提'!$B$59,IF(18<=36,'前提'!$B$60,IF(18<=48,'前提'!$B$61,'前提'!$B$62)))))) -> 2 | T55: =IF(19<=6,'前提'!$B$56,IF(19<=12,'前提'!$B$57,IF(19<=18,'前提'!$B$58,IF(19<=24,'前提'!$B$59,IF(19<=36,'前提'!$B$60,IF(19<=48,'前提'!$B$61,'前提'!$B$62)))))) -> 3 | U55: =IF(20<=6,'前提'!$B$56,IF(20<=12,'前提'!$B$57,IF(20<=18,'前提'!$B$58,IF(20<=24,'前提'!$B$59,IF(20<=36,'前提'!$B$60,IF(20<=48,'前提'!$B$61,'前提'!$B$62)))))) -> 3 | V55: =IF(21<=6,'前提'!$B$56,IF(21<=12,'前提'!$B$57,IF(21<=18,'前提'!$B$58,IF(21<=24,'前提'!$B$59,IF(21<=36,'前提'!$B$60,IF(21<=48,'前提'!$B$61,'前提'!$B$62)))))) -> 3 | W55: =IF(22<=6,'前提'!$B$56,IF(22<=12,'前提'!$B$57,IF(22<=18,'前提'!$B$58,IF(22<=24,'前提'!$B$59,IF(22<=36,'前提'!$B$60,IF(22<=48,'前提'!$B$61,'前提'!$B$62)))))) -> 3 | X55: =IF(23<=6,'前提'!$B$56,IF(23<=12,'前提'!$B$57,IF(23<=18,'前提'!$B$58,IF(23<=24,'前提'!$B$59,IF(23<=36,'前提'!$B$60,IF(23<=48,'前提'!$B$61,'前提'!$B$62)))))) -> 3 | Y55: =IF(24<=6,'前提'!$B$56,IF(24<=12,'前提'!$B$57,IF(24<=18,'前提'!$B$58,IF(24<=24,'前提'!$B$59,IF(24<=36,'前提'!$B$60,IF(24<=48,'前提'!$B$61,'前提'!$B$62)))))) -> 3 | Z55: =IF(25<=6,'前提'!$B$56,IF(25<=12,'前提'!$B$57,IF(25<=18,'前提'!$B$58,IF(25<=24,'前提'!$B$59,IF(25<=36,'前提'!$B$60,IF(25<=48,'前提'!$B$61,'前提'!$B$62)))))) -> 4 | AA55: =IF(26<=6,'前提'!$B$56,IF(26<=12,'前提'!$B$57,IF(26<=18,'前提'!$B$58,IF(26<=24,'前提'!$B$59,IF(26<=36,'前提'!$B$60,IF(26<=48,'前提'!$B$61,'前提'!$B$62)))))) -> 4 | AB55: =IF(27<=6,'前提'!$B$56,IF(27<=12,'前提'!$B$57,IF(27<=18,'前提'!$B$58,IF(27<=24,'前提'!$B$59,IF(27<=36,'前提'!$B$60,IF(27<=48,'前提'!$B$61,'前提'!$B$62)))))) -> 4 | AC55: =IF(28<=6,'前提'!$B$56,IF(28<=12,'前提'!$B$57,IF(28<=18,'前提'!$B$58,IF(28<=24,'前提'!$B$59,IF(28<=36,'前提'!$B$60,IF(28<=48,'前提'!$B$61,'前提'!$B$62)))))) -> 4 | AD55: =IF(29<=6,'前提'!$B$56,IF(29<=12,'前提'!$B$57,IF(29<=18,'前提'!$B$58,IF(29<=24,'前提'!$B$59,IF(29<=36,'前提'!$B$60,IF(29<=48,'前提'!$B$61,'前提'!$B$62)))))) -> 4 | AE55: =IF(30<=6,'前提'!$B$56,IF(30<=12,'前提'!$B$57,IF(30<=18,'前提'!$B$58,IF(30<=24,'前提'!$B$59,IF(30<=36,'前提'!$B$60,IF(30<=48,'前提'!$B$61,'前提'!$B$62)))))) -> 4 | AF55: =IF(31<=6,'前提'!$B$56,IF(31<=12,'前提'!$B$57,IF(31<=18,'前提'!$B$58,IF(31<=24,'前提'!$B$59,IF(31<=36,'前提'!$B$60,IF(31<=48,'前提'!$B$61,'前提'!$B$62)))))) -> 4 | AG55: =IF(32<=6,'前提'!$B$56,IF(32<=12,'前提'!$B$57,IF(32<=18,'前提'!$B$58,IF(32<=24,'前提'!$B$59,IF(32<=36,'前提'!$B$60,IF(32<=48,'前提'!$B$61,'前提'!$B$62)))))) -> 4 | AH55: =IF(33<=6,'前提'!$B$56,IF(33<=12,'前提'!$B$57,IF(33<=18,'前提'!$B$58,IF(33<=24,'前提'!$B$59,IF(33<=36,'前提'!$B$60,IF(33<=48,'前提'!$B$61,'前提'!$B$62)))))) -> 4 | AI55: =IF(34<=6,'前提'!$B$56,IF(34<=12,'前提'!$B$57,IF(34<=18,'前提'!$B$58,IF(34<=24,'前提'!$B$59,IF(34<=36,'前提'!$B$60,IF(34<=48,'前提'!$B$61,'前提'!$B$62)))))) -> 4 | AJ55: =IF(35<=6,'前提'!$B$56,IF(35<=12,'前提'!$B$57,IF(35<=18,'前提'!$B$58,IF(35<=24,'前提'!$B$59,IF(35<=36,'前提'!$B$60,IF(35<=48,'前提'!$B$61,'前提'!$B$62)))))) -> 4 | AK55: =IF(36<=6,'前提'!$B$56,IF(36<=12,'前提'!$B$57,IF(36<=18,'前提'!$B$58,IF(36<=24,'前提'!$B$59,IF(36<=36,'前提'!$B$60,IF(36<=48,'前提'!$B$61,'前提'!$B$62)))))) -> 4 | AL55: =IF(37<=6,'前提'!$B$56,IF(37<=12,'前提'!$B$57,IF(37<=18,'前提'!$B$58,IF(37<=24,'前提'!$B$59,IF(37<=36,'前提'!$B$60,IF(37<=48,'前提'!$B$61,'前提'!$B$62)))))) -> 5 | AM55: =IF(38<=6,'前提'!$B$56,IF(38<=12,'前提'!$B$57,IF(38<=18,'前提'!$B$58,IF(38<=24,'前提'!$B$59,IF(38<=36,'前提'!$B$60,IF(38<=48,'前提'!$B$61,'前提'!$B$62)))))) -> 5 | AN55: =IF(39<=6,'前提'!$B$56,IF(39<=12,'前提'!$B$57,IF(39<=18,'前提'!$B$58,IF(39<=24,'前提'!$B$59,IF(39<=36,'前提'!$B$60,IF(39<=48,'前提'!$B$61,'前提'!$B$62)))))) -> 5 | AO55: =IF(40<=6,'前提'!$B$56,IF(40<=12,'前提'!$B$57,IF(40<=18,'前提'!$B$58,IF(40<=24,'前提'!$B$59,IF(40<=36,'前提'!$B$60,IF(40<=48,'前提'!$B$61,'前提'!$B$62)))))) -> 5 | AP55: =IF(41<=6,'前提'!$B$56,IF(41<=12,'前提'!$B$57,IF(41<=18,'前提'!$B$58,IF(41<=24,'前提'!$B$59,IF(41<=36,'前提'!$B$60,IF(41<=48,'前提'!$B$61,'前提'!$B$62)))))) -> 5 | AQ55: =IF(42<=6,'前提'!$B$56,IF(42<=12,'前提'!$B$57,IF(42<=18,'前提'!$B$58,IF(42<=24,'前提'!$B$59,IF(42<=36,'前提'!$B$60,IF(42<=48,'前提'!$B$61,'前提'!$B$62)))))) -> 5 | AR55: =IF(43<=6,'前提'!$B$56,IF(43<=12,'前提'!$B$57,IF(43<=18,'前提'!$B$58,IF(43<=24,'前提'!$B$59,IF(43<=36,'前提'!$B$60,IF(43<=48,'前提'!$B$61,'前提'!$B$62)))))) -> 5 | AS55: =IF(44<=6,'前提'!$B$56,IF(44<=12,'前提'!$B$57,IF(44<=18,'前提'!$B$58,IF(44<=24,'前提'!$B$59,IF(44<=36,'前提'!$B$60,IF(44<=48,'前提'!$B$61,'前提'!$B$62)))))) -> 5 | AT55: =IF(45<=6,'前提'!$B$56,IF(45<=12,'前提'!$B$57,IF(45<=18,'前提'!$B$58,IF(45<=24,'前提'!$B$59,IF(45<=36,'前提'!$B$60,IF(45<=48,'前提'!$B$61,'前提'!$B$62)))))) -> 5 | AU55: =IF(46<=6,'前提'!$B$56,IF(46<=12,'前提'!$B$57,IF(46<=18,'前提'!$B$58,IF(46<=24,'前提'!$B$59,IF(46<=36,'前提'!$B$60,IF(46<=48,'前提'!$B$61,'前提'!$B$62)))))) -> 5 | AV55: =IF(47<=6,'前提'!$B$56,IF(47<=12,'前提'!$B$57,IF(47<=18,'前提'!$B$58,IF(47<=24,'前提'!$B$59,IF(47<=36,'前提'!$B$60,IF(47<=48,'前提'!$B$61,'前提'!$B$62)))))) -> 5 | AW55: =IF(48<=6,'前提'!$B$56,IF(48<=12,'前提'!$B$57,IF(48<=18,'前提'!$B$58,IF(48<=24,'前提'!$B$59,IF(48<=36,'前提'!$B$60,IF(48<=48,'前提'!$B$61,'前提'!$B$62)))))) -> 5 | AX55: =IF(49<=6,'前提'!$B$56,IF(49<=12,'前提'!$B$57,IF(49<=18,'前提'!$B$58,IF(49<=24,'前提'!$B$59,IF(49<=36,'前提'!$B$60,IF(49<=48,'前提'!$B$61,'前提'!$B$62)))))) -> 6 | AY55: =IF(50<=6,'前提'!$B$56,IF(50<=12,'前提'!$B$57,IF(50<=18,'前提'!$B$58,IF(50<=24,'前提'!$B$59,IF(50<=36,'前提'!$B$60,IF(50<=48,'前提'!$B$61,'前提'!$B$62)))))) -> 6 | AZ55: =IF(51<=6,'前提'!$B$56,IF(51<=12,'前提'!$B$57,IF(51<=18,'前提'!$B$58,IF(51<=24,'前提'!$B$59,IF(51<=36,'前提'!$B$60,IF(51<=48,'前提'!$B$61,'前提'!$B$62)))))) -> 6 | BA55: =IF(52<=6,'前提'!$B$56,IF(52<=12,'前提'!$B$57,IF(52<=18,'前提'!$B$58,IF(52<=24,'前提'!$B$59,IF(52<=36,'前提'!$B$60,IF(52<=48,'前提'!$B$61,'前提'!$B$62)))))) -> 6 | BB55: =IF(53<=6,'前提'!$B$56,IF(53<=12,'前提'!$B$57,IF(53<=18,'前提'!$B$58,IF(53<=24,'前提'!$B$59,IF(53<=36,'前提'!$B$60,IF(53<=48,'前提'!$B$61,'前提'!$B$62)))))) -> 6 | BC55: =IF(54<=6,'前提'!$B$56,IF(54<=12,'前提'!$B$57,IF(54<=18,'前提'!$B$58,IF(54<=24,'前提'!$B$59,IF(54<=36,'前提'!$B$60,IF(54<=48,'前提'!$B$61,'前提'!$B$62)))))) -> 6 | BD55: =IF(55<=6,'前提'!$B$56,IF(55<=12,'前提'!$B$57,IF(55<=18,'前提'!$B$58,IF(55<=24,'前提'!$B$59,IF(55<=36,'前提'!$B$60,IF(55<=48,'前提'!$B$61,'前提'!$B$62)))))) -> 6 | BE55: =IF(56<=6,'前提'!$B$56,IF(56<=12,'前提'!$B$57,IF(56<=18,'前提'!$B$58,IF(56<=24,'前提'!$B$59,IF(56<=36,'前提'!$B$60,IF(56<=48,'前提'!$B$61,'前提'!$B$62)))))) -> 6 | BF55: =IF(57<=6,'前提'!$B$56,IF(57<=12,'前提'!$B$57,IF(57<=18,'前提'!$B$58,IF(57<=24,'前提'!$B$59,IF(57<=36,'前提'!$B$60,IF(57<=48,'前提'!$B$61,'前提'!$B$62)))))) -> 6 | BG55: =IF(58<=6,'前提'!$B$56,IF(58<=12,'前提'!$B$57,IF(58<=18,'前提'!$B$58,IF(58<=24,'前提'!$B$59,IF(58<=36,'前提'!$B$60,IF(58<=48,'前提'!$B$61,'前提'!$B$62)))))) -> 6 | BH55: =IF(59<=6,'前提'!$B$56,IF(59<=12,'前提'!$B$57,IF(59<=18,'前提'!$B$58,IF(59<=24,'前提'!$B$59,IF(59<=36,'前提'!$B$60,IF(59<=48,'前提'!$B$61,'前提'!$B$62)))))) -> 6 | BI55: =IF(60<=6,'前提'!$B$56,IF(60<=12,'前提'!$B$57,IF(60<=18,'前提'!$B$58,IF(60<=24,'前提'!$B$59,IF(60<=36,'前提'!$B$60,IF(60<=48,'前提'!$B$61,'前提'!$B$62)))))) -> 6
A56: BPOオペレーター | B56: =IF(1<=6,'前提'!$C$56,IF(1<=12,'前提'!$C$57,IF(1<=18,'前提'!$C$58,IF(1<=24,'前提'!$C$59,IF(1<=36,'前提'!$C$60,IF(1<=48,'前提'!$C$61,'前提'!$C$62)))))) -> 0 | C56: =IF(2<=6,'前提'!$C$56,IF(2<=12,'前提'!$C$57,IF(2<=18,'前提'!$C$58,IF(2<=24,'前提'!$C$59,IF(2<=36,'前提'!$C$60,IF(2<=48,'前提'!$C$61,'前提'!$C$62)))))) -> 0 | D56: =IF(3<=6,'前提'!$C$56,IF(3<=12,'前提'!$C$57,IF(3<=18,'前提'!$C$58,IF(3<=24,'前提'!$C$59,IF(3<=36,'前提'!$C$60,IF(3<=48,'前提'!$C$61,'前提'!$C$62)))))) -> 0 | E56: =IF(4<=6,'前提'!$C$56,IF(4<=12,'前提'!$C$57,IF(4<=18,'前提'!$C$58,IF(4<=24,'前提'!$C$59,IF(4<=36,'前提'!$C$60,IF(4<=48,'前提'!$C$61,'前提'!$C$62)))))) -> 0 | F56: =IF(5<=6,'前提'!$C$56,IF(5<=12,'前提'!$C$57,IF(5<=18,'前提'!$C$58,IF(5<=24,'前提'!$C$59,IF(5<=36,'前提'!$C$60,IF(5<=48,'前提'!$C$61,'前提'!$C$62)))))) -> 0 | G56: =IF(6<=6,'前提'!$C$56,IF(6<=12,'前提'!$C$57,IF(6<=18,'前提'!$C$58,IF(6<=24,'前提'!$C$59,IF(6<=36,'前提'!$C$60,IF(6<=48,'前提'!$C$61,'前提'!$C$62)))))) -> 0 | H56: =IF(7<=6,'前提'!$C$56,IF(7<=12,'前提'!$C$57,IF(7<=18,'前提'!$C$58,IF(7<=24,'前提'!$C$59,IF(7<=36,'前提'!$C$60,IF(7<=48,'前提'!$C$61,'前提'!$C$62)))))) -> 2 | I56: =IF(8<=6,'前提'!$C$56,IF(8<=12,'前提'!$C$57,IF(8<=18,'前提'!$C$58,IF(8<=24,'前提'!$C$59,IF(8<=36,'前提'!$C$60,IF(8<=48,'前提'!$C$61,'前提'!$C$62)))))) -> 2 | J56: =IF(9<=6,'前提'!$C$56,IF(9<=12,'前提'!$C$57,IF(9<=18,'前提'!$C$58,IF(9<=24,'前提'!$C$59,IF(9<=36,'前提'!$C$60,IF(9<=48,'前提'!$C$61,'前提'!$C$62)))))) -> 2 | K56: =IF(10<=6,'前提'!$C$56,IF(10<=12,'前提'!$C$57,IF(10<=18,'前提'!$C$58,IF(10<=24,'前提'!$C$59,IF(10<=36,'前提'!$C$60,IF(10<=48,'前提'!$C$61,'前提'!$C$62)))))) -> 2 | L56: =IF(11<=6,'前提'!$C$56,IF(11<=12,'前提'!$C$57,IF(11<=18,'前提'!$C$58,IF(11<=24,'前提'!$C$59,IF(11<=36,'前提'!$C$60,IF(11<=48,'前提'!$C$61,'前提'!$C$62)))))) -> 2 | M56: =IF(12<=6,'前提'!$C$56,IF(12<=12,'前提'!$C$57,IF(12<=18,'前提'!$C$58,IF(12<=24,'前提'!$C$59,IF(12<=36,'前提'!$C$60,IF(12<=48,'前提'!$C$61,'前提'!$C$62)))))) -> 2 | N56: =IF(13<=6,'前提'!$C$56,IF(13<=12,'前提'!$C$57,IF(13<=18,'前提'!$C$58,IF(13<=24,'前提'!$C$59,IF(13<=36,'前提'!$C$60,IF(13<=48,'前提'!$C$61,'前提'!$C$62)))))) -> 4 | O56: =IF(14<=6,'前提'!$C$56,IF(14<=12,'前提'!$C$57,IF(14<=18,'前提'!$C$58,IF(14<=24,'前提'!$C$59,IF(14<=36,'前提'!$C$60,IF(14<=48,'前提'!$C$61,'前提'!$C$62)))))) -> 4 | P56: =IF(15<=6,'前提'!$C$56,IF(15<=12,'前提'!$C$57,IF(15<=18,'前提'!$C$58,IF(15<=24,'前提'!$C$59,IF(15<=36,'前提'!$C$60,IF(15<=48,'前提'!$C$61,'前提'!$C$62)))))) -> 4 | Q56: =IF(16<=6,'前提'!$C$56,IF(16<=12,'前提'!$C$57,IF(16<=18,'前提'!$C$58,IF(16<=24,'前提'!$C$59,IF(16<=36,'前提'!$C$60,IF(16<=48,'前提'!$C$61,'前提'!$C$62)))))) -> 4 | R56: =IF(17<=6,'前提'!$C$56,IF(17<=12,'前提'!$C$57,IF(17<=18,'前提'!$C$58,IF(17<=24,'前提'!$C$59,IF(17<=36,'前提'!$C$60,IF(17<=48,'前提'!$C$61,'前提'!$C$62)))))) -> 4 | S56: =IF(18<=6,'前提'!$C$56,IF(18<=12,'前提'!$C$57,IF(18<=18,'前提'!$C$58,IF(18<=24,'前提'!$C$59,IF(18<=36,'前提'!$C$60,IF(18<=48,'前提'!$C$61,'前提'!$C$62)))))) -> 4 | T56: =IF(19<=6,'前提'!$C$56,IF(19<=12,'前提'!$C$57,IF(19<=18,'前提'!$C$58,IF(19<=24,'前提'!$C$59,IF(19<=36,'前提'!$C$60,IF(19<=48,'前提'!$C$61,'前提'!$C$62)))))) -> 5 | U56: =IF(20<=6,'前提'!$C$56,IF(20<=12,'前提'!$C$57,IF(20<=18,'前提'!$C$58,IF(20<=24,'前提'!$C$59,IF(20<=36,'前提'!$C$60,IF(20<=48,'前提'!$C$61,'前提'!$C$62)))))) -> 5 | V56: =IF(21<=6,'前提'!$C$56,IF(21<=12,'前提'!$C$57,IF(21<=18,'前提'!$C$58,IF(21<=24,'前提'!$C$59,IF(21<=36,'前提'!$C$60,IF(21<=48,'前提'!$C$61,'前提'!$C$62)))))) -> 5 | W56: =IF(22<=6,'前提'!$C$56,IF(22<=12,'前提'!$C$57,IF(22<=18,'前提'!$C$58,IF(22<=24,'前提'!$C$59,IF(22<=36,'前提'!$C$60,IF(22<=48,'前提'!$C$61,'前提'!$C$62)))))) -> 5 | X56: =IF(23<=6,'前提'!$C$56,IF(23<=12,'前提'!$C$57,IF(23<=18,'前提'!$C$58,IF(23<=24,'前提'!$C$59,IF(23<=36,'前提'!$C$60,IF(23<=48,'前提'!$C$61,'前提'!$C$62)))))) -> 5 | Y56: =IF(24<=6,'前提'!$C$56,IF(24<=12,'前提'!$C$57,IF(24<=18,'前提'!$C$58,IF(24<=24,'前提'!$C$59,IF(24<=36,'前提'!$C$60,IF(24<=48,'前提'!$C$61,'前提'!$C$62)))))) -> 5 | Z56: =IF(25<=6,'前提'!$C$56,IF(25<=12,'前提'!$C$57,IF(25<=18,'前提'!$C$58,IF(25<=24,'前提'!$C$59,IF(25<=36,'前提'!$C$60,IF(25<=48,'前提'!$C$61,'前提'!$C$62)))))) -> 7 | AA56: =IF(26<=6,'前提'!$C$56,IF(26<=12,'前提'!$C$57,IF(26<=18,'前提'!$C$58,IF(26<=24,'前提'!$C$59,IF(26<=36,'前提'!$C$60,IF(26<=48,'前提'!$C$61,'前提'!$C$62)))))) -> 7 | AB56: =IF(27<=6,'前提'!$C$56,IF(27<=12,'前提'!$C$57,IF(27<=18,'前提'!$C$58,IF(27<=24,'前提'!$C$59,IF(27<=36,'前提'!$C$60,IF(27<=48,'前提'!$C$61,'前提'!$C$62)))))) -> 7 | AC56: =IF(28<=6,'前提'!$C$56,IF(28<=12,'前提'!$C$57,IF(28<=18,'前提'!$C$58,IF(28<=24,'前提'!$C$59,IF(28<=36,'前提'!$C$60,IF(28<=48,'前提'!$C$61,'前提'!$C$62)))))) -> 7 | AD56: =IF(29<=6,'前提'!$C$56,IF(29<=12,'前提'!$C$57,IF(29<=18,'前提'!$C$58,IF(29<=24,'前提'!$C$59,IF(29<=36,'前提'!$C$60,IF(29<=48,'前提'!$C$61,'前提'!$C$62)))))) -> 7 | AE56: =IF(30<=6,'前提'!$C$56,IF(30<=12,'前提'!$C$57,IF(30<=18,'前提'!$C$58,IF(30<=24,'前提'!$C$59,IF(30<=36,'前提'!$C$60,IF(30<=48,'前提'!$C$61,'前提'!$C$62)))))) -> 7 | AF56: =IF(31<=6,'前提'!$C$56,IF(31<=12,'前提'!$C$57,IF(31<=18,'前提'!$C$58,IF(31<=24,'前提'!$C$59,IF(31<=36,'前提'!$C$60,IF(31<=48,'前提'!$C$61,'前提'!$C$62)))))) -> 7 | AG56: =IF(32<=6,'前提'!$C$56,IF(32<=12,'前提'!$C$57,IF(32<=18,'前提'!$C$58,IF(32<=24,'前提'!$C$59,IF(32<=36,'前提'!$C$60,IF(32<=48,'前提'!$C$61,'前提'!$C$62)))))) -> 7 | AH56: =IF(33<=6,'前提'!$C$56,IF(33<=12,'前提'!$C$57,IF(33<=18,'前提'!$C$58,IF(33<=24,'前提'!$C$59,IF(33<=36,'前提'!$C$60,IF(33<=48,'前提'!$C$61,'前提'!$C$62)))))) -> 7 | AI56: =IF(34<=6,'前提'!$C$56,IF(34<=12,'前提'!$C$57,IF(34<=18,'前提'!$C$58,IF(34<=24,'前提'!$C$59,IF(34<=36,'前提'!$C$60,IF(34<=48,'前提'!$C$61,'前提'!$C$62)))))) -> 7 | AJ56: =IF(35<=6,'前提'!$C$56,IF(35<=12,'前提'!$C$57,IF(35<=18,'前提'!$C$58,IF(35<=24,'前提'!$C$59,IF(35<=36,'前提'!$C$60,IF(35<=48,'前提'!$C$61,'前提'!$C$62)))))) -> 7 | AK56: =IF(36<=6,'前提'!$C$56,IF(36<=12,'前提'!$C$57,IF(36<=18,'前提'!$C$58,IF(36<=24,'前提'!$C$59,IF(36<=36,'前提'!$C$60,IF(36<=48,'前提'!$C$61,'前提'!$C$62)))))) -> 7 | AL56: =IF(37<=6,'前提'!$C$56,IF(37<=12,'前提'!$C$57,IF(37<=18,'前提'!$C$58,IF(37<=24,'前提'!$C$59,IF(37<=36,'前提'!$C$60,IF(37<=48,'前提'!$C$61,'前提'!$C$62)))))) -> 9 | AM56: =IF(38<=6,'前提'!$C$56,IF(38<=12,'前提'!$C$57,IF(38<=18,'前提'!$C$58,IF(38<=24,'前提'!$C$59,IF(38<=36,'前提'!$C$60,IF(38<=48,'前提'!$C$61,'前提'!$C$62)))))) -> 9 | AN56: =IF(39<=6,'前提'!$C$56,IF(39<=12,'前提'!$C$57,IF(39<=18,'前提'!$C$58,IF(39<=24,'前提'!$C$59,IF(39<=36,'前提'!$C$60,IF(39<=48,'前提'!$C$61,'前提'!$C$62)))))) -> 9 | AO56: =IF(40<=6,'前提'!$C$56,IF(40<=12,'前提'!$C$57,IF(40<=18,'前提'!$C$58,IF(40<=24,'前提'!$C$59,IF(40<=36,'前提'!$C$60,IF(40<=48,'前提'!$C$61,'前提'!$C$62)))))) -> 9 | AP56: =IF(41<=6,'前提'!$C$56,IF(41<=12,'前提'!$C$57,IF(41<=18,'前提'!$C$58,IF(41<=24,'前提'!$C$59,IF(41<=36,'前提'!$C$60,IF(41<=48,'前提'!$C$61,'前提'!$C$62)))))) -> 9 | AQ56: =IF(42<=6,'前提'!$C$56,IF(42<=12,'前提'!$C$57,IF(42<=18,'前提'!$C$58,IF(42<=24,'前提'!$C$59,IF(42<=36,'前提'!$C$60,IF(42<=48,'前提'!$C$61,'前提'!$C$62)))))) -> 9 | AR56: =IF(43<=6,'前提'!$C$56,IF(43<=12,'前提'!$C$57,IF(43<=18,'前提'!$C$58,IF(43<=24,'前提'!$C$59,IF(43<=36,'前提'!$C$60,IF(43<=48,'前提'!$C$61,'前提'!$C$62)))))) -> 9 | AS56: =IF(44<=6,'前提'!$C$56,IF(44<=12,'前提'!$C$57,IF(44<=18,'前提'!$C$58,IF(44<=24,'前提'!$C$59,IF(44<=36,'前提'!$C$60,IF(44<=48,'前提'!$C$61,'前提'!$C$62)))))) -> 9 | AT56: =IF(45<=6,'前提'!$C$56,IF(45<=12,'前提'!$C$57,IF(45<=18,'前提'!$C$58,IF(45<=24,'前提'!$C$59,IF(45<=36,'前提'!$C$60,IF(45<=48,'前提'!$C$61,'前提'!$C$62)))))) -> 9 | AU56: =IF(46<=6,'前提'!$C$56,IF(46<=12,'前提'!$C$57,IF(46<=18,'前提'!$C$58,IF(46<=24,'前提'!$C$59,IF(46<=36,'前提'!$C$60,IF(46<=48,'前提'!$C$61,'前提'!$C$62)))))) -> 9 | AV56: =IF(47<=6,'前提'!$C$56,IF(47<=12,'前提'!$C$57,IF(47<=18,'前提'!$C$58,IF(47<=24,'前提'!$C$59,IF(47<=36,'前提'!$C$60,IF(47<=48,'前提'!$C$61,'前提'!$C$62)))))) -> 9 | AW56: =IF(48<=6,'前提'!$C$56,IF(48<=12,'前提'!$C$57,IF(48<=18,'前提'!$C$58,IF(48<=24,'前提'!$C$59,IF(48<=36,'前提'!$C$60,IF(48<=48,'前提'!$C$61,'前提'!$C$62)))))) -> 9 | AX56: =IF(49<=6,'前提'!$C$56,IF(49<=12,'前提'!$C$57,IF(49<=18,'前提'!$C$58,IF(49<=24,'前提'!$C$59,IF(49<=36,'前提'!$C$60,IF(49<=48,'前提'!$C$61,'前提'!$C$62)))))) -> 10 | AY56: =IF(50<=6,'前提'!$C$56,IF(50<=12,'前提'!$C$57,IF(50<=18,'前提'!$C$58,IF(50<=24,'前提'!$C$59,IF(50<=36,'前提'!$C$60,IF(50<=48,'前提'!$C$61,'前提'!$C$62)))))) -> 10 | AZ56: =IF(51<=6,'前提'!$C$56,IF(51<=12,'前提'!$C$57,IF(51<=18,'前提'!$C$58,IF(51<=24,'前提'!$C$59,IF(51<=36,'前提'!$C$60,IF(51<=48,'前提'!$C$61,'前提'!$C$62)))))) -> 10 | BA56: =IF(52<=6,'前提'!$C$56,IF(52<=12,'前提'!$C$57,IF(52<=18,'前提'!$C$58,IF(52<=24,'前提'!$C$59,IF(52<=36,'前提'!$C$60,IF(52<=48,'前提'!$C$61,'前提'!$C$62)))))) -> 10 | BB56: =IF(53<=6,'前提'!$C$56,IF(53<=12,'前提'!$C$57,IF(53<=18,'前提'!$C$58,IF(53<=24,'前提'!$C$59,IF(53<=36,'前提'!$C$60,IF(53<=48,'前提'!$C$61,'前提'!$C$62)))))) -> 10 | BC56: =IF(54<=6,'前提'!$C$56,IF(54<=12,'前提'!$C$57,IF(54<=18,'前提'!$C$58,IF(54<=24,'前提'!$C$59,IF(54<=36,'前提'!$C$60,IF(54<=48,'前提'!$C$61,'前提'!$C$62)))))) -> 10 | BD56: =IF(55<=6,'前提'!$C$56,IF(55<=12,'前提'!$C$57,IF(55<=18,'前提'!$C$58,IF(55<=24,'前提'!$C$59,IF(55<=36,'前提'!$C$60,IF(55<=48,'前提'!$C$61,'前提'!$C$62)))))) -> 10 | BE56: =IF(56<=6,'前提'!$C$56,IF(56<=12,'前提'!$C$57,IF(56<=18,'前提'!$C$58,IF(56<=24,'前提'!$C$59,IF(56<=36,'前提'!$C$60,IF(56<=48,'前提'!$C$61,'前提'!$C$62)))))) -> 10 | BF56: =IF(57<=6,'前提'!$C$56,IF(57<=12,'前提'!$C$57,IF(57<=18,'前提'!$C$58,IF(57<=24,'前提'!$C$59,IF(57<=36,'前提'!$C$60,IF(57<=48,'前提'!$C$61,'前提'!$C$62)))))) -> 10 | BG56: =IF(58<=6,'前提'!$C$56,IF(58<=12,'前提'!$C$57,IF(58<=18,'前提'!$C$58,IF(58<=24,'前提'!$C$59,IF(58<=36,'前提'!$C$60,IF(58<=48,'前提'!$C$61,'前提'!$C$62)))))) -> 10 | BH56: =IF(59<=6,'前提'!$C$56,IF(59<=12,'前提'!$C$57,IF(59<=18,'前提'!$C$58,IF(59<=24,'前提'!$C$59,IF(59<=36,'前提'!$C$60,IF(59<=48,'前提'!$C$61,'前提'!$C$62)))))) -> 10 | BI56: =IF(60<=6,'前提'!$C$56,IF(60<=12,'前提'!$C$57,IF(60<=18,'前提'!$C$58,IF(60<=24,'前提'!$C$59,IF(60<=36,'前提'!$C$60,IF(60<=48,'前提'!$C$61,'前提'!$C$62)))))) -> 10
A57: 合計 | B57: =ROUND(SUM(B51:B56),0) -> 2 | C57: =ROUND(SUM(C51:C56),0) -> 2 | D57: =ROUND(SUM(D51:D56),0) -> 2 | E57: =ROUND(SUM(E51:E56),0) -> 2 | F57: =ROUND(SUM(F51:F56),0) -> 2 | G57: =ROUND(SUM(G51:G56),0) -> 2 | H57: =ROUND(SUM(H51:H56),0) -> 6 | I57: =ROUND(SUM(I51:I56),0) -> 6 | ... BI57: =ROUND(SUM(BI51:BI56),0) -> 33

Sheet 年次事業計画
A1: 年次事業計画（5年）
B3: 1年目 | C3: 2年目 | D3: 3年目 | E3: 4年目 | F3: 5年目
A4: 【顧客数】
A5: SuguDesk期末院数 | B5: ='月次事業計画'!M10 -> 41 | C5: ='月次事業計画'!Y10 -> 97 | D5: ='月次事業計画'!AK10 -> 167 | E5: ='月次事業計画'!AW10 -> 244 | F5: ='月次事業計画'!BI10 -> 325
A6: BPO期末院数 | B6: ='月次事業計画'!M14 -> 6 | C6: ='月次事業計画'!Y14 -> 42 | D6: ='月次事業計画'!AK14 -> 117 | E6: ='月次事業計画'!AW14 -> 224 | F6: ='月次事業計画'!BI14 -> 363
A8: 【売上】
A9: MRR（期末） | B9: ='月次事業計画'!M21 -> 1371500 | C9: ='月次事業計画'!Y21 -> 9515500 | D9: ='月次事業計画'!AK21 -> 25320500 | E9: ='月次事業計画'!AW21 -> 47606000 | F9: ='月次事業計画'!BI21 -> 76337500
A10: ARR（期末） | B10: =B9*12 -> 16458000 | C10: =C9*12 -> 114186000 | D10: =D9*12 -> 303846000 | E10: =E9*12 -> 571272000 | F10: =F9*12 -> 916050000
A11: 年間売上合計 | B11: =SUM('月次事業計画'!B22:M22) -> 13780500 | C11: =SUM('月次事業計画'!N22:Y22) -> 79402000 | D11: =SUM('月次事業計画'!Z22:AK22) -> 232437000 | E11: =SUM('月次事業計画'!AL22:AW22) -> 469003000 | F11: =SUM('月次事業計画'!AX22:BI22) -> 784374000
A13: 【コスト】
A14: 年間コスト合計 | B14: =SUM('月次事業計画'!B35:M35) -> 20807676 | C14: =SUM('月次事業計画'!N35:Y35) -> 52953464 | D14: =SUM('月次事業計画'!Z35:AK35) -> 86561176 | E14: =SUM('月次事業計画'!AL35:AW35) -> 106435044 | F14: =SUM('月次事業計画'!AX35:BI35) -> 127264432
A16: 【損益】
A17: 年間営業利益 | B17: =B11-B14 -> -7027176 | C17: =C11-C14 -> 26448536 | D17: =D11-D14 -> 145875824 | E17: =E11-E14 -> 362567956 | F17: =F11-F14 -> 657109568
A18: 営業利益率 | B18: =IF(B11<>0,B17/B11,0) -> -0.50993621 | C18: =IF(C11<>0,C17/C11,0) -> 0.3330966 | D18: =IF(D11<>0,D17/D11,0) -> 0.62759296 | E18: =IF(E11<>0,E17/E11,0) -> 0.77306106 | F18: =IF(F11<>0,F17/F11,0) -> 0.83775032
A19: 累積損益 | B19: ='月次事業計画'!M40 -> -7027176 | C19: ='月次事業計画'!Y40 -> 19421360 | D19: ='月次事業計画'!AK40 -> 165297184 | E19: ='月次事業計画'!AW40 -> 527865140 | F19: ='月次事業計画'!BI40 -> 1184974708
A21: 期末キャッシュ残高 | B21: ='月次事業計画'!M47 -> 30397824 | C21: ='月次事業計画'!Y47 -> 156771360 | D21: ='月次事業計画'!AK47 -> 302572184 | E21: ='月次事業計画'!AW47 -> 665065140 | F21: ='月次事業計画'!BI47 -> 1322099708
A22: 期末人員合計 | B22: ='月次事業計画'!M57 -> 7 | C22: ='月次事業計画'!Y57 -> 15 | D22: ='月次事業計画'!AK57 -> 22 | E22: ='月次事業計画'!AW57 -> 28 | F22: ='月次事業計画'!BI57 -> 33

Sheet 資本政策表
A1: 資本政策表
B3: 設立 | C3: シード | D3: Series A
A4: プレバリュー | C4: ='前提'!B76 -> 170000000 | D4: ='前提'!B84 -> 500000000
A5: エクイティ調達額 | B5: ='前提'!B75 -> 1000000 | C5: ='前提'!B77+'前提'!B78+'前提'!B79 -> 32500000 | D5: ='前提'!B85 -> 100000000
A6: デット（公庫） | C6: ='前提'!B80 -> 5000000
A7: ポストバリュー | C7: =C4+C5 -> 202500000 | D7: =D4+D5 -> 600000000
A9: 【株式数】
A10: シード株価 | C10: ='前提'!B76/'前提'!B74 -> 170
A11: VC新規株数 | C11: =ROUNDDOWN('前提'!B77/C10,0) -> 176470
A12: 佐藤さん株数 | C12: =ROUNDDOWN('前提'!B78/C10,0) -> 11764
A13: 洋介さん株数 | C13: =ROUNDDOWN('前提'!B79/C10,0) -> 2941
A14: シード後 発行済株数 | C14: ='前提'!B74+C11+C12+C13 -> 1191175
A15: Series A株価 | D15: ='前提'!B84/C14 -> 419.7536
A16: Series A新規株数 | D16: =ROUNDDOWN('前提'!B85/D15,0) -> 238235
A17: SOPプール株数 | D17: =ROUNDDOWN((C14+D16)*'前提'!B86/(1-'前提'!B86),0) -> 102647
A18: Series A後 発行済株数 | D18: =C14+D16+D17 -> 1532057
A20: 【Cap Table 持分比率】
A21: Anna（代表） | C21: ='前提'!B74/C14 -> 0.83950721 | D21: ='前提'!B74/D18 -> 0.65271723
A22: Oikaze | C22: =C11/C14 -> 0.14814784 | D22: =C11/D18 -> 0.11518501
A23: 佐藤さん | C23: =C12/C14 -> 0.0098759628 | D23: =C12/D18 -> 0.0076785655
A24: 洋介さん | C24: =C13/C14 -> 0.0024689907 | D24: =C13/D18 -> 0.0019196414
A25: SOPプール | D25: =D17/D18 -> 0.066999465
A26: Series A投資家 | D26: =D16/D18 -> 0.15550009
A27: 合計 | C27: =SUM(C21:C26) -> 1 | D27: =SUM(D21:D26) -> 1
A31: みなし優先に入ってもらうのが
A33: シードラウンドの当事者にエンジェルがいる
A34: みなし優先に調達します→これで
A36: ポスト2億にする株価で分配をする
A37: エンジェル2人が300万ぐらいにおさめてくれる
A39: Oikaze
A40: 投資委員会があって、16日（木）12:00に
A41: →ピッチデックと事業計画

Sheet 資金使途
A1: シードラウンド 資金使途
A2: 調達額合計 | B2: ='前提'!B77+'前提'!B78+'前提'!B79+'前提'!B80 -> 37500000
A4: 項目 | B4: 18ヶ月合計 | C4: 比率 | D4: 備考
A5: CEO人件費 | B5: =SUM('月次事業計画'!B25:S25) -> 5400000 | C5: =B5/B15 -> 0.12153201
A6: エンジニア | B6: =SUM('月次事業計画'!B26:S26) -> 7335000 | C6: =B6/B15 -> 0.16508097 | D6: 業務委託
A7: CS人件費 | B7: =SUM('月次事業計画'!B27:S27) -> 8050000 | C7: =B7/B15 -> 0.18117271 | D7: 院数連動
A8: 営業サポート | B8: =SUM('月次事業計画'!B28:S28) -> 3600000 | C8: =B8/B15 -> 0.081021337 | D8: 業務委託
A9: BPO事務長 | B9: =SUM('月次事業計画'!B29:S29) -> 7200000 | C9: =B9/B15 -> 0.16204267
A10: BPOオペ | B10: =SUM('月次事業計画'!B30:S30) -> 7200000 | C10: =B10/B15 -> 0.16204267
A11: LLM API | B11: =SUM('月次事業計画'!B31:S31) -> 7740 | C11: =B11/B15 -> 0.00017419587 | D11: Vertex AI実績ベース
A12: インフラ | B12: =SUM('月次事業計画'!B32:S32) -> 240000 | C12: =B12/B15 -> 0.0054014225 | D12: Cloud SQL+Run
A13: 営業/GTM | B13: =SUM('月次事業計画'!B33:S33) -> 1800000 | C13: =B13/B15 -> 0.040510668
A14: その他 | B14: =SUM('月次事業計画'!B34:S34) -> 3600000 | C14: =B14/B15 -> 0.081021337 | D14: 法務・会計
A15: 合計 | B15: =SUM(B5:B14) -> 44432740
A17: 売上における補填 | B17: =SUM('月次事業計画'!B22:S22) -> 40652000
A18: 予備費 | B18: =B15-B17 -> 3780740
A21: 【ランウェイ試算】
A22: Phase1バーンレート（月平均） | B22: =AVERAGE('月次事業計画'!B35:G35) -> 1132572
A23: Phase2バーンレート（月平均） | B23: =AVERAGE('月次事業計画'!H35:M35) -> 2335374
A24: ランウェイ（売上ゼロ想定） | B24: =B2/B22 -> 33.110478
A25: M12末キャッシュ | B25: ='月次事業計画'!M47 -> 30397824
A26: M18末キャッシュ | B26: ='月次事業計画'!S47 -> 33606760
A27: M24末キャッシュ | B27: ='月次事業計画'!Y47 -> 156771360
A28: M36末キャッシュ | B28: ='月次事業計画'!AK47 -> 302572184
A29: M48末キャッシュ | B29: ='月次事業計画'!AW47 -> 665065140
A30: M60末キャッシュ | B30: ='月次事業計画'!BI47 -> 1322099708
