Workbook

Sheet 前提
A1: SuguDesk 事業計画v5 前提条件
A3: 【価格前提】
A4: SuguDesk ARPA（月額） | B4: 11500 | D4: ライト/スタンダード平均
A5: SuguDesk 導入費（初期） | B5: 225000 | D5: 1院あたり平均
A6: BPO事務長代行 ARPA（月額） | B6: 150000 | D6: 算定業務＋事務長代行
A7: BPO採用/集患 ARPA（月額） | B7: 50000 | D7: BPO#2、M13以降
A8: SuguDeskチャーン率（月次） | B8: 0.02
A9: BPOチャーン率（月次） | B9: 0.01 | D9: 粘着性高い
A11: 【売上計上前提】
A12: 新規契約 月内係数 | B12: 0.5 | D12: 期中入金想定で半月分計上
A13: 導入費 計上係数 | B13: 1 | D13: 契約月に全額
A15: 【SuguDesk直接原価（変動費）】
A16: FAQ構築原価/新規件 | B16: 36000 | D16: 30h×¥1,200（pricing.md）
A17: 月額メンテ原価/件 | B17: 4800 | D17: 4h×¥1,200
A18: LLM API/件・月 | B18: 12 | D18: Gemini Flash実績
A20: 【インフラ（顧客数連動）】
A21: Cloud SQL 〜50院 | B21: 8000
A22: Cloud SQL 50-200院 | B22: 15000
A23: Cloud SQL 200院超 | B23: 25000
A24: Cloud Run 〜50院 | B24: 2000
A25: Cloud Run 50-200院 | B25: 5000
A26: Cloud Run 200院超 | B26: 15000
A28: 【人員担当比率（レバー）】
A29: BPO事務長 担当社数/人 | B29: 10 | D29: ★変数：下げると人件費増、上げると減
A30: BPOオペ 担当社数/人 | B30: 15 | D30: ★変数
A31: CS 担当社数/人 | B31: 20 | D31: ★変数
A33: 【人件費単価（月額）】
A34: CEO報酬 | B34: 300000
A35: エンジニア時給（業務委託） | B35: 5000
A36: エンジニア月間稼働h(P1) | B36: 64.5
A37: エンジニア月間稼働h(P2) | B37: 40
A38: エンジニア正社員 単価/人 | B38: 700000
A39: BPO事務長 単価/人 | B39: 400000
A40: BPOオペ 単価/人 | B40: 200000
A41: 営業サポート 単価/人 | B41: 200000
A42: CS 単価/人 | B42: 350000
A43: 社会保険料率（正社員のみ） | B43: 0.15 | D43: CEO・エンジニア正社員に適用
A44: 福利厚生/人・月（全員） | B44: 5000
A46: 【固定費・販管費（月額）】
A47: オフィス家賃（Phase1-3） | B47: 50000 | D47: コワーキング想定
A48: オフィス家賃（Phase4+） | B48: 150000
A49: SaaS費用/人・月 | B49: 20000 | D49: Slack/Notion/Figma等
A50: 通信費/月 | B50: 10000
A51: 会計顧問/月 | B51: 50000
A52: 弁護士・法務/月 | B52: 50000
A53: 情報セキュリティ保険/月 | B53: 30000 | D53: 医療データ取扱必須
A54: 決済手数料率 | B54: 0.035 | D54: Stripe等
A55: その他固定費/月 | B55: 100000 | D55: 雑費
A57: 【新規SuguDesk契約数（Phase別、月間）】
A58: Phase1 | B58: 2 | D58: M1-6 直販
A59: Phase2 | B59: 5 | D59: M7-12 ギミック提携加速
A60: Phase3 | B60: 5 | D60: M13-18
A61: Phase4 | B61: 6 | D61: M19-24 SeriesA前
A62: Phase5 | B62: 8 | D62: M25-36 SeriesA後
A63: Phase6 | B63: 10 | D63: M37-48 スケール
A64: Phase7 | B64: 12 | D64: M49-60 成熟
A66: 【BPOアップセル率（Phase別、月次）】
A67: Phase1 | B67: 0 | D67: P1: BPO体制立ち上げ前
A68: Phase2 | B68: 0.06 | D68: P2: ギミック経由＆既存深耕
A69: Phase3 | B69: 0.05
A70: Phase4 | B70: 0.05
A71: Phase5 | B71: 0.04
A72: Phase6 | B72: 0.04
A73: Phase7 | B73: 0.03
A75: 【広告宣伝費（Phase別、月額）】
A76: Phase1 | B76: 50000
A77: Phase2 | B77: 200000
A78: Phase3 | B78: 300000
A79: Phase4 | B79: 500000
A80: Phase5 | B80: 800000
A81: Phase6 | B81: 1000000
A82: Phase7 | B82: 1500000
A84: 【エンジニア正社員人員（Phase別）】 | D84: P1-2は業務委託時給、P3+から正社員
A85: Phase1 | B85: 0
A86: Phase2 | B86: 0
A87: Phase3 | B87: 1
A88: Phase4 | B88: 1
A89: Phase5 | B89: 2
A90: Phase6 | B90: 2
A91: Phase7 | B91: 2
A93: 【営業サポート人員（Phase別）】
A94: Phase1 | B94: 1
A95: Phase2 | B95: 1
A96: Phase3 | B96: 1
A97: Phase4 | B97: 1
A98: Phase5 | B98: 2
A99: Phase6 | B99: 2
A100: Phase7 | B100: 3
A102: 【資本政策前提（Misuzu条件反映）】
A103: 設立時株数 | B103: 1000000
A104: 設立時資本金 | B104: 1000000 | D104: 1株1円
A105: シードプレバリュー | B105: 170000000 | D105: 1.7億
A106: Oikaze（みなし優先株） | B106: 26000070 | D106: Post2億・希薄化15%調整
A107: 佐藤さん（エンジェル） | B107: 3000000
A108: 洋介さん（エンジェル） | B108: 999930 | D108: エンジェル枠合計¥3,999,930
A109: 公庫（資本性ローン・デット） | B109: 5000000 | D109: 希薄化対象外
A110: 公庫金利（年率） | B110: 0.015
A111: 公庫据置期間（月） | B111: 24
A112: 公庫返済期間（月） | B112: 60
A113: Series Aプレバリュー | B113: 500000000 | D113: 想定
...

Sheet 月次事業計画
A1: 月次事業計画（5年=60ヶ月）
A2: フェーズ | B2: P1 | C2: P1 | D2: P1 | E2: P1 | F2: P1 | G2: P1 | H2: P2 | I2: P2 | J2: P2 | K2: P2 | L2: P2 | M2: P2 | N2: P3 | O2: P3 | P2: P3 | Q2: P3 | R2: P3 | S2: P3 | T2: P4 | U2: P4 | V2: P4 | W2: P4 | X2: P4 | Y2: P4 | Z2: P5 | AA2: P5 | AB2: P5 | AC2: P5 | AD2: P5 | AE2: P5 | AF2: P5 | AG2: P5 | AH2: P5 | AI2: P5 | AJ2: P5 | AK2: P5 | AL2: P6 | AM2: P6 | AN2: P6 | AO2: P6 | AP2: P6 | AQ2: P6 | AR2: P6 | AS2: P6 | AT2: P6 | AU2: P6 | AV2: P6 | AW2: P6 | AX2: P7 | AY2: P7 | AZ2: P7 | BA2: P7 | BB2: P7 | BC2: P7 | BD2: P7 | BE2: P7 | BF2: P7 | BG2: P7 | BH2: P7 | BI2: P7
A3: 月 | B3: M1 | C3: M2 | D3: M3 | E3: M4 | F3: M5 | G3: M6 | H3: M7 | I3: M8 | J3: M9 | K3: M10 | L3: M11 | M3: M12 | N3: M13 | O3: M14 | P3: M15 | Q3: M16 | R3: M17 | S3: M18 | T3: M19 | U3: M20 | V3: M21 | W3: M22 | X3: M23 | Y3: M24 | Z3: M25 | AA3: M26 | AB3: M27 | AC3: M28 | AD3: M29 | AE3: M30 | AF3: M31 | AG3: M32 | AH3: M33 | AI3: M34 | AJ3: M35 | AK3: M36 | AL3: M37 | AM3: M38 | AN3: M39 | AO3: M40 | AP3: M41 | AQ3: M42 | AR3: M43 | AS3: M44 | AT3: M45 | AU3: M46 | AV3: M47 | AW3: M48 | AX3: M49 | AY3: M50 | AZ3: M51 | BA3: M52 | BB3: M53 | BC3: M54 | BD3: M55 | BE3: M56 | BF3: M57 | BG3: M58 | BH3: M59 | BI3: M60
A4: 【営業活動】
A5: 月間新規SuguDesk契約数 | B5: =IF(1<=6,'前提'!$B$58,IF(1<=12,'前提'!$B$59,IF(1<=18,'前提'!$B$60,IF(1<=24,'前提'!$B$61,IF(1<=36,'前提'!$B$62,IF(1<=48,'前提'!$B$63,'前提'!$B$64)))))) | C5: =IF(2<=6,'前提'!$B$58,IF(2<=12,'前提'!$B$59,IF(2<=18,'前提'!$B$60,IF(2<=24,'前提'!$B$61,IF(2<=36,'前提'!$B$62,IF(2<=48,'前提'!$B$63,'前提'!$B$64)))))) | D5: =IF(3<=6,'前提'!$B$58,IF(3<=12,'前提'!$B$59,IF(3<=18,'前提'!$B$60,IF(3<=24,'前提'!$B$61,IF(3<=36,'前提'!$B$62,IF(3<=48,'前提'!$B$63,'前提'!$B$64)))))) | E5: =IF(4<=6,'前提'!$B$58,IF(4<=12,'前提'!$B$59,IF(4<=18,'前提'!$B$60,IF(4<=24,'前提'!$B$61,IF(4<=36,'前提'!$B$62,IF(4<=48,'前提'!$B$63,'前提'!$B$64)))))) | F5: =IF(5<=6,'前提'!$B$58,IF(5<=12,'前提'!$B$59,IF(5<=18,'前提'!$B$60,IF(5<=24,'前提'!$B$61,IF(5<=36,'前提'!$B$62,IF(5<=48,'前提'!$B$63,'前提'!$B$64)))))) | G5: =IF(6<=6,'前提'!$B$58,IF(6<=12,'前提'!$B$59,IF(6<=18,'前提'!$B$60,IF(6<=24,'前提'!$B$61,IF(6<=36,'前提'!$B$62,IF(6<=48,'前提'!$B$63,'前提'!$B$64)))))) | H5: =IF(7<=6,'前提'!$B$58,IF(7<=12,'前提'!$B$59,IF(7<=18,'前提'!$B$60,IF(7<=24,'前提'!$B$61,IF(7<=36,'前提'!$B$62,IF(7<=48,'前提'!$B$63,'前提'!$B$64)))))) | I5: =IF(8<=6,'前提'!$B$58,IF(8<=12,'前提'!$B$59,IF(8<=18,'前提'!$B$60,IF(8<=24,'前提'!$B$61,IF(8<=36,'前提'!$B$62,IF(8<=48,'前提'!$B$63,'前提'!$B$64)))))) | J5: =IF(9<=6,'前提'!$B$58,IF(9<=12,'前提'!$B$59,IF(9<=18,'前提'!$B$60,IF(9<=24,'前提'!$B$61,IF(9<=36,'前提'!$B$62,IF(9<=48,'前提'!$B$63,'前提'!$B$64)))))) | K5: =IF(10<=6,'前提'!$B$58,IF(10<=12,'前提'!$B$59,IF(10<=18,'前提'!$B$60,IF(10<=24,'前提'!$B$61,IF(10<=36,'前提'!$B$62,IF(10<=48,'前提'!$B$63,'前提'!$B$64)))))) | L5: =IF(11<=6,'前提'!$B$58,IF(11<=12,'前提'!$B$59,IF(11<=18,'前提'!$B$60,IF(11<=24,'前提'!$B$61,IF(11<=36,'前提'!$B$62,IF(11<=48,'前提'!$B$63,'前提'!$B$64)))))) | M5: =IF(12<=6,'前提'!$B$58,IF(12<=12,'前提'!$B$59,IF(12<=18,'前提'!$B$60,IF(12<=24,'前提'!$B$61,IF(12<=36,'前提'!$B$62,IF(12<=48,'前提'!$B$63,'前提'!$B$64)))))) | N5: =IF(13<=6,'前提'!$B$58,IF(13<=12,'前提'!$B$59,IF(13<=18,'前提'!$B$60,IF(13<=24,'前提'!$B$61,IF(13<=36,'前提'!$B$62,IF(13<=48,'前提'!$B$63,'前提'!$B$64)))))) | O5: =IF(14<=6,'前提'!$B$58,IF(14<=12,'前提'!$B$59,IF(14<=18,'前提'!$B$60,IF(14<=24,'前提'!$B$61,IF(14<=36,'前提'!$B$62,IF(14<=48,'前提'!$B$63,'前提'!$B$64)))))) | P5: =IF(15<=6,'前提'!$B$58,IF(15<=12,'前提'!$B$59,IF(15<=18,'前提'!$B$60,IF(15<=24,'前提'!$B$61,IF(15<=36,'前提'!$B$62,IF(15<=48,'前提'!$B$63,'前提'!$B$64)))))) | Q5: =IF(16<=6,'前提'!$B$58,IF(16<=12,'前提'!$B$59,IF(16<=18,'前提'!$B$60,IF(16<=24,'前提'!$B$61,IF(16<=36,'前提'!$B$62,IF(16<=48,'前提'!$B$63,'前提'!$B$64)))))) | R5: =IF(17<=6,'前提'!$B$58,IF(17<=12,'前提'!$B$59,IF(17<=18,'前提'!$B$60,IF(17<=24,'前提'!$B$61,IF(17<=36,'前提'!$B$62,IF(17<=48,'前提'!$B$63,'前提'!$B$64)))))) | S5: =IF(18<=6,'前提'!$B$58,IF(18<=12,'前提'!$B$59,IF(18<=18,'前提'!$B$60,IF(18<=24,'前提'!$B$61,IF(18<=36,'前提'!$B$62,IF(18<=48,'前提'!$B$63,'前提'!$B$64)))))) | T5: =IF(19<=6,'前提'!$B$58,IF(19<=12,'前提'!$B$59,IF(19<=18,'前提'!$B$60,IF(19<=24,'前提'!$B$61,IF(19<=36,'前提'!$B$62,IF(19<=48,'前提'!$B$63,'前提'!$B$64)))))) | U5: =IF(20<=6,'前提'!$B$58,IF(20<=12,'前提'!$B$59,IF(20<=18,'前提'!$B$60,IF(20<=24,'前提'!$B$61,IF(20<=36,'前提'!$B$62,IF(20<=48,'前提'!$B$63,'前提'!$B$64)))))) | V5: =IF(21<=6,'前提'!$B$58,IF(21<=12,'前提'!$B$59,IF(21<=18,'前提'!$B$60,IF(21<=24,'前提'!$B$61,IF(21<=36,'前提'!$B$62,IF(21<=48,'前提'!$B$63,'前提'!$B$64)))))) | W5: =IF(22<=6,'前提'!$B$58,IF(22<=12,'前提'!$B$59,IF(22<=18,'前提'!$B$60,IF(22<=24,'前提'!$B$61,IF(22<=36,'前提'!$B$62,IF(22<=48,'前提'!$B$63,'前提'!$B$64)))))) | X5: =IF(23<=6,'前提'!$B$58,IF(23<=12,'前提'!$B$59,IF(23<=18,'前提'!$B$60,IF(23<=24,'前提'!$B$61,IF(23<=36,'前提'!$B$62,IF(23<=48,'前提'!$B$63,'前提'!$B$64)))))) | Y5: =IF(24<=6,'前提'!$B$58,IF(24<=12,'前提'!$B$59,IF(24<=18,'前提'!$B$60,IF(24<=24,'前提'!$B$61,IF(24<=36,'前提'!$B$62,IF(24<=48,'前提'!$B$63,'前提'!$B$64)))))) | Z5: =IF(25<=6,'前提'!$B$58,IF(25<=12,'前提'!$B$59,IF(25<=18,'前提'!$B$60,IF(25<=24,'前提'!$B$61,IF(25<=36,'前提'!$B$62,IF(25<=48,'前提'!$B$63,'前提'!$B$64)))))) | AA5: =IF(26<=6,'前提'!$B$58,IF(26<=12,'前提'!$B$59,IF(26<=18,'前提'!$B$60,IF(26<=24,'前提'!$B$61,IF(26<=36,'前提'!$B$62,IF(26<=48,'前提'!$B$63,'前提'!$B$64)))))) | AB5: =IF(27<=6,'前提'!$B$58,IF(27<=12,'前提'!$B$59,IF(27<=18,'前提'!$B$60,IF(27<=24,'前提'!$B$61,IF(27<=36,'前提'!$B$62,IF(27<=48,'前提'!$B$63,'前提'!$B$64)))))) | AC5: =IF(28<=6,'前提'!$B$58,IF(28<=12,'前提'!$B$59,IF(28<=18,'前提'!$B$60,IF(28<=24,'前提'!$B$61,IF(28<=36,'前提'!$B$62,IF(28<=48,'前提'!$B$63,'前提'!$B$64)))))) | AD5: =IF(29<=6,'前提'!$B$58,IF(29<=12,'前提'!$B$59,IF(29<=18,'前提'!$B$60,IF(29<=24,'前提'!$B$61,IF(29<=36,'前提'!$B$62,IF(29<=48,'前提'!$B$63,'前提'!$B$64)))))) | AE5: =IF(30<=6,'前提'!$B$58,IF(30<=12,'前提'!$B$59,IF(30<=18,'前提'!$B$60,IF(30<=24,'前提'!$B$61,IF(30<=36,'前提'!$B$62,IF(30<=48,'前提'!$B$63,'前提'!$B$64)))))) | AF5: =IF(31<=6,'前提'!$B$58,IF(31<=12,'前提'!$B$59,IF(31<=18,'前提'!$B$60,IF(31<=24,'前提'!$B$61,IF(31<=36,'前提'!$B$62,IF(31<=48,'前提'!$B$63,'前提'!$B$64)))))) | AG5: =IF(32<=6,'前提'!$B$58,IF(32<=12,'前提'!$B$59,IF(32<=18,'前提'!$B$60,IF(32<=24,'前提'!$B$61,IF(32<=36,'前提'!$B$62,IF(32<=48,'前提'!$B$63,'前提'!$B$64)))))) | AH5: =IF(33<=6,'前提'!$B$58,IF(33<=12,'前提'!$B$59,IF(33<=18,'前提'!$B$60,IF(33<=24,'前提'!$B$61,IF(33<=36,'前提'!$B$62,IF(33<=48,'前提'!$B$63,'前提'!$B$64)))))) | AI5: =IF(34<=6,'前提'!$B$58,IF(34<=12,'前提'!$B$59,IF(34<=18,'前提'!$B$60,IF(34<=24,'前提'!$B$61,IF(34<=36,'前提'!$B$62,IF(34<=48,'前提'!$B$63,'前提'!$B$64)))))) | AJ5: =IF(35<=6,'前提'!$B$58,IF(35<=12,'前提'!$B$59,IF(35<=18,'前提'!$B$60,IF(35<=24,'前提'!$B$61,IF(35<=36,'前提'!$B$62,IF(35<=48,'前提'!$B$63,'前提'!$B$64)))))) | AK5: =IF(36<=6,'前提'!$B$58,IF(36<=12,'前提'!$B$59,IF(36<=18,'前提'!$B$60,IF(36<=24,'前提'!$B$61,IF(36<=36,'前提'!$B$62,IF(36<=48,'前提'!$B$63,'前提'!$B$64)))))) | AL5: =IF(37<=6,'前提'!$B$58,IF(37<=12,'前提'!$B$59,IF(37<=18,'前提'!$B$60,IF(37<=24,'前提'!$B$61,IF(37<=36,'前提'!$B$62,IF(37<=48,'前提'!$B$63,'前提'!$B$64)))))) | AM5: =IF(38<=6,'前提'!$B$58,IF(38<=12,'前提'!$B$59,IF(38<=18,'前提'!$B$60,IF(38<=24,'前提'!$B$61,IF(38<=36,'前提'!$B$62,IF(38<=48,'前提'!$B$63,'前提'!$B$64)))))) | AN5: =IF(39<=6,'前提'!$B$58,IF(39<=12,'前提'!$B$59,IF(39<=18,'前提'!$B$60,IF(39<=24,'前提'!$B$61,IF(39<=36,'前提'!$B$62,IF(39<=48,'前提'!$B$63,'前提'!$B$64)))))) | AO5: =IF(40<=6,'前提'!$B$58,IF(40<=12,'前提'!$B$59,IF(40<=18,'前提'!$B$60,IF(40<=24,'前提'!$B$61,IF(40<=36,'前提'!$B$62,IF(40<=48,'前提'!$B$63,'前提'!$B$64)))))) | AP5: =IF(41<=6,'前提'!$B$58,IF(41<=12,'前提'!$B$59,IF(41<=18,'前提'!$B$60,IF(41<=24,'前提'!$B$61,IF(41<=36,'前提'!$B$62,IF(41<=48,'前提'!$B$63,'前提'!$B$64)))))) | AQ5: =IF(42<=6,'前提'!$B$58,IF(42<=12,'前提'!$B$59,IF(42<=18,'前提'!$B$60,IF(42<=24,'前提'!$B$61,IF(42<=36,'前提'!$B$62,IF(42<=48,'前提'!$B$63,'前提'!$B$64)))))) | AR5: =IF(43<=6,'前提'!$B$58,IF(43<=12,'前提'!$B$59,IF(43<=18,'前提'!$B$60,IF(43<=24,'前提'!$B$61,IF(43<=36,'前提'!$B$62,IF(43<=48,'前提'!$B$63,'前提'!$B$64)))))) | AS5: =IF(44<=6,'前提'!$B$58,IF(44<=12,'前提'!$B$59,IF(44<=18,'前提'!$B$60,IF(44<=24,'前提'!$B$61,IF(44<=36,'前提'!$B$62,IF(44<=48,'前提'!$B$63,'前提'!$B$64)))))) | AT5: =IF(45<=6,'前提'!$B$58,IF(45<=12,'前提'!$B$59,IF(45<=18,'前提'!$B$60,IF(45<=24,'前提'!$B$61,IF(45<=36,'前提'!$B$62,IF(45<=48,'前提'!$B$63,'前提'!$B$64)))))) | AU5: =IF(46<=6,'前提'!$B$58,IF(46<=12,'前提'!$B$59,IF(46<=18,'前提'!$B$60,IF(46<=24,'前提'!$B$61,IF(46<=36,'前提'!$B$62,IF(46<=48,'前提'!$B$63,'前提'!$B$64)))))) | AV5: =IF(47<=6,'前提'!$B$58,IF(47<=12,'前提'!$B$59,IF(47<=18,'前提'!$B$60,IF(47<=24,'前提'!$B$61,IF(47<=36,'前提'!$B$62,IF(47<=48,'前提'!$B$63,'前提'!$B$64)))))) | AW5: =IF(48<=6,'前提'!$B$58,IF(48<=12,'前提'!$B$59,IF(48<=18,'前提'!$B$60,IF(48<=24,'前提'!$B$61,IF(48<=36,'前提'!$B$62,IF(48<=48,'前提'!$B$63,'前提'!$B$64)))))) | AX5: =IF(49<=6,'前提'!$B$58,IF(49<=12,'前提'!$B$59,IF(49<=18,'前提'!$B$60,IF(49<=24,'前提'!$B$61,IF(49<=36,'前提'!$B$62,IF(49<=48,'前提'!$B$63,'前提'!$B$64)))))) | AY5: =IF(50<=6,'前提'!$B$58,IF(50<=12,'前提'!$B$59,IF(50<=18,'前提'!$B$60,IF(50<=24,'前提'!$B$61,IF(50<=36,'前提'!$B$62,IF(50<=48,'前提'!$B$63,'前提'!$B$64)))))) | AZ5: =IF(51<=6,'前提'!$B$58,IF(51<=12,'前提'!$B$59,IF(51<=18,'前提'!$B$60,IF(51<=24,'前提'!$B$61,IF(51<=36,'前提'!$B$62,IF(51<=48,'前提'!$B$63,'前提'!$B$64)))))) | BA5: =IF(52<=6,'前提'!$B$58,IF(52<=12,'前提'!$B$59,IF(52<=18,'前提'!$B$60,IF(52<=24,'前提'!$B$61,IF(52<=36,'前提'!$B$62,IF(52<=48,'前提'!$B$63,'前提'!$B$64)))))) | BB5: =IF(53<=6,'前提'!$B$58,IF(53<=12,'前提'!$B$59,IF(53<=18,'前提'!$B$60,IF(53<=24,'前提'!$B$61,IF(53<=36,'前提'!$B$62,IF(53<=48,'前提'!$B$63,'前提'!$B$64)))))) | BC5: =IF(54<=6,'前提'!$B$58,IF(54<=12,'前提'!$B$59,IF(54<=18,'前提'!$B$60,IF(54<=24,'前提'!$B$61,IF(54<=36,'前提'!$B$62,IF(54<=48,'前提'!$B$63,'前提'!$B$64)))))) | BD5: =IF(55<=6,'前提'!$B$58,IF(55<=12,'前提'!$B$59,IF(55<=18,'前提'!$B$60,IF(55<=24,'前提'!$B$61,IF(55<=36,'前提'!$B$62,IF(55<=48,'前提'!$B$63,'前提'!$B$64)))))) | BE5: =IF(56<=6,'前提'!$B$58,IF(56<=12,'前提'!$B$59,IF(56<=18,'前提'!$B$60,IF(56<=24,'前提'!$B$61,IF(56<=36,'前提'!$B$62,IF(56<=48,'前提'!$B$63,'前提'!$B$64)))))) | BF5: =IF(57<=6,'前提'!$B$58,IF(57<=12,'前提'!$B$59,IF(57<=18,'前提'!$B$60,IF(57<=24,'前提'!$B$61,IF(57<=36,'前提'!$B$62,IF(57<=48,'前提'!$B$63,'前提'!$B$64)))))) | BG5: =IF(58<=6,'前提'!$B$58,IF(58<=12,'前提'!$B$59,IF(58<=18,'前提'!$B$60,IF(58<=24,'前提'!$B$61,IF(58<=36,'前提'!$B$62,IF(58<=48,'前提'!$B$63,'前提'!$B$64)))))) | BH5: =IF(59<=6,'前提'!$B$58,IF(59<=12,'前提'!$B$59,IF(59<=18,'前提'!$B$60,IF(59<=24,'前提'!$B$61,IF(59<=36,'前提'!$B$62,IF(59<=48,'前提'!$B$63,'前提'!$B$64)))))) | BI5: =IF(60<=6,'前提'!$B$58,IF(60<=12,'前提'!$B$59,IF(60<=18,'前提'!$B$60,IF(60<=24,'前提'!$B$61,IF(60<=36,'前提'!$B$62,IF(60<=48,'前提'!$B$63,'前提'!$B$64))))))
A7: 【顧客数】
A8: SuguDesk期首 | B8: 1 | C8: =B10 | D8: =C10 | E8: =D10 | F8: =E10 | G8: =F10 | H8: =G10 | I8: =H10 | J8: =I10 | ... BI8: =BH10
A9: SuguDesk解約 | B9: =ROUNDDOWN(B8*'前提'!$B$8,0) | C9: =ROUNDDOWN(C8*'前提'!$B$8,0) | D9: =ROUNDDOWN(D8*'前提'!$B$8,0) | E9: =ROUNDDOWN(E8*'前提'!$B$8,0) | F9: =ROUNDDOWN(F8*'前提'!$B$8,0) | G9: =ROUNDDOWN(G8*'前提'!$B$8,0) | H9: =ROUNDDOWN(H8*'前提'!$B$8,0) | I9: =ROUNDDOWN(I8*'前提'!$B$8,0) | ... BI9: =ROUNDDOWN(BI8*'前提'!$B$8,0)
A10: SuguDesk期末 | B10: =B8+B5-B9 | C10: =C8+C5-C9 | D10: =D8+D5-D9 | E10: =E8+E5-E9 | F10: =F8+F5-F9 | G10: =G8+G5-G9 | H10: =H8+H5-H9 | I10: =I8+I5-I9 | ... BI10: =BI8+BI5-BI9
A11: BPO新規転換 | B11: =IF(1>=7,ROUNDDOWN(B10*(IF(1<=6,'前提'!$B$67,IF(1<=12,'前提'!$B$68,IF(1<=18,'前提'!$B$69,IF(1<=24,'前提'!$B$70,IF(1<=36,'前提'!$B$71,IF(1<=48,'前提'!$B$72,'前提'!$B$73))))))),0),0) | C11: =IF(2>=7,ROUNDDOWN(C10*(IF(2<=6,'前提'!$B$67,IF(2<=12,'前提'!$B$68,IF(2<=18,'前提'!$B$69,IF(2<=24,'前提'!$B$70,IF(2<=36,'前提'!$B$71,IF(2<=48,'前提'!$B$72,'前提'!$B$73))))))),0),0) | D11: =IF(3>=7,ROUNDDOWN(D10*(IF(3<=6,'前提'!$B$67,IF(3<=12,'前提'!$B$68,IF(3<=18,'前提'!$B$69,IF(3<=24,'前提'!$B$70,IF(3<=36,'前提'!$B$71,IF(3<=48,'前提'!$B$72,'前提'!$B$73))))))),0),0) | E11: =IF(4>=7,ROUNDDOWN(E10*(IF(4<=6,'前提'!$B$67,IF(4<=12,'前提'!$B$68,IF(4<=18,'前提'!$B$69,IF(4<=24,'前提'!$B$70,IF(4<=36,'前提'!$B$71,IF(4<=48,'前提'!$B$72,'前提'!$B$73))))))),0),0) | F11: =IF(5>=7,ROUNDDOWN(F10*(IF(5<=6,'前提'!$B$67,IF(5<=12,'前提'!$B$68,IF(5<=18,'前提'!$B$69,IF(5<=24,'前提'!$B$70,IF(5<=36,'前提'!$B$71,IF(5<=48,'前提'!$B$72,'前提'!$B$73))))))),0),0) | G11: =IF(6>=7,ROUNDDOWN(G10*(IF(6<=6,'前提'!$B$67,IF(6<=12,'前提'!$B$68,IF(6<=18,'前提'!$B$69,IF(6<=24,'前提'!$B$70,IF(6<=36,'前提'!$B$71,IF(6<=48,'前提'!$B$72,'前提'!$B$73))))))),0),0) | H11: =IF(7>=7,ROUNDDOWN(H10*(IF(7<=6,'前提'!$B$67,IF(7<=12,'前提'!$B$68,IF(7<=18,'前提'!$B$69,IF(7<=24,'前提'!$B$70,IF(7<=36,'前提'!$B$71,IF(7<=48,'前提'!$B$72,'前提'!$B$73))))))),0),0) | I11: =IF(8>=7,ROUNDDOWN(I10*(IF(8<=6,'前提'!$B$67,IF(8<=12,'前提'!$B$68,IF(8<=18,'前提'!$B$69,IF(8<=24,'前提'!$B$70,IF(8<=36,'前提'!$B$71,IF(8<=48,'前提'!$B$72,'前提'!$B$73))))))),0),0) | J11: =IF(9>=7,ROUNDDOWN(J10*(IF(9<=6,'前提'!$B$67,IF(9<=12,'前提'!$B$68,IF(9<=18,'前提'!$B$69,IF(9<=24,'前提'!$B$70,IF(9<=36,'前提'!$B$71,IF(9<=48,'前提'!$B$72,'前提'!$B$73))))))),0),0) | K11: =IF(10>=7,ROUNDDOWN(K10*(IF(10<=6,'前提'!$B$67,IF(10<=12,'前提'!$B$68,IF(10<=18,'前提'!$B$69,IF(10<=24,'前提'!$B$70,IF(10<=36,'前提'!$B$71,IF(10<=48,'前提'!$B$72,'前提'!$B$73))))))),0),0) | L11: =IF(11>=7,ROUNDDOWN(L10*(IF(11<=6,'前提'!$B$67,IF(11<=12,'前提'!$B$68,IF(11<=18,'前提'!$B$69,IF(11<=24,'前提'!$B$70,IF(11<=36,'前提'!$B$71,IF(11<=48,'前提'!$B$72,'前提'!$B$73))))))),0),0) | M11: =IF(12>=7,ROUNDDOWN(M10*(IF(12<=6,'前提'!$B$67,IF(12<=12,'前提'!$B$68,IF(12<=18,'前提'!$B$69,IF(12<=24,'前提'!$B$70,IF(12<=36,'前提'!$B$71,IF(12<=48,'前提'!$B$72,'前提'!$B$73))))))),0),0) | N11: =IF(13>=7,ROUNDDOWN(N10*(IF(13<=6,'前提'!$B$67,IF(13<=12,'前提'!$B$68,IF(13<=18,'前提'!$B$69,IF(13<=24,'前提'!$B$70,IF(13<=36,'前提'!$B$71,IF(13<=48,'前提'!$B$72,'前提'!$B$73))))))),0),0) | O11: =IF(14>=7,ROUNDDOWN(O10*(IF(14<=6,'前提'!$B$67,IF(14<=12,'前提'!$B$68,IF(14<=18,'前提'!$B$69,IF(14<=24,'前提'!$B$70,IF(14<=36,'前提'!$B$71,IF(14<=48,'前提'!$B$72,'前提'!$B$73))))))),0),0) | P11: =IF(15>=7,ROUNDDOWN(P10*(IF(15<=6,'前提'!$B$67,IF(15<=12,'前提'!$B$68,IF(15<=18,'前提'!$B$69,IF(15<=24,'前提'!$B$70,IF(15<=36,'前提'!$B$71,IF(15<=48,'前提'!$B$72,'前提'!$B$73))))))),0),0) | Q11: =IF(16>=7,ROUNDDOWN(Q10*(IF(16<=6,'前提'!$B$67,IF(16<=12,'前提'!$B$68,IF(16<=18,'前提'!$B$69,IF(16<=24,'前提'!$B$70,IF(16<=36,'前提'!$B$71,IF(16<=48,'前提'!$B$72,'前提'!$B$73))))))),0),0) | R11: =IF(17>=7,ROUNDDOWN(R10*(IF(17<=6,'前提'!$B$67,IF(17<=12,'前提'!$B$68,IF(17<=18,'前提'!$B$69,IF(17<=24,'前提'!$B$70,IF(17<=36,'前提'!$B$71,IF(17<=48,'前提'!$B$72,'前提'!$B$73))))))),0),0) | S11: =IF(18>=7,ROUNDDOWN(S10*(IF(18<=6,'前提'!$B$67,IF(18<=12,'前提'!$B$68,IF(18<=18,'前提'!$B$69,IF(18<=24,'前提'!$B$70,IF(18<=36,'前提'!$B$71,IF(18<=48,'前提'!$B$72,'前提'!$B$73))))))),0),0) | T11: =IF(19>=7,ROUNDDOWN(T10*(IF(19<=6,'前提'!$B$67,IF(19<=12,'前提'!$B$68,IF(19<=18,'前提'!$B$69,IF(19<=24,'前提'!$B$70,IF(19<=36,'前提'!$B$71,IF(19<=48,'前提'!$B$72,'前提'!$B$73))))))),0),0) | U11: =IF(20>=7,ROUNDDOWN(U10*(IF(20<=6,'前提'!$B$67,IF(20<=12,'前提'!$B$68,IF(20<=18,'前提'!$B$69,IF(20<=24,'前提'!$B$70,IF(20<=36,'前提'!$B$71,IF(20<=48,'前提'!$B$72,'前提'!$B$73))))))),0),0) | V11: =IF(21>=7,ROUNDDOWN(V10*(IF(21<=6,'前提'!$B$67,IF(21<=12,'前提'!$B$68,IF(21<=18,'前提'!$B$69,IF(21<=24,'前提'!$B$70,IF(21<=36,'前提'!$B$71,IF(21<=48,'前提'!$B$72,'前提'!$B$73))))))),0),0) | W11: =IF(22>=7,ROUNDDOWN(W10*(IF(22<=6,'前提'!$B$67,IF(22<=12,'前提'!$B$68,IF(22<=18,'前提'!$B$69,IF(22<=24,'前提'!$B$70,IF(22<=36,'前提'!$B$71,IF(22<=48,'前提'!$B$72,'前提'!$B$73))))))),0),0) | X11: =IF(23>=7,ROUNDDOWN(X10*(IF(23<=6,'前提'!$B$67,IF(23<=12,'前提'!$B$68,IF(23<=18,'前提'!$B$69,IF(23<=24,'前提'!$B$70,IF(23<=36,'前提'!$B$71,IF(23<=48,'前提'!$B$72,'前提'!$B$73))))))),0),0) | Y11: =IF(24>=7,ROUNDDOWN(Y10*(IF(24<=6,'前提'!$B$67,IF(24<=12,'前提'!$B$68,IF(24<=18,'前提'!$B$69,IF(24<=24,'前提'!$B$70,IF(24<=36,'前提'!$B$71,IF(24<=48,'前提'!$B$72,'前提'!$B$73))))))),0),0) | Z11: =IF(25>=7,ROUNDDOWN(Z10*(IF(25<=6,'前提'!$B$67,IF(25<=12,'前提'!$B$68,IF(25<=18,'前提'!$B$69,IF(25<=24,'前提'!$B$70,IF(25<=36,'前提'!$B$71,IF(25<=48,'前提'!$B$72,'前提'!$B$73))))))),0),0) | AA11: =IF(26>=7,ROUNDDOWN(AA10*(IF(26<=6,'前提'!$B$67,IF(26<=12,'前提'!$B$68,IF(26<=18,'前提'!$B$69,IF(26<=24,'前提'!$B$70,IF(26<=36,'前提'!$B$71,IF(26<=48,'前提'!$B$72,'前提'!$B$73))))))),0),0) | AB11: =IF(27>=7,ROUNDDOWN(AB10*(IF(27<=6,'前提'!$B$67,IF(27<=12,'前提'!$B$68,IF(27<=18,'前提'!$B$69,IF(27<=24,'前提'!$B$70,IF(27<=36,'前提'!$B$71,IF(27<=48,'前提'!$B$72,'前提'!$B$73))))))),0),0) | AC11: =IF(28>=7,ROUNDDOWN(AC10*(IF(28<=6,'前提'!$B$67,IF(28<=12,'前提'!$B$68,IF(28<=18,'前提'!$B$69,IF(28<=24,'前提'!$B$70,IF(28<=36,'前提'!$B$71,IF(28<=48,'前提'!$B$72,'前提'!$B$73))))))),0),0) | AD11: =IF(29>=7,ROUNDDOWN(AD10*(IF(29<=6,'前提'!$B$67,IF(29<=12,'前提'!$B$68,IF(29<=18,'前提'!$B$69,IF(29<=24,'前提'!$B$70,IF(29<=36,'前提'!$B$71,IF(29<=48,'前提'!$B$72,'前提'!$B$73))))))),0),0) | AE11: =IF(30>=7,ROUNDDOWN(AE10*(IF(30<=6,'前提'!$B$67,IF(30<=12,'前提'!$B$68,IF(30<=18,'前提'!$B$69,IF(30<=24,'前提'!$B$70,IF(30<=36,'前提'!$B$71,IF(30<=48,'前提'!$B$72,'前提'!$B$73))))))),0),0) | AF11: =IF(31>=7,ROUNDDOWN(AF10*(IF(31<=6,'前提'!$B$67,IF(31<=12,'前提'!$B$68,IF(31<=18,'前提'!$B$69,IF(31<=24,'前提'!$B$70,IF(31<=36,'前提'!$B$71,IF(31<=48,'前提'!$B$72,'前提'!$B$73))))))),0),0) | AG11: =IF(32>=7,ROUNDDOWN(AG10*(IF(32<=6,'前提'!$B$67,IF(32<=12,'前提'!$B$68,IF(32<=18,'前提'!$B$69,IF(32<=24,'前提'!$B$70,IF(32<=36,'前提'!$B$71,IF(32<=48,'前提'!$B$72,'前提'!$B$73))))))),0),0) | AH11: =IF(33>=7,ROUNDDOWN(AH10*(IF(33<=6,'前提'!$B$67,IF(33<=12,'前提'!$B$68,IF(33<=18,'前提'!$B$69,IF(33<=24,'前提'!$B$70,IF(33<=36,'前提'!$B$71,IF(33<=48,'前提'!$B$72,'前提'!$B$73))))))),0),0) | AI11: =IF(34>=7,ROUNDDOWN(AI10*(IF(34<=6,'前提'!$B$67,IF(34<=12,'前提'!$B$68,IF(34<=18,'前提'!$B$69,IF(34<=24,'前提'!$B$70,IF(34<=36,'前提'!$B$71,IF(34<=48,'前提'!$B$72,'前提'!$B$73))))))),0),0) | AJ11: =IF(35>=7,ROUNDDOWN(AJ10*(IF(35<=6,'前提'!$B$67,IF(35<=12,'前提'!$B$68,IF(35<=18,'前提'!$B$69,IF(35<=24,'前提'!$B$70,IF(35<=36,'前提'!$B$71,IF(35<=48,'前提'!$B$72,'前提'!$B$73))))))),0),0) | AK11: =IF(36>=7,ROUNDDOWN(AK10*(IF(36<=6,'前提'!$B$67,IF(36<=12,'前提'!$B$68,IF(36<=18,'前提'!$B$69,IF(36<=24,'前提'!$B$70,IF(36<=36,'前提'!$B$71,IF(36<=48,'前提'!$B$72,'前提'!$B$73))))))),0),0) | AL11: =IF(37>=7,ROUNDDOWN(AL10*(IF(37<=6,'前提'!$B$67,IF(37<=12,'前提'!$B$68,IF(37<=18,'前提'!$B$69,IF(37<=24,'前提'!$B$70,IF(37<=36,'前提'!$B$71,IF(37<=48,'前提'!$B$72,'前提'!$B$73))))))),0),0) | AM11: =IF(38>=7,ROUNDDOWN(AM10*(IF(38<=6,'前提'!$B$67,IF(38<=12,'前提'!$B$68,IF(38<=18,'前提'!$B$69,IF(38<=24,'前提'!$B$70,IF(38<=36,'前提'!$B$71,IF(38<=48,'前提'!$B$72,'前提'!$B$73))))))),0),0) | AN11: =IF(39>=7,ROUNDDOWN(AN10*(IF(39<=6,'前提'!$B$67,IF(39<=12,'前提'!$B$68,IF(39<=18,'前提'!$B$69,IF(39<=24,'前提'!$B$70,IF(39<=36,'前提'!$B$71,IF(39<=48,'前提'!$B$72,'前提'!$B$73))))))),0),0) | AO11: =IF(40>=7,ROUNDDOWN(AO10*(IF(40<=6,'前提'!$B$67,IF(40<=12,'前提'!$B$68,IF(40<=18,'前提'!$B$69,IF(40<=24,'前提'!$B$70,IF(40<=36,'前提'!$B$71,IF(40<=48,'前提'!$B$72,'前提'!$B$73))))))),0),0) | AP11: =IF(41>=7,ROUNDDOWN(AP10*(IF(41<=6,'前提'!$B$67,IF(41<=12,'前提'!$B$68,IF(41<=18,'前提'!$B$69,IF(41<=24,'前提'!$B$70,IF(41<=36,'前提'!$B$71,IF(41<=48,'前提'!$B$72,'前提'!$B$73))))))),0),0) | AQ11: =IF(42>=7,ROUNDDOWN(AQ10*(IF(42<=6,'前提'!$B$67,IF(42<=12,'前提'!$B$68,IF(42<=18,'前提'!$B$69,IF(42<=24,'前提'!$B$70,IF(42<=36,'前提'!$B$71,IF(42<=48,'前提'!$B$72,'前提'!$B$73))))))),0),0) | AR11: =IF(43>=7,ROUNDDOWN(AR10*(IF(43<=6,'前提'!$B$67,IF(43<=12,'前提'!$B$68,IF(43<=18,'前提'!$B$69,IF(43<=24,'前提'!$B$70,IF(43<=36,'前提'!$B$71,IF(43<=48,'前提'!$B$72,'前提'!$B$73))))))),0),0) | AS11: =IF(44>=7,ROUNDDOWN(AS10*(IF(44<=6,'前提'!$B$67,IF(44<=12,'前提'!$B$68,IF(44<=18,'前提'!$B$69,IF(44<=24,'前提'!$B$70,IF(44<=36,'前提'!$B$71,IF(44<=48,'前提'!$B$72,'前提'!$B$73))))))),0),0) | AT11: =IF(45>=7,ROUNDDOWN(AT10*(IF(45<=6,'前提'!$B$67,IF(45<=12,'前提'!$B$68,IF(45<=18,'前提'!$B$69,IF(45<=24,'前提'!$B$70,IF(45<=36,'前提'!$B$71,IF(45<=48,'前提'!$B$72,'前提'!$B$73))))))),0),0) | AU11: =IF(46>=7,ROUNDDOWN(AU10*(IF(46<=6,'前提'!$B$67,IF(46<=12,'前提'!$B$68,IF(46<=18,'前提'!$B$69,IF(46<=24,'前提'!$B$70,IF(46<=36,'前提'!$B$71,IF(46<=48,'前提'!$B$72,'前提'!$B$73))))))),0),0) | AV11: =IF(47>=7,ROUNDDOWN(AV10*(IF(47<=6,'前提'!$B$67,IF(47<=12,'前提'!$B$68,IF(47<=18,'前提'!$B$69,IF(47<=24,'前提'!$B$70,IF(47<=36,'前提'!$B$71,IF(47<=48,'前提'!$B$72,'前提'!$B$73))))))),0),0) | AW11: =IF(48>=7,ROUNDDOWN(AW10*(IF(48<=6,'前提'!$B$67,IF(48<=12,'前提'!$B$68,IF(48<=18,'前提'!$B$69,IF(48<=24,'前提'!$B$70,IF(48<=36,'前提'!$B$71,IF(48<=48,'前提'!$B$72,'前提'!$B$73))))))),0),0) | AX11: =IF(49>=7,ROUNDDOWN(AX10*(IF(49<=6,'前提'!$B$67,IF(49<=12,'前提'!$B$68,IF(49<=18,'前提'!$B$69,IF(49<=24,'前提'!$B$70,IF(49<=36,'前提'!$B$71,IF(49<=48,'前提'!$B$72,'前提'!$B$73))))))),0),0) | AY11: =IF(50>=7,ROUNDDOWN(AY10*(IF(50<=6,'前提'!$B$67,IF(50<=12,'前提'!$B$68,IF(50<=18,'前提'!$B$69,IF(50<=24,'前提'!$B$70,IF(50<=36,'前提'!$B$71,IF(50<=48,'前提'!$B$72,'前提'!$B$73))))))),0),0) | AZ11: =IF(51>=7,ROUNDDOWN(AZ10*(IF(51<=6,'前提'!$B$67,IF(51<=12,'前提'!$B$68,IF(51<=18,'前提'!$B$69,IF(51<=24,'前提'!$B$70,IF(51<=36,'前提'!$B$71,IF(51<=48,'前提'!$B$72,'前提'!$B$73))))))),0),0) | BA11: =IF(52>=7,ROUNDDOWN(BA10*(IF(52<=6,'前提'!$B$67,IF(52<=12,'前提'!$B$68,IF(52<=18,'前提'!$B$69,IF(52<=24,'前提'!$B$70,IF(52<=36,'前提'!$B$71,IF(52<=48,'前提'!$B$72,'前提'!$B$73))))))),0),0) | BB11: =IF(53>=7,ROUNDDOWN(BB10*(IF(53<=6,'前提'!$B$67,IF(53<=12,'前提'!$B$68,IF(53<=18,'前提'!$B$69,IF(53<=24,'前提'!$B$70,IF(53<=36,'前提'!$B$71,IF(53<=48,'前提'!$B$72,'前提'!$B$73))))))),0),0) | BC11: =IF(54>=7,ROUNDDOWN(BC10*(IF(54<=6,'前提'!$B$67,IF(54<=12,'前提'!$B$68,IF(54<=18,'前提'!$B$69,IF(54<=24,'前提'!$B$70,IF(54<=36,'前提'!$B$71,IF(54<=48,'前提'!$B$72,'前提'!$B$73))))))),0),0) | BD11: =IF(55>=7,ROUNDDOWN(BD10*(IF(55<=6,'前提'!$B$67,IF(55<=12,'前提'!$B$68,IF(55<=18,'前提'!$B$69,IF(55<=24,'前提'!$B$70,IF(55<=36,'前提'!$B$71,IF(55<=48,'前提'!$B$72,'前提'!$B$73))))))),0),0) | BE11: =IF(56>=7,ROUNDDOWN(BE10*(IF(56<=6,'前提'!$B$67,IF(56<=12,'前提'!$B$68,IF(56<=18,'前提'!$B$69,IF(56<=24,'前提'!$B$70,IF(56<=36,'前提'!$B$71,IF(56<=48,'前提'!$B$72,'前提'!$B$73))))))),0),0) | BF11: =IF(57>=7,ROUNDDOWN(BF10*(IF(57<=6,'前提'!$B$67,IF(57<=12,'前提'!$B$68,IF(57<=18,'前提'!$B$69,IF(57<=24,'前提'!$B$70,IF(57<=36,'前提'!$B$71,IF(57<=48,'前提'!$B$72,'前提'!$B$73))))))),0),0) | BG11: =IF(58>=7,ROUNDDOWN(BG10*(IF(58<=6,'前提'!$B$67,IF(58<=12,'前提'!$B$68,IF(58<=18,'前提'!$B$69,IF(58<=24,'前提'!$B$70,IF(58<=36,'前提'!$B$71,IF(58<=48,'前提'!$B$72,'前提'!$B$73))))))),0),0) | BH11: =IF(59>=7,ROUNDDOWN(BH10*(IF(59<=6,'前提'!$B$67,IF(59<=12,'前提'!$B$68,IF(59<=18,'前提'!$B$69,IF(59<=24,'前提'!$B$70,IF(59<=36,'前提'!$B$71,IF(59<=48,'前提'!$B$72,'前提'!$B$73))))))),0),0) | BI11: =IF(60>=7,ROUNDDOWN(BI10*(IF(60<=6,'前提'!$B$67,IF(60<=12,'前提'!$B$68,IF(60<=18,'前提'!$B$69,IF(60<=24,'前提'!$B$70,IF(60<=36,'前提'!$B$71,IF(60<=48,'前提'!$B$72,'前提'!$B$73))))))),0),0)
A12: BPO解約 | B12: =ROUNDDOWN(B13*'前提'!$B$9,0) | C12: =ROUNDDOWN(C13*'前提'!$B$9,0) | D12: =ROUNDDOWN(D13*'前提'!$B$9,0) | E12: =ROUNDDOWN(E13*'前提'!$B$9,0) | F12: =ROUNDDOWN(F13*'前提'!$B$9,0) | G12: =ROUNDDOWN(G13*'前提'!$B$9,0) | H12: =ROUNDDOWN(H13*'前提'!$B$9,0) | I12: =ROUNDDOWN(I13*'前提'!$B$9,0) | ... BI12: =ROUNDDOWN(BI13*'前提'!$B$9,0)
A13: BPO期首 | B13: 0 | C13: =B14 | D13: =C14 | E13: =D14 | F13: =E14 | G13: =F14 | H13: =G14 | I13: =H14 | J13: =I14 | ... BI13: =BH14
A14: BPO期末 | B14: =B13+B11-B12 | C14: =C13+C11-C12 | D14: =D13+D11-D12 | E14: =E13+E11-E12 | F14: =F13+F11-F12 | G14: =G13+G11-G12 | H14: =H13+H11-H12 | I14: =I13+I11-I12 | ... BI14: =BI13+BI11-BI12
A16: 【売上】
A17: SuguDesk月額売上 | B17: =(B8+B5*'前提'!$B$12-B9*'前提'!$B$12)*'前提'!$B$4 | C17: =(C8+C5*'前提'!$B$12-C9*'前提'!$B$12)*'前提'!$B$4 | D17: =(D8+D5*'前提'!$B$12-D9*'前提'!$B$12)*'前提'!$B$4 | E17: =(E8+E5*'前提'!$B$12-E9*'前提'!$B$12)*'前提'!$B$4 | F17: =(F8+F5*'前提'!$B$12-F9*'前提'!$B$12)*'前提'!$B$4 | G17: =(G8+G5*'前提'!$B$12-G9*'前提'!$B$12)*'前提'!$B$4 | H17: =(H8+H5*'前提'!$B$12-H9*'前提'!$B$12)*'前提'!$B$4 | I17: =(I8+I5*'前提'!$B$12-I9*'前提'!$B$12)*'前提'!$B$4 | ... BI17: =(BI8+BI5*'前提'!$B$12-BI9*'前提'!$B$12)*'前提'!$B$4
A18: BPO事務長代行売上 | B18: =(B13+B11*'前提'!$B$12-B12*'前提'!$B$12)*'前提'!$B$6 | C18: =(C13+C11*'前提'!$B$12-C12*'前提'!$B$12)*'前提'!$B$6 | D18: =(D13+D11*'前提'!$B$12-D12*'前提'!$B$12)*'前提'!$B$6 | E18: =(E13+E11*'前提'!$B$12-E12*'前提'!$B$12)*'前提'!$B$6 | F18: =(F13+F11*'前提'!$B$12-F12*'前提'!$B$12)*'前提'!$B$6 | G18: =(G13+G11*'前提'!$B$12-G12*'前提'!$B$12)*'前提'!$B$6 | H18: =(H13+H11*'前提'!$B$12-H12*'前提'!$B$12)*'前提'!$B$6 | I18: =(I13+I11*'前提'!$B$12-I12*'前提'!$B$12)*'前提'!$B$6 | ... BI18: =(BI13+BI11*'前提'!$B$12-BI12*'前提'!$B$12)*'前提'!$B$6
A19: BPO採用/集患売上（M13+） | B19: =IF(1>=13,(B13+B11*'前提'!$B$12-B12*'前提'!$B$12)*'前提'!$B$7,0) | C19: =IF(2>=13,(C13+C11*'前提'!$B$12-C12*'前提'!$B$12)*'前提'!$B$7,0) | D19: =IF(3>=13,(D13+D11*'前提'!$B$12-D12*'前提'!$B$12)*'前提'!$B$7,0) | E19: =IF(4>=13,(E13+E11*'前提'!$B$12-E12*'前提'!$B$12)*'前提'!$B$7,0) | F19: =IF(5>=13,(F13+F11*'前提'!$B$12-F12*'前提'!$B$12)*'前提'!$B$7,0) | G19: =IF(6>=13,(G13+G11*'前提'!$B$12-G12*'前提'!$B$12)*'前提'!$B$7,0) | H19: =IF(7>=13,(H13+H11*'前提'!$B$12-H12*'前提'!$B$12)*'前提'!$B$7,0) | I19: =IF(8>=13,(I13+I11*'前提'!$B$12-I12*'前提'!$B$12)*'前提'!$B$7,0) | J19: =IF(9>=13,(J13+J11*'前提'!$B$12-J12*'前提'!$B$12)*'前提'!$B$7,0) | K19: =IF(10>=13,(K13+K11*'前提'!$B$12-K12*'前提'!$B$12)*'前提'!$B$7,0) | L19: =IF(11>=13,(L13+L11*'前提'!$B$12-L12*'前提'!$B$12)*'前提'!$B$7,0) | M19: =IF(12>=13,(M13+M11*'前提'!$B$12-M12*'前提'!$B$12)*'前提'!$B$7,0) | N19: =IF(13>=13,(N13+N11*'前提'!$B$12-N12*'前提'!$B$12)*'前提'!$B$7,0) | O19: =IF(14>=13,(O13+O11*'前提'!$B$12-O12*'前提'!$B$12)*'前提'!$B$7,0) | P19: =IF(15>=13,(P13+P11*'前提'!$B$12-P12*'前提'!$B$12)*'前提'!$B$7,0) | Q19: =IF(16>=13,(Q13+Q11*'前提'!$B$12-Q12*'前提'!$B$12)*'前提'!$B$7,0) | R19: =IF(17>=13,(R13+R11*'前提'!$B$12-R12*'前提'!$B$12)*'前提'!$B$7,0) | S19: =IF(18>=13,(S13+S11*'前提'!$B$12-S12*'前提'!$B$12)*'前提'!$B$7,0) | T19: =IF(19>=13,(T13+T11*'前提'!$B$12-T12*'前提'!$B$12)*'前提'!$B$7,0) | U19: =IF(20>=13,(U13+U11*'前提'!$B$12-U12*'前提'!$B$12)*'前提'!$B$7,0) | V19: =IF(21>=13,(V13+V11*'前提'!$B$12-V12*'前提'!$B$12)*'前提'!$B$7,0) | W19: =IF(22>=13,(W13+W11*'前提'!$B$12-W12*'前提'!$B$12)*'前提'!$B$7,0) | X19: =IF(23>=13,(X13+X11*'前提'!$B$12-X12*'前提'!$B$12)*'前提'!$B$7,0) | Y19: =IF(24>=13,(Y13+Y11*'前提'!$B$12-Y12*'前提'!$B$12)*'前提'!$B$7,0) | Z19: =IF(25>=13,(Z13+Z11*'前提'!$B$12-Z12*'前提'!$B$12)*'前提'!$B$7,0) | AA19: =IF(26>=13,(AA13+AA11*'前提'!$B$12-AA12*'前提'!$B$12)*'前提'!$B$7,0) | AB19: =IF(27>=13,(AB13+AB11*'前提'!$B$12-AB12*'前提'!$B$12)*'前提'!$B$7,0) | AC19: =IF(28>=13,(AC13+AC11*'前提'!$B$12-AC12*'前提'!$B$12)*'前提'!$B$7,0) | AD19: =IF(29>=13,(AD13+AD11*'前提'!$B$12-AD12*'前提'!$B$12)*'前提'!$B$7,0) | AE19: =IF(30>=13,(AE13+AE11*'前提'!$B$12-AE12*'前提'!$B$12)*'前提'!$B$7,0) | AF19: =IF(31>=13,(AF13+AF11*'前提'!$B$12-AF12*'前提'!$B$12)*'前提'!$B$7,0) | AG19: =IF(32>=13,(AG13+AG11*'前提'!$B$12-AG12*'前提'!$B$12)*'前提'!$B$7,0) | AH19: =IF(33>=13,(AH13+AH11*'前提'!$B$12-AH12*'前提'!$B$12)*'前提'!$B$7,0) | AI19: =IF(34>=13,(AI13+AI11*'前提'!$B$12-AI12*'前提'!$B$12)*'前提'!$B$7,0) | AJ19: =IF(35>=13,(AJ13+AJ11*'前提'!$B$12-AJ12*'前提'!$B$12)*'前提'!$B$7,0) | AK19: =IF(36>=13,(AK13+AK11*'前提'!$B$12-AK12*'前提'!$B$12)*'前提'!$B$7,0) | AL19: =IF(37>=13,(AL13+AL11*'前提'!$B$12-AL12*'前提'!$B$12)*'前提'!$B$7,0) | AM19: =IF(38>=13,(AM13+AM11*'前提'!$B$12-AM12*'前提'!$B$12)*'前提'!$B$7,0) | AN19: =IF(39>=13,(AN13+AN11*'前提'!$B$12-AN12*'前提'!$B$12)*'前提'!$B$7,0) | AO19: =IF(40>=13,(AO13+AO11*'前提'!$B$12-AO12*'前提'!$B$12)*'前提'!$B$7,0) | AP19: =IF(41>=13,(AP13+AP11*'前提'!$B$12-AP12*'前提'!$B$12)*'前提'!$B$7,0) | AQ19: =IF(42>=13,(AQ13+AQ11*'前提'!$B$12-AQ12*'前提'!$B$12)*'前提'!$B$7,0) | AR19: =IF(43>=13,(AR13+AR11*'前提'!$B$12-AR12*'前提'!$B$12)*'前提'!$B$7,0) | AS19: =IF(44>=13,(AS13+AS11*'前提'!$B$12-AS12*'前提'!$B$12)*'前提'!$B$7,0) | AT19: =IF(45>=13,(AT13+AT11*'前提'!$B$12-AT12*'前提'!$B$12)*'前提'!$B$7,0) | AU19: =IF(46>=13,(AU13+AU11*'前提'!$B$12-AU12*'前提'!$B$12)*'前提'!$B$7,0) | AV19: =IF(47>=13,(AV13+AV11*'前提'!$B$12-AV12*'前提'!$B$12)*'前提'!$B$7,0) | AW19: =IF(48>=13,(AW13+AW11*'前提'!$B$12-AW12*'前提'!$B$12)*'前提'!$B$7,0) | AX19: =IF(49>=13,(AX13+AX11*'前提'!$B$12-AX12*'前提'!$B$12)*'前提'!$B$7,0) | AY19: =IF(50>=13,(AY13+AY11*'前提'!$B$12-AY12*'前提'!$B$12)*'前提'!$B$7,0) | AZ19: =IF(51>=13,(AZ13+AZ11*'前提'!$B$12-AZ12*'前提'!$B$12)*'前提'!$B$7,0) | BA19: =IF(52>=13,(BA13+BA11*'前提'!$B$12-BA12*'前提'!$B$12)*'前提'!$B$7,0) | BB19: =IF(53>=13,(BB13+BB11*'前提'!$B$12-BB12*'前提'!$B$12)*'前提'!$B$7,0) | BC19: =IF(54>=13,(BC13+BC11*'前提'!$B$12-BC12*'前提'!$B$12)*'前提'!$B$7,0) | BD19: =IF(55>=13,(BD13+BD11*'前提'!$B$12-BD12*'前提'!$B$12)*'前提'!$B$7,0) | BE19: =IF(56>=13,(BE13+BE11*'前提'!$B$12-BE12*'前提'!$B$12)*'前提'!$B$7,0) | BF19: =IF(57>=13,(BF13+BF11*'前提'!$B$12-BF12*'前提'!$B$12)*'前提'!$B$7,0) | BG19: =IF(58>=13,(BG13+BG11*'前提'!$B$12-BG12*'前提'!$B$12)*'前提'!$B$7,0) | BH19: =IF(59>=13,(BH13+BH11*'前提'!$B$12-BH12*'前提'!$B$12)*'前提'!$B$7,0) | BI19: =IF(60>=13,(BI13+BI11*'前提'!$B$12-BI12*'前提'!$B$12)*'前提'!$B$7,0)
A20: 導入費用 | B20: =B5*'前提'!$B$5*'前提'!$B$13 | C20: =C5*'前提'!$B$5*'前提'!$B$13 | D20: =D5*'前提'!$B$5*'前提'!$B$13 | E20: =E5*'前提'!$B$5*'前提'!$B$13 | F20: =F5*'前提'!$B$5*'前提'!$B$13 | G20: =G5*'前提'!$B$5*'前提'!$B$13 | H20: =H5*'前提'!$B$5*'前提'!$B$13 | I20: =I5*'前提'!$B$5*'前提'!$B$13 | ... BI20: =BI5*'前提'!$B$5*'前提'!$B$13
A21: MRR | B21: =B17+B18+B19 | C21: =C17+C18+C19 | D21: =D17+D18+D19 | E21: =E17+E18+E19 | F21: =F17+F18+F19 | G21: =G17+G18+G19 | H21: =H17+H18+H19 | I21: =I17+I18+I19 | ... BI21: =BI17+BI18+BI19
A22: 売上合計 | B22: =B21+B20 | C22: =C21+C20 | D22: =D21+D20 | E22: =E21+E20 | F22: =F21+F20 | G22: =G21+G20 | H22: =H21+H20 | I22: =I21+I20 | ... BI22: =BI21+BI20
A24: 【直接原価（変動費）】
A25: FAQ構築原価（新規件連動） | B25: =B5*'前提'!$B$16 | C25: =C5*'前提'!$B$16 | D25: =D5*'前提'!$B$16 | E25: =E5*'前提'!$B$16 | F25: =F5*'前提'!$B$16 | G25: =G5*'前提'!$B$16 | H25: =H5*'前提'!$B$16 | I25: =I5*'前提'!$B$16 | ... BI25: =BI5*'前提'!$B$16
A26: 月額メンテ原価（既存件連動） | B26: =B10*'前提'!$B$17 | C26: =C10*'前提'!$B$17 | D26: =D10*'前提'!$B$17 | E26: =E10*'前提'!$B$17 | F26: =F10*'前提'!$B$17 | G26: =G10*'前提'!$B$17 | H26: =H10*'前提'!$B$17 | I26: =I10*'前提'!$B$17 | ... BI26: =BI10*'前提'!$B$17
A27: LLM API変動費 | B27: =(B10+B14)*'前提'!$B$18 | C27: =(C10+C14)*'前提'!$B$18 | D27: =(D10+D14)*'前提'!$B$18 | E27: =(E10+E14)*'前提'!$B$18 | F27: =(F10+F14)*'前提'!$B$18 | G27: =(G10+G14)*'前提'!$B$18 | H27: =(H10+H14)*'前提'!$B$18 | I27: =(I10+I14)*'前提'!$B$18 | ... BI27: =(BI10+BI14)*'前提'!$B$18
A28: インフラ（Cloud SQL+Run） | B28: =IF((B10+B14)<=50,'前提'!$B$21,IF((B10+B14)<=200,'前提'!$B$22,'前提'!$B$23))+IF((B10+B14)<=50,'前提'!$B$24,IF((B10+B14)<=200,'前提'!$B$25,'前提'!$B$26)) | C28: =IF((C10+C14)<=50,'前提'!$B$21,IF((C10+C14)<=200,'前提'!$B$22,'前提'!$B$23))+IF((C10+C14)<=50,'前提'!$B$24,IF((C10+C14)<=200,'前提'!$B$25,'前提'!$B$26)) | D28: =IF((D10+D14)<=50,'前提'!$B$21,IF((D10+D14)<=200,'前提'!$B$22,'前提'!$B$23))+IF((D10+D14)<=50,'前提'!$B$24,IF((D10+D14)<=200,'前提'!$B$25,'前提'!$B$26)) | E28: =IF((E10+E14)<=50,'前提'!$B$21,IF((E10+E14)<=200,'前提'!$B$22,'前提'!$B$23))+IF((E10+E14)<=50,'前提'!$B$24,IF((E10+E14)<=200,'前提'!$B$25,'前提'!$B$26)) | F28: =IF((F10+F14)<=50,'前提'!$B$21,IF((F10+F14)<=200,'前提'!$B$22,'前提'!$B$23))+IF((F10+F14)<=50,'前提'!$B$24,IF((F10+F14)<=200,'前提'!$B$25,'前提'!$B$26)) | G28: =IF((G10+G14)<=50,'前提'!$B$21,IF((G10+G14)<=200,'前提'!$B$22,'前提'!$B$23))+IF((G10+G14)<=50,'前提'!$B$24,IF((G10+G14)<=200,'前提'!$B$25,'前提'!$B$26)) | H28: =IF((H10+H14)<=50,'前提'!$B$21,IF((H10+H14)<=200,'前提'!$B$22,'前提'!$B$23))+IF((H10+H14)<=50,'前提'!$B$24,IF((H10+H14)<=200,'前提'!$B$25,'前提'!$B$26)) | I28: =IF((I10+I14)<=50,'前提'!$B$21,IF((I10+I14)<=200,'前提'!$B$22,'前提'!$B$23))+IF((I10+I14)<=50,'前提'!$B$24,IF((I10+I14)<=200,'前提'!$B$25,'前提'!$B$26)) | ... BI28: =IF((BI10+BI14)<=50,'前提'!$B$21,IF((BI10+BI14)<=200,'前提'!$B$22,'前提'!$B$23))+IF((BI10+BI14)<=50,'前提'!$B$24,IF((BI10+BI14)<=200,'前提'!$B$25,'前提'!$B$26))
A29: 決済手数料 | B29: =B22*'前提'!$B$54 | C29: =C22*'前提'!$B$54 | D29: =D22*'前提'!$B$54 | E29: =E22*'前提'!$B$54 | F29: =F22*'前提'!$B$54 | G29: =G22*'前提'!$B$54 | H29: =H22*'前提'!$B$54 | I29: =I22*'前提'!$B$54 | ... BI29: =BI22*'前提'!$B$54
A31: 【人件費】
A32: CEO報酬 | B32: ='前提'!$B$34 | C32: ='前提'!$B$34 | D32: ='前提'!$B$34 | E32: ='前提'!$B$34 | F32: ='前提'!$B$34 | G32: ='前提'!$B$34 | H32: ='前提'!$B$34 | I32: ='前提'!$B$34 | ... BI32: ='前提'!$B$34
A33: エンジニア | B33: =IF(1<=6,'前提'!$B$35*'前提'!$B$36,IF(1<=12,'前提'!$B$35*'前提'!$B$37,'前提'!$B$38*(IF(1<=6,'前提'!$B$85,IF(1<=12,'前提'!$B$86,IF(1<=18,'前提'!$B$87,IF(1<=24,'前提'!$B$88,IF(1<=36,'前提'!$B$89,IF(1<=48,'前提'!$B$90,'前提'!$B$91))))))))) | C33: =IF(2<=6,'前提'!$B$35*'前提'!$B$36,IF(2<=12,'前提'!$B$35*'前提'!$B$37,'前提'!$B$38*(IF(2<=6,'前提'!$B$85,IF(2<=12,'前提'!$B$86,IF(2<=18,'前提'!$B$87,IF(2<=24,'前提'!$B$88,IF(2<=36,'前提'!$B$89,IF(2<=48,'前提'!$B$90,'前提'!$B$91))))))))) | D33: =IF(3<=6,'前提'!$B$35*'前提'!$B$36,IF(3<=12,'前提'!$B$35*'前提'!$B$37,'前提'!$B$38*(IF(3<=6,'前提'!$B$85,IF(3<=12,'前提'!$B$86,IF(3<=18,'前提'!$B$87,IF(3<=24,'前提'!$B$88,IF(3<=36,'前提'!$B$89,IF(3<=48,'前提'!$B$90,'前提'!$B$91))))))))) | E33: =IF(4<=6,'前提'!$B$35*'前提'!$B$36,IF(4<=12,'前提'!$B$35*'前提'!$B$37,'前提'!$B$38*(IF(4<=6,'前提'!$B$85,IF(4<=12,'前提'!$B$86,IF(4<=18,'前提'!$B$87,IF(4<=24,'前提'!$B$88,IF(4<=36,'前提'!$B$89,IF(4<=48,'前提'!$B$90,'前提'!$B$91))))))))) | F33: =IF(5<=6,'前提'!$B$35*'前提'!$B$36,IF(5<=12,'前提'!$B$35*'前提'!$B$37,'前提'!$B$38*(IF(5<=6,'前提'!$B$85,IF(5<=12,'前提'!$B$86,IF(5<=18,'前提'!$B$87,IF(5<=24,'前提'!$B$88,IF(5<=36,'前提'!$B$89,IF(5<=48,'前提'!$B$90,'前提'!$B$91))))))))) | G33: =IF(6<=6,'前提'!$B$35*'前提'!$B$36,IF(6<=12,'前提'!$B$35*'前提'!$B$37,'前提'!$B$38*(IF(6<=6,'前提'!$B$85,IF(6<=12,'前提'!$B$86,IF(6<=18,'前提'!$B$87,IF(6<=24,'前提'!$B$88,IF(6<=36,'前提'!$B$89,IF(6<=48,'前提'!$B$90,'前提'!$B$91))))))))) | H33: =IF(7<=6,'前提'!$B$35*'前提'!$B$36,IF(7<=12,'前提'!$B$35*'前提'!$B$37,'前提'!$B$38*(IF(7<=6,'前提'!$B$85,IF(7<=12,'前提'!$B$86,IF(7<=18,'前提'!$B$87,IF(7<=24,'前提'!$B$88,IF(7<=36,'前提'!$B$89,IF(7<=48,'前提'!$B$90,'前提'!$B$91))))))))) | I33: =IF(8<=6,'前提'!$B$35*'前提'!$B$36,IF(8<=12,'前提'!$B$35*'前提'!$B$37,'前提'!$B$38*(IF(8<=6,'前提'!$B$85,IF(8<=12,'前提'!$B$86,IF(8<=18,'前提'!$B$87,IF(8<=24,'前提'!$B$88,IF(8<=36,'前提'!$B$89,IF(8<=48,'前提'!$B$90,'前提'!$B$91))))))))) | J33: =IF(9<=6,'前提'!$B$35*'前提'!$B$36,IF(9<=12,'前提'!$B$35*'前提'!$B$37,'前提'!$B$38*(IF(9<=6,'前提'!$B$85,IF(9<=12,'前提'!$B$86,IF(9<=18,'前提'!$B$87,IF(9<=24,'前提'!$B$88,IF(9<=36,'前提'!$B$89,IF(9<=48,'前提'!$B$90,'前提'!$B$91))))))))) | K33: =IF(10<=6,'前提'!$B$35*'前提'!$B$36,IF(10<=12,'前提'!$B$35*'前提'!$B$37,'前提'!$B$38*(IF(10<=6,'前提'!$B$85,IF(10<=12,'前提'!$B$86,IF(10<=18,'前提'!$B$87,IF(10<=24,'前提'!$B$88,IF(10<=36,'前提'!$B$89,IF(10<=48,'前提'!$B$90,'前提'!$B$91))))))))) | L33: =IF(11<=6,'前提'!$B$35*'前提'!$B$36,IF(11<=12,'前提'!$B$35*'前提'!$B$37,'前提'!$B$38*(IF(11<=6,'前提'!$B$85,IF(11<=12,'前提'!$B$86,IF(11<=18,'前提'!$B$87,IF(11<=24,'前提'!$B$88,IF(11<=36,'前提'!$B$89,IF(11<=48,'前提'!$B$90,'前提'!$B$91))))))))) | M33: =IF(12<=6,'前提'!$B$35*'前提'!$B$36,IF(12<=12,'前提'!$B$35*'前提'!$B$37,'前提'!$B$38*(IF(12<=6,'前提'!$B$85,IF(12<=12,'前提'!$B$86,IF(12<=18,'前提'!$B$87,IF(12<=24,'前提'!$B$88,IF(12<=36,'前提'!$B$89,IF(12<=48,'前提'!$B$90,'前提'!$B$91))))))))) | N33: =IF(13<=6,'前提'!$B$35*'前提'!$B$36,IF(13<=12,'前提'!$B$35*'前提'!$B$37,'前提'!$B$38*(IF(13<=6,'前提'!$B$85,IF(13<=12,'前提'!$B$86,IF(13<=18,'前提'!$B$87,IF(13<=24,'前提'!$B$88,IF(13<=36,'前提'!$B$89,IF(13<=48,'前提'!$B$90,'前提'!$B$91))))))))) | O33: =IF(14<=6,'前提'!$B$35*'前提'!$B$36,IF(14<=12,'前提'!$B$35*'前提'!$B$37,'前提'!$B$38*(IF(14<=6,'前提'!$B$85,IF(14<=12,'前提'!$B$86,IF(14<=18,'前提'!$B$87,IF(14<=24,'前提'!$B$88,IF(14<=36,'前提'!$B$89,IF(14<=48,'前提'!$B$90,'前提'!$B$91))))))))) | P33: =IF(15<=6,'前提'!$B$35*'前提'!$B$36,IF(15<=12,'前提'!$B$35*'前提'!$B$37,'前提'!$B$38*(IF(15<=6,'前提'!$B$85,IF(15<=12,'前提'!$B$86,IF(15<=18,'前提'!$B$87,IF(15<=24,'前提'!$B$88,IF(15<=36,'前提'!$B$89,IF(15<=48,'前提'!$B$90,'前提'!$B$91))))))))) | Q33: =IF(16<=6,'前提'!$B$35*'前提'!$B$36,IF(16<=12,'前提'!$B$35*'前提'!$B$37,'前提'!$B$38*(IF(16<=6,'前提'!$B$85,IF(16<=12,'前提'!$B$86,IF(16<=18,'前提'!$B$87,IF(16<=24,'前提'!$B$88,IF(16<=36,'前提'!$B$89,IF(16<=48,'前提'!$B$90,'前提'!$B$91))))))))) | R33: =IF(17<=6,'前提'!$B$35*'前提'!$B$36,IF(17<=12,'前提'!$B$35*'前提'!$B$37,'前提'!$B$38*(IF(17<=6,'前提'!$B$85,IF(17<=12,'前提'!$B$86,IF(17<=18,'前提'!$B$87,IF(17<=24,'前提'!$B$88,IF(17<=36,'前提'!$B$89,IF(17<=48,'前提'!$B$90,'前提'!$B$91))))))))) | S33: =IF(18<=6,'前提'!$B$35*'前提'!$B$36,IF(18<=12,'前提'!$B$35*'前提'!$B$37,'前提'!$B$38*(IF(18<=6,'前提'!$B$85,IF(18<=12,'前提'!$B$86,IF(18<=18,'前提'!$B$87,IF(18<=24,'前提'!$B$88,IF(18<=36,'前提'!$B$89,IF(18<=48,'前提'!$B$90,'前提'!$B$91))))))))) | T33: =IF(19<=6,'前提'!$B$35*'前提'!$B$36,IF(19<=12,'前提'!$B$35*'前提'!$B$37,'前提'!$B$38*(IF(19<=6,'前提'!$B$85,IF(19<=12,'前提'!$B$86,IF(19<=18,'前提'!$B$87,IF(19<=24,'前提'!$B$88,IF(19<=36,'前提'!$B$89,IF(19<=48,'前提'!$B$90,'前提'!$B$91))))))))) | U33: =IF(20<=6,'前提'!$B$35*'前提'!$B$36,IF(20<=12,'前提'!$B$35*'前提'!$B$37,'前提'!$B$38*(IF(20<=6,'前提'!$B$85,IF(20<=12,'前提'!$B$86,IF(20<=18,'前提'!$B$87,IF(20<=24,'前提'!$B$88,IF(20<=36,'前提'!$B$89,IF(20<=48,'前提'!$B$90,'前提'!$B$91))))))))) | V33: =IF(21<=6,'前提'!$B$35*'前提'!$B$36,IF(21<=12,'前提'!$B$35*'前提'!$B$37,'前提'!$B$38*(IF(21<=6,'前提'!$B$85,IF(21<=12,'前提'!$B$86,IF(21<=18,'前提'!$B$87,IF(21<=24,'前提'!$B$88,IF(21<=36,'前提'!$B$89,IF(21<=48,'前提'!$B$90,'前提'!$B$91))))))))) | W33: =IF(22<=6,'前提'!$B$35*'前提'!$B$36,IF(22<=12,'前提'!$B$35*'前提'!$B$37,'前提'!$B$38*(IF(22<=6,'前提'!$B$85,IF(22<=12,'前提'!$B$86,IF(22<=18,'前提'!$B$87,IF(22<=24,'前提'!$B$88,IF(22<=36,'前提'!$B$89,IF(22<=48,'前提'!$B$90,'前提'!$B$91))))))))) | X33: =IF(23<=6,'前提'!$B$35*'前提'!$B$36,IF(23<=12,'前提'!$B$35*'前提'!$B$37,'前提'!$B$38*(IF(23<=6,'前提'!$B$85,IF(23<=12,'前提'!$B$86,IF(23<=18,'前提'!$B$87,IF(23<=24,'前提'!$B$88,IF(23<=36,'前提'!$B$89,IF(23<=48,'前提'!$B$90,'前提'!$B$91))))))))) | Y33: =IF(24<=6,'前提'!$B$35*'前提'!$B$36,IF(24<=12,'前提'!$B$35*'前提'!$B$37,'前提'!$B$38*(IF(24<=6,'前提'!$B$85,IF(24<=12,'前提'!$B$86,IF(24<=18,'前提'!$B$87,IF(24<=24,'前提'!$B$88,IF(24<=36,'前提'!$B$89,IF(24<=48,'前提'!$B$90,'前提'!$B$91))))))))) | Z33: =IF(25<=6,'前提'!$B$35*'前提'!$B$36,IF(25<=12,'前提'!$B$35*'前提'!$B$37,'前提'!$B$38*(IF(25<=6,'前提'!$B$85,IF(25<=12,'前提'!$B$86,IF(25<=18,'前提'!$B$87,IF(25<=24,'前提'!$B$88,IF(25<=36,'前提'!$B$89,IF(25<=48,'前提'!$B$90,'前提'!$B$91))))))))) | AA33: =IF(26<=6,'前提'!$B$35*'前提'!$B$36,IF(26<=12,'前提'!$B$35*'前提'!$B$37,'前提'!$B$38*(IF(26<=6,'前提'!$B$85,IF(26<=12,'前提'!$B$86,IF(26<=18,'前提'!$B$87,IF(26<=24,'前提'!$B$88,IF(26<=36,'前提'!$B$89,IF(26<=48,'前提'!$B$90,'前提'!$B$91))))))))) | AB33: =IF(27<=6,'前提'!$B$35*'前提'!$B$36,IF(27<=12,'前提'!$B$35*'前提'!$B$37,'前提'!$B$38*(IF(27<=6,'前提'!$B$85,IF(27<=12,'前提'!$B$86,IF(27<=18,'前提'!$B$87,IF(27<=24,'前提'!$B$88,IF(27<=36,'前提'!$B$89,IF(27<=48,'前提'!$B$90,'前提'!$B$91))))))))) | AC33: =IF(28<=6,'前提'!$B$35*'前提'!$B$36,IF(28<=12,'前提'!$B$35*'前提'!$B$37,'前提'!$B$38*(IF(28<=6,'前提'!$B$85,IF(28<=12,'前提'!$B$86,IF(28<=18,'前提'!$B$87,IF(28<=24,'前提'!$B$88,IF(28<=36,'前提'!$B$89,IF(28<=48,'前提'!$B$90,'前提'!$B$91))))))))) | AD33: =IF(29<=6,'前提'!$B$35*'前提'!$B$36,IF(29<=12,'前提'!$B$35*'前提'!$B$37,'前提'!$B$38*(IF(29<=6,'前提'!$B$85,IF(29<=12,'前提'!$B$86,IF(29<=18,'前提'!$B$87,IF(29<=24,'前提'!$B$88,IF(29<=36,'前提'!$B$89,IF(29<=48,'前提'!$B$90,'前提'!$B$91))))))))) | AE33: =IF(30<=6,'前提'!$B$35*'前提'!$B$36,IF(30<=12,'前提'!$B$35*'前提'!$B$37,'前提'!$B$38*(IF(30<=6,'前提'!$B$85,IF(30<=12,'前提'!$B$86,IF(30<=18,'前提'!$B$87,IF(30<=24,'前提'!$B$88,IF(30<=36,'前提'!$B$89,IF(30<=48,'前提'!$B$90,'前提'!$B$91))))))))) | AF33: =IF(31<=6,'前提'!$B$35*'前提'!$B$36,IF(31<=12,'前提'!$B$35*'前提'!$B$37,'前提'!$B$38*(IF(31<=6,'前提'!$B$85,IF(31<=12,'前提'!$B$86,IF(31<=18,'前提'!$B$87,IF(31<=24,'前提'!$B$88,IF(31<=36,'前提'!$B$89,IF(31<=48,'前提'!$B$90,'前提'!$B$91))))))))) | AG33: =IF(32<=6,'前提'!$B$35*'前提'!$B$36,IF(32<=12,'前提'!$B$35*'前提'!$B$37,'前提'!$B$38*(IF(32<=6,'前提'!$B$85,IF(32<=12,'前提'!$B$86,IF(32<=18,'前提'!$B$87,IF(32<=24,'前提'!$B$88,IF(32<=36,'前提'!$B$89,IF(32<=48,'前提'!$B$90,'前提'!$B$91))))))))) | AH33: =IF(33<=6,'前提'!$B$35*'前提'!$B$36,IF(33<=12,'前提'!$B$35*'前提'!$B$37,'前提'!$B$38*(IF(33<=6,'前提'!$B$85,IF(33<=12,'前提'!$B$86,IF(33<=18,'前提'!$B$87,IF(33<=24,'前提'!$B$88,IF(33<=36,'前提'!$B$89,IF(33<=48,'前提'!$B$90,'前提'!$B$91))))))))) | AI33: =IF(34<=6,'前提'!$B$35*'前提'!$B$36,IF(34<=12,'前提'!$B$35*'前提'!$B$37,'前提'!$B$38*(IF(34<=6,'前提'!$B$85,IF(34<=12,'前提'!$B$86,IF(34<=18,'前提'!$B$87,IF(34<=24,'前提'!$B$88,IF(34<=36,'前提'!$B$89,IF(34<=48,'前提'!$B$90,'前提'!$B$91))))))))) | AJ33: =IF(35<=6,'前提'!$B$35*'前提'!$B$36,IF(35<=12,'前提'!$B$35*'前提'!$B$37,'前提'!$B$38*(IF(35<=6,'前提'!$B$85,IF(35<=12,'前提'!$B$86,IF(35<=18,'前提'!$B$87,IF(35<=24,'前提'!$B$88,IF(35<=36,'前提'!$B$89,IF(35<=48,'前提'!$B$90,'前提'!$B$91))))))))) | AK33: =IF(36<=6,'前提'!$B$35*'前提'!$B$36,IF(36<=12,'前提'!$B$35*'前提'!$B$37,'前提'!$B$38*(IF(36<=6,'前提'!$B$85,IF(36<=12,'前提'!$B$86,IF(36<=18,'前提'!$B$87,IF(36<=24,'前提'!$B$88,IF(36<=36,'前提'!$B$89,IF(36<=48,'前提'!$B$90,'前提'!$B$91))))))))) | AL33: =IF(37<=6,'前提'!$B$35*'前提'!$B$36,IF(37<=12,'前提'!$B$35*'前提'!$B$37,'前提'!$B$38*(IF(37<=6,'前提'!$B$85,IF(37<=12,'前提'!$B$86,IF(37<=18,'前提'!$B$87,IF(37<=24,'前提'!$B$88,IF(37<=36,'前提'!$B$89,IF(37<=48,'前提'!$B$90,'前提'!$B$91))))))))) | AM33: =IF(38<=6,'前提'!$B$35*'前提'!$B$36,IF(38<=12,'前提'!$B$35*'前提'!$B$37,'前提'!$B$38*(IF(38<=6,'前提'!$B$85,IF(38<=12,'前提'!$B$86,IF(38<=18,'前提'!$B$87,IF(38<=24,'前提'!$B$88,IF(38<=36,'前提'!$B$89,IF(38<=48,'前提'!$B$90,'前提'!$B$91))))))))) | AN33: =IF(39<=6,'前提'!$B$35*'前提'!$B$36,IF(39<=12,'前提'!$B$35*'前提'!$B$37,'前提'!$B$38*(IF(39<=6,'前提'!$B$85,IF(39<=12,'前提'!$B$86,IF(39<=18,'前提'!$B$87,IF(39<=24,'前提'!$B$88,IF(39<=36,'前提'!$B$89,IF(39<=48,'前提'!$B$90,'前提'!$B$91))))))))) | AO33: =IF(40<=6,'前提'!$B$35*'前提'!$B$36,IF(40<=12,'前提'!$B$35*'前提'!$B$37,'前提'!$B$38*(IF(40<=6,'前提'!$B$85,IF(40<=12,'前提'!$B$86,IF(40<=18,'前提'!$B$87,IF(40<=24,'前提'!$B$88,IF(40<=36,'前提'!$B$89,IF(40<=48,'前提'!$B$90,'前提'!$B$91))))))))) | AP33: =IF(41<=6,'前提'!$B$35*'前提'!$B$36,IF(41<=12,'前提'!$B$35*'前提'!$B$37,'前提'!$B$38*(IF(41<=6,'前提'!$B$85,IF(41<=12,'前提'!$B$86,IF(41<=18,'前提'!$B$87,IF(41<=24,'前提'!$B$88,IF(41<=36,'前提'!$B$89,IF(41<=48,'前提'!$B$90,'前提'!$B$91))))))))) | AQ33: =IF(42<=6,'前提'!$B$35*'前提'!$B$36,IF(42<=12,'前提'!$B$35*'前提'!$B$37,'前提'!$B$38*(IF(42<=6,'前提'!$B$85,IF(42<=12,'前提'!$B$86,IF(42<=18,'前提'!$B$87,IF(42<=24,'前提'!$B$88,IF(42<=36,'前提'!$B$89,IF(42<=48,'前提'!$B$90,'前提'!$B$91))))))))) | AR33: =IF(43<=6,'前提'!$B$35*'前提'!$B$36,IF(43<=12,'前提'!$B$35*'前提'!$B$37,'前提'!$B$38*(IF(43<=6,'前提'!$B$85,IF(43<=12,'前提'!$B$86,IF(43<=18,'前提'!$B$87,IF(43<=24,'前提'!$B$88,IF(43<=36,'前提'!$B$89,IF(43<=48,'前提'!$B$90,'前提'!$B$91))))))))) | AS33: =IF(44<=6,'前提'!$B$35*'前提'!$B$36,IF(44<=12,'前提'!$B$35*'前提'!$B$37,'前提'!$B$38*(IF(44<=6,'前提'!$B$85,IF(44<=12,'前提'!$B$86,IF(44<=18,'前提'!$B$87,IF(44<=24,'前提'!$B$88,IF(44<=36,'前提'!$B$89,IF(44<=48,'前提'!$B$90,'前提'!$B$91))))))))) | AT33: =IF(45<=6,'前提'!$B$35*'前提'!$B$36,IF(45<=12,'前提'!$B$35*'前提'!$B$37,'前提'!$B$38*(IF(45<=6,'前提'!$B$85,IF(45<=12,'前提'!$B$86,IF(45<=18,'前提'!$B$87,IF(45<=24,'前提'!$B$88,IF(45<=36,'前提'!$B$89,IF(45<=48,'前提'!$B$90,'前提'!$B$91))))))))) | AU33: =IF(46<=6,'前提'!$B$35*'前提'!$B$36,IF(46<=12,'前提'!$B$35*'前提'!$B$37,'前提'!$B$38*(IF(46<=6,'前提'!$B$85,IF(46<=12,'前提'!$B$86,IF(46<=18,'前提'!$B$87,IF(46<=24,'前提'!$B$88,IF(46<=36,'前提'!$B$89,IF(46<=48,'前提'!$B$90,'前提'!$B$91))))))))) | AV33: =IF(47<=6,'前提'!$B$35*'前提'!$B$36,IF(47<=12,'前提'!$B$35*'前提'!$B$37,'前提'!$B$38*(IF(47<=6,'前提'!$B$85,IF(47<=12,'前提'!$B$86,IF(47<=18,'前提'!$B$87,IF(47<=24,'前提'!$B$88,IF(47<=36,'前提'!$B$89,IF(47<=48,'前提'!$B$90,'前提'!$B$91))))))))) | AW33: =IF(48<=6,'前提'!$B$35*'前提'!$B$36,IF(48<=12,'前提'!$B$35*'前提'!$B$37,'前提'!$B$38*(IF(48<=6,'前提'!$B$85,IF(48<=12,'前提'!$B$86,IF(48<=18,'前提'!$B$87,IF(48<=24,'前提'!$B$88,IF(48<=36,'前提'!$B$89,IF(48<=48,'前提'!$B$90,'前提'!$B$91))))))))) | AX33: =IF(49<=6,'前提'!$B$35*'前提'!$B$36,IF(49<=12,'前提'!$B$35*'前提'!$B$37,'前提'!$B$38*(IF(49<=6,'前提'!$B$85,IF(49<=12,'前提'!$B$86,IF(49<=18,'前提'!$B$87,IF(49<=24,'前提'!$B$88,IF(49<=36,'前提'!$B$89,IF(49<=48,'前提'!$B$90,'前提'!$B$91))))))))) | AY33: =IF(50<=6,'前提'!$B$35*'前提'!$B$36,IF(50<=12,'前提'!$B$35*'前提'!$B$37,'前提'!$B$38*(IF(50<=6,'前提'!$B$85,IF(50<=12,'前提'!$B$86,IF(50<=18,'前提'!$B$87,IF(50<=24,'前提'!$B$88,IF(50<=36,'前提'!$B$89,IF(50<=48,'前提'!$B$90,'前提'!$B$91))))))))) | AZ33: =IF(51<=6,'前提'!$B$35*'前提'!$B$36,IF(51<=12,'前提'!$B$35*'前提'!$B$37,'前提'!$B$38*(IF(51<=6,'前提'!$B$85,IF(51<=12,'前提'!$B$86,IF(51<=18,'前提'!$B$87,IF(51<=24,'前提'!$B$88,IF(51<=36,'前提'!$B$89,IF(51<=48,'前提'!$B$90,'前提'!$B$91))))))))) | BA33: =IF(52<=6,'前提'!$B$35*'前提'!$B$36,IF(52<=12,'前提'!$B$35*'前提'!$B$37,'前提'!$B$38*(IF(52<=6,'前提'!$B$85,IF(52<=12,'前提'!$B$86,IF(52<=18,'前提'!$B$87,IF(52<=24,'前提'!$B$88,IF(52<=36,'前提'!$B$89,IF(52<=48,'前提'!$B$90,'前提'!$B$91))))))))) | BB33: =IF(53<=6,'前提'!$B$35*'前提'!$B$36,IF(53<=12,'前提'!$B$35*'前提'!$B$37,'前提'!$B$38*(IF(53<=6,'前提'!$B$85,IF(53<=12,'前提'!$B$86,IF(53<=18,'前提'!$B$87,IF(53<=24,'前提'!$B$88,IF(53<=36,'前提'!$B$89,IF(53<=48,'前提'!$B$90,'前提'!$B$91))))))))) | BC33: =IF(54<=6,'前提'!$B$35*'前提'!$B$36,IF(54<=12,'前提'!$B$35*'前提'!$B$37,'前提'!$B$38*(IF(54<=6,'前提'!$B$85,IF(54<=12,'前提'!$B$86,IF(54<=18,'前提'!$B$87,IF(54<=24,'前提'!$B$88,IF(54<=36,'前提'!$B$89,IF(54<=48,'前提'!$B$90,'前提'!$B$91))))))))) | BD33: =IF(55<=6,'前提'!$B$35*'前提'!$B$36,IF(55<=12,'前提'!$B$35*'前提'!$B$37,'前提'!$B$38*(IF(55<=6,'前提'!$B$85,IF(55<=12,'前提'!$B$86,IF(55<=18,'前提'!$B$87,IF(55<=24,'前提'!$B$88,IF(55<=36,'前提'!$B$89,IF(55<=48,'前提'!$B$90,'前提'!$B$91))))))))) | BE33: =IF(56<=6,'前提'!$B$35*'前提'!$B$36,IF(56<=12,'前提'!$B$35*'前提'!$B$37,'前提'!$B$38*(IF(56<=6,'前提'!$B$85,IF(56<=12,'前提'!$B$86,IF(56<=18,'前提'!$B$87,IF(56<=24,'前提'!$B$88,IF(56<=36,'前提'!$B$89,IF(56<=48,'前提'!$B$90,'前提'!$B$91))))))))) | BF33: =IF(57<=6,'前提'!$B$35*'前提'!$B$36,IF(57<=12,'前提'!$B$35*'前提'!$B$37,'前提'!$B$38*(IF(57<=6,'前提'!$B$85,IF(57<=12,'前提'!$B$86,IF(57<=18,'前提'!$B$87,IF(57<=24,'前提'!$B$88,IF(57<=36,'前提'!$B$89,IF(57<=48,'前提'!$B$90,'前提'!$B$91))))))))) | BG33: =IF(58<=6,'前提'!$B$35*'前提'!$B$36,IF(58<=12,'前提'!$B$35*'前提'!$B$37,'前提'!$B$38*(IF(58<=6,'前提'!$B$85,IF(58<=12,'前提'!$B$86,IF(58<=18,'前提'!$B$87,IF(58<=24,'前提'!$B$88,IF(58<=36,'前提'!$B$89,IF(58<=48,'前提'!$B$90,'前提'!$B$91))))))))) | BH33: =IF(59<=6,'前提'!$B$35*'前提'!$B$36,IF(59<=12,'前提'!$B$35*'前提'!$B$37,'前提'!$B$38*(IF(59<=6,'前提'!$B$85,IF(59<=12,'前提'!$B$86,IF(59<=18,'前提'!$B$87,IF(59<=24,'前提'!$B$88,IF(59<=36,'前提'!$B$89,IF(59<=48,'前提'!$B$90,'前提'!$B$91))))))))) | BI33: =IF(60<=6,'前提'!$B$35*'前提'!$B$36,IF(60<=12,'前提'!$B$35*'前提'!$B$37,'前提'!$B$38*(IF(60<=6,'前提'!$B$85,IF(60<=12,'前提'!$B$86,IF(60<=18,'前提'!$B$87,IF(60<=24,'前提'!$B$88,IF(60<=36,'前提'!$B$89,IF(60<=48,'前提'!$B$90,'前提'!$B$91)))))))))
A34: 営業サポート | B34: ='前提'!$B$41*(IF(1<=6,'前提'!$B$94,IF(1<=12,'前提'!$B$95,IF(1<=18,'前提'!$B$96,IF(1<=24,'前提'!$B$97,IF(1<=36,'前提'!$B$98,IF(1<=48,'前提'!$B$99,'前提'!$B$100))))))) | C34: ='前提'!$B$41*(IF(2<=6,'前提'!$B$94,IF(2<=12,'前提'!$B$95,IF(2<=18,'前提'!$B$96,IF(2<=24,'前提'!$B$97,IF(2<=36,'前提'!$B$98,IF(2<=48,'前提'!$B$99,'前提'!$B$100))))))) | D34: ='前提'!$B$41*(IF(3<=6,'前提'!$B$94,IF(3<=12,'前提'!$B$95,IF(3<=18,'前提'!$B$96,IF(3<=24,'前提'!$B$97,IF(3<=36,'前提'!$B$98,IF(3<=48,'前提'!$B$99,'前提'!$B$100))))))) | E34: ='前提'!$B$41*(IF(4<=6,'前提'!$B$94,IF(4<=12,'前提'!$B$95,IF(4<=18,'前提'!$B$96,IF(4<=24,'前提'!$B$97,IF(4<=36,'前提'!$B$98,IF(4<=48,'前提'!$B$99,'前提'!$B$100))))))) | F34: ='前提'!$B$41*(IF(5<=6,'前提'!$B$94,IF(5<=12,'前提'!$B$95,IF(5<=18,'前提'!$B$96,IF(5<=24,'前提'!$B$97,IF(5<=36,'前提'!$B$98,IF(5<=48,'前提'!$B$99,'前提'!$B$100))))))) | G34: ='前提'!$B$41*(IF(6<=6,'前提'!$B$94,IF(6<=12,'前提'!$B$95,IF(6<=18,'前提'!$B$96,IF(6<=24,'前提'!$B$97,IF(6<=36,'前提'!$B$98,IF(6<=48,'前提'!$B$99,'前提'!$B$100))))))) | H34: ='前提'!$B$41*(IF(7<=6,'前提'!$B$94,IF(7<=12,'前提'!$B$95,IF(7<=18,'前提'!$B$96,IF(7<=24,'前提'!$B$97,IF(7<=36,'前提'!$B$98,IF(7<=48,'前提'!$B$99,'前提'!$B$100))))))) | I34: ='前提'!$B$41*(IF(8<=6,'前提'!$B$94,IF(8<=12,'前提'!$B$95,IF(8<=18,'前提'!$B$96,IF(8<=24,'前提'!$B$97,IF(8<=36,'前提'!$B$98,IF(8<=48,'前提'!$B$99,'前提'!$B$100))))))) | J34: ='前提'!$B$41*(IF(9<=6,'前提'!$B$94,IF(9<=12,'前提'!$B$95,IF(9<=18,'前提'!$B$96,IF(9<=24,'前提'!$B$97,IF(9<=36,'前提'!$B$98,IF(9<=48,'前提'!$B$99,'前提'!$B$100))))))) | K34: ='前提'!$B$41*(IF(10<=6,'前提'!$B$94,IF(10<=12,'前提'!$B$95,IF(10<=18,'前提'!$B$96,IF(10<=24,'前提'!$B$97,IF(10<=36,'前提'!$B$98,IF(10<=48,'前提'!$B$99,'前提'!$B$100))))))) | L34: ='前提'!$B$41*(IF(11<=6,'前提'!$B$94,IF(11<=12,'前提'!$B$95,IF(11<=18,'前提'!$B$96,IF(11<=24,'前提'!$B$97,IF(11<=36,'前提'!$B$98,IF(11<=48,'前提'!$B$99,'前提'!$B$100))))))) | M34: ='前提'!$B$41*(IF(12<=6,'前提'!$B$94,IF(12<=12,'前提'!$B$95,IF(12<=18,'前提'!$B$96,IF(12<=24,'前提'!$B$97,IF(12<=36,'前提'!$B$98,IF(12<=48,'前提'!$B$99,'前提'!$B$100))))))) | N34: ='前提'!$B$41*(IF(13<=6,'前提'!$B$94,IF(13<=12,'前提'!$B$95,IF(13<=18,'前提'!$B$96,IF(13<=24,'前提'!$B$97,IF(13<=36,'前提'!$B$98,IF(13<=48,'前提'!$B$99,'前提'!$B$100))))))) | O34: ='前提'!$B$41*(IF(14<=6,'前提'!$B$94,IF(14<=12,'前提'!$B$95,IF(14<=18,'前提'!$B$96,IF(14<=24,'前提'!$B$97,IF(14<=36,'前提'!$B$98,IF(14<=48,'前提'!$B$99,'前提'!$B$100))))))) | P34: ='前提'!$B$41*(IF(15<=6,'前提'!$B$94,IF(15<=12,'前提'!$B$95,IF(15<=18,'前提'!$B$96,IF(15<=24,'前提'!$B$97,IF(15<=36,'前提'!$B$98,IF(15<=48,'前提'!$B$99,'前提'!$B$100))))))) | Q34: ='前提'!$B$41*(IF(16<=6,'前提'!$B$94,IF(16<=12,'前提'!$B$95,IF(16<=18,'前提'!$B$96,IF(16<=24,'前提'!$B$97,IF(16<=36,'前提'!$B$98,IF(16<=48,'前提'!$B$99,'前提'!$B$100))))))) | R34: ='前提'!$B$41*(IF(17<=6,'前提'!$B$94,IF(17<=12,'前提'!$B$95,IF(17<=18,'前提'!$B$96,IF(17<=24,'前提'!$B$97,IF(17<=36,'前提'!$B$98,IF(17<=48,'前提'!$B$99,'前提'!$B$100))))))) | S34: ='前提'!$B$41*(IF(18<=6,'前提'!$B$94,IF(18<=12,'前提'!$B$95,IF(18<=18,'前提'!$B$96,IF(18<=24,'前提'!$B$97,IF(18<=36,'前提'!$B$98,IF(18<=48,'前提'!$B$99,'前提'!$B$100))))))) | T34: ='前提'!$B$41*(IF(19<=6,'前提'!$B$94,IF(19<=12,'前提'!$B$95,IF(19<=18,'前提'!$B$96,IF(19<=24,'前提'!$B$97,IF(19<=36,'前提'!$B$98,IF(19<=48,'前提'!$B$99,'前提'!$B$100))))))) | U34: ='前提'!$B$41*(IF(20<=6,'前提'!$B$94,IF(20<=12,'前提'!$B$95,IF(20<=18,'前提'!$B$96,IF(20<=24,'前提'!$B$97,IF(20<=36,'前提'!$B$98,IF(20<=48,'前提'!$B$99,'前提'!$B$100))))))) | V34: ='前提'!$B$41*(IF(21<=6,'前提'!$B$94,IF(21<=12,'前提'!$B$95,IF(21<=18,'前提'!$B$96,IF(21<=24,'前提'!$B$97,IF(21<=36,'前提'!$B$98,IF(21<=48,'前提'!$B$99,'前提'!$B$100))))))) | W34: ='前提'!$B$41*(IF(22<=6,'前提'!$B$94,IF(22<=12,'前提'!$B$95,IF(22<=18,'前提'!$B$96,IF(22<=24,'前提'!$B$97,IF(22<=36,'前提'!$B$98,IF(22<=48,'前提'!$B$99,'前提'!$B$100))))))) | X34: ='前提'!$B$41*(IF(23<=6,'前提'!$B$94,IF(23<=12,'前提'!$B$95,IF(23<=18,'前提'!$B$96,IF(23<=24,'前提'!$B$97,IF(23<=36,'前提'!$B$98,IF(23<=48,'前提'!$B$99,'前提'!$B$100))))))) | Y34: ='前提'!$B$41*(IF(24<=6,'前提'!$B$94,IF(24<=12,'前提'!$B$95,IF(24<=18,'前提'!$B$96,IF(24<=24,'前提'!$B$97,IF(24<=36,'前提'!$B$98,IF(24<=48,'前提'!$B$99,'前提'!$B$100))))))) | Z34: ='前提'!$B$41*(IF(25<=6,'前提'!$B$94,IF(25<=12,'前提'!$B$95,IF(25<=18,'前提'!$B$96,IF(25<=24,'前提'!$B$97,IF(25<=36,'前提'!$B$98,IF(25<=48,'前提'!$B$99,'前提'!$B$100))))))) | AA34: ='前提'!$B$41*(IF(26<=6,'前提'!$B$94,IF(26<=12,'前提'!$B$95,IF(26<=18,'前提'!$B$96,IF(26<=24,'前提'!$B$97,IF(26<=36,'前提'!$B$98,IF(26<=48,'前提'!$B$99,'前提'!$B$100))))))) | AB34: ='前提'!$B$41*(IF(27<=6,'前提'!$B$94,IF(27<=12,'前提'!$B$95,IF(27<=18,'前提'!$B$96,IF(27<=24,'前提'!$B$97,IF(27<=36,'前提'!$B$98,IF(27<=48,'前提'!$B$99,'前提'!$B$100))))))) | AC34: ='前提'!$B$41*(IF(28<=6,'前提'!$B$94,IF(28<=12,'前提'!$B$95,IF(28<=18,'前提'!$B$96,IF(28<=24,'前提'!$B$97,IF(28<=36,'前提'!$B$98,IF(28<=48,'前提'!$B$99,'前提'!$B$100))))))) | AD34: ='前提'!$B$41*(IF(29<=6,'前提'!$B$94,IF(29<=12,'前提'!$B$95,IF(29<=18,'前提'!$B$96,IF(29<=24,'前提'!$B$97,IF(29<=36,'前提'!$B$98,IF(29<=48,'前提'!$B$99,'前提'!$B$100))))))) | AE34: ='前提'!$B$41*(IF(30<=6,'前提'!$B$94,IF(30<=12,'前提'!$B$95,IF(30<=18,'前提'!$B$96,IF(30<=24,'前提'!$B$97,IF(30<=36,'前提'!$B$98,IF(30<=48,'前提'!$B$99,'前提'!$B$100))))))) | AF34: ='前提'!$B$41*(IF(31<=6,'前提'!$B$94,IF(31<=12,'前提'!$B$95,IF(31<=18,'前提'!$B$96,IF(31<=24,'前提'!$B$97,IF(31<=36,'前提'!$B$98,IF(31<=48,'前提'!$B$99,'前提'!$B$100))))))) | AG34: ='前提'!$B$41*(IF(32<=6,'前提'!$B$94,IF(32<=12,'前提'!$B$95,IF(32<=18,'前提'!$B$96,IF(32<=24,'前提'!$B$97,IF(32<=36,'前提'!$B$98,IF(32<=48,'前提'!$B$99,'前提'!$B$100))))))) | AH34: ='前提'!$B$41*(IF(33<=6,'前提'!$B$94,IF(33<=12,'前提'!$B$95,IF(33<=18,'前提'!$B$96,IF(33<=24,'前提'!$B$97,IF(33<=36,'前提'!$B$98,IF(33<=48,'前提'!$B$99,'前提'!$B$100))))))) | AI34: ='前提'!$B$41*(IF(34<=6,'前提'!$B$94,IF(34<=12,'前提'!$B$95,IF(34<=18,'前提'!$B$96,IF(34<=24,'前提'!$B$97,IF(34<=36,'前提'!$B$98,IF(34<=48,'前提'!$B$99,'前提'!$B$100))))))) | AJ34: ='前提'!$B$41*(IF(35<=6,'前提'!$B$94,IF(35<=12,'前提'!$B$95,IF(35<=18,'前提'!$B$96,IF(35<=24,'前提'!$B$97,IF(35<=36,'前提'!$B$98,IF(35<=48,'前提'!$B$99,'前提'!$B$100))))))) | AK34: ='前提'!$B$41*(IF(36<=6,'前提'!$B$94,IF(36<=12,'前提'!$B$95,IF(36<=18,'前提'!$B$96,IF(36<=24,'前提'!$B$97,IF(36<=36,'前提'!$B$98,IF(36<=48,'前提'!$B$99,'前提'!$B$100))))))) | AL34: ='前提'!$B$41*(IF(37<=6,'前提'!$B$94,IF(37<=12,'前提'!$B$95,IF(37<=18,'前提'!$B$96,IF(37<=24,'前提'!$B$97,IF(37<=36,'前提'!$B$98,IF(37<=48,'前提'!$B$99,'前提'!$B$100))))))) | AM34: ='前提'!$B$41*(IF(38<=6,'前提'!$B$94,IF(38<=12,'前提'!$B$95,IF(38<=18,'前提'!$B$96,IF(38<=24,'前提'!$B$97,IF(38<=36,'前提'!$B$98,IF(38<=48,'前提'!$B$99,'前提'!$B$100))))))) | AN34: ='前提'!$B$41*(IF(39<=6,'前提'!$B$94,IF(39<=12,'前提'!$B$95,IF(39<=18,'前提'!$B$96,IF(39<=24,'前提'!$B$97,IF(39<=36,'前提'!$B$98,IF(39<=48,'前提'!$B$99,'前提'!$B$100))))))) | AO34: ='前提'!$B$41*(IF(40<=6,'前提'!$B$94,IF(40<=12,'前提'!$B$95,IF(40<=18,'前提'!$B$96,IF(40<=24,'前提'!$B$97,IF(40<=36,'前提'!$B$98,IF(40<=48,'前提'!$B$99,'前提'!$B$100))))))) | AP34: ='前提'!$B$41*(IF(41<=6,'前提'!$B$94,IF(41<=12,'前提'!$B$95,IF(41<=18,'前提'!$B$96,IF(41<=24,'前提'!$B$97,IF(41<=36,'前提'!$B$98,IF(41<=48,'前提'!$B$99,'前提'!$B$100))))))) | AQ34: ='前提'!$B$41*(IF(42<=6,'前提'!$B$94,IF(42<=12,'前提'!$B$95,IF(42<=18,'前提'!$B$96,IF(42<=24,'前提'!$B$97,IF(42<=36,'前提'!$B$98,IF(42<=48,'前提'!$B$99,'前提'!$B$100))))))) | AR34: ='前提'!$B$41*(IF(43<=6,'前提'!$B$94,IF(43<=12,'前提'!$B$95,IF(43<=18,'前提'!$B$96,IF(43<=24,'前提'!$B$97,IF(43<=36,'前提'!$B$98,IF(43<=48,'前提'!$B$99,'前提'!$B$100))))))) | AS34: ='前提'!$B$41*(IF(44<=6,'前提'!$B$94,IF(44<=12,'前提'!$B$95,IF(44<=18,'前提'!$B$96,IF(44<=24,'前提'!$B$97,IF(44<=36,'前提'!$B$98,IF(44<=48,'前提'!$B$99,'前提'!$B$100))))))) | AT34: ='前提'!$B$41*(IF(45<=6,'前提'!$B$94,IF(45<=12,'前提'!$B$95,IF(45<=18,'前提'!$B$96,IF(45<=24,'前提'!$B$97,IF(45<=36,'前提'!$B$98,IF(45<=48,'前提'!$B$99,'前提'!$B$100))))))) | AU34: ='前提'!$B$41*(IF(46<=6,'前提'!$B$94,IF(46<=12,'前提'!$B$95,IF(46<=18,'前提'!$B$96,IF(46<=24,'前提'!$B$97,IF(46<=36,'前提'!$B$98,IF(46<=48,'前提'!$B$99,'前提'!$B$100))))))) | AV34: ='前提'!$B$41*(IF(47<=6,'前提'!$B$94,IF(47<=12,'前提'!$B$95,IF(47<=18,'前提'!$B$96,IF(47<=24,'前提'!$B$97,IF(47<=36,'前提'!$B$98,IF(47<=48,'前提'!$B$99,'前提'!$B$100))))))) | AW34: ='前提'!$B$41*(IF(48<=6,'前提'!$B$94,IF(48<=12,'前提'!$B$95,IF(48<=18,'前提'!$B$96,IF(48<=24,'前提'!$B$97,IF(48<=36,'前提'!$B$98,IF(48<=48,'前提'!$B$99,'前提'!$B$100))))))) | AX34: ='前提'!$B$41*(IF(49<=6,'前提'!$B$94,IF(49<=12,'前提'!$B$95,IF(49<=18,'前提'!$B$96,IF(49<=24,'前提'!$B$97,IF(49<=36,'前提'!$B$98,IF(49<=48,'前提'!$B$99,'前提'!$B$100))))))) | AY34: ='前提'!$B$41*(IF(50<=6,'前提'!$B$94,IF(50<=12,'前提'!$B$95,IF(50<=18,'前提'!$B$96,IF(50<=24,'前提'!$B$97,IF(50<=36,'前提'!$B$98,IF(50<=48,'前提'!$B$99,'前提'!$B$100))))))) | AZ34: ='前提'!$B$41*(IF(51<=6,'前提'!$B$94,IF(51<=12,'前提'!$B$95,IF(51<=18,'前提'!$B$96,IF(51<=24,'前提'!$B$97,IF(51<=36,'前提'!$B$98,IF(51<=48,'前提'!$B$99,'前提'!$B$100))))))) | BA34: ='前提'!$B$41*(IF(52<=6,'前提'!$B$94,IF(52<=12,'前提'!$B$95,IF(52<=18,'前提'!$B$96,IF(52<=24,'前提'!$B$97,IF(52<=36,'前提'!$B$98,IF(52<=48,'前提'!$B$99,'前提'!$B$100))))))) | BB34: ='前提'!$B$41*(IF(53<=6,'前提'!$B$94,IF(53<=12,'前提'!$B$95,IF(53<=18,'前提'!$B$96,IF(53<=24,'前提'!$B$97,IF(53<=36,'前提'!$B$98,IF(53<=48,'前提'!$B$99,'前提'!$B$100))))))) | BC34: ='前提'!$B$41*(IF(54<=6,'前提'!$B$94,IF(54<=12,'前提'!$B$95,IF(54<=18,'前提'!$B$96,IF(54<=24,'前提'!$B$97,IF(54<=36,'前提'!$B$98,IF(54<=48,'前提'!$B$99,'前提'!$B$100))))))) | BD34: ='前提'!$B$41*(IF(55<=6,'前提'!$B$94,IF(55<=12,'前提'!$B$95,IF(55<=18,'前提'!$B$96,IF(55<=24,'前提'!$B$97,IF(55<=36,'前提'!$B$98,IF(55<=48,'前提'!$B$99,'前提'!$B$100))))))) | BE34: ='前提'!$B$41*(IF(56<=6,'前提'!$B$94,IF(56<=12,'前提'!$B$95,IF(56<=18,'前提'!$B$96,IF(56<=24,'前提'!$B$97,IF(56<=36,'前提'!$B$98,IF(56<=48,'前提'!$B$99,'前提'!$B$100))))))) | BF34: ='前提'!$B$41*(IF(57<=6,'前提'!$B$94,IF(57<=12,'前提'!$B$95,IF(57<=18,'前提'!$B$96,IF(57<=24,'前提'!$B$97,IF(57<=36,'前提'!$B$98,IF(57<=48,'前提'!$B$99,'前提'!$B$100))))))) | BG34: ='前提'!$B$41*(IF(58<=6,'前提'!$B$94,IF(58<=12,'前提'!$B$95,IF(58<=18,'前提'!$B$96,IF(58<=24,'前提'!$B$97,IF(58<=36,'前提'!$B$98,IF(58<=48,'前提'!$B$99,'前提'!$B$100))))))) | BH34: ='前提'!$B$41*(IF(59<=6,'前提'!$B$94,IF(59<=12,'前提'!$B$95,IF(59<=18,'前提'!$B$96,IF(59<=24,'前提'!$B$97,IF(59<=36,'前提'!$B$98,IF(59<=48,'前提'!$B$99,'前提'!$B$100))))))) | BI34: ='前提'!$B$41*(IF(60<=6,'前提'!$B$94,IF(60<=12,'前提'!$B$95,IF(60<=18,'前提'!$B$96,IF(60<=24,'前提'!$B$97,IF(60<=36,'前提'!$B$98,IF(60<=48,'前提'!$B$99,'前提'!$B$100)))))))
A35: BPO事務長 | B35: =IF(1>=7,CEILING(B14/'前提'!$B$29,1)*'前提'!$B$39,0) | C35: =IF(2>=7,CEILING(C14/'前提'!$B$29,1)*'前提'!$B$39,0) | D35: =IF(3>=7,CEILING(D14/'前提'!$B$29,1)*'前提'!$B$39,0) | E35: =IF(4>=7,CEILING(E14/'前提'!$B$29,1)*'前提'!$B$39,0) | F35: =IF(5>=7,CEILING(F14/'前提'!$B$29,1)*'前提'!$B$39,0) | G35: =IF(6>=7,CEILING(G14/'前提'!$B$29,1)*'前提'!$B$39,0) | H35: =IF(7>=7,CEILING(H14/'前提'!$B$29,1)*'前提'!$B$39,0) | I35: =IF(8>=7,CEILING(I14/'前提'!$B$29,1)*'前提'!$B$39,0) | J35: =IF(9>=7,CEILING(J14/'前提'!$B$29,1)*'前提'!$B$39,0) | K35: =IF(10>=7,CEILING(K14/'前提'!$B$29,1)*'前提'!$B$39,0) | L35: =IF(11>=7,CEILING(L14/'前提'!$B$29,1)*'前提'!$B$39,0) | M35: =IF(12>=7,CEILING(M14/'前提'!$B$29,1)*'前提'!$B$39,0) | N35: =IF(13>=7,CEILING(N14/'前提'!$B$29,1)*'前提'!$B$39,0) | O35: =IF(14>=7,CEILING(O14/'前提'!$B$29,1)*'前提'!$B$39,0) | P35: =IF(15>=7,CEILING(P14/'前提'!$B$29,1)*'前提'!$B$39,0) | Q35: =IF(16>=7,CEILING(Q14/'前提'!$B$29,1)*'前提'!$B$39,0) | R35: =IF(17>=7,CEILING(R14/'前提'!$B$29,1)*'前提'!$B$39,0) | S35: =IF(18>=7,CEILING(S14/'前提'!$B$29,1)*'前提'!$B$39,0) | T35: =IF(19>=7,CEILING(T14/'前提'!$B$29,1)*'前提'!$B$39,0) | U35: =IF(20>=7,CEILING(U14/'前提'!$B$29,1)*'前提'!$B$39,0) | V35: =IF(21>=7,CEILING(V14/'前提'!$B$29,1)*'前提'!$B$39,0) | W35: =IF(22>=7,CEILING(W14/'前提'!$B$29,1)*'前提'!$B$39,0) | X35: =IF(23>=7,CEILING(X14/'前提'!$B$29,1)*'前提'!$B$39,0) | Y35: =IF(24>=7,CEILING(Y14/'前提'!$B$29,1)*'前提'!$B$39,0) | Z35: =IF(25>=7,CEILING(Z14/'前提'!$B$29,1)*'前提'!$B$39,0) | AA35: =IF(26>=7,CEILING(AA14/'前提'!$B$29,1)*'前提'!$B$39,0) | AB35: =IF(27>=7,CEILING(AB14/'前提'!$B$29,1)*'前提'!$B$39,0) | AC35: =IF(28>=7,CEILING(AC14/'前提'!$B$29,1)*'前提'!$B$39,0) | AD35: =IF(29>=7,CEILING(AD14/'前提'!$B$29,1)*'前提'!$B$39,0) | AE35: =IF(30>=7,CEILING(AE14/'前提'!$B$29,1)*'前提'!$B$39,0) | AF35: =IF(31>=7,CEILING(AF14/'前提'!$B$29,1)*'前提'!$B$39,0) | AG35: =IF(32>=7,CEILING(AG14/'前提'!$B$29,1)*'前提'!$B$39,0) | AH35: =IF(33>=7,CEILING(AH14/'前提'!$B$29,1)*'前提'!$B$39,0) | AI35: =IF(34>=7,CEILING(AI14/'前提'!$B$29,1)*'前提'!$B$39,0) | AJ35: =IF(35>=7,CEILING(AJ14/'前提'!$B$29,1)*'前提'!$B$39,0) | AK35: =IF(36>=7,CEILING(AK14/'前提'!$B$29,1)*'前提'!$B$39,0) | AL35: =IF(37>=7,CEILING(AL14/'前提'!$B$29,1)*'前提'!$B$39,0) | AM35: =IF(38>=7,CEILING(AM14/'前提'!$B$29,1)*'前提'!$B$39,0) | AN35: =IF(39>=7,CEILING(AN14/'前提'!$B$29,1)*'前提'!$B$39,0) | AO35: =IF(40>=7,CEILING(AO14/'前提'!$B$29,1)*'前提'!$B$39,0) | AP35: =IF(41>=7,CEILING(AP14/'前提'!$B$29,1)*'前提'!$B$39,0) | AQ35: =IF(42>=7,CEILING(AQ14/'前提'!$B$29,1)*'前提'!$B$39,0) | AR35: =IF(43>=7,CEILING(AR14/'前提'!$B$29,1)*'前提'!$B$39,0) | AS35: =IF(44>=7,CEILING(AS14/'前提'!$B$29,1)*'前提'!$B$39,0) | AT35: =IF(45>=7,CEILING(AT14/'前提'!$B$29,1)*'前提'!$B$39,0) | AU35: =IF(46>=7,CEILING(AU14/'前提'!$B$29,1)*'前提'!$B$39,0) | AV35: =IF(47>=7,CEILING(AV14/'前提'!$B$29,1)*'前提'!$B$39,0) | AW35: =IF(48>=7,CEILING(AW14/'前提'!$B$29,1)*'前提'!$B$39,0) | AX35: =IF(49>=7,CEILING(AX14/'前提'!$B$29,1)*'前提'!$B$39,0) | AY35: =IF(50>=7,CEILING(AY14/'前提'!$B$29,1)*'前提'!$B$39,0) | AZ35: =IF(51>=7,CEILING(AZ14/'前提'!$B$29,1)*'前提'!$B$39,0) | BA35: =IF(52>=7,CEILING(BA14/'前提'!$B$29,1)*'前提'!$B$39,0) | BB35: =IF(53>=7,CEILING(BB14/'前提'!$B$29,1)*'前提'!$B$39,0) | BC35: =IF(54>=7,CEILING(BC14/'前提'!$B$29,1)*'前提'!$B$39,0) | BD35: =IF(55>=7,CEILING(BD14/'前提'!$B$29,1)*'前提'!$B$39,0) | BE35: =IF(56>=7,CEILING(BE14/'前提'!$B$29,1)*'前提'!$B$39,0) | BF35: =IF(57>=7,CEILING(BF14/'前提'!$B$29,1)*'前提'!$B$39,0) | BG35: =IF(58>=7,CEILING(BG14/'前提'!$B$29,1)*'前提'!$B$39,0) | BH35: =IF(59>=7,CEILING(BH14/'前提'!$B$29,1)*'前提'!$B$39,0) | BI35: =IF(60>=7,CEILING(BI14/'前提'!$B$29,1)*'前提'!$B$39,0)
A36: BPOオペ | B36: =IF(1>=7,CEILING(B14/'前提'!$B$30,1)*'前提'!$B$40,0) | C36: =IF(2>=7,CEILING(C14/'前提'!$B$30,1)*'前提'!$B$40,0) | D36: =IF(3>=7,CEILING(D14/'前提'!$B$30,1)*'前提'!$B$40,0) | E36: =IF(4>=7,CEILING(E14/'前提'!$B$30,1)*'前提'!$B$40,0) | F36: =IF(5>=7,CEILING(F14/'前提'!$B$30,1)*'前提'!$B$40,0) | G36: =IF(6>=7,CEILING(G14/'前提'!$B$30,1)*'前提'!$B$40,0) | H36: =IF(7>=7,CEILING(H14/'前提'!$B$30,1)*'前提'!$B$40,0) | I36: =IF(8>=7,CEILING(I14/'前提'!$B$30,1)*'前提'!$B$40,0) | J36: =IF(9>=7,CEILING(J14/'前提'!$B$30,1)*'前提'!$B$40,0) | K36: =IF(10>=7,CEILING(K14/'前提'!$B$30,1)*'前提'!$B$40,0) | L36: =IF(11>=7,CEILING(L14/'前提'!$B$30,1)*'前提'!$B$40,0) | M36: =IF(12>=7,CEILING(M14/'前提'!$B$30,1)*'前提'!$B$40,0) | N36: =IF(13>=7,CEILING(N14/'前提'!$B$30,1)*'前提'!$B$40,0) | O36: =IF(14>=7,CEILING(O14/'前提'!$B$30,1)*'前提'!$B$40,0) | P36: =IF(15>=7,CEILING(P14/'前提'!$B$30,1)*'前提'!$B$40,0) | Q36: =IF(16>=7,CEILING(Q14/'前提'!$B$30,1)*'前提'!$B$40,0) | R36: =IF(17>=7,CEILING(R14/'前提'!$B$30,1)*'前提'!$B$40,0) | S36: =IF(18>=7,CEILING(S14/'前提'!$B$30,1)*'前提'!$B$40,0) | T36: =IF(19>=7,CEILING(T14/'前提'!$B$30,1)*'前提'!$B$40,0) | U36: =IF(20>=7,CEILING(U14/'前提'!$B$30,1)*'前提'!$B$40,0) | V36: =IF(21>=7,CEILING(V14/'前提'!$B$30,1)*'前提'!$B$40,0) | W36: =IF(22>=7,CEILING(W14/'前提'!$B$30,1)*'前提'!$B$40,0) | X36: =IF(23>=7,CEILING(X14/'前提'!$B$30,1)*'前提'!$B$40,0) | Y36: =IF(24>=7,CEILING(Y14/'前提'!$B$30,1)*'前提'!$B$40,0) | Z36: =IF(25>=7,CEILING(Z14/'前提'!$B$30,1)*'前提'!$B$40,0) | AA36: =IF(26>=7,CEILING(AA14/'前提'!$B$30,1)*'前提'!$B$40,0) | AB36: =IF(27>=7,CEILING(AB14/'前提'!$B$30,1)*'前提'!$B$40,0) | AC36: =IF(28>=7,CEILING(AC14/'前提'!$B$30,1)*'前提'!$B$40,0) | AD36: =IF(29>=7,CEILING(AD14/'前提'!$B$30,1)*'前提'!$B$40,0) | AE36: =IF(30>=7,CEILING(AE14/'前提'!$B$30,1)*'前提'!$B$40,0) | AF36: =IF(31>=7,CEILING(AF14/'前提'!$B$30,1)*'前提'!$B$40,0) | AG36: =IF(32>=7,CEILING(AG14/'前提'!$B$30,1)*'前提'!$B$40,0) | AH36: =IF(33>=7,CEILING(AH14/'前提'!$B$30,1)*'前提'!$B$40,0) | AI36: =IF(34>=7,CEILING(AI14/'前提'!$B$30,1)*'前提'!$B$40,0) | AJ36: =IF(35>=7,CEILING(AJ14/'前提'!$B$30,1)*'前提'!$B$40,0) | AK36: =IF(36>=7,CEILING(AK14/'前提'!$B$30,1)*'前提'!$B$40,0) | AL36: =IF(37>=7,CEILING(AL14/'前提'!$B$30,1)*'前提'!$B$40,0) | AM36: =IF(38>=7,CEILING(AM14/'前提'!$B$30,1)*'前提'!$B$40,0) | AN36: =IF(39>=7,CEILING(AN14/'前提'!$B$30,1)*'前提'!$B$40,0) | AO36: =IF(40>=7,CEILING(AO14/'前提'!$B$30,1)*'前提'!$B$40,0) | AP36: =IF(41>=7,CEILING(AP14/'前提'!$B$30,1)*'前提'!$B$40,0) | AQ36: =IF(42>=7,CEILING(AQ14/'前提'!$B$30,1)*'前提'!$B$40,0) | AR36: =IF(43>=7,CEILING(AR14/'前提'!$B$30,1)*'前提'!$B$40,0) | AS36: =IF(44>=7,CEILING(AS14/'前提'!$B$30,1)*'前提'!$B$40,0) | AT36: =IF(45>=7,CEILING(AT14/'前提'!$B$30,1)*'前提'!$B$40,0) | AU36: =IF(46>=7,CEILING(AU14/'前提'!$B$30,1)*'前提'!$B$40,0) | AV36: =IF(47>=7,CEILING(AV14/'前提'!$B$30,1)*'前提'!$B$40,0) | AW36: =IF(48>=7,CEILING(AW14/'前提'!$B$30,1)*'前提'!$B$40,0) | AX36: =IF(49>=7,CEILING(AX14/'前提'!$B$30,1)*'前提'!$B$40,0) | AY36: =IF(50>=7,CEILING(AY14/'前提'!$B$30,1)*'前提'!$B$40,0) | AZ36: =IF(51>=7,CEILING(AZ14/'前提'!$B$30,1)*'前提'!$B$40,0) | BA36: =IF(52>=7,CEILING(BA14/'前提'!$B$30,1)*'前提'!$B$40,0) | BB36: =IF(53>=7,CEILING(BB14/'前提'!$B$30,1)*'前提'!$B$40,0) | BC36: =IF(54>=7,CEILING(BC14/'前提'!$B$30,1)*'前提'!$B$40,0) | BD36: =IF(55>=7,CEILING(BD14/'前提'!$B$30,1)*'前提'!$B$40,0) | BE36: =IF(56>=7,CEILING(BE14/'前提'!$B$30,1)*'前提'!$B$40,0) | BF36: =IF(57>=7,CEILING(BF14/'前提'!$B$30,1)*'前提'!$B$40,0) | BG36: =IF(58>=7,CEILING(BG14/'前提'!$B$30,1)*'前提'!$B$40,0) | BH36: =IF(59>=7,CEILING(BH14/'前提'!$B$30,1)*'前提'!$B$40,0) | BI36: =IF(60>=7,CEILING(BI14/'前提'!$B$30,1)*'前提'!$B$40,0)
A37: CS | B37: =IF(1>=7,CEILING(B10/'前提'!$B$31,1)*'前提'!$B$42,0) | C37: =IF(2>=7,CEILING(C10/'前提'!$B$31,1)*'前提'!$B$42,0) | D37: =IF(3>=7,CEILING(D10/'前提'!$B$31,1)*'前提'!$B$42,0) | E37: =IF(4>=7,CEILING(E10/'前提'!$B$31,1)*'前提'!$B$42,0) | F37: =IF(5>=7,CEILING(F10/'前提'!$B$31,1)*'前提'!$B$42,0) | G37: =IF(6>=7,CEILING(G10/'前提'!$B$31,1)*'前提'!$B$42,0) | H37: =IF(7>=7,CEILING(H10/'前提'!$B$31,1)*'前提'!$B$42,0) | I37: =IF(8>=7,CEILING(I10/'前提'!$B$31,1)*'前提'!$B$42,0) | J37: =IF(9>=7,CEILING(J10/'前提'!$B$31,1)*'前提'!$B$42,0) | K37: =IF(10>=7,CEILING(K10/'前提'!$B$31,1)*'前提'!$B$42,0) | L37: =IF(11>=7,CEILING(L10/'前提'!$B$31,1)*'前提'!$B$42,0) | M37: =IF(12>=7,CEILING(M10/'前提'!$B$31,1)*'前提'!$B$42,0) | N37: =IF(13>=7,CEILING(N10/'前提'!$B$31,1)*'前提'!$B$42,0) | O37: =IF(14>=7,CEILING(O10/'前提'!$B$31,1)*'前提'!$B$42,0) | P37: =IF(15>=7,CEILING(P10/'前提'!$B$31,1)*'前提'!$B$42,0) | Q37: =IF(16>=7,CEILING(Q10/'前提'!$B$31,1)*'前提'!$B$42,0) | R37: =IF(17>=7,CEILING(R10/'前提'!$B$31,1)*'前提'!$B$42,0) | S37: =IF(18>=7,CEILING(S10/'前提'!$B$31,1)*'前提'!$B$42,0) | T37: =IF(19>=7,CEILING(T10/'前提'!$B$31,1)*'前提'!$B$42,0) | U37: =IF(20>=7,CEILING(U10/'前提'!$B$31,1)*'前提'!$B$42,0) | V37: =IF(21>=7,CEILING(V10/'前提'!$B$31,1)*'前提'!$B$42,0) | W37: =IF(22>=7,CEILING(W10/'前提'!$B$31,1)*'前提'!$B$42,0) | X37: =IF(23>=7,CEILING(X10/'前提'!$B$31,1)*'前提'!$B$42,0) | Y37: =IF(24>=7,CEILING(Y10/'前提'!$B$31,1)*'前提'!$B$42,0) | Z37: =IF(25>=7,CEILING(Z10/'前提'!$B$31,1)*'前提'!$B$42,0) | AA37: =IF(26>=7,CEILING(AA10/'前提'!$B$31,1)*'前提'!$B$42,0) | AB37: =IF(27>=7,CEILING(AB10/'前提'!$B$31,1)*'前提'!$B$42,0) | AC37: =IF(28>=7,CEILING(AC10/'前提'!$B$31,1)*'前提'!$B$42,0) | AD37: =IF(29>=7,CEILING(AD10/'前提'!$B$31,1)*'前提'!$B$42,0) | AE37: =IF(30>=7,CEILING(AE10/'前提'!$B$31,1)*'前提'!$B$42,0) | AF37: =IF(31>=7,CEILING(AF10/'前提'!$B$31,1)*'前提'!$B$42,0) | AG37: =IF(32>=7,CEILING(AG10/'前提'!$B$31,1)*'前提'!$B$42,0) | AH37: =IF(33>=7,CEILING(AH10/'前提'!$B$31,1)*'前提'!$B$42,0) | AI37: =IF(34>=7,CEILING(AI10/'前提'!$B$31,1)*'前提'!$B$42,0) | AJ37: =IF(35>=7,CEILING(AJ10/'前提'!$B$31,1)*'前提'!$B$42,0) | AK37: =IF(36>=7,CEILING(AK10/'前提'!$B$31,1)*'前提'!$B$42,0) | AL37: =IF(37>=7,CEILING(AL10/'前提'!$B$31,1)*'前提'!$B$42,0) | AM37: =IF(38>=7,CEILING(AM10/'前提'!$B$31,1)*'前提'!$B$42,0) | AN37: =IF(39>=7,CEILING(AN10/'前提'!$B$31,1)*'前提'!$B$42,0) | AO37: =IF(40>=7,CEILING(AO10/'前提'!$B$31,1)*'前提'!$B$42,0) | AP37: =IF(41>=7,CEILING(AP10/'前提'!$B$31,1)*'前提'!$B$42,0) | AQ37: =IF(42>=7,CEILING(AQ10/'前提'!$B$31,1)*'前提'!$B$42,0) | AR37: =IF(43>=7,CEILING(AR10/'前提'!$B$31,1)*'前提'!$B$42,0) | AS37: =IF(44>=7,CEILING(AS10/'前提'!$B$31,1)*'前提'!$B$42,0) | AT37: =IF(45>=7,CEILING(AT10/'前提'!$B$31,1)*'前提'!$B$42,0) | AU37: =IF(46>=7,CEILING(AU10/'前提'!$B$31,1)*'前提'!$B$42,0) | AV37: =IF(47>=7,CEILING(AV10/'前提'!$B$31,1)*'前提'!$B$42,0) | AW37: =IF(48>=7,CEILING(AW10/'前提'!$B$31,1)*'前提'!$B$42,0) | AX37: =IF(49>=7,CEILING(AX10/'前提'!$B$31,1)*'前提'!$B$42,0) | AY37: =IF(50>=7,CEILING(AY10/'前提'!$B$31,1)*'前提'!$B$42,0) | AZ37: =IF(51>=7,CEILING(AZ10/'前提'!$B$31,1)*'前提'!$B$42,0) | BA37: =IF(52>=7,CEILING(BA10/'前提'!$B$31,1)*'前提'!$B$42,0) | BB37: =IF(53>=7,CEILING(BB10/'前提'!$B$31,1)*'前提'!$B$42,0) | BC37: =IF(54>=7,CEILING(BC10/'前提'!$B$31,1)*'前提'!$B$42,0) | BD37: =IF(55>=7,CEILING(BD10/'前提'!$B$31,1)*'前提'!$B$42,0) | BE37: =IF(56>=7,CEILING(BE10/'前提'!$B$31,1)*'前提'!$B$42,0) | BF37: =IF(57>=7,CEILING(BF10/'前提'!$B$31,1)*'前提'!$B$42,0) | BG37: =IF(58>=7,CEILING(BG10/'前提'!$B$31,1)*'前提'!$B$42,0) | BH37: =IF(59>=7,CEILING(BH10/'前提'!$B$31,1)*'前提'!$B$42,0) | BI37: =IF(60>=7,CEILING(BI10/'前提'!$B$31,1)*'前提'!$B$42,0)
A38: 社会保険料（CEO+正社員） | B38: =(B32+IF(1<=12,0,'前提'!$B$38*(IF(1<=6,'前提'!$B$85,IF(1<=12,'前提'!$B$86,IF(1<=18,'前提'!$B$87,IF(1<=24,'前提'!$B$88,IF(1<=36,'前提'!$B$89,IF(1<=48,'前提'!$B$90,'前提'!$B$91)))))))))*'前提'!$B$43 | C38: =(C32+IF(2<=12,0,'前提'!$B$38*(IF(2<=6,'前提'!$B$85,IF(2<=12,'前提'!$B$86,IF(2<=18,'前提'!$B$87,IF(2<=24,'前提'!$B$88,IF(2<=36,'前提'!$B$89,IF(2<=48,'前提'!$B$90,'前提'!$B$91)))))))))*'前提'!$B$43 | D38: =(D32+IF(3<=12,0,'前提'!$B$38*(IF(3<=6,'前提'!$B$85,IF(3<=12,'前提'!$B$86,IF(3<=18,'前提'!$B$87,IF(3<=24,'前提'!$B$88,IF(3<=36,'前提'!$B$89,IF(3<=48,'前提'!$B$90,'前提'!$B$91)))))))))*'前提'!$B$43 | E38: =(E32+IF(4<=12,0,'前提'!$B$38*(IF(4<=6,'前提'!$B$85,IF(4<=12,'前提'!$B$86,IF(4<=18,'前提'!$B$87,IF(4<=24,'前提'!$B$88,IF(4<=36,'前提'!$B$89,IF(4<=48,'前提'!$B$90,'前提'!$B$91)))))))))*'前提'!$B$43 | F38: =(F32+IF(5<=12,0,'前提'!$B$38*(IF(5<=6,'前提'!$B$85,IF(5<=12,'前提'!$B$86,IF(5<=18,'前提'!$B$87,IF(5<=24,'前提'!$B$88,IF(5<=36,'前提'!$B$89,IF(5<=48,'前提'!$B$90,'前提'!$B$91)))))))))*'前提'!$B$43 | G38: =(G32+IF(6<=12,0,'前提'!$B$38*(IF(6<=6,'前提'!$B$85,IF(6<=12,'前提'!$B$86,IF(6<=18,'前提'!$B$87,IF(6<=24,'前提'!$B$88,IF(6<=36,'前提'!$B$89,IF(6<=48,'前提'!$B$90,'前提'!$B$91)))))))))*'前提'!$B$43 | H38: =(H32+IF(7<=12,0,'前提'!$B$38*(IF(7<=6,'前提'!$B$85,IF(7<=12,'前提'!$B$86,IF(7<=18,'前提'!$B$87,IF(7<=24,'前提'!$B$88,IF(7<=36,'前提'!$B$89,IF(7<=48,'前提'!$B$90,'前提'!$B$91)))))))))*'前提'!$B$43 | I38: =(I32+IF(8<=12,0,'前提'!$B$38*(IF(8<=6,'前提'!$B$85,IF(8<=12,'前提'!$B$86,IF(8<=18,'前提'!$B$87,IF(8<=24,'前提'!$B$88,IF(8<=36,'前提'!$B$89,IF(8<=48,'前提'!$B$90,'前提'!$B$91)))))))))*'前提'!$B$43 | J38: =(J32+IF(9<=12,0,'前提'!$B$38*(IF(9<=6,'前提'!$B$85,IF(9<=12,'前提'!$B$86,IF(9<=18,'前提'!$B$87,IF(9<=24,'前提'!$B$88,IF(9<=36,'前提'!$B$89,IF(9<=48,'前提'!$B$90,'前提'!$B$91)))))))))*'前提'!$B$43 | K38: =(K32+IF(10<=12,0,'前提'!$B$38*(IF(10<=6,'前提'!$B$85,IF(10<=12,'前提'!$B$86,IF(10<=18,'前提'!$B$87,IF(10<=24,'前提'!$B$88,IF(10<=36,'前提'!$B$89,IF(10<=48,'前提'!$B$90,'前提'!$B$91)))))))))*'前提'!$B$43 | L38: =(L32+IF(11<=12,0,'前提'!$B$38*(IF(11<=6,'前提'!$B$85,IF(11<=12,'前提'!$B$86,IF(11<=18,'前提'!$B$87,IF(11<=24,'前提'!$B$88,IF(11<=36,'前提'!$B$89,IF(11<=48,'前提'!$B$90,'前提'!$B$91)))))))))*'前提'!$B$43 | M38: =(M32+IF(12<=12,0,'前提'!$B$38*(IF(12<=6,'前提'!$B$85,IF(12<=12,'前提'!$B$86,IF(12<=18,'前提'!$B$87,IF(12<=24,'前提'!$B$88,IF(12<=36,'前提'!$B$89,IF(12<=48,'前提'!$B$90,'前提'!$B$91)))))))))*'前提'!$B$43 | N38: =(N32+IF(13<=12,0,'前提'!$B$38*(IF(13<=6,'前提'!$B$85,IF(13<=12,'前提'!$B$86,IF(13<=18,'前提'!$B$87,IF(13<=24,'前提'!$B$88,IF(13<=36,'前提'!$B$89,IF(13<=48,'前提'!$B$90,'前提'!$B$91)))))))))*'前提'!$B$43 | O38: =(O32+IF(14<=12,0,'前提'!$B$38*(IF(14<=6,'前提'!$B$85,IF(14<=12,'前提'!$B$86,IF(14<=18,'前提'!$B$87,IF(14<=24,'前提'!$B$88,IF(14<=36,'前提'!$B$89,IF(14<=48,'前提'!$B$90,'前提'!$B$91)))))))))*'前提'!$B$43 | P38: =(P32+IF(15<=12,0,'前提'!$B$38*(IF(15<=6,'前提'!$B$85,IF(15<=12,'前提'!$B$86,IF(15<=18,'前提'!$B$87,IF(15<=24,'前提'!$B$88,IF(15<=36,'前提'!$B$89,IF(15<=48,'前提'!$B$90,'前提'!$B$91)))))))))*'前提'!$B$43 | Q38: =(Q32+IF(16<=12,0,'前提'!$B$38*(IF(16<=6,'前提'!$B$85,IF(16<=12,'前提'!$B$86,IF(16<=18,'前提'!$B$87,IF(16<=24,'前提'!$B$88,IF(16<=36,'前提'!$B$89,IF(16<=48,'前提'!$B$90,'前提'!$B$91)))))))))*'前提'!$B$43 | R38: =(R32+IF(17<=12,0,'前提'!$B$38*(IF(17<=6,'前提'!$B$85,IF(17<=12,'前提'!$B$86,IF(17<=18,'前提'!$B$87,IF(17<=24,'前提'!$B$88,IF(17<=36,'前提'!$B$89,IF(17<=48,'前提'!$B$90,'前提'!$B$91)))))))))*'前提'!$B$43 | S38: =(S32+IF(18<=12,0,'前提'!$B$38*(IF(18<=6,'前提'!$B$85,IF(18<=12,'前提'!$B$86,IF(18<=18,'前提'!$B$87,IF(18<=24,'前提'!$B$88,IF(18<=36,'前提'!$B$89,IF(18<=48,'前提'!$B$90,'前提'!$B$91)))))))))*'前提'!$B$43 | T38: =(T32+IF(19<=12,0,'前提'!$B$38*(IF(19<=6,'前提'!$B$85,IF(19<=12,'前提'!$B$86,IF(19<=18,'前提'!$B$87,IF(19<=24,'前提'!$B$88,IF(19<=36,'前提'!$B$89,IF(19<=48,'前提'!$B$90,'前提'!$B$91)))))))))*'前提'!$B$43 | U38: =(U32+IF(20<=12,0,'前提'!$B$38*(IF(20<=6,'前提'!$B$85,IF(20<=12,'前提'!$B$86,IF(20<=18,'前提'!$B$87,IF(20<=24,'前提'!$B$88,IF(20<=36,'前提'!$B$89,IF(20<=48,'前提'!$B$90,'前提'!$B$91)))))))))*'前提'!$B$43 | V38: =(V32+IF(21<=12,0,'前提'!$B$38*(IF(21<=6,'前提'!$B$85,IF(21<=12,'前提'!$B$86,IF(21<=18,'前提'!$B$87,IF(21<=24,'前提'!$B$88,IF(21<=36,'前提'!$B$89,IF(21<=48,'前提'!$B$90,'前提'!$B$91)))))))))*'前提'!$B$43 | W38: =(W32+IF(22<=12,0,'前提'!$B$38*(IF(22<=6,'前提'!$B$85,IF(22<=12,'前提'!$B$86,IF(22<=18,'前提'!$B$87,IF(22<=24,'前提'!$B$88,IF(22<=36,'前提'!$B$89,IF(22<=48,'前提'!$B$90,'前提'!$B$91)))))))))*'前提'!$B$43 | X38: =(X32+IF(23<=12,0,'前提'!$B$38*(IF(23<=6,'前提'!$B$85,IF(23<=12,'前提'!$B$86,IF(23<=18,'前提'!$B$87,IF(23<=24,'前提'!$B$88,IF(23<=36,'前提'!$B$89,IF(23<=48,'前提'!$B$90,'前提'!$B$91)))))))))*'前提'!$B$43 | Y38: =(Y32+IF(24<=12,0,'前提'!$B$38*(IF(24<=6,'前提'!$B$85,IF(24<=12,'前提'!$B$86,IF(24<=18,'前提'!$B$87,IF(24<=24,'前提'!$B$88,IF(24<=36,'前提'!$B$89,IF(24<=48,'前提'!$B$90,'前提'!$B$91)))))))))*'前提'!$B$43 | Z38: =(Z32+IF(25<=12,0,'前提'!$B$38*(IF(25<=6,'前提'!$B$85,IF(25<=12,'前提'!$B$86,IF(25<=18,'前提'!$B$87,IF(25<=24,'前提'!$B$88,IF(25<=36,'前提'!$B$89,IF(25<=48,'前提'!$B$90,'前提'!$B$91)))))))))*'前提'!$B$43 | AA38: =(AA32+IF(26<=12,0,'前提'!$B$38*(IF(26<=6,'前提'!$B$85,IF(26<=12,'前提'!$B$86,IF(26<=18,'前提'!$B$87,IF(26<=24,'前提'!$B$88,IF(26<=36,'前提'!$B$89,IF(26<=48,'前提'!$B$90,'前提'!$B$91)))))))))*'前提'!$B$43 | AB38: =(AB32+IF(27<=12,0,'前提'!$B$38*(IF(27<=6,'前提'!$B$85,IF(27<=12,'前提'!$B$86,IF(27<=18,'前提'!$B$87,IF(27<=24,'前提'!$B$88,IF(27<=36,'前提'!$B$89,IF(27<=48,'前提'!$B$90,'前提'!$B$91)))))))))*'前提'!$B$43 | AC38: =(AC32+IF(28<=12,0,'前提'!$B$38*(IF(28<=6,'前提'!$B$85,IF(28<=12,'前提'!$B$86,IF(28<=18,'前提'!$B$87,IF(28<=24,'前提'!$B$88,IF(28<=36,'前提'!$B$89,IF(28<=48,'前提'!$B$90,'前提'!$B$91)))))))))*'前提'!$B$43 | AD38: =(AD32+IF(29<=12,0,'前提'!$B$38*(IF(29<=6,'前提'!$B$85,IF(29<=12,'前提'!$B$86,IF(29<=18,'前提'!$B$87,IF(29<=24,'前提'!$B$88,IF(29<=36,'前提'!$B$89,IF(29<=48,'前提'!$B$90,'前提'!$B$91)))))))))*'前提'!$B$43 | AE38: =(AE32+IF(30<=12,0,'前提'!$B$38*(IF(30<=6,'前提'!$B$85,IF(30<=12,'前提'!$B$86,IF(30<=18,'前提'!$B$87,IF(30<=24,'前提'!$B$88,IF(30<=36,'前提'!$B$89,IF(30<=48,'前提'!$B$90,'前提'!$B$91)))))))))*'前提'!$B$43 | AF38: =(AF32+IF(31<=12,0,'前提'!$B$38*(IF(31<=6,'前提'!$B$85,IF(31<=12,'前提'!$B$86,IF(31<=18,'前提'!$B$87,IF(31<=24,'前提'!$B$88,IF(31<=36,'前提'!$B$89,IF(31<=48,'前提'!$B$90,'前提'!$B$91)))))))))*'前提'!$B$43 | AG38: =(AG32+IF(32<=12,0,'前提'!$B$38*(IF(32<=6,'前提'!$B$85,IF(32<=12,'前提'!$B$86,IF(32<=18,'前提'!$B$87,IF(32<=24,'前提'!$B$88,IF(32<=36,'前提'!$B$89,IF(32<=48,'前提'!$B$90,'前提'!$B$91)))))))))*'前提'!$B$43 | AH38: =(AH32+IF(33<=12,0,'前提'!$B$38*(IF(33<=6,'前提'!$B$85,IF(33<=12,'前提'!$B$86,IF(33<=18,'前提'!$B$87,IF(33<=24,'前提'!$B$88,IF(33<=36,'前提'!$B$89,IF(33<=48,'前提'!$B$90,'前提'!$B$91)))))))))*'前提'!$B$43 | AI38: =(AI32+IF(34<=12,0,'前提'!$B$38*(IF(34<=6,'前提'!$B$85,IF(34<=12,'前提'!$B$86,IF(34<=18,'前提'!$B$87,IF(34<=24,'前提'!$B$88,IF(34<=36,'前提'!$B$89,IF(34<=48,'前提'!$B$90,'前提'!$B$91)))))))))*'前提'!$B$43 | AJ38: =(AJ32+IF(35<=12,0,'前提'!$B$38*(IF(35<=6,'前提'!$B$85,IF(35<=12,'前提'!$B$86,IF(35<=18,'前提'!$B$87,IF(35<=24,'前提'!$B$88,IF(35<=36,'前提'!$B$89,IF(35<=48,'前提'!$B$90,'前提'!$B$91)))))))))*'前提'!$B$43 | AK38: =(AK32+IF(36<=12,0,'前提'!$B$38*(IF(36<=6,'前提'!$B$85,IF(36<=12,'前提'!$B$86,IF(36<=18,'前提'!$B$87,IF(36<=24,'前提'!$B$88,IF(36<=36,'前提'!$B$89,IF(36<=48,'前提'!$B$90,'前提'!$B$91)))))))))*'前提'!$B$43 | AL38: =(AL32+IF(37<=12,0,'前提'!$B$38*(IF(37<=6,'前提'!$B$85,IF(37<=12,'前提'!$B$86,IF(37<=18,'前提'!$B$87,IF(37<=24,'前提'!$B$88,IF(37<=36,'前提'!$B$89,IF(37<=48,'前提'!$B$90,'前提'!$B$91)))))))))*'前提'!$B$43 | AM38: =(AM32+IF(38<=12,0,'前提'!$B$38*(IF(38<=6,'前提'!$B$85,IF(38<=12,'前提'!$B$86,IF(38<=18,'前提'!$B$87,IF(38<=24,'前提'!$B$88,IF(38<=36,'前提'!$B$89,IF(38<=48,'前提'!$B$90,'前提'!$B$91)))))))))*'前提'!$B$43 | AN38: =(AN32+IF(39<=12,0,'前提'!$B$38*(IF(39<=6,'前提'!$B$85,IF(39<=12,'前提'!$B$86,IF(39<=18,'前提'!$B$87,IF(39<=24,'前提'!$B$88,IF(39<=36,'前提'!$B$89,IF(39<=48,'前提'!$B$90,'前提'!$B$91)))))))))*'前提'!$B$43 | AO38: =(AO32+IF(40<=12,0,'前提'!$B$38*(IF(40<=6,'前提'!$B$85,IF(40<=12,'前提'!$B$86,IF(40<=18,'前提'!$B$87,IF(40<=24,'前提'!$B$88,IF(40<=36,'前提'!$B$89,IF(40<=48,'前提'!$B$90,'前提'!$B$91)))))))))*'前提'!$B$43 | AP38: =(AP32+IF(41<=12,0,'前提'!$B$38*(IF(41<=6,'前提'!$B$85,IF(41<=12,'前提'!$B$86,IF(41<=18,'前提'!$B$87,IF(41<=24,'前提'!$B$88,IF(41<=36,'前提'!$B$89,IF(41<=48,'前提'!$B$90,'前提'!$B$91)))))))))*'前提'!$B$43 | AQ38: =(AQ32+IF(42<=12,0,'前提'!$B$38*(IF(42<=6,'前提'!$B$85,IF(42<=12,'前提'!$B$86,IF(42<=18,'前提'!$B$87,IF(42<=24,'前提'!$B$88,IF(42<=36,'前提'!$B$89,IF(42<=48,'前提'!$B$90,'前提'!$B$91)))))))))*'前提'!$B$43 | AR38: =(AR32+IF(43<=12,0,'前提'!$B$38*(IF(43<=6,'前提'!$B$85,IF(43<=12,'前提'!$B$86,IF(43<=18,'前提'!$B$87,IF(43<=24,'前提'!$B$88,IF(43<=36,'前提'!$B$89,IF(43<=48,'前提'!$B$90,'前提'!$B$91)))))))))*'前提'!$B$43 | AS38: =(AS32+IF(44<=12,0,'前提'!$B$38*(IF(44<=6,'前提'!$B$85,IF(44<=12,'前提'!$B$86,IF(44<=18,'前提'!$B$87,IF(44<=24,'前提'!$B$88,IF(44<=36,'前提'!$B$89,IF(44<=48,'前提'!$B$90,'前提'!$B$91)))))))))*'前提'!$B$43 | AT38: =(AT32+IF(45<=12,0,'前提'!$B$38*(IF(45<=6,'前提'!$B$85,IF(45<=12,'前提'!$B$86,IF(45<=18,'前提'!$B$87,IF(45<=24,'前提'!$B$88,IF(45<=36,'前提'!$B$89,IF(45<=48,'前提'!$B$90,'前提'!$B$91)))))))))*'前提'!$B$43 | AU38: =(AU32+IF(46<=12,0,'前提'!$B$38*(IF(46<=6,'前提'!$B$85,IF(46<=12,'前提'!$B$86,IF(46<=18,'前提'!$B$87,IF(46<=24,'前提'!$B$88,IF(46<=36,'前提'!$B$89,IF(46<=48,'前提'!$B$90,'前提'!$B$91)))))))))*'前提'!$B$43 | AV38: =(AV32+IF(47<=12,0,'前提'!$B$38*(IF(47<=6,'前提'!$B$85,IF(47<=12,'前提'!$B$86,IF(47<=18,'前提'!$B$87,IF(47<=24,'前提'!$B$88,IF(47<=36,'前提'!$B$89,IF(47<=48,'前提'!$B$90,'前提'!$B$91)))))))))*'前提'!$B$43 | AW38: =(AW32+IF(48<=12,0,'前提'!$B$38*(IF(48<=6,'前提'!$B$85,IF(48<=12,'前提'!$B$86,IF(48<=18,'前提'!$B$87,IF(48<=24,'前提'!$B$88,IF(48<=36,'前提'!$B$89,IF(48<=48,'前提'!$B$90,'前提'!$B$91)))))))))*'前提'!$B$43 | AX38: =(AX32+IF(49<=12,0,'前提'!$B$38*(IF(49<=6,'前提'!$B$85,IF(49<=12,'前提'!$B$86,IF(49<=18,'前提'!$B$87,IF(49<=24,'前提'!$B$88,IF(49<=36,'前提'!$B$89,IF(49<=48,'前提'!$B$90,'前提'!$B$91)))))))))*'前提'!$B$43 | AY38: =(AY32+IF(50<=12,0,'前提'!$B$38*(IF(50<=6,'前提'!$B$85,IF(50<=12,'前提'!$B$86,IF(50<=18,'前提'!$B$87,IF(50<=24,'前提'!$B$88,IF(50<=36,'前提'!$B$89,IF(50<=48,'前提'!$B$90,'前提'!$B$91)))))))))*'前提'!$B$43 | AZ38: =(AZ32+IF(51<=12,0,'前提'!$B$38*(IF(51<=6,'前提'!$B$85,IF(51<=12,'前提'!$B$86,IF(51<=18,'前提'!$B$87,IF(51<=24,'前提'!$B$88,IF(51<=36,'前提'!$B$89,IF(51<=48,'前提'!$B$90,'前提'!$B$91)))))))))*'前提'!$B$43 | BA38: =(BA32+IF(52<=12,0,'前提'!$B$38*(IF(52<=6,'前提'!$B$85,IF(52<=12,'前提'!$B$86,IF(52<=18,'前提'!$B$87,IF(52<=24,'前提'!$B$88,IF(52<=36,'前提'!$B$89,IF(52<=48,'前提'!$B$90,'前提'!$B$91)))))))))*'前提'!$B$43 | BB38: =(BB32+IF(53<=12,0,'前提'!$B$38*(IF(53<=6,'前提'!$B$85,IF(53<=12,'前提'!$B$86,IF(53<=18,'前提'!$B$87,IF(53<=24,'前提'!$B$88,IF(53<=36,'前提'!$B$89,IF(53<=48,'前提'!$B$90,'前提'!$B$91)))))))))*'前提'!$B$43 | BC38: =(BC32+IF(54<=12,0,'前提'!$B$38*(IF(54<=6,'前提'!$B$85,IF(54<=12,'前提'!$B$86,IF(54<=18,'前提'!$B$87,IF(54<=24,'前提'!$B$88,IF(54<=36,'前提'!$B$89,IF(54<=48,'前提'!$B$90,'前提'!$B$91)))))))))*'前提'!$B$43 | BD38: =(BD32+IF(55<=12,0,'前提'!$B$38*(IF(55<=6,'前提'!$B$85,IF(55<=12,'前提'!$B$86,IF(55<=18,'前提'!$B$87,IF(55<=24,'前提'!$B$88,IF(55<=36,'前提'!$B$89,IF(55<=48,'前提'!$B$90,'前提'!$B$91)))))))))*'前提'!$B$43 | BE38: =(BE32+IF(56<=12,0,'前提'!$B$38*(IF(56<=6,'前提'!$B$85,IF(56<=12,'前提'!$B$86,IF(56<=18,'前提'!$B$87,IF(56<=24,'前提'!$B$88,IF(56<=36,'前提'!$B$89,IF(56<=48,'前提'!$B$90,'前提'!$B$91)))))))))*'前提'!$B$43 | BF38: =(BF32+IF(57<=12,0,'前提'!$B$38*(IF(57<=6,'前提'!$B$85,IF(57<=12,'前提'!$B$86,IF(57<=18,'前提'!$B$87,IF(57<=24,'前提'!$B$88,IF(57<=36,'前提'!$B$89,IF(57<=48,'前提'!$B$90,'前提'!$B$91)))))))))*'前提'!$B$43 | BG38: =(BG32+IF(58<=12,0,'前提'!$B$38*(IF(58<=6,'前提'!$B$85,IF(58<=12,'前提'!$B$86,IF(58<=18,'前提'!$B$87,IF(58<=24,'前提'!$B$88,IF(58<=36,'前提'!$B$89,IF(58<=48,'前提'!$B$90,'前提'!$B$91)))))))))*'前提'!$B$43 | BH38: =(BH32+IF(59<=12,0,'前提'!$B$38*(IF(59<=6,'前提'!$B$85,IF(59<=12,'前提'!$B$86,IF(59<=18,'前提'!$B$87,IF(59<=24,'前提'!$B$88,IF(59<=36,'前提'!$B$89,IF(59<=48,'前提'!$B$90,'前提'!$B$91)))))))))*'前提'!$B$43 | BI38: =(BI32+IF(60<=12,0,'前提'!$B$38*(IF(60<=6,'前提'!$B$85,IF(60<=12,'前提'!$B$86,IF(60<=18,'前提'!$B$87,IF(60<=24,'前提'!$B$88,IF(60<=36,'前提'!$B$89,IF(60<=48,'前提'!$B$90,'前提'!$B$91)))))))))*'前提'!$B$43
A39: 福利厚生（全員） | B39: =(1+IF(1<=6,'前提'!$B$36/160,IF(1<=12,'前提'!$B$37/160,(IF(1<=6,'前提'!$B$85,IF(1<=12,'前提'!$B$86,IF(1<=18,'前提'!$B$87,IF(1<=24,'前提'!$B$88,IF(1<=36,'前提'!$B$89,IF(1<=48,'前提'!$B$90,'前提'!$B$91)))))))))+(IF(1<=6,'前提'!$B$94,IF(1<=12,'前提'!$B$95,IF(1<=18,'前提'!$B$96,IF(1<=24,'前提'!$B$97,IF(1<=36,'前提'!$B$98,IF(1<=48,'前提'!$B$99,'前提'!$B$100)))))))+IF(1>=7,CEILING(B14/'前提'!$B$29,1),0)+IF(1>=7,CEILING(B14/'前提'!$B$30,1),0)+IF(1>=7,CEILING(B10/'前提'!$B$31,1),0))*'前提'!$B$44 | C39: =(1+IF(2<=6,'前提'!$B$36/160,IF(2<=12,'前提'!$B$37/160,(IF(2<=6,'前提'!$B$85,IF(2<=12,'前提'!$B$86,IF(2<=18,'前提'!$B$87,IF(2<=24,'前提'!$B$88,IF(2<=36,'前提'!$B$89,IF(2<=48,'前提'!$B$90,'前提'!$B$91)))))))))+(IF(2<=6,'前提'!$B$94,IF(2<=12,'前提'!$B$95,IF(2<=18,'前提'!$B$96,IF(2<=24,'前提'!$B$97,IF(2<=36,'前提'!$B$98,IF(2<=48,'前提'!$B$99,'前提'!$B$100)))))))+IF(2>=7,CEILING(C14/'前提'!$B$29,1),0)+IF(2>=7,CEILING(C14/'前提'!$B$30,1),0)+IF(2>=7,CEILING(C10/'前提'!$B$31,1),0))*'前提'!$B$44 | D39: =(1+IF(3<=6,'前提'!$B$36/160,IF(3<=12,'前提'!$B$37/160,(IF(3<=6,'前提'!$B$85,IF(3<=12,'前提'!$B$86,IF(3<=18,'前提'!$B$87,IF(3<=24,'前提'!$B$88,IF(3<=36,'前提'!$B$89,IF(3<=48,'前提'!$B$90,'前提'!$B$91)))))))))+(IF(3<=6,'前提'!$B$94,IF(3<=12,'前提'!$B$95,IF(3<=18,'前提'!$B$96,IF(3<=24,'前提'!$B$97,IF(3<=36,'前提'!$B$98,IF(3<=48,'前提'!$B$99,'前提'!$B$100)))))))+IF(3>=7,CEILING(D14/'前提'!$B$29,1),0)+IF(3>=7,CEILING(D14/'前提'!$B$30,1),0)+IF(3>=7,CEILING(D10/'前提'!$B$31,1),0))*'前提'!$B$44 | E39: =(1+IF(4<=6,'前提'!$B$36/160,IF(4<=12,'前提'!$B$37/160,(IF(4<=6,'前提'!$B$85,IF(4<=12,'前提'!$B$86,IF(4<=18,'前提'!$B$87,IF(4<=24,'前提'!$B$88,IF(4<=36,'前提'!$B$89,IF(4<=48,'前提'!$B$90,'前提'!$B$91)))))))))+(IF(4<=6,'前提'!$B$94,IF(4<=12,'前提'!$B$95,IF(4<=18,'前提'!$B$96,IF(4<=24,'前提'!$B$97,IF(4<=36,'前提'!$B$98,IF(4<=48,'前提'!$B$99,'前提'!$B$100)))))))+IF(4>=7,CEILING(E14/'前提'!$B$29,1),0)+IF(4>=7,CEILING(E14/'前提'!$B$30,1),0)+IF(4>=7,CEILING(E10/'前提'!$B$31,1),0))*'前提'!$B$44 | F39: =(1+IF(5<=6,'前提'!$B$36/160,IF(5<=12,'前提'!$B$37/160,(IF(5<=6,'前提'!$B$85,IF(5<=12,'前提'!$B$86,IF(5<=18,'前提'!$B$87,IF(5<=24,'前提'!$B$88,IF(5<=36,'前提'!$B$89,IF(5<=48,'前提'!$B$90,'前提'!$B$91)))))))))+(IF(5<=6,'前提'!$B$94,IF(5<=12,'前提'!$B$95,IF(5<=18,'前提'!$B$96,IF(5<=24,'前提'!$B$97,IF(5<=36,'前提'!$B$98,IF(5<=48,'前提'!$B$99,'前提'!$B$100)))))))+IF(5>=7,CEILING(F14/'前提'!$B$29,1),0)+IF(5>=7,CEILING(F14/'前提'!$B$30,1),0)+IF(5>=7,CEILING(F10/'前提'!$B$31,1),0))*'前提'!$B$44 | G39: =(1+IF(6<=6,'前提'!$B$36/160,IF(6<=12,'前提'!$B$37/160,(IF(6<=6,'前提'!$B$85,IF(6<=12,'前提'!$B$86,IF(6<=18,'前提'!$B$87,IF(6<=24,'前提'!$B$88,IF(6<=36,'前提'!$B$89,IF(6<=48,'前提'!$B$90,'前提'!$B$91)))))))))+(IF(6<=6,'前提'!$B$94,IF(6<=12,'前提'!$B$95,IF(6<=18,'前提'!$B$96,IF(6<=24,'前提'!$B$97,IF(6<=36,'前提'!$B$98,IF(6<=48,'前提'!$B$99,'前提'!$B$100)))))))+IF(6>=7,CEILING(G14/'前提'!$B$29,1),0)+IF(6>=7,CEILING(G14/'前提'!$B$30,1),0)+IF(6>=7,CEILING(G10/'前提'!$B$31,1),0))*'前提'!$B$44 | H39: =(1+IF(7<=6,'前提'!$B$36/160,IF(7<=12,'前提'!$B$37/160,(IF(7<=6,'前提'!$B$85,IF(7<=12,'前提'!$B$86,IF(7<=18,'前提'!$B$87,IF(7<=24,'前提'!$B$88,IF(7<=36,'前提'!$B$89,IF(7<=48,'前提'!$B$90,'前提'!$B$91)))))))))+(IF(7<=6,'前提'!$B$94,IF(7<=12,'前提'!$B$95,IF(7<=18,'前提'!$B$96,IF(7<=24,'前提'!$B$97,IF(7<=36,'前提'!$B$98,IF(7<=48,'前提'!$B$99,'前提'!$B$100)))))))+IF(7>=7,CEILING(H14/'前提'!$B$29,1),0)+IF(7>=7,CEILING(H14/'前提'!$B$30,1),0)+IF(7>=7,CEILING(H10/'前提'!$B$31,1),0))*'前提'!$B$44 | I39: =(1+IF(8<=6,'前提'!$B$36/160,IF(8<=12,'前提'!$B$37/160,(IF(8<=6,'前提'!$B$85,IF(8<=12,'前提'!$B$86,IF(8<=18,'前提'!$B$87,IF(8<=24,'前提'!$B$88,IF(8<=36,'前提'!$B$89,IF(8<=48,'前提'!$B$90,'前提'!$B$91)))))))))+(IF(8<=6,'前提'!$B$94,IF(8<=12,'前提'!$B$95,IF(8<=18,'前提'!$B$96,IF(8<=24,'前提'!$B$97,IF(8<=36,'前提'!$B$98,IF(8<=48,'前提'!$B$99,'前提'!$B$100)))))))+IF(8>=7,CEILING(I14/'前提'!$B$29,1),0)+IF(8>=7,CEILING(I14/'前提'!$B$30,1),0)+IF(8>=7,CEILING(I10/'前提'!$B$31,1),0))*'前提'!$B$44 | J39: =(1+IF(9<=6,'前提'!$B$36/160,IF(9<=12,'前提'!$B$37/160,(IF(9<=6,'前提'!$B$85,IF(9<=12,'前提'!$B$86,IF(9<=18,'前提'!$B$87,IF(9<=24,'前提'!$B$88,IF(9<=36,'前提'!$B$89,IF(9<=48,'前提'!$B$90,'前提'!$B$91)))))))))+(IF(9<=6,'前提'!$B$94,IF(9<=12,'前提'!$B$95,IF(9<=18,'前提'!$B$96,IF(9<=24,'前提'!$B$97,IF(9<=36,'前提'!$B$98,IF(9<=48,'前提'!$B$99,'前提'!$B$100)))))))+IF(9>=7,CEILING(J14/'前提'!$B$29,1),0)+IF(9>=7,CEILING(J14/'前提'!$B$30,1),0)+IF(9>=7,CEILING(J10/'前提'!$B$31,1),0))*'前提'!$B$44 | K39: =(1+IF(10<=6,'前提'!$B$36/160,IF(10<=12,'前提'!$B$37/160,(IF(10<=6,'前提'!$B$85,IF(10<=12,'前提'!$B$86,IF(10<=18,'前提'!$B$87,IF(10<=24,'前提'!$B$88,IF(10<=36,'前提'!$B$89,IF(10<=48,'前提'!$B$90,'前提'!$B$91)))))))))+(IF(10<=6,'前提'!$B$94,IF(10<=12,'前提'!$B$95,IF(10<=18,'前提'!$B$96,IF(10<=24,'前提'!$B$97,IF(10<=36,'前提'!$B$98,IF(10<=48,'前提'!$B$99,'前提'!$B$100)))))))+IF(10>=7,CEILING(K14/'前提'!$B$29,1),0)+IF(10>=7,CEILING(K14/'前提'!$B$30,1),0)+IF(10>=7,CEILING(K10/'前提'!$B$31,1),0))*'前提'!$B$44 | L39: =(1+IF(11<=6,'前提'!$B$36/160,IF(11<=12,'前提'!$B$37/160,(IF(11<=6,'前提'!$B$85,IF(11<=12,'前提'!$B$86,IF(11<=18,'前提'!$B$87,IF(11<=24,'前提'!$B$88,IF(11<=36,'前提'!$B$89,IF(11<=48,'前提'!$B$90,'前提'!$B$91)))))))))+(IF(11<=6,'前提'!$B$94,IF(11<=12,'前提'!$B$95,IF(11<=18,'前提'!$B$96,IF(11<=24,'前提'!$B$97,IF(11<=36,'前提'!$B$98,IF(11<=48,'前提'!$B$99,'前提'!$B$100)))))))+IF(11>=7,CEILING(L14/'前提'!$B$29,1),0)+IF(11>=7,CEILING(L14/'前提'!$B$30,1),0)+IF(11>=7,CEILING(L10/'前提'!$B$31,1),0))*'前提'!$B$44 | M39: =(1+IF(12<=6,'前提'!$B$36/160,IF(12<=12,'前提'!$B$37/160,(IF(12<=6,'前提'!$B$85,IF(12<=12,'前提'!$B$86,IF(12<=18,'前提'!$B$87,IF(12<=24,'前提'!$B$88,IF(12<=36,'前提'!$B$89,IF(12<=48,'前提'!$B$90,'前提'!$B$91)))))))))+(IF(12<=6,'前提'!$B$94,IF(12<=12,'前提'!$B$95,IF(12<=18,'前提'!$B$96,IF(12<=24,'前提'!$B$97,IF(12<=36,'前提'!$B$98,IF(12<=48,'前提'!$B$99,'前提'!$B$100)))))))+IF(12>=7,CEILING(M14/'前提'!$B$29,1),0)+IF(12>=7,CEILING(M14/'前提'!$B$30,1),0)+IF(12>=7,CEILING(M10/'前提'!$B$31,1),0))*'前提'!$B$44 | N39: =(1+IF(13<=6,'前提'!$B$36/160,IF(13<=12,'前提'!$B$37/160,(IF(13<=6,'前提'!$B$85,IF(13<=12,'前提'!$B$86,IF(13<=18,'前提'!$B$87,IF(13<=24,'前提'!$B$88,IF(13<=36,'前提'!$B$89,IF(13<=48,'前提'!$B$90,'前提'!$B$91)))))))))+(IF(13<=6,'前提'!$B$94,IF(13<=12,'前提'!$B$95,IF(13<=18,'前提'!$B$96,IF(13<=24,'前提'!$B$97,IF(13<=36,'前提'!$B$98,IF(13<=48,'前提'!$B$99,'前提'!$B$100)))))))+IF(13>=7,CEILING(N14/'前提'!$B$29,1),0)+IF(13>=7,CEILING(N14/'前提'!$B$30,1),0)+IF(13>=7,CEILING(N10/'前提'!$B$31,1),0))*'前提'!$B$44 | O39: =(1+IF(14<=6,'前提'!$B$36/160,IF(14<=12,'前提'!$B$37/160,(IF(14<=6,'前提'!$B$85,IF(14<=12,'前提'!$B$86,IF(14<=18,'前提'!$B$87,IF(14<=24,'前提'!$B$88,IF(14<=36,'前提'!$B$89,IF(14<=48,'前提'!$B$90,'前提'!$B$91)))))))))+(IF(14<=6,'前提'!$B$94,IF(14<=12,'前提'!$B$95,IF(14<=18,'前提'!$B$96,IF(14<=24,'前提'!$B$97,IF(14<=36,'前提'!$B$98,IF(14<=48,'前提'!$B$99,'前提'!$B$100)))))))+IF(14>=7,CEILING(O14/'前提'!$B$29,1),0)+IF(14>=7,CEILING(O14/'前提'!$B$30,1),0)+IF(14>=7,CEILING(O10/'前提'!$B$31,1),0))*'前提'!$B$44 | P39: =(1+IF(15<=6,'前提'!$B$36/160,IF(15<=12,'前提'!$B$37/160,(IF(15<=6,'前提'!$B$85,IF(15<=12,'前提'!$B$86,IF(15<=18,'前提'!$B$87,IF(15<=24,'前提'!$B$88,IF(15<=36,'前提'!$B$89,IF(15<=48,'前提'!$B$90,'前提'!$B$91)))))))))+(IF(15<=6,'前提'!$B$94,IF(15<=12,'前提'!$B$95,IF(15<=18,'前提'!$B$96,IF(15<=24,'前提'!$B$97,IF(15<=36,'前提'!$B$98,IF(15<=48,'前提'!$B$99,'前提'!$B$100)))))))+IF(15>=7,CEILING(P14/'前提'!$B$29,1),0)+IF(15>=7,CEILING(P14/'前提'!$B$30,1),0)+IF(15>=7,CEILING(P10/'前提'!$B$31,1),0))*'前提'!$B$44 | Q39: =(1+IF(16<=6,'前提'!$B$36/160,IF(16<=12,'前提'!$B$37/160,(IF(16<=6,'前提'!$B$85,IF(16<=12,'前提'!$B$86,IF(16<=18,'前提'!$B$87,IF(16<=24,'前提'!$B$88,IF(16<=36,'前提'!$B$89,IF(16<=48,'前提'!$B$90,'前提'!$B$91)))))))))+(IF(16<=6,'前提'!$B$94,IF(16<=12,'前提'!$B$95,IF(16<=18,'前提'!$B$96,IF(16<=24,'前提'!$B$97,IF(16<=36,'前提'!$B$98,IF(16<=48,'前提'!$B$99,'前提'!$B$100)))))))+IF(16>=7,CEILING(Q14/'前提'!$B$29,1),0)+IF(16>=7,CEILING(Q14/'前提'!$B$30,1),0)+IF(16>=7,CEILING(Q10/'前提'!$B$31,1),0))*'前提'!$B$44 | R39: =(1+IF(17<=6,'前提'!$B$36/160,IF(17<=12,'前提'!$B$37/160,(IF(17<=6,'前提'!$B$85,IF(17<=12,'前提'!$B$86,IF(17<=18,'前提'!$B$87,IF(17<=24,'前提'!$B$88,IF(17<=36,'前提'!$B$89,IF(17<=48,'前提'!$B$90,'前提'!$B$91)))))))))+(IF(17<=6,'前提'!$B$94,IF(17<=12,'前提'!$B$95,IF(17<=18,'前提'!$B$96,IF(17<=24,'前提'!$B$97,IF(17<=36,'前提'!$B$98,IF(17<=48,'前提'!$B$99,'前提'!$B$100)))))))+IF(17>=7,CEILING(R14/'前提'!$B$29,1),0)+IF(17>=7,CEILING(R14/'前提'!$B$30,1),0)+IF(17>=7,CEILING(R10/'前提'!$B$31,1),0))*'前提'!$B$44 | S39: =(1+IF(18<=6,'前提'!$B$36/160,IF(18<=12,'前提'!$B$37/160,(IF(18<=6,'前提'!$B$85,IF(18<=12,'前提'!$B$86,IF(18<=18,'前提'!$B$87,IF(18<=24,'前提'!$B$88,IF(18<=36,'前提'!$B$89,IF(18<=48,'前提'!$B$90,'前提'!$B$91)))))))))+(IF(18<=6,'前提'!$B$94,IF(18<=12,'前提'!$B$95,IF(18<=18,'前提'!$B$96,IF(18<=24,'前提'!$B$97,IF(18<=36,'前提'!$B$98,IF(18<=48,'前提'!$B$99,'前提'!$B$100)))))))+IF(18>=7,CEILING(S14/'前提'!$B$29,1),0)+IF(18>=7,CEILING(S14/'前提'!$B$30,1),0)+IF(18>=7,CEILING(S10/'前提'!$B$31,1),0))*'前提'!$B$44 | T39: =(1+IF(19<=6,'前提'!$B$36/160,IF(19<=12,'前提'!$B$37/160,(IF(19<=6,'前提'!$B$85,IF(19<=12,'前提'!$B$86,IF(19<=18,'前提'!$B$87,IF(19<=24,'前提'!$B$88,IF(19<=36,'前提'!$B$89,IF(19<=48,'前提'!$B$90,'前提'!$B$91)))))))))+(IF(19<=6,'前提'!$B$94,IF(19<=12,'前提'!$B$95,IF(19<=18,'前提'!$B$96,IF(19<=24,'前提'!$B$97,IF(19<=36,'前提'!$B$98,IF(19<=48,'前提'!$B$99,'前提'!$B$100)))))))+IF(19>=7,CEILING(T14/'前提'!$B$29,1),0)+IF(19>=7,CEILING(T14/'前提'!$B$30,1),0)+IF(19>=7,CEILING(T10/'前提'!$B$31,1),0))*'前提'!$B$44 | U39: =(1+IF(20<=6,'前提'!$B$36/160,IF(20<=12,'前提'!$B$37/160,(IF(20<=6,'前提'!$B$85,IF(20<=12,'前提'!$B$86,IF(20<=18,'前提'!$B$87,IF(20<=24,'前提'!$B$88,IF(20<=36,'前提'!$B$89,IF(20<=48,'前提'!$B$90,'前提'!$B$91)))))))))+(IF(20<=6,'前提'!$B$94,IF(20<=12,'前提'!$B$95,IF(20<=18,'前提'!$B$96,IF(20<=24,'前提'!$B$97,IF(20<=36,'前提'!$B$98,IF(20<=48,'前提'!$B$99,'前提'!$B$100)))))))+IF(20>=7,CEILING(U14/'前提'!$B$29,1),0)+IF(20>=7,CEILING(U14/'前提'!$B$30,1),0)+IF(20>=7,CEILING(U10/'前提'!$B$31,1),0))*'前提'!$B$44 | V39: =(1+IF(21<=6,'前提'!$B$36/160,IF(21<=12,'前提'!$B$37/160,(IF(21<=6,'前提'!$B$85,IF(21<=12,'前提'!$B$86,IF(21<=18,'前提'!$B$87,IF(21<=24,'前提'!$B$88,IF(21<=36,'前提'!$B$89,IF(21<=48,'前提'!$B$90,'前提'!$B$91)))))))))+(IF(21<=6,'前提'!$B$94,IF(21<=12,'前提'!$B$95,IF(21<=18,'前提'!$B$96,IF(21<=24,'前提'!$B$97,IF(21<=36,'前提'!$B$98,IF(21<=48,'前提'!$B$99,'前提'!$B$100)))))))+IF(21>=7,CEILING(V14/'前提'!$B$29,1),0)+IF(21>=7,CEILING(V14/'前提'!$B$30,1),0)+IF(21>=7,CEILING(V10/'前提'!$B$31,1),0))*'前提'!$B$44 | W39: =(1+IF(22<=6,'前提'!$B$36/160,IF(22<=12,'前提'!$B$37/160,(IF(22<=6,'前提'!$B$85,IF(22<=12,'前提'!$B$86,IF(22<=18,'前提'!$B$87,IF(22<=24,'前提'!$B$88,IF(22<=36,'前提'!$B$89,IF(22<=48,'前提'!$B$90,'前提'!$B$91)))))))))+(IF(22<=6,'前提'!$B$94,IF(22<=12,'前提'!$B$95,IF(22<=18,'前提'!$B$96,IF(22<=24,'前提'!$B$97,IF(22<=36,'前提'!$B$98,IF(22<=48,'前提'!$B$99,'前提'!$B$100)))))))+IF(22>=7,CEILING(W14/'前提'!$B$29,1),0)+IF(22>=7,CEILING(W14/'前提'!$B$30,1),0)+IF(22>=7,CEILING(W10/'前提'!$B$31,1),0))*'前提'!$B$44 | X39: =(1+IF(23<=6,'前提'!$B$36/160,IF(23<=12,'前提'!$B$37/160,(IF(23<=6,'前提'!$B$85,IF(23<=12,'前提'!$B$86,IF(23<=18,'前提'!$B$87,IF(23<=24,'前提'!$B$88,IF(23<=36,'前提'!$B$89,IF(23<=48,'前提'!$B$90,'前提'!$B$91)))))))))+(IF(23<=6,'前提'!$B$94,IF(23<=12,'前提'!$B$95,IF(23<=18,'前提'!$B$96,IF(23<=24,'前提'!$B$97,IF(23<=36,'前提'!$B$98,IF(23<=48,'前提'!$B$99,'前提'!$B$100)))))))+IF(23>=7,CEILING(X14/'前提'!$B$29,1),0)+IF(23>=7,CEILING(X14/'前提'!$B$30,1),0)+IF(23>=7,CEILING(X10/'前提'!$B$31,1),0))*'前提'!$B$44 | Y39: =(1+IF(24<=6,'前提'!$B$36/160,IF(24<=12,'前提'!$B$37/160,(IF(24<=6,'前提'!$B$85,IF(24<=12,'前提'!$B$86,IF(24<=18,'前提'!$B$87,IF(24<=24,'前提'!$B$88,IF(24<=36,'前提'!$B$89,IF(24<=48,'前提'!$B$90,'前提'!$B$91)))))))))+(IF(24<=6,'前提'!$B$94,IF(24<=12,'前提'!$B$95,IF(24<=18,'前提'!$B$96,IF(24<=24,'前提'!$B$97,IF(24<=36,'前提'!$B$98,IF(24<=48,'前提'!$B$99,'前提'!$B$100)))))))+IF(24>=7,CEILING(Y14/'前提'!$B$29,1),0)+IF(24>=7,CEILING(Y14/'前提'!$B$30,1),0)+IF(24>=7,CEILING(Y10/'前提'!$B$31,1),0))*'前提'!$B$44 | Z39: =(1+IF(25<=6,'前提'!$B$36/160,IF(25<=12,'前提'!$B$37/160,(IF(25<=6,'前提'!$B$85,IF(25<=12,'前提'!$B$86,IF(25<=18,'前提'!$B$87,IF(25<=24,'前提'!$B$88,IF(25<=36,'前提'!$B$89,IF(25<=48,'前提'!$B$90,'前提'!$B$91)))))))))+(IF(25<=6,'前提'!$B$94,IF(25<=12,'前提'!$B$95,IF(25<=18,'前提'!$B$96,IF(25<=24,'前提'!$B$97,IF(25<=36,'前提'!$B$98,IF(25<=48,'前提'!$B$99,'前提'!$B$100)))))))+IF(25>=7,CEILING(Z14/'前提'!$B$29,1),0)+IF(25>=7,CEILING(Z14/'前提'!$B$30,1),0)+IF(25>=7,CEILING(Z10/'前提'!$B$31,1),0))*'前提'!$B$44 | AA39: =(1+IF(26<=6,'前提'!$B$36/160,IF(26<=12,'前提'!$B$37/160,(IF(26<=6,'前提'!$B$85,IF(26<=12,'前提'!$B$86,IF(26<=18,'前提'!$B$87,IF(26<=24,'前提'!$B$88,IF(26<=36,'前提'!$B$89,IF(26<=48,'前提'!$B$90,'前提'!$B$91)))))))))+(IF(26<=6,'前提'!$B$94,IF(26<=12,'前提'!$B$95,IF(26<=18,'前提'!$B$96,IF(26<=24,'前提'!$B$97,IF(26<=36,'前提'!$B$98,IF(26<=48,'前提'!$B$99,'前提'!$B$100)))))))+IF(26>=7,CEILING(AA14/'前提'!$B$29,1),0)+IF(26>=7,CEILING(AA14/'前提'!$B$30,1),0)+IF(26>=7,CEILING(AA10/'前提'!$B$31,1),0))*'前提'!$B$44 | AB39: =(1+IF(27<=6,'前提'!$B$36/160,IF(27<=12,'前提'!$B$37/160,(IF(27<=6,'前提'!$B$85,IF(27<=12,'前提'!$B$86,IF(27<=18,'前提'!$B$87,IF(27<=24,'前提'!$B$88,IF(27<=36,'前提'!$B$89,IF(27<=48,'前提'!$B$90,'前提'!$B$91)))))))))+(IF(27<=6,'前提'!$B$94,IF(27<=12,'前提'!$B$95,IF(27<=18,'前提'!$B$96,IF(27<=24,'前提'!$B$97,IF(27<=36,'前提'!$B$98,IF(27<=48,'前提'!$B$99,'前提'!$B$100)))))))+IF(27>=7,CEILING(AB14/'前提'!$B$29,1),0)+IF(27>=7,CEILING(AB14/'前提'!$B$30,1),0)+IF(27>=7,CEILING(AB10/'前提'!$B$31,1),0))*'前提'!$B$44 | AC39: =(1+IF(28<=6,'前提'!$B$36/160,IF(28<=12,'前提'!$B$37/160,(IF(28<=6,'前提'!$B$85,IF(28<=12,'前提'!$B$86,IF(28<=18,'前提'!$B$87,IF(28<=24,'前提'!$B$88,IF(28<=36,'前提'!$B$89,IF(28<=48,'前提'!$B$90,'前提'!$B$91)))))))))+(IF(28<=6,'前提'!$B$94,IF(28<=12,'前提'!$B$95,IF(28<=18,'前提'!$B$96,IF(28<=24,'前提'!$B$97,IF(28<=36,'前提'!$B$98,IF(28<=48,'前提'!$B$99,'前提'!$B$100)))))))+IF(28>=7,CEILING(AC14/'前提'!$B$29,1),0)+IF(28>=7,CEILING(AC14/'前提'!$B$30,1),0)+IF(28>=7,CEILING(AC10/'前提'!$B$31,1),0))*'前提'!$B$44 | AD39: =(1+IF(29<=6,'前提'!$B$36/160,IF(29<=12,'前提'!$B$37/160,(IF(29<=6,'前提'!$B$85,IF(29<=12,'前提'!$B$86,IF(29<=18,'前提'!$B$87,IF(29<=24,'前提'!$B$88,IF(29<=36,'前提'!$B$89,IF(29<=48,'前提'!$B$90,'前提'!$B$91)))))))))+(IF(29<=6,'前提'!$B$94,IF(29<=12,'前提'!$B$95,IF(29<=18,'前提'!$B$96,IF(29<=24,'前提'!$B$97,IF(29<=36,'前提'!$B$98,IF(29<=48,'前提'!$B$99,'前提'!$B$100)))))))+IF(29>=7,CEILING(AD14/'前提'!$B$29,1),0)+IF(29>=7,CEILING(AD14/'前提'!$B$30,1),0)+IF(29>=7,CEILING(AD10/'前提'!$B$31,1),0))*'前提'!$B$44 | AE39: =(1+IF(30<=6,'前提'!$B$36/160,IF(30<=12,'前提'!$B$37/160,(IF(30<=6,'前提'!$B$85,IF(30<=12,'前提'!$B$86,IF(30<=18,'前提'!$B$87,IF(30<=24,'前提'!$B$88,IF(30<=36,'前提'!$B$89,IF(30<=48,'前提'!$B$90,'前提'!$B$91)))))))))+(IF(30<=6,'前提'!$B$94,IF(30<=12,'前提'!$B$95,IF(30<=18,'前提'!$B$96,IF(30<=24,'前提'!$B$97,IF(30<=36,'前提'!$B$98,IF(30<=48,'前提'!$B$99,'前提'!$B$100)))))))+IF(30>=7,CEILING(AE14/'前提'!$B$29,1),0)+IF(30>=7,CEILING(AE14/'前提'!$B$30,1),0)+IF(30>=7,CEILING(AE10/'前提'!$B$31,1),0))*'前提'!$B$44 | AF39: =(1+IF(31<=6,'前提'!$B$36/160,IF(31<=12,'前提'!$B$37/160,(IF(31<=6,'前提'!$B$85,IF(31<=12,'前提'!$B$86,IF(31<=18,'前提'!$B$87,IF(31<=24,'前提'!$B$88,IF(31<=36,'前提'!$B$89,IF(31<=48,'前提'!$B$90,'前提'!$B$91)))))))))+(IF(31<=6,'前提'!$B$94,IF(31<=12,'前提'!$B$95,IF(31<=18,'前提'!$B$96,IF(31<=24,'前提'!$B$97,IF(31<=36,'前提'!$B$98,IF(31<=48,'前提'!$B$99,'前提'!$B$100)))))))+IF(31>=7,CEILING(AF14/'前提'!$B$29,1),0)+IF(31>=7,CEILING(AF14/'前提'!$B$30,1),0)+IF(31>=7,CEILING(AF10/'前提'!$B$31,1),0))*'前提'!$B$44 | AG39: =(1+IF(32<=6,'前提'!$B$36/160,IF(32<=12,'前提'!$B$37/160,(IF(32<=6,'前提'!$B$85,IF(32<=12,'前提'!$B$86,IF(32<=18,'前提'!$B$87,IF(32<=24,'前提'!$B$88,IF(32<=36,'前提'!$B$89,IF(32<=48,'前提'!$B$90,'前提'!$B$91)))))))))+(IF(32<=6,'前提'!$B$94,IF(32<=12,'前提'!$B$95,IF(32<=18,'前提'!$B$96,IF(32<=24,'前提'!$B$97,IF(32<=36,'前提'!$B$98,IF(32<=48,'前提'!$B$99,'前提'!$B$100)))))))+IF(32>=7,CEILING(AG14/'前提'!$B$29,1),0)+IF(32>=7,CEILING(AG14/'前提'!$B$30,1),0)+IF(32>=7,CEILING(AG10/'前提'!$B$31,1),0))*'前提'!$B$44 | AH39: =(1+IF(33<=6,'前提'!$B$36/160,IF(33<=12,'前提'!$B$37/160,(IF(33<=6,'前提'!$B$85,IF(33<=12,'前提'!$B$86,IF(33<=18,'前提'!$B$87,IF(33<=24,'前提'!$B$88,IF(33<=36,'前提'!$B$89,IF(33<=48,'前提'!$B$90,'前提'!$B$91)))))))))+(IF(33<=6,'前提'!$B$94,IF(33<=12,'前提'!$B$95,IF(33<=18,'前提'!$B$96,IF(33<=24,'前提'!$B$97,IF(33<=36,'前提'!$B$98,IF(33<=48,'前提'!$B$99,'前提'!$B$100)))))))+IF(33>=7,CEILING(AH14/'前提'!$B$29,1),0)+IF(33>=7,CEILING(AH14/'前提'!$B$30,1),0)+IF(33>=7,CEILING(AH10/'前提'!$B$31,1),0))*'前提'!$B$44 | AI39: =(1+IF(34<=6,'前提'!$B$36/160,IF(34<=12,'前提'!$B$37/160,(IF(34<=6,'前提'!$B$85,IF(34<=12,'前提'!$B$86,IF(34<=18,'前提'!$B$87,IF(34<=24,'前提'!$B$88,IF(34<=36,'前提'!$B$89,IF(34<=48,'前提'!$B$90,'前提'!$B$91)))))))))+(IF(34<=6,'前提'!$B$94,IF(34<=12,'前提'!$B$95,IF(34<=18,'前提'!$B$96,IF(34<=24,'前提'!$B$97,IF(34<=36,'前提'!$B$98,IF(34<=48,'前提'!$B$99,'前提'!$B$100)))))))+IF(34>=7,CEILING(AI14/'前提'!$B$29,1),0)+IF(34>=7,CEILING(AI14/'前提'!$B$30,1),0)+IF(34>=7,CEILING(AI10/'前提'!$B$31,1),0))*'前提'!$B$44 | AJ39: =(1+IF(35<=6,'前提'!$B$36/160,IF(35<=12,'前提'!$B$37/160,(IF(35<=6,'前提'!$B$85,IF(35<=12,'前提'!$B$86,IF(35<=18,'前提'!$B$87,IF(35<=24,'前提'!$B$88,IF(35<=36,'前提'!$B$89,IF(35<=48,'前提'!$B$90,'前提'!$B$91)))))))))+(IF(35<=6,'前提'!$B$94,IF(35<=12,'前提'!$B$95,IF(35<=18,'前提'!$B$96,IF(35<=24,'前提'!$B$97,IF(35<=36,'前提'!$B$98,IF(35<=48,'前提'!$B$99,'前提'!$B$100)))))))+IF(35>=7,CEILING(AJ14/'前提'!$B$29,1),0)+IF(35>=7,CEILING(AJ14/'前提'!$B$30,1),0)+IF(35>=7,CEILING(AJ10/'前提'!$B$31,1),0))*'前提'!$B$44 | AK39: =(1+IF(36<=6,'前提'!$B$36/160,IF(36<=12,'前提'!$B$37/160,(IF(36<=6,'前提'!$B$85,IF(36<=12,'前提'!$B$86,IF(36<=18,'前提'!$B$87,IF(36<=24,'前提'!$B$88,IF(36<=36,'前提'!$B$89,IF(36<=48,'前提'!$B$90,'前提'!$B$91)))))))))+(IF(36<=6,'前提'!$B$94,IF(36<=12,'前提'!$B$95,IF(36<=18,'前提'!$B$96,IF(36<=24,'前提'!$B$97,IF(36<=36,'前提'!$B$98,IF(36<=48,'前提'!$B$99,'前提'!$B$100)))))))+IF(36>=7,CEILING(AK14/'前提'!$B$29,1),0)+IF(36>=7,CEILING(AK14/'前提'!$B$30,1),0)+IF(36>=7,CEILING(AK10/'前提'!$B$31,1),0))*'前提'!$B$44 | AL39: =(1+IF(37<=6,'前提'!$B$36/160,IF(37<=12,'前提'!$B$37/160,(IF(37<=6,'前提'!$B$85,IF(37<=12,'前提'!$B$86,IF(37<=18,'前提'!$B$87,IF(37<=24,'前提'!$B$88,IF(37<=36,'前提'!$B$89,IF(37<=48,'前提'!$B$90,'前提'!$B$91)))))))))+(IF(37<=6,'前提'!$B$94,IF(37<=12,'前提'!$B$95,IF(37<=18,'前提'!$B$96,IF(37<=24,'前提'!$B$97,IF(37<=36,'前提'!$B$98,IF(37<=48,'前提'!$B$99,'前提'!$B$100)))))))+IF(37>=7,CEILING(AL14/'前提'!$B$29,1),0)+IF(37>=7,CEILING(AL14/'前提'!$B$30,1),0)+IF(37>=7,CEILING(AL10/'前提'!$B$31,1),0))*'前提'!$B$44 | AM39: =(1+IF(38<=6,'前提'!$B$36/160,IF(38<=12,'前提'!$B$37/160,(IF(38<=6,'前提'!$B$85,IF(38<=12,'前提'!$B$86,IF(38<=18,'前提'!$B$87,IF(38<=24,'前提'!$B$88,IF(38<=36,'前提'!$B$89,IF(38<=48,'前提'!$B$90,'前提'!$B$91)))))))))+(IF(38<=6,'前提'!$B$94,IF(38<=12,'前提'!$B$95,IF(38<=18,'前提'!$B$96,IF(38<=24,'前提'!$B$97,IF(38<=36,'前提'!$B$98,IF(38<=48,'前提'!$B$99,'前提'!$B$100)))))))+IF(38>=7,CEILING(AM14/'前提'!$B$29,1),0)+IF(38>=7,CEILING(AM14/'前提'!$B$30,1),0)+IF(38>=7,CEILING(AM10/'前提'!$B$31,1),0))*'前提'!$B$44 | AN39: =(1+IF(39<=6,'前提'!$B$36/160,IF(39<=12,'前提'!$B$37/160,(IF(39<=6,'前提'!$B$85,IF(39<=12,'前提'!$B$86,IF(39<=18,'前提'!$B$87,IF(39<=24,'前提'!$B$88,IF(39<=36,'前提'!$B$89,IF(39<=48,'前提'!$B$90,'前提'!$B$91)))))))))+(IF(39<=6,'前提'!$B$94,IF(39<=12,'前提'!$B$95,IF(39<=18,'前提'!$B$96,IF(39<=24,'前提'!$B$97,IF(39<=36,'前提'!$B$98,IF(39<=48,'前提'!$B$99,'前提'!$B$100)))))))+IF(39>=7,CEILING(AN14/'前提'!$B$29,1),0)+IF(39>=7,CEILING(AN14/'前提'!$B$30,1),0)+IF(39>=7,CEILING(AN10/'前提'!$B$31,1),0))*'前提'!$B$44 | AO39: =(1+IF(40<=6,'前提'!$B$36/160,IF(40<=12,'前提'!$B$37/160,(IF(40<=6,'前提'!$B$85,IF(40<=12,'前提'!$B$86,IF(40<=18,'前提'!$B$87,IF(40<=24,'前提'!$B$88,IF(40<=36,'前提'!$B$89,IF(40<=48,'前提'!$B$90,'前提'!$B$91)))))))))+(IF(40<=6,'前提'!$B$94,IF(40<=12,'前提'!$B$95,IF(40<=18,'前提'!$B$96,IF(40<=24,'前提'!$B$97,IF(40<=36,'前提'!$B$98,IF(40<=48,'前提'!$B$99,'前提'!$B$100)))))))+IF(40>=7,CEILING(AO14/'前提'!$B$29,1),0)+IF(40>=7,CEILING(AO14/'前提'!$B$30,1),0)+IF(40>=7,CEILING(AO10/'前提'!$B$31,1),0))*'前提'!$B$44 | AP39: =(1+IF(41<=6,'前提'!$B$36/160,IF(41<=12,'前提'!$B$37/160,(IF(41<=6,'前提'!$B$85,IF(41<=12,'前提'!$B$86,IF(41<=18,'前提'!$B$87,IF(41<=24,'前提'!$B$88,IF(41<=36,'前提'!$B$89,IF(41<=48,'前提'!$B$90,'前提'!$B$91)))))))))+(IF(41<=6,'前提'!$B$94,IF(41<=12,'前提'!$B$95,IF(41<=18,'前提'!$B$96,IF(41<=24,'前提'!$B$97,IF(41<=36,'前提'!$B$98,IF(41<=48,'前提'!$B$99,'前提'!$B$100)))))))+IF(41>=7,CEILING(AP14/'前提'!$B$29,1),0)+IF(41>=7,CEILING(AP14/'前提'!$B$30,1),0)+IF(41>=7,CEILING(AP10/'前提'!$B$31,1),0))*'前提'!$B$44 | AQ39: =(1+IF(42<=6,'前提'!$B$36/160,IF(42<=12,'前提'!$B$37/160,(IF(42<=6,'前提'!$B$85,IF(42<=12,'前提'!$B$86,IF(42<=18,'前提'!$B$87,IF(42<=24,'前提'!$B$88,IF(42<=36,'前提'!$B$89,IF(42<=48,'前提'!$B$90,'前提'!$B$91)))))))))+(IF(42<=6,'前提'!$B$94,IF(42<=12,'前提'!$B$95,IF(42<=18,'前提'!$B$96,IF(42<=24,'前提'!$B$97,IF(42<=36,'前提'!$B$98,IF(42<=48,'前提'!$B$99,'前提'!$B$100)))))))+IF(42>=7,CEILING(AQ14/'前提'!$B$29,1),0)+IF(42>=7,CEILING(AQ14/'前提'!$B$30,1),0)+IF(42>=7,CEILING(AQ10/'前提'!$B$31,1),0))*'前提'!$B$44 | AR39: =(1+IF(43<=6,'前提'!$B$36/160,IF(43<=12,'前提'!$B$37/160,(IF(43<=6,'前提'!$B$85,IF(43<=12,'前提'!$B$86,IF(43<=18,'前提'!$B$87,IF(43<=24,'前提'!$B$88,IF(43<=36,'前提'!$B$89,IF(43<=48,'前提'!$B$90,'前提'!$B$91)))))))))+(IF(43<=6,'前提'!$B$94,IF(43<=12,'前提'!$B$95,IF(43<=18,'前提'!$B$96,IF(43<=24,'前提'!$B$97,IF(43<=36,'前提'!$B$98,IF(43<=48,'前提'!$B$99,'前提'!$B$100)))))))+IF(43>=7,CEILING(AR14/'前提'!$B$29,1),0)+IF(43>=7,CEILING(AR14/'前提'!$B$30,1),0)+IF(43>=7,CEILING(AR10/'前提'!$B$31,1),0))*'前提'!$B$44 | AS39: =(1+IF(44<=6,'前提'!$B$36/160,IF(44<=12,'前提'!$B$37/160,(IF(44<=6,'前提'!$B$85,IF(44<=12,'前提'!$B$86,IF(44<=18,'前提'!$B$87,IF(44<=24,'前提'!$B$88,IF(44<=36,'前提'!$B$89,IF(44<=48,'前提'!$B$90,'前提'!$B$91)))))))))+(IF(44<=6,'前提'!$B$94,IF(44<=12,'前提'!$B$95,IF(44<=18,'前提'!$B$96,IF(44<=24,'前提'!$B$97,IF(44<=36,'前提'!$B$98,IF(44<=48,'前提'!$B$99,'前提'!$B$100)))))))+IF(44>=7,CEILING(AS14/'前提'!$B$29,1),0)+IF(44>=7,CEILING(AS14/'前提'!$B$30,1),0)+IF(44>=7,CEILING(AS10/'前提'!$B$31,1),0))*'前提'!$B$44 | AT39: =(1+IF(45<=6,'前提'!$B$36/160,IF(45<=12,'前提'!$B$37/160,(IF(45<=6,'前提'!$B$85,IF(45<=12,'前提'!$B$86,IF(45<=18,'前提'!$B$87,IF(45<=24,'前提'!$B$88,IF(45<=36,'前提'!$B$89,IF(45<=48,'前提'!$B$90,'前提'!$B$91)))))))))+(IF(45<=6,'前提'!$B$94,IF(45<=12,'前提'!$B$95,IF(45<=18,'前提'!$B$96,IF(45<=24,'前提'!$B$97,IF(45<=36,'前提'!$B$98,IF(45<=48,'前提'!$B$99,'前提'!$B$100)))))))+IF(45>=7,CEILING(AT14/'前提'!$B$29,1),0)+IF(45>=7,CEILING(AT14/'前提'!$B$30,1),0)+IF(45>=7,CEILING(AT10/'前提'!$B$31,1),0))*'前提'!$B$44 | AU39: =(1+IF(46<=6,'前提'!$B$36/160,IF(46<=12,'前提'!$B$37/160,(IF(46<=6,'前提'!$B$85,IF(46<=12,'前提'!$B$86,IF(46<=18,'前提'!$B$87,IF(46<=24,'前提'!$B$88,IF(46<=36,'前提'!$B$89,IF(46<=48,'前提'!$B$90,'前提'!$B$91)))))))))+(IF(46<=6,'前提'!$B$94,IF(46<=12,'前提'!$B$95,IF(46<=18,'前提'!$B$96,IF(46<=24,'前提'!$B$97,IF(46<=36,'前提'!$B$98,IF(46<=48,'前提'!$B$99,'前提'!$B$100)))))))+IF(46>=7,CEILING(AU14/'前提'!$B$29,1),0)+IF(46>=7,CEILING(AU14/'前提'!$B$30,1),0)+IF(46>=7,CEILING(AU10/'前提'!$B$31,1),0))*'前提'!$B$44 | AV39: =(1+IF(47<=6,'前提'!$B$36/160,IF(47<=12,'前提'!$B$37/160,(IF(47<=6,'前提'!$B$85,IF(47<=12,'前提'!$B$86,IF(47<=18,'前提'!$B$87,IF(47<=24,'前提'!$B$88,IF(47<=36,'前提'!$B$89,IF(47<=48,'前提'!$B$90,'前提'!$B$91)))))))))+(IF(47<=6,'前提'!$B$94,IF(47<=12,'前提'!$B$95,IF(47<=18,'前提'!$B$96,IF(47<=24,'前提'!$B$97,IF(47<=36,'前提'!$B$98,IF(47<=48,'前提'!$B$99,'前提'!$B$100)))))))+IF(47>=7,CEILING(AV14/'前提'!$B$29,1),0)+IF(47>=7,CEILING(AV14/'前提'!$B$30,1),0)+IF(47>=7,CEILING(AV10/'前提'!$B$31,1),0))*'前提'!$B$44 | AW39: =(1+IF(48<=6,'前提'!$B$36/160,IF(48<=12,'前提'!$B$37/160,(IF(48<=6,'前提'!$B$85,IF(48<=12,'前提'!$B$86,IF(48<=18,'前提'!$B$87,IF(48<=24,'前提'!$B$88,IF(48<=36,'前提'!$B$89,IF(48<=48,'前提'!$B$90,'前提'!$B$91)))))))))+(IF(48<=6,'前提'!$B$94,IF(48<=12,'前提'!$B$95,IF(48<=18,'前提'!$B$96,IF(48<=24,'前提'!$B$97,IF(48<=36,'前提'!$B$98,IF(48<=48,'前提'!$B$99,'前提'!$B$100)))))))+IF(48>=7,CEILING(AW14/'前提'!$B$29,1),0)+IF(48>=7,CEILING(AW14/'前提'!$B$30,1),0)+IF(48>=7,CEILING(AW10/'前提'!$B$31,1),0))*'前提'!$B$44 | AX39: =(1+IF(49<=6,'前提'!$B$36/160,IF(49<=12,'前提'!$B$37/160,(IF(49<=6,'前提'!$B$85,IF(49<=12,'前提'!$B$86,IF(49<=18,'前提'!$B$87,IF(49<=24,'前提'!$B$88,IF(49<=36,'前提'!$B$89,IF(49<=48,'前提'!$B$90,'前提'!$B$91)))))))))+(IF(49<=6,'前提'!$B$94,IF(49<=12,'前提'!$B$95,IF(49<=18,'前提'!$B$96,IF(49<=24,'前提'!$B$97,IF(49<=36,'前提'!$B$98,IF(49<=48,'前提'!$B$99,'前提'!$B$100)))))))+IF(49>=7,CEILING(AX14/'前提'!$B$29,1),0)+IF(49>=7,CEILING(AX14/'前提'!$B$30,1),0)+IF(49>=7,CEILING(AX10/'前提'!$B$31,1),0))*'前提'!$B$44 | AY39: =(1+IF(50<=6,'前提'!$B$36/160,IF(50<=12,'前提'!$B$37/160,(IF(50<=6,'前提'!$B$85,IF(50<=12,'前提'!$B$86,IF(50<=18,'前提'!$B$87,IF(50<=24,'前提'!$B$88,IF(50<=36,'前提'!$B$89,IF(50<=48,'前提'!$B$90,'前提'!$B$91)))))))))+(IF(50<=6,'前提'!$B$94,IF(50<=12,'前提'!$B$95,IF(50<=18,'前提'!$B$96,IF(50<=24,'前提'!$B$97,IF(50<=36,'前提'!$B$98,IF(50<=48,'前提'!$B$99,'前提'!$B$100)))))))+IF(50>=7,CEILING(AY14/'前提'!$B$29,1),0)+IF(50>=7,CEILING(AY14/'前提'!$B$30,1),0)+IF(50>=7,CEILING(AY10/'前提'!$B$31,1),0))*'前提'!$B$44 | AZ39: =(1+IF(51<=6,'前提'!$B$36/160,IF(51<=12,'前提'!$B$37/160,(IF(51<=6,'前提'!$B$85,IF(51<=12,'前提'!$B$86,IF(51<=18,'前提'!$B$87,IF(51<=24,'前提'!$B$88,IF(51<=36,'前提'!$B$89,IF(51<=48,'前提'!$B$90,'前提'!$B$91)))))))))+(IF(51<=6,'前提'!$B$94,IF(51<=12,'前提'!$B$95,IF(51<=18,'前提'!$B$96,IF(51<=24,'前提'!$B$97,IF(51<=36,'前提'!$B$98,IF(51<=48,'前提'!$B$99,'前提'!$B$100)))))))+IF(51>=7,CEILING(AZ14/'前提'!$B$29,1),0)+IF(51>=7,CEILING(AZ14/'前提'!$B$30,1),0)+IF(51>=7,CEILING(AZ10/'前提'!$B$31,1),0))*'前提'!$B$44 | BA39: =(1+IF(52<=6,'前提'!$B$36/160,IF(52<=12,'前提'!$B$37/160,(IF(52<=6,'前提'!$B$85,IF(52<=12,'前提'!$B$86,IF(52<=18,'前提'!$B$87,IF(52<=24,'前提'!$B$88,IF(52<=36,'前提'!$B$89,IF(52<=48,'前提'!$B$90,'前提'!$B$91)))))))))+(IF(52<=6,'前提'!$B$94,IF(52<=12,'前提'!$B$95,IF(52<=18,'前提'!$B$96,IF(52<=24,'前提'!$B$97,IF(52<=36,'前提'!$B$98,IF(52<=48,'前提'!$B$99,'前提'!$B$100)))))))+IF(52>=7,CEILING(BA14/'前提'!$B$29,1),0)+IF(52>=7,CEILING(BA14/'前提'!$B$30,1),0)+IF(52>=7,CEILING(BA10/'前提'!$B$31,1),0))*'前提'!$B$44 | BB39: =(1+IF(53<=6,'前提'!$B$36/160,IF(53<=12,'前提'!$B$37/160,(IF(53<=6,'前提'!$B$85,IF(53<=12,'前提'!$B$86,IF(53<=18,'前提'!$B$87,IF(53<=24,'前提'!$B$88,IF(53<=36,'前提'!$B$89,IF(53<=48,'前提'!$B$90,'前提'!$B$91)))))))))+(IF(53<=6,'前提'!$B$94,IF(53<=12,'前提'!$B$95,IF(53<=18,'前提'!$B$96,IF(53<=24,'前提'!$B$97,IF(53<=36,'前提'!$B$98,IF(53<=48,'前提'!$B$99,'前提'!$B$100)))))))+IF(53>=7,CEILING(BB14/'前提'!$B$29,1),0)+IF(53>=7,CEILING(BB14/'前提'!$B$30,1),0)+IF(53>=7,CEILING(BB10/'前提'!$B$31,1),0))*'前提'!$B$44 | BC39: =(1+IF(54<=6,'前提'!$B$36/160,IF(54<=12,'前提'!$B$37/160,(IF(54<=6,'前提'!$B$85,IF(54<=12,'前提'!$B$86,IF(54<=18,'前提'!$B$87,IF(54<=24,'前提'!$B$88,IF(54<=36,'前提'!$B$89,IF(54<=48,'前提'!$B$90,'前提'!$B$91)))))))))+(IF(54<=6,'前提'!$B$94,IF(54<=12,'前提'!$B$95,IF(54<=18,'前提'!$B$96,IF(54<=24,'前提'!$B$97,IF(54<=36,'前提'!$B$98,IF(54<=48,'前提'!$B$99,'前提'!$B$100)))))))+IF(54>=7,CEILING(BC14/'前提'!$B$29,1),0)+IF(54>=7,CEILING(BC14/'前提'!$B$30,1),0)+IF(54>=7,CEILING(BC10/'前提'!$B$31,1),0))*'前提'!$B$44 | BD39: =(1+IF(55<=6,'前提'!$B$36/160,IF(55<=12,'前提'!$B$37/160,(IF(55<=6,'前提'!$B$85,IF(55<=12,'前提'!$B$86,IF(55<=18,'前提'!$B$87,IF(55<=24,'前提'!$B$88,IF(55<=36,'前提'!$B$89,IF(55<=48,'前提'!$B$90,'前提'!$B$91)))))))))+(IF(55<=6,'前提'!$B$94,IF(55<=12,'前提'!$B$95,IF(55<=18,'前提'!$B$96,IF(55<=24,'前提'!$B$97,IF(55<=36,'前提'!$B$98,IF(55<=48,'前提'!$B$99,'前提'!$B$100)))))))+IF(55>=7,CEILING(BD14/'前提'!$B$29,1),0)+IF(55>=7,CEILING(BD14/'前提'!$B$30,1),0)+IF(55>=7,CEILING(BD10/'前提'!$B$31,1),0))*'前提'!$B$44 | BE39: =(1+IF(56<=6,'前提'!$B$36/160,IF(56<=12,'前提'!$B$37/160,(IF(56<=6,'前提'!$B$85,IF(56<=12,'前提'!$B$86,IF(56<=18,'前提'!$B$87,IF(56<=24,'前提'!$B$88,IF(56<=36,'前提'!$B$89,IF(56<=48,'前提'!$B$90,'前提'!$B$91)))))))))+(IF(56<=6,'前提'!$B$94,IF(56<=12,'前提'!$B$95,IF(56<=18,'前提'!$B$96,IF(56<=24,'前提'!$B$97,IF(56<=36,'前提'!$B$98,IF(56<=48,'前提'!$B$99,'前提'!$B$100)))))))+IF(56>=7,CEILING(BE14/'前提'!$B$29,1),0)+IF(56>=7,CEILING(BE14/'前提'!$B$30,1),0)+IF(56>=7,CEILING(BE10/'前提'!$B$31,1),0))*'前提'!$B$44 | BF39: =(1+IF(57<=6,'前提'!$B$36/160,IF(57<=12,'前提'!$B$37/160,(IF(57<=6,'前提'!$B$85,IF(57<=12,'前提'!$B$86,IF(57<=18,'前提'!$B$87,IF(57<=24,'前提'!$B$88,IF(57<=36,'前提'!$B$89,IF(57<=48,'前提'!$B$90,'前提'!$B$91)))))))))+(IF(57<=6,'前提'!$B$94,IF(57<=12,'前提'!$B$95,IF(57<=18,'前提'!$B$96,IF(57<=24,'前提'!$B$97,IF(57<=36,'前提'!$B$98,IF(57<=48,'前提'!$B$99,'前提'!$B$100)))))))+IF(57>=7,CEILING(BF14/'前提'!$B$29,1),0)+IF(57>=7,CEILING(BF14/'前提'!$B$30,1),0)+IF(57>=7,CEILING(BF10/'前提'!$B$31,1),0))*'前提'!$B$44 | BG39: =(1+IF(58<=6,'前提'!$B$36/160,IF(58<=12,'前提'!$B$37/160,(IF(58<=6,'前提'!$B$85,IF(58<=12,'前提'!$B$86,IF(58<=18,'前提'!$B$87,IF(58<=24,'前提'!$B$88,IF(58<=36,'前提'!$B$89,IF(58<=48,'前提'!$B$90,'前提'!$B$91)))))))))+(IF(58<=6,'前提'!$B$94,IF(58<=12,'前提'!$B$95,IF(58<=18,'前提'!$B$96,IF(58<=24,'前提'!$B$97,IF(58<=36,'前提'!$B$98,IF(58<=48,'前提'!$B$99,'前提'!$B$100)))))))+IF(58>=7,CEILING(BG14/'前提'!$B$29,1),0)+IF(58>=7,CEILING(BG14/'前提'!$B$30,1),0)+IF(58>=7,CEILING(BG10/'前提'!$B$31,1),0))*'前提'!$B$44 | BH39: =(1+IF(59<=6,'前提'!$B$36/160,IF(59<=12,'前提'!$B$37/160,(IF(59<=6,'前提'!$B$85,IF(59<=12,'前提'!$B$86,IF(59<=18,'前提'!$B$87,IF(59<=24,'前提'!$B$88,IF(59<=36,'前提'!$B$89,IF(59<=48,'前提'!$B$90,'前提'!$B$91)))))))))+(IF(59<=6,'前提'!$B$94,IF(59<=12,'前提'!$B$95,IF(59<=18,'前提'!$B$96,IF(59<=24,'前提'!$B$97,IF(59<=36,'前提'!$B$98,IF(59<=48,'前提'!$B$99,'前提'!$B$100)))))))+IF(59>=7,CEILING(BH14/'前提'!$B$29,1),0)+IF(59>=7,CEILING(BH14/'前提'!$B$30,1),0)+IF(59>=7,CEILING(BH10/'前提'!$B$31,1),0))*'前提'!$B$44 | BI39: =(1+IF(60<=6,'前提'!$B$36/160,IF(60<=12,'前提'!$B$37/160,(IF(60<=6,'前提'!$B$85,IF(60<=12,'前提'!$B$86,IF(60<=18,'前提'!$B$87,IF(60<=24,'前提'!$B$88,IF(60<=36,'前提'!$B$89,IF(60<=48,'前提'!$B$90,'前提'!$B$91)))))))))+(IF(60<=6,'前提'!$B$94,IF(60<=12,'前提'!$B$95,IF(60<=18,'前提'!$B$96,IF(60<=24,'前提'!$B$97,IF(60<=36,'前提'!$B$98,IF(60<=48,'前提'!$B$99,'前提'!$B$100)))))))+IF(60>=7,CEILING(BI14/'前提'!$B$29,1),0)+IF(60>=7,CEILING(BI14/'前提'!$B$30,1),0)+IF(60>=7,CEILING(BI10/'前提'!$B$31,1),0))*'前提'!$B$44
A40: 人件費合計 | B40: =SUM(B32:B39) | C40: =SUM(C32:C39) | D40: =SUM(D32:D39) | E40: =SUM(E32:E39) | F40: =SUM(F32:F39) | G40: =SUM(G32:G39) | H40: =SUM(H32:H39) | I40: =SUM(I32:I39) | ... BI40: =SUM(BI32:BI39)
A42: 【固定費・販管費】
A43: オフィス家賃 | B43: =IF(1<=18,'前提'!$B$47,'前提'!$B$48) | C43: =IF(2<=18,'前提'!$B$47,'前提'!$B$48) | D43: =IF(3<=18,'前提'!$B$47,'前提'!$B$48) | E43: =IF(4<=18,'前提'!$B$47,'前提'!$B$48) | F43: =IF(5<=18,'前提'!$B$47,'前提'!$B$48) | G43: =IF(6<=18,'前提'!$B$47,'前提'!$B$48) | H43: =IF(7<=18,'前提'!$B$47,'前提'!$B$48) | I43: =IF(8<=18,'前提'!$B$47,'前提'!$B$48) | J43: =IF(9<=18,'前提'!$B$47,'前提'!$B$48) | K43: =IF(10<=18,'前提'!$B$47,'前提'!$B$48) | L43: =IF(11<=18,'前提'!$B$47,'前提'!$B$48) | M43: =IF(12<=18,'前提'!$B$47,'前提'!$B$48) | N43: =IF(13<=18,'前提'!$B$47,'前提'!$B$48) | O43: =IF(14<=18,'前提'!$B$47,'前提'!$B$48) | P43: =IF(15<=18,'前提'!$B$47,'前提'!$B$48) | Q43: =IF(16<=18,'前提'!$B$47,'前提'!$B$48) | R43: =IF(17<=18,'前提'!$B$47,'前提'!$B$48) | S43: =IF(18<=18,'前提'!$B$47,'前提'!$B$48) | T43: =IF(19<=18,'前提'!$B$47,'前提'!$B$48) | U43: =IF(20<=18,'前提'!$B$47,'前提'!$B$48) | V43: =IF(21<=18,'前提'!$B$47,'前提'!$B$48) | W43: =IF(22<=18,'前提'!$B$47,'前提'!$B$48) | X43: =IF(23<=18,'前提'!$B$47,'前提'!$B$48) | Y43: =IF(24<=18,'前提'!$B$47,'前提'!$B$48) | Z43: =IF(25<=18,'前提'!$B$47,'前提'!$B$48) | AA43: =IF(26<=18,'前提'!$B$47,'前提'!$B$48) | AB43: =IF(27<=18,'前提'!$B$47,'前提'!$B$48) | AC43: =IF(28<=18,'前提'!$B$47,'前提'!$B$48) | AD43: =IF(29<=18,'前提'!$B$47,'前提'!$B$48) | AE43: =IF(30<=18,'前提'!$B$47,'前提'!$B$48) | AF43: =IF(31<=18,'前提'!$B$47,'前提'!$B$48) | AG43: =IF(32<=18,'前提'!$B$47,'前提'!$B$48) | AH43: =IF(33<=18,'前提'!$B$47,'前提'!$B$48) | AI43: =IF(34<=18,'前提'!$B$47,'前提'!$B$48) | AJ43: =IF(35<=18,'前提'!$B$47,'前提'!$B$48) | AK43: =IF(36<=18,'前提'!$B$47,'前提'!$B$48) | AL43: =IF(37<=18,'前提'!$B$47,'前提'!$B$48) | AM43: =IF(38<=18,'前提'!$B$47,'前提'!$B$48) | AN43: =IF(39<=18,'前提'!$B$47,'前提'!$B$48) | AO43: =IF(40<=18,'前提'!$B$47,'前提'!$B$48) | AP43: =IF(41<=18,'前提'!$B$47,'前提'!$B$48) | AQ43: =IF(42<=18,'前提'!$B$47,'前提'!$B$48) | AR43: =IF(43<=18,'前提'!$B$47,'前提'!$B$48) | AS43: =IF(44<=18,'前提'!$B$47,'前提'!$B$48) | AT43: =IF(45<=18,'前提'!$B$47,'前提'!$B$48) | AU43: =IF(46<=18,'前提'!$B$47,'前提'!$B$48) | AV43: =IF(47<=18,'前提'!$B$47,'前提'!$B$48) | AW43: =IF(48<=18,'前提'!$B$47,'前提'!$B$48) | AX43: =IF(49<=18,'前提'!$B$47,'前提'!$B$48) | AY43: =IF(50<=18,'前提'!$B$47,'前提'!$B$48) | AZ43: =IF(51<=18,'前提'!$B$47,'前提'!$B$48) | BA43: =IF(52<=18,'前提'!$B$47,'前提'!$B$48) | BB43: =IF(53<=18,'前提'!$B$47,'前提'!$B$48) | BC43: =IF(54<=18,'前提'!$B$47,'前提'!$B$48) | BD43: =IF(55<=18,'前提'!$B$47,'前提'!$B$48) | BE43: =IF(56<=18,'前提'!$B$47,'前提'!$B$48) | BF43: =IF(57<=18,'前提'!$B$47,'前提'!$B$48) | BG43: =IF(58<=18,'前提'!$B$47,'前提'!$B$48) | BH43: =IF(59<=18,'前提'!$B$47,'前提'!$B$48) | BI43: =IF(60<=18,'前提'!$B$47,'前提'!$B$48)
A44: SaaS費用（人員連動） | B44: =(1+IF(1<=6,'前提'!$B$36/160,IF(1<=12,'前提'!$B$37/160,(IF(1<=6,'前提'!$B$85,IF(1<=12,'前提'!$B$86,IF(1<=18,'前提'!$B$87,IF(1<=24,'前提'!$B$88,IF(1<=36,'前提'!$B$89,IF(1<=48,'前提'!$B$90,'前提'!$B$91)))))))))+(IF(1<=6,'前提'!$B$94,IF(1<=12,'前提'!$B$95,IF(1<=18,'前提'!$B$96,IF(1<=24,'前提'!$B$97,IF(1<=36,'前提'!$B$98,IF(1<=48,'前提'!$B$99,'前提'!$B$100)))))))+IF(1>=7,CEILING(B14/'前提'!$B$29,1),0)+IF(1>=7,CEILING(B14/'前提'!$B$30,1),0)+IF(1>=7,CEILING(B10/'前提'!$B$31,1),0))*'前提'!$B$49 | C44: =(1+IF(2<=6,'前提'!$B$36/160,IF(2<=12,'前提'!$B$37/160,(IF(2<=6,'前提'!$B$85,IF(2<=12,'前提'!$B$86,IF(2<=18,'前提'!$B$87,IF(2<=24,'前提'!$B$88,IF(2<=36,'前提'!$B$89,IF(2<=48,'前提'!$B$90,'前提'!$B$91)))))))))+(IF(2<=6,'前提'!$B$94,IF(2<=12,'前提'!$B$95,IF(2<=18,'前提'!$B$96,IF(2<=24,'前提'!$B$97,IF(2<=36,'前提'!$B$98,IF(2<=48,'前提'!$B$99,'前提'!$B$100)))))))+IF(2>=7,CEILING(C14/'前提'!$B$29,1),0)+IF(2>=7,CEILING(C14/'前提'!$B$30,1),0)+IF(2>=7,CEILING(C10/'前提'!$B$31,1),0))*'前提'!$B$49 | D44: =(1+IF(3<=6,'前提'!$B$36/160,IF(3<=12,'前提'!$B$37/160,(IF(3<=6,'前提'!$B$85,IF(3<=12,'前提'!$B$86,IF(3<=18,'前提'!$B$87,IF(3<=24,'前提'!$B$88,IF(3<=36,'前提'!$B$89,IF(3<=48,'前提'!$B$90,'前提'!$B$91)))))))))+(IF(3<=6,'前提'!$B$94,IF(3<=12,'前提'!$B$95,IF(3<=18,'前提'!$B$96,IF(3<=24,'前提'!$B$97,IF(3<=36,'前提'!$B$98,IF(3<=48,'前提'!$B$99,'前提'!$B$100)))))))+IF(3>=7,CEILING(D14/'前提'!$B$29,1),0)+IF(3>=7,CEILING(D14/'前提'!$B$30,1),0)+IF(3>=7,CEILING(D10/'前提'!$B$31,1),0))*'前提'!$B$49 | E44: =(1+IF(4<=6,'前提'!$B$36/160,IF(4<=12,'前提'!$B$37/160,(IF(4<=6,'前提'!$B$85,IF(4<=12,'前提'!$B$86,IF(4<=18,'前提'!$B$87,IF(4<=24,'前提'!$B$88,IF(4<=36,'前提'!$B$89,IF(4<=48,'前提'!$B$90,'前提'!$B$91)))))))))+(IF(4<=6,'前提'!$B$94,IF(4<=12,'前提'!$B$95,IF(4<=18,'前提'!$B$96,IF(4<=24,'前提'!$B$97,IF(4<=36,'前提'!$B$98,IF(4<=48,'前提'!$B$99,'前提'!$B$100)))))))+IF(4>=7,CEILING(E14/'前提'!$B$29,1),0)+IF(4>=7,CEILING(E14/'前提'!$B$30,1),0)+IF(4>=7,CEILING(E10/'前提'!$B$31,1),0))*'前提'!$B$49 | F44: =(1+IF(5<=6,'前提'!$B$36/160,IF(5<=12,'前提'!$B$37/160,(IF(5<=6,'前提'!$B$85,IF(5<=12,'前提'!$B$86,IF(5<=18,'前提'!$B$87,IF(5<=24,'前提'!$B$88,IF(5<=36,'前提'!$B$89,IF(5<=48,'前提'!$B$90,'前提'!$B$91)))))))))+(IF(5<=6,'前提'!$B$94,IF(5<=12,'前提'!$B$95,IF(5<=18,'前提'!$B$96,IF(5<=24,'前提'!$B$97,IF(5<=36,'前提'!$B$98,IF(5<=48,'前提'!$B$99,'前提'!$B$100)))))))+IF(5>=7,CEILING(F14/'前提'!$B$29,1),0)+IF(5>=7,CEILING(F14/'前提'!$B$30,1),0)+IF(5>=7,CEILING(F10/'前提'!$B$31,1),0))*'前提'!$B$49 | G44: =(1+IF(6<=6,'前提'!$B$36/160,IF(6<=12,'前提'!$B$37/160,(IF(6<=6,'前提'!$B$85,IF(6<=12,'前提'!$B$86,IF(6<=18,'前提'!$B$87,IF(6<=24,'前提'!$B$88,IF(6<=36,'前提'!$B$89,IF(6<=48,'前提'!$B$90,'前提'!$B$91)))))))))+(IF(6<=6,'前提'!$B$94,IF(6<=12,'前提'!$B$95,IF(6<=18,'前提'!$B$96,IF(6<=24,'前提'!$B$97,IF(6<=36,'前提'!$B$98,IF(6<=48,'前提'!$B$99,'前提'!$B$100)))))))+IF(6>=7,CEILING(G14/'前提'!$B$29,1),0)+IF(6>=7,CEILING(G14/'前提'!$B$30,1),0)+IF(6>=7,CEILING(G10/'前提'!$B$31,1),0))*'前提'!$B$49 | H44: =(1+IF(7<=6,'前提'!$B$36/160,IF(7<=12,'前提'!$B$37/160,(IF(7<=6,'前提'!$B$85,IF(7<=12,'前提'!$B$86,IF(7<=18,'前提'!$B$87,IF(7<=24,'前提'!$B$88,IF(7<=36,'前提'!$B$89,IF(7<=48,'前提'!$B$90,'前提'!$B$91)))))))))+(IF(7<=6,'前提'!$B$94,IF(7<=12,'前提'!$B$95,IF(7<=18,'前提'!$B$96,IF(7<=24,'前提'!$B$97,IF(7<=36,'前提'!$B$98,IF(7<=48,'前提'!$B$99,'前提'!$B$100)))))))+IF(7>=7,CEILING(H14/'前提'!$B$29,1),0)+IF(7>=7,CEILING(H14/'前提'!$B$30,1),0)+IF(7>=7,CEILING(H10/'前提'!$B$31,1),0))*'前提'!$B$49 | I44: =(1+IF(8<=6,'前提'!$B$36/160,IF(8<=12,'前提'!$B$37/160,(IF(8<=6,'前提'!$B$85,IF(8<=12,'前提'!$B$86,IF(8<=18,'前提'!$B$87,IF(8<=24,'前提'!$B$88,IF(8<=36,'前提'!$B$89,IF(8<=48,'前提'!$B$90,'前提'!$B$91)))))))))+(IF(8<=6,'前提'!$B$94,IF(8<=12,'前提'!$B$95,IF(8<=18,'前提'!$B$96,IF(8<=24,'前提'!$B$97,IF(8<=36,'前提'!$B$98,IF(8<=48,'前提'!$B$99,'前提'!$B$100)))))))+IF(8>=7,CEILING(I14/'前提'!$B$29,1),0)+IF(8>=7,CEILING(I14/'前提'!$B$30,1),0)+IF(8>=7,CEILING(I10/'前提'!$B$31,1),0))*'前提'!$B$49 | J44: =(1+IF(9<=6,'前提'!$B$36/160,IF(9<=12,'前提'!$B$37/160,(IF(9<=6,'前提'!$B$85,IF(9<=12,'前提'!$B$86,IF(9<=18,'前提'!$B$87,IF(9<=24,'前提'!$B$88,IF(9<=36,'前提'!$B$89,IF(9<=48,'前提'!$B$90,'前提'!$B$91)))))))))+(IF(9<=6,'前提'!$B$94,IF(9<=12,'前提'!$B$95,IF(9<=18,'前提'!$B$96,IF(9<=24,'前提'!$B$97,IF(9<=36,'前提'!$B$98,IF(9<=48,'前提'!$B$99,'前提'!$B$100)))))))+IF(9>=7,CEILING(J14/'前提'!$B$29,1),0)+IF(9>=7,CEILING(J14/'前提'!$B$30,1),0)+IF(9>=7,CEILING(J10/'前提'!$B$31,1),0))*'前提'!$B$49 | K44: =(1+IF(10<=6,'前提'!$B$36/160,IF(10<=12,'前提'!$B$37/160,(IF(10<=6,'前提'!$B$85,IF(10<=12,'前提'!$B$86,IF(10<=18,'前提'!$B$87,IF(10<=24,'前提'!$B$88,IF(10<=36,'前提'!$B$89,IF(10<=48,'前提'!$B$90,'前提'!$B$91)))))))))+(IF(10<=6,'前提'!$B$94,IF(10<=12,'前提'!$B$95,IF(10<=18,'前提'!$B$96,IF(10<=24,'前提'!$B$97,IF(10<=36,'前提'!$B$98,IF(10<=48,'前提'!$B$99,'前提'!$B$100)))))))+IF(10>=7,CEILING(K14/'前提'!$B$29,1),0)+IF(10>=7,CEILING(K14/'前提'!$B$30,1),0)+IF(10>=7,CEILING(K10/'前提'!$B$31,1),0))*'前提'!$B$49 | L44: =(1+IF(11<=6,'前提'!$B$36/160,IF(11<=12,'前提'!$B$37/160,(IF(11<=6,'前提'!$B$85,IF(11<=12,'前提'!$B$86,IF(11<=18,'前提'!$B$87,IF(11<=24,'前提'!$B$88,IF(11<=36,'前提'!$B$89,IF(11<=48,'前提'!$B$90,'前提'!$B$91)))))))))+(IF(11<=6,'前提'!$B$94,IF(11<=12,'前提'!$B$95,IF(11<=18,'前提'!$B$96,IF(11<=24,'前提'!$B$97,IF(11<=36,'前提'!$B$98,IF(11<=48,'前提'!$B$99,'前提'!$B$100)))))))+IF(11>=7,CEILING(L14/'前提'!$B$29,1),0)+IF(11>=7,CEILING(L14/'前提'!$B$30,1),0)+IF(11>=7,CEILING(L10/'前提'!$B$31,1),0))*'前提'!$B$49 | M44: =(1+IF(12<=6,'前提'!$B$36/160,IF(12<=12,'前提'!$B$37/160,(IF(12<=6,'前提'!$B$85,IF(12<=12,'前提'!$B$86,IF(12<=18,'前提'!$B$87,IF(12<=24,'前提'!$B$88,IF(12<=36,'前提'!$B$89,IF(12<=48,'前提'!$B$90,'前提'!$B$91)))))))))+(IF(12<=6,'前提'!$B$94,IF(12<=12,'前提'!$B$95,IF(12<=18,'前提'!$B$96,IF(12<=24,'前提'!$B$97,IF(12<=36,'前提'!$B$98,IF(12<=48,'前提'!$B$99,'前提'!$B$100)))))))+IF(12>=7,CEILING(M14/'前提'!$B$29,1),0)+IF(12>=7,CEILING(M14/'前提'!$B$30,1),0)+IF(12>=7,CEILING(M10/'前提'!$B$31,1),0))*'前提'!$B$49 | N44: =(1+IF(13<=6,'前提'!$B$36/160,IF(13<=12,'前提'!$B$37/160,(IF(13<=6,'前提'!$B$85,IF(13<=12,'前提'!$B$86,IF(13<=18,'前提'!$B$87,IF(13<=24,'前提'!$B$88,IF(13<=36,'前提'!$B$89,IF(13<=48,'前提'!$B$90,'前提'!$B$91)))))))))+(IF(13<=6,'前提'!$B$94,IF(13<=12,'前提'!$B$95,IF(13<=18,'前提'!$B$96,IF(13<=24,'前提'!$B$97,IF(13<=36,'前提'!$B$98,IF(13<=48,'前提'!$B$99,'前提'!$B$100)))))))+IF(13>=7,CEILING(N14/'前提'!$B$29,1),0)+IF(13>=7,CEILING(N14/'前提'!$B$30,1),0)+IF(13>=7,CEILING(N10/'前提'!$B$31,1),0))*'前提'!$B$49 | O44: =(1+IF(14<=6,'前提'!$B$36/160,IF(14<=12,'前提'!$B$37/160,(IF(14<=6,'前提'!$B$85,IF(14<=12,'前提'!$B$86,IF(14<=18,'前提'!$B$87,IF(14<=24,'前提'!$B$88,IF(14<=36,'前提'!$B$89,IF(14<=48,'前提'!$B$90,'前提'!$B$91)))))))))+(IF(14<=6,'前提'!$B$94,IF(14<=12,'前提'!$B$95,IF(14<=18,'前提'!$B$96,IF(14<=24,'前提'!$B$97,IF(14<=36,'前提'!$B$98,IF(14<=48,'前提'!$B$99,'前提'!$B$100)))))))+IF(14>=7,CEILING(O14/'前提'!$B$29,1),0)+IF(14>=7,CEILING(O14/'前提'!$B$30,1),0)+IF(14>=7,CEILING(O10/'前提'!$B$31,1),0))*'前提'!$B$49 | P44: =(1+IF(15<=6,'前提'!$B$36/160,IF(15<=12,'前提'!$B$37/160,(IF(15<=6,'前提'!$B$85,IF(15<=12,'前提'!$B$86,IF(15<=18,'前提'!$B$87,IF(15<=24,'前提'!$B$88,IF(15<=36,'前提'!$B$89,IF(15<=48,'前提'!$B$90,'前提'!$B$91)))))))))+(IF(15<=6,'前提'!$B$94,IF(15<=12,'前提'!$B$95,IF(15<=18,'前提'!$B$96,IF(15<=24,'前提'!$B$97,IF(15<=36,'前提'!$B$98,IF(15<=48,'前提'!$B$99,'前提'!$B$100)))))))+IF(15>=7,CEILING(P14/'前提'!$B$29,1),0)+IF(15>=7,CEILING(P14/'前提'!$B$30,1),0)+IF(15>=7,CEILING(P10/'前提'!$B$31,1),0))*'前提'!$B$49 | Q44: =(1+IF(16<=6,'前提'!$B$36/160,IF(16<=12,'前提'!$B$37/160,(IF(16<=6,'前提'!$B$85,IF(16<=12,'前提'!$B$86,IF(16<=18,'前提'!$B$87,IF(16<=24,'前提'!$B$88,IF(16<=36,'前提'!$B$89,IF(16<=48,'前提'!$B$90,'前提'!$B$91)))))))))+(IF(16<=6,'前提'!$B$94,IF(16<=12,'前提'!$B$95,IF(16<=18,'前提'!$B$96,IF(16<=24,'前提'!$B$97,IF(16<=36,'前提'!$B$98,IF(16<=48,'前提'!$B$99,'前提'!$B$100)))))))+IF(16>=7,CEILING(Q14/'前提'!$B$29,1),0)+IF(16>=7,CEILING(Q14/'前提'!$B$30,1),0)+IF(16>=7,CEILING(Q10/'前提'!$B$31,1),0))*'前提'!$B$49 | R44: =(1+IF(17<=6,'前提'!$B$36/160,IF(17<=12,'前提'!$B$37/160,(IF(17<=6,'前提'!$B$85,IF(17<=12,'前提'!$B$86,IF(17<=18,'前提'!$B$87,IF(17<=24,'前提'!$B$88,IF(17<=36,'前提'!$B$89,IF(17<=48,'前提'!$B$90,'前提'!$B$91)))))))))+(IF(17<=6,'前提'!$B$94,IF(17<=12,'前提'!$B$95,IF(17<=18,'前提'!$B$96,IF(17<=24,'前提'!$B$97,IF(17<=36,'前提'!$B$98,IF(17<=48,'前提'!$B$99,'前提'!$B$100)))))))+IF(17>=7,CEILING(R14/'前提'!$B$29,1),0)+IF(17>=7,CEILING(R14/'前提'!$B$30,1),0)+IF(17>=7,CEILING(R10/'前提'!$B$31,1),0))*'前提'!$B$49 | S44: =(1+IF(18<=6,'前提'!$B$36/160,IF(18<=12,'前提'!$B$37/160,(IF(18<=6,'前提'!$B$85,IF(18<=12,'前提'!$B$86,IF(18<=18,'前提'!$B$87,IF(18<=24,'前提'!$B$88,IF(18<=36,'前提'!$B$89,IF(18<=48,'前提'!$B$90,'前提'!$B$91)))))))))+(IF(18<=6,'前提'!$B$94,IF(18<=12,'前提'!$B$95,IF(18<=18,'前提'!$B$96,IF(18<=24,'前提'!$B$97,IF(18<=36,'前提'!$B$98,IF(18<=48,'前提'!$B$99,'前提'!$B$100)))))))+IF(18>=7,CEILING(S14/'前提'!$B$29,1),0)+IF(18>=7,CEILING(S14/'前提'!$B$30,1),0)+IF(18>=7,CEILING(S10/'前提'!$B$31,1),0))*'前提'!$B$49 | T44: =(1+IF(19<=6,'前提'!$B$36/160,IF(19<=12,'前提'!$B$37/160,(IF(19<=6,'前提'!$B$85,IF(19<=12,'前提'!$B$86,IF(19<=18,'前提'!$B$87,IF(19<=24,'前提'!$B$88,IF(19<=36,'前提'!$B$89,IF(19<=48,'前提'!$B$90,'前提'!$B$91)))))))))+(IF(19<=6,'前提'!$B$94,IF(19<=12,'前提'!$B$95,IF(19<=18,'前提'!$B$96,IF(19<=24,'前提'!$B$97,IF(19<=36,'前提'!$B$98,IF(19<=48,'前提'!$B$99,'前提'!$B$100)))))))+IF(19>=7,CEILING(T14/'前提'!$B$29,1),0)+IF(19>=7,CEILING(T14/'前提'!$B$30,1),0)+IF(19>=7,CEILING(T10/'前提'!$B$31,1),0))*'前提'!$B$49 | U44: =(1+IF(20<=6,'前提'!$B$36/160,IF(20<=12,'前提'!$B$37/160,(IF(20<=6,'前提'!$B$85,IF(20<=12,'前提'!$B$86,IF(20<=18,'前提'!$B$87,IF(20<=24,'前提'!$B$88,IF(20<=36,'前提'!$B$89,IF(20<=48,'前提'!$B$90,'前提'!$B$91)))))))))+(IF(20<=6,'前提'!$B$94,IF(20<=12,'前提'!$B$95,IF(20<=18,'前提'!$B$96,IF(20<=24,'前提'!$B$97,IF(20<=36,'前提'!$B$98,IF(20<=48,'前提'!$B$99,'前提'!$B$100)))))))+IF(20>=7,CEILING(U14/'前提'!$B$29,1),0)+IF(20>=7,CEILING(U14/'前提'!$B$30,1),0)+IF(20>=7,CEILING(U10/'前提'!$B$31,1),0))*'前提'!$B$49 | V44: =(1+IF(21<=6,'前提'!$B$36/160,IF(21<=12,'前提'!$B$37/160,(IF(21<=6,'前提'!$B$85,IF(21<=12,'前提'!$B$86,IF(21<=18,'前提'!$B$87,IF(21<=24,'前提'!$B$88,IF(21<=36,'前提'!$B$89,IF(21<=48,'前提'!$B$90,'前提'!$B$91)))))))))+(IF(21<=6,'前提'!$B$94,IF(21<=12,'前提'!$B$95,IF(21<=18,'前提'!$B$96,IF(21<=24,'前提'!$B$97,IF(21<=36,'前提'!$B$98,IF(21<=48,'前提'!$B$99,'前提'!$B$100)))))))+IF(21>=7,CEILING(V14/'前提'!$B$29,1),0)+IF(21>=7,CEILING(V14/'前提'!$B$30,1),0)+IF(21>=7,CEILING(V10/'前提'!$B$31,1),0))*'前提'!$B$49 | W44: =(1+IF(22<=6,'前提'!$B$36/160,IF(22<=12,'前提'!$B$37/160,(IF(22<=6,'前提'!$B$85,IF(22<=12,'前提'!$B$86,IF(22<=18,'前提'!$B$87,IF(22<=24,'前提'!$B$88,IF(22<=36,'前提'!$B$89,IF(22<=48,'前提'!$B$90,'前提'!$B$91)))))))))+(IF(22<=6,'前提'!$B$94,IF(22<=12,'前提'!$B$95,IF(22<=18,'前提'!$B$96,IF(22<=24,'前提'!$B$97,IF(22<=36,'前提'!$B$98,IF(22<=48,'前提'!$B$99,'前提'!$B$100)))))))+IF(22>=7,CEILING(W14/'前提'!$B$29,1),0)+IF(22>=7,CEILING(W14/'前提'!$B$30,1),0)+IF(22>=7,CEILING(W10/'前提'!$B$31,1),0))*'前提'!$B$49 | X44: =(1+IF(23<=6,'前提'!$B$36/160,IF(23<=12,'前提'!$B$37/160,(IF(23<=6,'前提'!$B$85,IF(23<=12,'前提'!$B$86,IF(23<=18,'前提'!$B$87,IF(23<=24,'前提'!$B$88,IF(23<=36,'前提'!$B$89,IF(23<=48,'前提'!$B$90,'前提'!$B$91)))))))))+(IF(23<=6,'前提'!$B$94,IF(23<=12,'前提'!$B$95,IF(23<=18,'前提'!$B$96,IF(23<=24,'前提'!$B$97,IF(23<=36,'前提'!$B$98,IF(23<=48,'前提'!$B$99,'前提'!$B$100)))))))+IF(23>=7,CEILING(X14/'前提'!$B$29,1),0)+IF(23>=7,CEILING(X14/'前提'!$B$30,1),0)+IF(23>=7,CEILING(X10/'前提'!$B$31,1),0))*'前提'!$B$49 | Y44: =(1+IF(24<=6,'前提'!$B$36/160,IF(24<=12,'前提'!$B$37/160,(IF(24<=6,'前提'!$B$85,IF(24<=12,'前提'!$B$86,IF(24<=18,'前提'!$B$87,IF(24<=24,'前提'!$B$88,IF(24<=36,'前提'!$B$89,IF(24<=48,'前提'!$B$90,'前提'!$B$91)))))))))+(IF(24<=6,'前提'!$B$94,IF(24<=12,'前提'!$B$95,IF(24<=18,'前提'!$B$96,IF(24<=24,'前提'!$B$97,IF(24<=36,'前提'!$B$98,IF(24<=48,'前提'!$B$99,'前提'!$B$100)))))))+IF(24>=7,CEILING(Y14/'前提'!$B$29,1),0)+IF(24>=7,CEILING(Y14/'前提'!$B$30,1),0)+IF(24>=7,CEILING(Y10/'前提'!$B$31,1),0))*'前提'!$B$49 | Z44: =(1+IF(25<=6,'前提'!$B$36/160,IF(25<=12,'前提'!$B$37/160,(IF(25<=6,'前提'!$B$85,IF(25<=12,'前提'!$B$86,IF(25<=18,'前提'!$B$87,IF(25<=24,'前提'!$B$88,IF(25<=36,'前提'!$B$89,IF(25<=48,'前提'!$B$90,'前提'!$B$91)))))))))+(IF(25<=6,'前提'!$B$94,IF(25<=12,'前提'!$B$95,IF(25<=18,'前提'!$B$96,IF(25<=24,'前提'!$B$97,IF(25<=36,'前提'!$B$98,IF(25<=48,'前提'!$B$99,'前提'!$B$100)))))))+IF(25>=7,CEILING(Z14/'前提'!$B$29,1),0)+IF(25>=7,CEILING(Z14/'前提'!$B$30,1),0)+IF(25>=7,CEILING(Z10/'前提'!$B$31,1),0))*'前提'!$B$49 | AA44: =(1+IF(26<=6,'前提'!$B$36/160,IF(26<=12,'前提'!$B$37/160,(IF(26<=6,'前提'!$B$85,IF(26<=12,'前提'!$B$86,IF(26<=18,'前提'!$B$87,IF(26<=24,'前提'!$B$88,IF(26<=36,'前提'!$B$89,IF(26<=48,'前提'!$B$90,'前提'!$B$91)))))))))+(IF(26<=6,'前提'!$B$94,IF(26<=12,'前提'!$B$95,IF(26<=18,'前提'!$B$96,IF(26<=24,'前提'!$B$97,IF(26<=36,'前提'!$B$98,IF(26<=48,'前提'!$B$99,'前提'!$B$100)))))))+IF(26>=7,CEILING(AA14/'前提'!$B$29,1),0)+IF(26>=7,CEILING(AA14/'前提'!$B$30,1),0)+IF(26>=7,CEILING(AA10/'前提'!$B$31,1),0))*'前提'!$B$49 | AB44: =(1+IF(27<=6,'前提'!$B$36/160,IF(27<=12,'前提'!$B$37/160,(IF(27<=6,'前提'!$B$85,IF(27<=12,'前提'!$B$86,IF(27<=18,'前提'!$B$87,IF(27<=24,'前提'!$B$88,IF(27<=36,'前提'!$B$89,IF(27<=48,'前提'!$B$90,'前提'!$B$91)))))))))+(IF(27<=6,'前提'!$B$94,IF(27<=12,'前提'!$B$95,IF(27<=18,'前提'!$B$96,IF(27<=24,'前提'!$B$97,IF(27<=36,'前提'!$B$98,IF(27<=48,'前提'!$B$99,'前提'!$B$100)))))))+IF(27>=7,CEILING(AB14/'前提'!$B$29,1),0)+IF(27>=7,CEILING(AB14/'前提'!$B$30,1),0)+IF(27>=7,CEILING(AB10/'前提'!$B$31,1),0))*'前提'!$B$49 | AC44: =(1+IF(28<=6,'前提'!$B$36/160,IF(28<=12,'前提'!$B$37/160,(IF(28<=6,'前提'!$B$85,IF(28<=12,'前提'!$B$86,IF(28<=18,'前提'!$B$87,IF(28<=24,'前提'!$B$88,IF(28<=36,'前提'!$B$89,IF(28<=48,'前提'!$B$90,'前提'!$B$91)))))))))+(IF(28<=6,'前提'!$B$94,IF(28<=12,'前提'!$B$95,IF(28<=18,'前提'!$B$96,IF(28<=24,'前提'!$B$97,IF(28<=36,'前提'!$B$98,IF(28<=48,'前提'!$B$99,'前提'!$B$100)))))))+IF(28>=7,CEILING(AC14/'前提'!$B$29,1),0)+IF(28>=7,CEILING(AC14/'前提'!$B$30,1),0)+IF(28>=7,CEILING(AC10/'前提'!$B$31,1),0))*'前提'!$B$49 | AD44: =(1+IF(29<=6,'前提'!$B$36/160,IF(29<=12,'前提'!$B$37/160,(IF(29<=6,'前提'!$B$85,IF(29<=12,'前提'!$B$86,IF(29<=18,'前提'!$B$87,IF(29<=24,'前提'!$B$88,IF(29<=36,'前提'!$B$89,IF(29<=48,'前提'!$B$90,'前提'!$B$91)))))))))+(IF(29<=6,'前提'!$B$94,IF(29<=12,'前提'!$B$95,IF(29<=18,'前提'!$B$96,IF(29<=24,'前提'!$B$97,IF(29<=36,'前提'!$B$98,IF(29<=48,'前提'!$B$99,'前提'!$B$100)))))))+IF(29>=7,CEILING(AD14/'前提'!$B$29,1),0)+IF(29>=7,CEILING(AD14/'前提'!$B$30,1),0)+IF(29>=7,CEILING(AD10/'前提'!$B$31,1),0))*'前提'!$B$49 | AE44: =(1+IF(30<=6,'前提'!$B$36/160,IF(30<=12,'前提'!$B$37/160,(IF(30<=6,'前提'!$B$85,IF(30<=12,'前提'!$B$86,IF(30<=18,'前提'!$B$87,IF(30<=24,'前提'!$B$88,IF(30<=36,'前提'!$B$89,IF(30<=48,'前提'!$B$90,'前提'!$B$91)))))))))+(IF(30<=6,'前提'!$B$94,IF(30<=12,'前提'!$B$95,IF(30<=18,'前提'!$B$96,IF(30<=24,'前提'!$B$97,IF(30<=36,'前提'!$B$98,IF(30<=48,'前提'!$B$99,'前提'!$B$100)))))))+IF(30>=7,CEILING(AE14/'前提'!$B$29,1),0)+IF(30>=7,CEILING(AE14/'前提'!$B$30,1),0)+IF(30>=7,CEILING(AE10/'前提'!$B$31,1),0))*'前提'!$B$49 | AF44: =(1+IF(31<=6,'前提'!$B$36/160,IF(31<=12,'前提'!$B$37/160,(IF(31<=6,'前提'!$B$85,IF(31<=12,'前提'!$B$86,IF(31<=18,'前提'!$B$87,IF(31<=24,'前提'!$B$88,IF(31<=36,'前提'!$B$89,IF(31<=48,'前提'!$B$90,'前提'!$B$91)))))))))+(IF(31<=6,'前提'!$B$94,IF(31<=12,'前提'!$B$95,IF(31<=18,'前提'!$B$96,IF(31<=24,'前提'!$B$97,IF(31<=36,'前提'!$B$98,IF(31<=48,'前提'!$B$99,'前提'!$B$100)))))))+IF(31>=7,CEILING(AF14/'前提'!$B$29,1),0)+IF(31>=7,CEILING(AF14/'前提'!$B$30,1),0)+IF(31>=7,CEILING(AF10/'前提'!$B$31,1),0))*'前提'!$B$49 | AG44: =(1+IF(32<=6,'前提'!$B$36/160,IF(32<=12,'前提'!$B$37/160,(IF(32<=6,'前提'!$B$85,IF(32<=12,'前提'!$B$86,IF(32<=18,'前提'!$B$87,IF(32<=24,'前提'!$B$88,IF(32<=36,'前提'!$B$89,IF(32<=48,'前提'!$B$90,'前提'!$B$91)))))))))+(IF(32<=6,'前提'!$B$94,IF(32<=12,'前提'!$B$95,IF(32<=18,'前提'!$B$96,IF(32<=24,'前提'!$B$97,IF(32<=36,'前提'!$B$98,IF(32<=48,'前提'!$B$99,'前提'!$B$100)))))))+IF(32>=7,CEILING(AG14/'前提'!$B$29,1),0)+IF(32>=7,CEILING(AG14/'前提'!$B$30,1),0)+IF(32>=7,CEILING(AG10/'前提'!$B$31,1),0))*'前提'!$B$49 | AH44: =(1+IF(33<=6,'前提'!$B$36/160,IF(33<=12,'前提'!$B$37/160,(IF(33<=6,'前提'!$B$85,IF(33<=12,'前提'!$B$86,IF(33<=18,'前提'!$B$87,IF(33<=24,'前提'!$B$88,IF(33<=36,'前提'!$B$89,IF(33<=48,'前提'!$B$90,'前提'!$B$91)))))))))+(IF(33<=6,'前提'!$B$94,IF(33<=12,'前提'!$B$95,IF(33<=18,'前提'!$B$96,IF(33<=24,'前提'!$B$97,IF(33<=36,'前提'!$B$98,IF(33<=48,'前提'!$B$99,'前提'!$B$100)))))))+IF(33>=7,CEILING(AH14/'前提'!$B$29,1),0)+IF(33>=7,CEILING(AH14/'前提'!$B$30,1),0)+IF(33>=7,CEILING(AH10/'前提'!$B$31,1),0))*'前提'!$B$49 | AI44: =(1+IF(34<=6,'前提'!$B$36/160,IF(34<=12,'前提'!$B$37/160,(IF(34<=6,'前提'!$B$85,IF(34<=12,'前提'!$B$86,IF(34<=18,'前提'!$B$87,IF(34<=24,'前提'!$B$88,IF(34<=36,'前提'!$B$89,IF(34<=48,'前提'!$B$90,'前提'!$B$91)))))))))+(IF(34<=6,'前提'!$B$94,IF(34<=12,'前提'!$B$95,IF(34<=18,'前提'!$B$96,IF(34<=24,'前提'!$B$97,IF(34<=36,'前提'!$B$98,IF(34<=48,'前提'!$B$99,'前提'!$B$100)))))))+IF(34>=7,CEILING(AI14/'前提'!$B$29,1),0)+IF(34>=7,CEILING(AI14/'前提'!$B$30,1),0)+IF(34>=7,CEILING(AI10/'前提'!$B$31,1),0))*'前提'!$B$49 | AJ44: =(1+IF(35<=6,'前提'!$B$36/160,IF(35<=12,'前提'!$B$37/160,(IF(35<=6,'前提'!$B$85,IF(35<=12,'前提'!$B$86,IF(35<=18,'前提'!$B$87,IF(35<=24,'前提'!$B$88,IF(35<=36,'前提'!$B$89,IF(35<=48,'前提'!$B$90,'前提'!$B$91)))))))))+(IF(35<=6,'前提'!$B$94,IF(35<=12,'前提'!$B$95,IF(35<=18,'前提'!$B$96,IF(35<=24,'前提'!$B$97,IF(35<=36,'前提'!$B$98,IF(35<=48,'前提'!$B$99,'前提'!$B$100)))))))+IF(35>=7,CEILING(AJ14/'前提'!$B$29,1),0)+IF(35>=7,CEILING(AJ14/'前提'!$B$30,1),0)+IF(35>=7,CEILING(AJ10/'前提'!$B$31,1),0))*'前提'!$B$49 | AK44: =(1+IF(36<=6,'前提'!$B$36/160,IF(36<=12,'前提'!$B$37/160,(IF(36<=6,'前提'!$B$85,IF(36<=12,'前提'!$B$86,IF(36<=18,'前提'!$B$87,IF(36<=24,'前提'!$B$88,IF(36<=36,'前提'!$B$89,IF(36<=48,'前提'!$B$90,'前提'!$B$91)))))))))+(IF(36<=6,'前提'!$B$94,IF(36<=12,'前提'!$B$95,IF(36<=18,'前提'!$B$96,IF(36<=24,'前提'!$B$97,IF(36<=36,'前提'!$B$98,IF(36<=48,'前提'!$B$99,'前提'!$B$100)))))))+IF(36>=7,CEILING(AK14/'前提'!$B$29,1),0)+IF(36>=7,CEILING(AK14/'前提'!$B$30,1),0)+IF(36>=7,CEILING(AK10/'前提'!$B$31,1),0))*'前提'!$B$49 | AL44: =(1+IF(37<=6,'前提'!$B$36/160,IF(37<=12,'前提'!$B$37/160,(IF(37<=6,'前提'!$B$85,IF(37<=12,'前提'!$B$86,IF(37<=18,'前提'!$B$87,IF(37<=24,'前提'!$B$88,IF(37<=36,'前提'!$B$89,IF(37<=48,'前提'!$B$90,'前提'!$B$91)))))))))+(IF(37<=6,'前提'!$B$94,IF(37<=12,'前提'!$B$95,IF(37<=18,'前提'!$B$96,IF(37<=24,'前提'!$B$97,IF(37<=36,'前提'!$B$98,IF(37<=48,'前提'!$B$99,'前提'!$B$100)))))))+IF(37>=7,CEILING(AL14/'前提'!$B$29,1),0)+IF(37>=7,CEILING(AL14/'前提'!$B$30,1),0)+IF(37>=7,CEILING(AL10/'前提'!$B$31,1),0))*'前提'!$B$49 | AM44: =(1+IF(38<=6,'前提'!$B$36/160,IF(38<=12,'前提'!$B$37/160,(IF(38<=6,'前提'!$B$85,IF(38<=12,'前提'!$B$86,IF(38<=18,'前提'!$B$87,IF(38<=24,'前提'!$B$88,IF(38<=36,'前提'!$B$89,IF(38<=48,'前提'!$B$90,'前提'!$B$91)))))))))+(IF(38<=6,'前提'!$B$94,IF(38<=12,'前提'!$B$95,IF(38<=18,'前提'!$B$96,IF(38<=24,'前提'!$B$97,IF(38<=36,'前提'!$B$98,IF(38<=48,'前提'!$B$99,'前提'!$B$100)))))))+IF(38>=7,CEILING(AM14/'前提'!$B$29,1),0)+IF(38>=7,CEILING(AM14/'前提'!$B$30,1),0)+IF(38>=7,CEILING(AM10/'前提'!$B$31,1),0))*'前提'!$B$49 | AN44: =(1+IF(39<=6,'前提'!$B$36/160,IF(39<=12,'前提'!$B$37/160,(IF(39<=6,'前提'!$B$85,IF(39<=12,'前提'!$B$86,IF(39<=18,'前提'!$B$87,IF(39<=24,'前提'!$B$88,IF(39<=36,'前提'!$B$89,IF(39<=48,'前提'!$B$90,'前提'!$B$91)))))))))+(IF(39<=6,'前提'!$B$94,IF(39<=12,'前提'!$B$95,IF(39<=18,'前提'!$B$96,IF(39<=24,'前提'!$B$97,IF(39<=36,'前提'!$B$98,IF(39<=48,'前提'!$B$99,'前提'!$B$100)))))))+IF(39>=7,CEILING(AN14/'前提'!$B$29,1),0)+IF(39>=7,CEILING(AN14/'前提'!$B$30,1),0)+IF(39>=7,CEILING(AN10/'前提'!$B$31,1),0))*'前提'!$B$49 | AO44: =(1+IF(40<=6,'前提'!$B$36/160,IF(40<=12,'前提'!$B$37/160,(IF(40<=6,'前提'!$B$85,IF(40<=12,'前提'!$B$86,IF(40<=18,'前提'!$B$87,IF(40<=24,'前提'!$B$88,IF(40<=36,'前提'!$B$89,IF(40<=48,'前提'!$B$90,'前提'!$B$91)))))))))+(IF(40<=6,'前提'!$B$94,IF(40<=12,'前提'!$B$95,IF(40<=18,'前提'!$B$96,IF(40<=24,'前提'!$B$97,IF(40<=36,'前提'!$B$98,IF(40<=48,'前提'!$B$99,'前提'!$B$100)))))))+IF(40>=7,CEILING(AO14/'前提'!$B$29,1),0)+IF(40>=7,CEILING(AO14/'前提'!$B$30,1),0)+IF(40>=7,CEILING(AO10/'前提'!$B$31,1),0))*'前提'!$B$49 | AP44: =(1+IF(41<=6,'前提'!$B$36/160,IF(41<=12,'前提'!$B$37/160,(IF(41<=6,'前提'!$B$85,IF(41<=12,'前提'!$B$86,IF(41<=18,'前提'!$B$87,IF(41<=24,'前提'!$B$88,IF(41<=36,'前提'!$B$89,IF(41<=48,'前提'!$B$90,'前提'!$B$91)))))))))+(IF(41<=6,'前提'!$B$94,IF(41<=12,'前提'!$B$95,IF(41<=18,'前提'!$B$96,IF(41<=24,'前提'!$B$97,IF(41<=36,'前提'!$B$98,IF(41<=48,'前提'!$B$99,'前提'!$B$100)))))))+IF(41>=7,CEILING(AP14/'前提'!$B$29,1),0)+IF(41>=7,CEILING(AP14/'前提'!$B$30,1),0)+IF(41>=7,CEILING(AP10/'前提'!$B$31,1),0))*'前提'!$B$49 | AQ44: =(1+IF(42<=6,'前提'!$B$36/160,IF(42<=12,'前提'!$B$37/160,(IF(42<=6,'前提'!$B$85,IF(42<=12,'前提'!$B$86,IF(42<=18,'前提'!$B$87,IF(42<=24,'前提'!$B$88,IF(42<=36,'前提'!$B$89,IF(42<=48,'前提'!$B$90,'前提'!$B$91)))))))))+(IF(42<=6,'前提'!$B$94,IF(42<=12,'前提'!$B$95,IF(42<=18,'前提'!$B$96,IF(42<=24,'前提'!$B$97,IF(42<=36,'前提'!$B$98,IF(42<=48,'前提'!$B$99,'前提'!$B$100)))))))+IF(42>=7,CEILING(AQ14/'前提'!$B$29,1),0)+IF(42>=7,CEILING(AQ14/'前提'!$B$30,1),0)+IF(42>=7,CEILING(AQ10/'前提'!$B$31,1),0))*'前提'!$B$49 | AR44: =(1+IF(43<=6,'前提'!$B$36/160,IF(43<=12,'前提'!$B$37/160,(IF(43<=6,'前提'!$B$85,IF(43<=12,'前提'!$B$86,IF(43<=18,'前提'!$B$87,IF(43<=24,'前提'!$B$88,IF(43<=36,'前提'!$B$89,IF(43<=48,'前提'!$B$90,'前提'!$B$91)))))))))+(IF(43<=6,'前提'!$B$94,IF(43<=12,'前提'!$B$95,IF(43<=18,'前提'!$B$96,IF(43<=24,'前提'!$B$97,IF(43<=36,'前提'!$B$98,IF(43<=48,'前提'!$B$99,'前提'!$B$100)))))))+IF(43>=7,CEILING(AR14/'前提'!$B$29,1),0)+IF(43>=7,CEILING(AR14/'前提'!$B$30,1),0)+IF(43>=7,CEILING(AR10/'前提'!$B$31,1),0))*'前提'!$B$49 | AS44: =(1+IF(44<=6,'前提'!$B$36/160,IF(44<=12,'前提'!$B$37/160,(IF(44<=6,'前提'!$B$85,IF(44<=12,'前提'!$B$86,IF(44<=18,'前提'!$B$87,IF(44<=24,'前提'!$B$88,IF(44<=36,'前提'!$B$89,IF(44<=48,'前提'!$B$90,'前提'!$B$91)))))))))+(IF(44<=6,'前提'!$B$94,IF(44<=12,'前提'!$B$95,IF(44<=18,'前提'!$B$96,IF(44<=24,'前提'!$B$97,IF(44<=36,'前提'!$B$98,IF(44<=48,'前提'!$B$99,'前提'!$B$100)))))))+IF(44>=7,CEILING(AS14/'前提'!$B$29,1),0)+IF(44>=7,CEILING(AS14/'前提'!$B$30,1),0)+IF(44>=7,CEILING(AS10/'前提'!$B$31,1),0))*'前提'!$B$49 | AT44: =(1+IF(45<=6,'前提'!$B$36/160,IF(45<=12,'前提'!$B$37/160,(IF(45<=6,'前提'!$B$85,IF(45<=12,'前提'!$B$86,IF(45<=18,'前提'!$B$87,IF(45<=24,'前提'!$B$88,IF(45<=36,'前提'!$B$89,IF(45<=48,'前提'!$B$90,'前提'!$B$91)))))))))+(IF(45<=6,'前提'!$B$94,IF(45<=12,'前提'!$B$95,IF(45<=18,'前提'!$B$96,IF(45<=24,'前提'!$B$97,IF(45<=36,'前提'!$B$98,IF(45<=48,'前提'!$B$99,'前提'!$B$100)))))))+IF(45>=7,CEILING(AT14/'前提'!$B$29,1),0)+IF(45>=7,CEILING(AT14/'前提'!$B$30,1),0)+IF(45>=7,CEILING(AT10/'前提'!$B$31,1),0))*'前提'!$B$49 | AU44: =(1+IF(46<=6,'前提'!$B$36/160,IF(46<=12,'前提'!$B$37/160,(IF(46<=6,'前提'!$B$85,IF(46<=12,'前提'!$B$86,IF(46<=18,'前提'!$B$87,IF(46<=24,'前提'!$B$88,IF(46<=36,'前提'!$B$89,IF(46<=48,'前提'!$B$90,'前提'!$B$91)))))))))+(IF(46<=6,'前提'!$B$94,IF(46<=12,'前提'!$B$95,IF(46<=18,'前提'!$B$96,IF(46<=24,'前提'!$B$97,IF(46<=36,'前提'!$B$98,IF(46<=48,'前提'!$B$99,'前提'!$B$100)))))))+IF(46>=7,CEILING(AU14/'前提'!$B$29,1),0)+IF(46>=7,CEILING(AU14/'前提'!$B$30,1),0)+IF(46>=7,CEILING(AU10/'前提'!$B$31,1),0))*'前提'!$B$49 | AV44: =(1+IF(47<=6,'前提'!$B$36/160,IF(47<=12,'前提'!$B$37/160,(IF(47<=6,'前提'!$B$85,IF(47<=12,'前提'!$B$86,IF(47<=18,'前提'!$B$87,IF(47<=24,'前提'!$B$88,IF(47<=36,'前提'!$B$89,IF(47<=48,'前提'!$B$90,'前提'!$B$91)))))))))+(IF(47<=6,'前提'!$B$94,IF(47<=12,'前提'!$B$95,IF(47<=18,'前提'!$B$96,IF(47<=24,'前提'!$B$97,IF(47<=36,'前提'!$B$98,IF(47<=48,'前提'!$B$99,'前提'!$B$100)))))))+IF(47>=7,CEILING(AV14/'前提'!$B$29,1),0)+IF(47>=7,CEILING(AV14/'前提'!$B$30,1),0)+IF(47>=7,CEILING(AV10/'前提'!$B$31,1),0))*'前提'!$B$49 | AW44: =(1+IF(48<=6,'前提'!$B$36/160,IF(48<=12,'前提'!$B$37/160,(IF(48<=6,'前提'!$B$85,IF(48<=12,'前提'!$B$86,IF(48<=18,'前提'!$B$87,IF(48<=24,'前提'!$B$88,IF(48<=36,'前提'!$B$89,IF(48<=48,'前提'!$B$90,'前提'!$B$91)))))))))+(IF(48<=6,'前提'!$B$94,IF(48<=12,'前提'!$B$95,IF(48<=18,'前提'!$B$96,IF(48<=24,'前提'!$B$97,IF(48<=36,'前提'!$B$98,IF(48<=48,'前提'!$B$99,'前提'!$B$100)))))))+IF(48>=7,CEILING(AW14/'前提'!$B$29,1),0)+IF(48>=7,CEILING(AW14/'前提'!$B$30,1),0)+IF(48>=7,CEILING(AW10/'前提'!$B$31,1),0))*'前提'!$B$49 | AX44: =(1+IF(49<=6,'前提'!$B$36/160,IF(49<=12,'前提'!$B$37/160,(IF(49<=6,'前提'!$B$85,IF(49<=12,'前提'!$B$86,IF(49<=18,'前提'!$B$87,IF(49<=24,'前提'!$B$88,IF(49<=36,'前提'!$B$89,IF(49<=48,'前提'!$B$90,'前提'!$B$91)))))))))+(IF(49<=6,'前提'!$B$94,IF(49<=12,'前提'!$B$95,IF(49<=18,'前提'!$B$96,IF(49<=24,'前提'!$B$97,IF(49<=36,'前提'!$B$98,IF(49<=48,'前提'!$B$99,'前提'!$B$100)))))))+IF(49>=7,CEILING(AX14/'前提'!$B$29,1),0)+IF(49>=7,CEILING(AX14/'前提'!$B$30,1),0)+IF(49>=7,CEILING(AX10/'前提'!$B$31,1),0))*'前提'!$B$49 | AY44: =(1+IF(50<=6,'前提'!$B$36/160,IF(50<=12,'前提'!$B$37/160,(IF(50<=6,'前提'!$B$85,IF(50<=12,'前提'!$B$86,IF(50<=18,'前提'!$B$87,IF(50<=24,'前提'!$B$88,IF(50<=36,'前提'!$B$89,IF(50<=48,'前提'!$B$90,'前提'!$B$91)))))))))+(IF(50<=6,'前提'!$B$94,IF(50<=12,'前提'!$B$95,IF(50<=18,'前提'!$B$96,IF(50<=24,'前提'!$B$97,IF(50<=36,'前提'!$B$98,IF(50<=48,'前提'!$B$99,'前提'!$B$100)))))))+IF(50>=7,CEILING(AY14/'前提'!$B$29,1),0)+IF(50>=7,CEILING(AY14/'前提'!$B$30,1),0)+IF(50>=7,CEILING(AY10/'前提'!$B$31,1),0))*'前提'!$B$49 | AZ44: =(1+IF(51<=6,'前提'!$B$36/160,IF(51<=12,'前提'!$B$37/160,(IF(51<=6,'前提'!$B$85,IF(51<=12,'前提'!$B$86,IF(51<=18,'前提'!$B$87,IF(51<=24,'前提'!$B$88,IF(51<=36,'前提'!$B$89,IF(51<=48,'前提'!$B$90,'前提'!$B$91)))))))))+(IF(51<=6,'前提'!$B$94,IF(51<=12,'前提'!$B$95,IF(51<=18,'前提'!$B$96,IF(51<=24,'前提'!$B$97,IF(51<=36,'前提'!$B$98,IF(51<=48,'前提'!$B$99,'前提'!$B$100)))))))+IF(51>=7,CEILING(AZ14/'前提'!$B$29,1),0)+IF(51>=7,CEILING(AZ14/'前提'!$B$30,1),0)+IF(51>=7,CEILING(AZ10/'前提'!$B$31,1),0))*'前提'!$B$49 | BA44: =(1+IF(52<=6,'前提'!$B$36/160,IF(52<=12,'前提'!$B$37/160,(IF(52<=6,'前提'!$B$85,IF(52<=12,'前提'!$B$86,IF(52<=18,'前提'!$B$87,IF(52<=24,'前提'!$B$88,IF(52<=36,'前提'!$B$89,IF(52<=48,'前提'!$B$90,'前提'!$B$91)))))))))+(IF(52<=6,'前提'!$B$94,IF(52<=12,'前提'!$B$95,IF(52<=18,'前提'!$B$96,IF(52<=24,'前提'!$B$97,IF(52<=36,'前提'!$B$98,IF(52<=48,'前提'!$B$99,'前提'!$B$100)))))))+IF(52>=7,CEILING(BA14/'前提'!$B$29,1),0)+IF(52>=7,CEILING(BA14/'前提'!$B$30,1),0)+IF(52>=7,CEILING(BA10/'前提'!$B$31,1),0))*'前提'!$B$49 | BB44: =(1+IF(53<=6,'前提'!$B$36/160,IF(53<=12,'前提'!$B$37/160,(IF(53<=6,'前提'!$B$85,IF(53<=12,'前提'!$B$86,IF(53<=18,'前提'!$B$87,IF(53<=24,'前提'!$B$88,IF(53<=36,'前提'!$B$89,IF(53<=48,'前提'!$B$90,'前提'!$B$91)))))))))+(IF(53<=6,'前提'!$B$94,IF(53<=12,'前提'!$B$95,IF(53<=18,'前提'!$B$96,IF(53<=24,'前提'!$B$97,IF(53<=36,'前提'!$B$98,IF(53<=48,'前提'!$B$99,'前提'!$B$100)))))))+IF(53>=7,CEILING(BB14/'前提'!$B$29,1),0)+IF(53>=7,CEILING(BB14/'前提'!$B$30,1),0)+IF(53>=7,CEILING(BB10/'前提'!$B$31,1),0))*'前提'!$B$49 | BC44: =(1+IF(54<=6,'前提'!$B$36/160,IF(54<=12,'前提'!$B$37/160,(IF(54<=6,'前提'!$B$85,IF(54<=12,'前提'!$B$86,IF(54<=18,'前提'!$B$87,IF(54<=24,'前提'!$B$88,IF(54<=36,'前提'!$B$89,IF(54<=48,'前提'!$B$90,'前提'!$B$91)))))))))+(IF(54<=6,'前提'!$B$94,IF(54<=12,'前提'!$B$95,IF(54<=18,'前提'!$B$96,IF(54<=24,'前提'!$B$97,IF(54<=36,'前提'!$B$98,IF(54<=48,'前提'!$B$99,'前提'!$B$100)))))))+IF(54>=7,CEILING(BC14/'前提'!$B$29,1),0)+IF(54>=7,CEILING(BC14/'前提'!$B$30,1),0)+IF(54>=7,CEILING(BC10/'前提'!$B$31,1),0))*'前提'!$B$49 | BD44: =(1+IF(55<=6,'前提'!$B$36/160,IF(55<=12,'前提'!$B$37/160,(IF(55<=6,'前提'!$B$85,IF(55<=12,'前提'!$B$86,IF(55<=18,'前提'!$B$87,IF(55<=24,'前提'!$B$88,IF(55<=36,'前提'!$B$89,IF(55<=48,'前提'!$B$90,'前提'!$B$91)))))))))+(IF(55<=6,'前提'!$B$94,IF(55<=12,'前提'!$B$95,IF(55<=18,'前提'!$B$96,IF(55<=24,'前提'!$B$97,IF(55<=36,'前提'!$B$98,IF(55<=48,'前提'!$B$99,'前提'!$B$100)))))))+IF(55>=7,CEILING(BD14/'前提'!$B$29,1),0)+IF(55>=7,CEILING(BD14/'前提'!$B$30,1),0)+IF(55>=7,CEILING(BD10/'前提'!$B$31,1),0))*'前提'!$B$49 | BE44: =(1+IF(56<=6,'前提'!$B$36/160,IF(56<=12,'前提'!$B$37/160,(IF(56<=6,'前提'!$B$85,IF(56<=12,'前提'!$B$86,IF(56<=18,'前提'!$B$87,IF(56<=24,'前提'!$B$88,IF(56<=36,'前提'!$B$89,IF(56<=48,'前提'!$B$90,'前提'!$B$91)))))))))+(IF(56<=6,'前提'!$B$94,IF(56<=12,'前提'!$B$95,IF(56<=18,'前提'!$B$96,IF(56<=24,'前提'!$B$97,IF(56<=36,'前提'!$B$98,IF(56<=48,'前提'!$B$99,'前提'!$B$100)))))))+IF(56>=7,CEILING(BE14/'前提'!$B$29,1),0)+IF(56>=7,CEILING(BE14/'前提'!$B$30,1),0)+IF(56>=7,CEILING(BE10/'前提'!$B$31,1),0))*'前提'!$B$49 | BF44: =(1+IF(57<=6,'前提'!$B$36/160,IF(57<=12,'前提'!$B$37/160,(IF(57<=6,'前提'!$B$85,IF(57<=12,'前提'!$B$86,IF(57<=18,'前提'!$B$87,IF(57<=24,'前提'!$B$88,IF(57<=36,'前提'!$B$89,IF(57<=48,'前提'!$B$90,'前提'!$B$91)))))))))+(IF(57<=6,'前提'!$B$94,IF(57<=12,'前提'!$B$95,IF(57<=18,'前提'!$B$96,IF(57<=24,'前提'!$B$97,IF(57<=36,'前提'!$B$98,IF(57<=48,'前提'!$B$99,'前提'!$B$100)))))))+IF(57>=7,CEILING(BF14/'前提'!$B$29,1),0)+IF(57>=7,CEILING(BF14/'前提'!$B$30,1),0)+IF(57>=7,CEILING(BF10/'前提'!$B$31,1),0))*'前提'!$B$49 | BG44: =(1+IF(58<=6,'前提'!$B$36/160,IF(58<=12,'前提'!$B$37/160,(IF(58<=6,'前提'!$B$85,IF(58<=12,'前提'!$B$86,IF(58<=18,'前提'!$B$87,IF(58<=24,'前提'!$B$88,IF(58<=36,'前提'!$B$89,IF(58<=48,'前提'!$B$90,'前提'!$B$91)))))))))+(IF(58<=6,'前提'!$B$94,IF(58<=12,'前提'!$B$95,IF(58<=18,'前提'!$B$96,IF(58<=24,'前提'!$B$97,IF(58<=36,'前提'!$B$98,IF(58<=48,'前提'!$B$99,'前提'!$B$100)))))))+IF(58>=7,CEILING(BG14/'前提'!$B$29,1),0)+IF(58>=7,CEILING(BG14/'前提'!$B$30,1),0)+IF(58>=7,CEILING(BG10/'前提'!$B$31,1),0))*'前提'!$B$49 | BH44: =(1+IF(59<=6,'前提'!$B$36/160,IF(59<=12,'前提'!$B$37/160,(IF(59<=6,'前提'!$B$85,IF(59<=12,'前提'!$B$86,IF(59<=18,'前提'!$B$87,IF(59<=24,'前提'!$B$88,IF(59<=36,'前提'!$B$89,IF(59<=48,'前提'!$B$90,'前提'!$B$91)))))))))+(IF(59<=6,'前提'!$B$94,IF(59<=12,'前提'!$B$95,IF(59<=18,'前提'!$B$96,IF(59<=24,'前提'!$B$97,IF(59<=36,'前提'!$B$98,IF(59<=48,'前提'!$B$99,'前提'!$B$100)))))))+IF(59>=7,CEILING(BH14/'前提'!$B$29,1),0)+IF(59>=7,CEILING(BH14/'前提'!$B$30,1),0)+IF(59>=7,CEILING(BH10/'前提'!$B$31,1),0))*'前提'!$B$49 | BI44: =(1+IF(60<=6,'前提'!$B$36/160,IF(60<=12,'前提'!$B$37/160,(IF(60<=6,'前提'!$B$85,IF(60<=12,'前提'!$B$86,IF(60<=18,'前提'!$B$87,IF(60<=24,'前提'!$B$88,IF(60<=36,'前提'!$B$89,IF(60<=48,'前提'!$B$90,'前提'!$B$91)))))))))+(IF(60<=6,'前提'!$B$94,IF(60<=12,'前提'!$B$95,IF(60<=18,'前提'!$B$96,IF(60<=24,'前提'!$B$97,IF(60<=36,'前提'!$B$98,IF(60<=48,'前提'!$B$99,'前提'!$B$100)))))))+IF(60>=7,CEILING(BI14/'前提'!$B$29,1),0)+IF(60>=7,CEILING(BI14/'前提'!$B$30,1),0)+IF(60>=7,CEILING(BI10/'前提'!$B$31,1),0))*'前提'!$B$49
A45: 通信費 | B45: ='前提'!$B$50 | C45: ='前提'!$B$50 | D45: ='前提'!$B$50 | E45: ='前提'!$B$50 | F45: ='前提'!$B$50 | G45: ='前提'!$B$50 | H45: ='前提'!$B$50 | I45: ='前提'!$B$50 | ... BI45: ='前提'!$B$50
A46: 会計顧問 | B46: ='前提'!$B$51 | C46: ='前提'!$B$51 | D46: ='前提'!$B$51 | E46: ='前提'!$B$51 | F46: ='前提'!$B$51 | G46: ='前提'!$B$51 | H46: ='前提'!$B$51 | I46: ='前提'!$B$51 | ... BI46: ='前提'!$B$51
A47: 弁護士・法務 | B47: ='前提'!$B$52 | C47: ='前提'!$B$52 | D47: ='前提'!$B$52 | E47: ='前提'!$B$52 | F47: ='前提'!$B$52 | G47: ='前提'!$B$52 | H47: ='前提'!$B$52 | I47: ='前提'!$B$52 | ... BI47: ='前提'!$B$52
A48: 情報セキュリティ保険 | B48: ='前提'!$B$53 | C48: ='前提'!$B$53 | D48: ='前提'!$B$53 | E48: ='前提'!$B$53 | F48: ='前提'!$B$53 | G48: ='前提'!$B$53 | H48: ='前提'!$B$53 | I48: ='前提'!$B$53 | ... BI48: ='前提'!$B$53
A49: 広告宣伝費（Phase別） | B49: =IF(1<=6,'前提'!$B$76,IF(1<=12,'前提'!$B$77,IF(1<=18,'前提'!$B$78,IF(1<=24,'前提'!$B$79,IF(1<=36,'前提'!$B$80,IF(1<=48,'前提'!$B$81,'前提'!$B$82)))))) | C49: =IF(2<=6,'前提'!$B$76,IF(2<=12,'前提'!$B$77,IF(2<=18,'前提'!$B$78,IF(2<=24,'前提'!$B$79,IF(2<=36,'前提'!$B$80,IF(2<=48,'前提'!$B$81,'前提'!$B$82)))))) | D49: =IF(3<=6,'前提'!$B$76,IF(3<=12,'前提'!$B$77,IF(3<=18,'前提'!$B$78,IF(3<=24,'前提'!$B$79,IF(3<=36,'前提'!$B$80,IF(3<=48,'前提'!$B$81,'前提'!$B$82)))))) | E49: =IF(4<=6,'前提'!$B$76,IF(4<=12,'前提'!$B$77,IF(4<=18,'前提'!$B$78,IF(4<=24,'前提'!$B$79,IF(4<=36,'前提'!$B$80,IF(4<=48,'前提'!$B$81,'前提'!$B$82)))))) | F49: =IF(5<=6,'前提'!$B$76,IF(5<=12,'前提'!$B$77,IF(5<=18,'前提'!$B$78,IF(5<=24,'前提'!$B$79,IF(5<=36,'前提'!$B$80,IF(5<=48,'前提'!$B$81,'前提'!$B$82)))))) | G49: =IF(6<=6,'前提'!$B$76,IF(6<=12,'前提'!$B$77,IF(6<=18,'前提'!$B$78,IF(6<=24,'前提'!$B$79,IF(6<=36,'前提'!$B$80,IF(6<=48,'前提'!$B$81,'前提'!$B$82)))))) | H49: =IF(7<=6,'前提'!$B$76,IF(7<=12,'前提'!$B$77,IF(7<=18,'前提'!$B$78,IF(7<=24,'前提'!$B$79,IF(7<=36,'前提'!$B$80,IF(7<=48,'前提'!$B$81,'前提'!$B$82)))))) | I49: =IF(8<=6,'前提'!$B$76,IF(8<=12,'前提'!$B$77,IF(8<=18,'前提'!$B$78,IF(8<=24,'前提'!$B$79,IF(8<=36,'前提'!$B$80,IF(8<=48,'前提'!$B$81,'前提'!$B$82)))))) | J49: =IF(9<=6,'前提'!$B$76,IF(9<=12,'前提'!$B$77,IF(9<=18,'前提'!$B$78,IF(9<=24,'前提'!$B$79,IF(9<=36,'前提'!$B$80,IF(9<=48,'前提'!$B$81,'前提'!$B$82)))))) | K49: =IF(10<=6,'前提'!$B$76,IF(10<=12,'前提'!$B$77,IF(10<=18,'前提'!$B$78,IF(10<=24,'前提'!$B$79,IF(10<=36,'前提'!$B$80,IF(10<=48,'前提'!$B$81,'前提'!$B$82)))))) | L49: =IF(11<=6,'前提'!$B$76,IF(11<=12,'前提'!$B$77,IF(11<=18,'前提'!$B$78,IF(11<=24,'前提'!$B$79,IF(11<=36,'前提'!$B$80,IF(11<=48,'前提'!$B$81,'前提'!$B$82)))))) | M49: =IF(12<=6,'前提'!$B$76,IF(12<=12,'前提'!$B$77,IF(12<=18,'前提'!$B$78,IF(12<=24,'前提'!$B$79,IF(12<=36,'前提'!$B$80,IF(12<=48,'前提'!$B$81,'前提'!$B$82)))))) | N49: =IF(13<=6,'前提'!$B$76,IF(13<=12,'前提'!$B$77,IF(13<=18,'前提'!$B$78,IF(13<=24,'前提'!$B$79,IF(13<=36,'前提'!$B$80,IF(13<=48,'前提'!$B$81,'前提'!$B$82)))))) | O49: =IF(14<=6,'前提'!$B$76,IF(14<=12,'前提'!$B$77,IF(14<=18,'前提'!$B$78,IF(14<=24,'前提'!$B$79,IF(14<=36,'前提'!$B$80,IF(14<=48,'前提'!$B$81,'前提'!$B$82)))))) | P49: =IF(15<=6,'前提'!$B$76,IF(15<=12,'前提'!$B$77,IF(15<=18,'前提'!$B$78,IF(15<=24,'前提'!$B$79,IF(15<=36,'前提'!$B$80,IF(15<=48,'前提'!$B$81,'前提'!$B$82)))))) | Q49: =IF(16<=6,'前提'!$B$76,IF(16<=12,'前提'!$B$77,IF(16<=18,'前提'!$B$78,IF(16<=24,'前提'!$B$79,IF(16<=36,'前提'!$B$80,IF(16<=48,'前提'!$B$81,'前提'!$B$82)))))) | R49: =IF(17<=6,'前提'!$B$76,IF(17<=12,'前提'!$B$77,IF(17<=18,'前提'!$B$78,IF(17<=24,'前提'!$B$79,IF(17<=36,'前提'!$B$80,IF(17<=48,'前提'!$B$81,'前提'!$B$82)))))) | S49: =IF(18<=6,'前提'!$B$76,IF(18<=12,'前提'!$B$77,IF(18<=18,'前提'!$B$78,IF(18<=24,'前提'!$B$79,IF(18<=36,'前提'!$B$80,IF(18<=48,'前提'!$B$81,'前提'!$B$82)))))) | T49: =IF(19<=6,'前提'!$B$76,IF(19<=12,'前提'!$B$77,IF(19<=18,'前提'!$B$78,IF(19<=24,'前提'!$B$79,IF(19<=36,'前提'!$B$80,IF(19<=48,'前提'!$B$81,'前提'!$B$82)))))) | U49: =IF(20<=6,'前提'!$B$76,IF(20<=12,'前提'!$B$77,IF(20<=18,'前提'!$B$78,IF(20<=24,'前提'!$B$79,IF(20<=36,'前提'!$B$80,IF(20<=48,'前提'!$B$81,'前提'!$B$82)))))) | V49: =IF(21<=6,'前提'!$B$76,IF(21<=12,'前提'!$B$77,IF(21<=18,'前提'!$B$78,IF(21<=24,'前提'!$B$79,IF(21<=36,'前提'!$B$80,IF(21<=48,'前提'!$B$81,'前提'!$B$82)))))) | W49: =IF(22<=6,'前提'!$B$76,IF(22<=12,'前提'!$B$77,IF(22<=18,'前提'!$B$78,IF(22<=24,'前提'!$B$79,IF(22<=36,'前提'!$B$80,IF(22<=48,'前提'!$B$81,'前提'!$B$82)))))) | X49: =IF(23<=6,'前提'!$B$76,IF(23<=12,'前提'!$B$77,IF(23<=18,'前提'!$B$78,IF(23<=24,'前提'!$B$79,IF(23<=36,'前提'!$B$80,IF(23<=48,'前提'!$B$81,'前提'!$B$82)))))) | Y49: =IF(24<=6,'前提'!$B$76,IF(24<=12,'前提'!$B$77,IF(24<=18,'前提'!$B$78,IF(24<=24,'前提'!$B$79,IF(24<=36,'前提'!$B$80,IF(24<=48,'前提'!$B$81,'前提'!$B$82)))))) | Z49: =IF(25<=6,'前提'!$B$76,IF(25<=12,'前提'!$B$77,IF(25<=18,'前提'!$B$78,IF(25<=24,'前提'!$B$79,IF(25<=36,'前提'!$B$80,IF(25<=48,'前提'!$B$81,'前提'!$B$82)))))) | AA49: =IF(26<=6,'前提'!$B$76,IF(26<=12,'前提'!$B$77,IF(26<=18,'前提'!$B$78,IF(26<=24,'前提'!$B$79,IF(26<=36,'前提'!$B$80,IF(26<=48,'前提'!$B$81,'前提'!$B$82)))))) | AB49: =IF(27<=6,'前提'!$B$76,IF(27<=12,'前提'!$B$77,IF(27<=18,'前提'!$B$78,IF(27<=24,'前提'!$B$79,IF(27<=36,'前提'!$B$80,IF(27<=48,'前提'!$B$81,'前提'!$B$82)))))) | AC49: =IF(28<=6,'前提'!$B$76,IF(28<=12,'前提'!$B$77,IF(28<=18,'前提'!$B$78,IF(28<=24,'前提'!$B$79,IF(28<=36,'前提'!$B$80,IF(28<=48,'前提'!$B$81,'前提'!$B$82)))))) | AD49: =IF(29<=6,'前提'!$B$76,IF(29<=12,'前提'!$B$77,IF(29<=18,'前提'!$B$78,IF(29<=24,'前提'!$B$79,IF(29<=36,'前提'!$B$80,IF(29<=48,'前提'!$B$81,'前提'!$B$82)))))) | AE49: =IF(30<=6,'前提'!$B$76,IF(30<=12,'前提'!$B$77,IF(30<=18,'前提'!$B$78,IF(30<=24,'前提'!$B$79,IF(30<=36,'前提'!$B$80,IF(30<=48,'前提'!$B$81,'前提'!$B$82)))))) | AF49: =IF(31<=6,'前提'!$B$76,IF(31<=12,'前提'!$B$77,IF(31<=18,'前提'!$B$78,IF(31<=24,'前提'!$B$79,IF(31<=36,'前提'!$B$80,IF(31<=48,'前提'!$B$81,'前提'!$B$82)))))) | AG49: =IF(32<=6,'前提'!$B$76,IF(32<=12,'前提'!$B$77,IF(32<=18,'前提'!$B$78,IF(32<=24,'前提'!$B$79,IF(32<=36,'前提'!$B$80,IF(32<=48,'前提'!$B$81,'前提'!$B$82)))))) | AH49: =IF(33<=6,'前提'!$B$76,IF(33<=12,'前提'!$B$77,IF(33<=18,'前提'!$B$78,IF(33<=24,'前提'!$B$79,IF(33<=36,'前提'!$B$80,IF(33<=48,'前提'!$B$81,'前提'!$B$82)))))) | AI49: =IF(34<=6,'前提'!$B$76,IF(34<=12,'前提'!$B$77,IF(34<=18,'前提'!$B$78,IF(34<=24,'前提'!$B$79,IF(34<=36,'前提'!$B$80,IF(34<=48,'前提'!$B$81,'前提'!$B$82)))))) | AJ49: =IF(35<=6,'前提'!$B$76,IF(35<=12,'前提'!$B$77,IF(35<=18,'前提'!$B$78,IF(35<=24,'前提'!$B$79,IF(35<=36,'前提'!$B$80,IF(35<=48,'前提'!$B$81,'前提'!$B$82)))))) | AK49: =IF(36<=6,'前提'!$B$76,IF(36<=12,'前提'!$B$77,IF(36<=18,'前提'!$B$78,IF(36<=24,'前提'!$B$79,IF(36<=36,'前提'!$B$80,IF(36<=48,'前提'!$B$81,'前提'!$B$82)))))) | AL49: =IF(37<=6,'前提'!$B$76,IF(37<=12,'前提'!$B$77,IF(37<=18,'前提'!$B$78,IF(37<=24,'前提'!$B$79,IF(37<=36,'前提'!$B$80,IF(37<=48,'前提'!$B$81,'前提'!$B$82)))))) | AM49: =IF(38<=6,'前提'!$B$76,IF(38<=12,'前提'!$B$77,IF(38<=18,'前提'!$B$78,IF(38<=24,'前提'!$B$79,IF(38<=36,'前提'!$B$80,IF(38<=48,'前提'!$B$81,'前提'!$B$82)))))) | AN49: =IF(39<=6,'前提'!$B$76,IF(39<=12,'前提'!$B$77,IF(39<=18,'前提'!$B$78,IF(39<=24,'前提'!$B$79,IF(39<=36,'前提'!$B$80,IF(39<=48,'前提'!$B$81,'前提'!$B$82)))))) | AO49: =IF(40<=6,'前提'!$B$76,IF(40<=12,'前提'!$B$77,IF(40<=18,'前提'!$B$78,IF(40<=24,'前提'!$B$79,IF(40<=36,'前提'!$B$80,IF(40<=48,'前提'!$B$81,'前提'!$B$82)))))) | AP49: =IF(41<=6,'前提'!$B$76,IF(41<=12,'前提'!$B$77,IF(41<=18,'前提'!$B$78,IF(41<=24,'前提'!$B$79,IF(41<=36,'前提'!$B$80,IF(41<=48,'前提'!$B$81,'前提'!$B$82)))))) | AQ49: =IF(42<=6,'前提'!$B$76,IF(42<=12,'前提'!$B$77,IF(42<=18,'前提'!$B$78,IF(42<=24,'前提'!$B$79,IF(42<=36,'前提'!$B$80,IF(42<=48,'前提'!$B$81,'前提'!$B$82)))))) | AR49: =IF(43<=6,'前提'!$B$76,IF(43<=12,'前提'!$B$77,IF(43<=18,'前提'!$B$78,IF(43<=24,'前提'!$B$79,IF(43<=36,'前提'!$B$80,IF(43<=48,'前提'!$B$81,'前提'!$B$82)))))) | AS49: =IF(44<=6,'前提'!$B$76,IF(44<=12,'前提'!$B$77,IF(44<=18,'前提'!$B$78,IF(44<=24,'前提'!$B$79,IF(44<=36,'前提'!$B$80,IF(44<=48,'前提'!$B$81,'前提'!$B$82)))))) | AT49: =IF(45<=6,'前提'!$B$76,IF(45<=12,'前提'!$B$77,IF(45<=18,'前提'!$B$78,IF(45<=24,'前提'!$B$79,IF(45<=36,'前提'!$B$80,IF(45<=48,'前提'!$B$81,'前提'!$B$82)))))) | AU49: =IF(46<=6,'前提'!$B$76,IF(46<=12,'前提'!$B$77,IF(46<=18,'前提'!$B$78,IF(46<=24,'前提'!$B$79,IF(46<=36,'前提'!$B$80,IF(46<=48,'前提'!$B$81,'前提'!$B$82)))))) | AV49: =IF(47<=6,'前提'!$B$76,IF(47<=12,'前提'!$B$77,IF(47<=18,'前提'!$B$78,IF(47<=24,'前提'!$B$79,IF(47<=36,'前提'!$B$80,IF(47<=48,'前提'!$B$81,'前提'!$B$82)))))) | AW49: =IF(48<=6,'前提'!$B$76,IF(48<=12,'前提'!$B$77,IF(48<=18,'前提'!$B$78,IF(48<=24,'前提'!$B$79,IF(48<=36,'前提'!$B$80,IF(48<=48,'前提'!$B$81,'前提'!$B$82)))))) | AX49: =IF(49<=6,'前提'!$B$76,IF(49<=12,'前提'!$B$77,IF(49<=18,'前提'!$B$78,IF(49<=24,'前提'!$B$79,IF(49<=36,'前提'!$B$80,IF(49<=48,'前提'!$B$81,'前提'!$B$82)))))) | AY49: =IF(50<=6,'前提'!$B$76,IF(50<=12,'前提'!$B$77,IF(50<=18,'前提'!$B$78,IF(50<=24,'前提'!$B$79,IF(50<=36,'前提'!$B$80,IF(50<=48,'前提'!$B$81,'前提'!$B$82)))))) | AZ49: =IF(51<=6,'前提'!$B$76,IF(51<=12,'前提'!$B$77,IF(51<=18,'前提'!$B$78,IF(51<=24,'前提'!$B$79,IF(51<=36,'前提'!$B$80,IF(51<=48,'前提'!$B$81,'前提'!$B$82)))))) | BA49: =IF(52<=6,'前提'!$B$76,IF(52<=12,'前提'!$B$77,IF(52<=18,'前提'!$B$78,IF(52<=24,'前提'!$B$79,IF(52<=36,'前提'!$B$80,IF(52<=48,'前提'!$B$81,'前提'!$B$82)))))) | BB49: =IF(53<=6,'前提'!$B$76,IF(53<=12,'前提'!$B$77,IF(53<=18,'前提'!$B$78,IF(53<=24,'前提'!$B$79,IF(53<=36,'前提'!$B$80,IF(53<=48,'前提'!$B$81,'前提'!$B$82)))))) | BC49: =IF(54<=6,'前提'!$B$76,IF(54<=12,'前提'!$B$77,IF(54<=18,'前提'!$B$78,IF(54<=24,'前提'!$B$79,IF(54<=36,'前提'!$B$80,IF(54<=48,'前提'!$B$81,'前提'!$B$82)))))) | BD49: =IF(55<=6,'前提'!$B$76,IF(55<=12,'前提'!$B$77,IF(55<=18,'前提'!$B$78,IF(55<=24,'前提'!$B$79,IF(55<=36,'前提'!$B$80,IF(55<=48,'前提'!$B$81,'前提'!$B$82)))))) | BE49: =IF(56<=6,'前提'!$B$76,IF(56<=12,'前提'!$B$77,IF(56<=18,'前提'!$B$78,IF(56<=24,'前提'!$B$79,IF(56<=36,'前提'!$B$80,IF(56<=48,'前提'!$B$81,'前提'!$B$82)))))) | BF49: =IF(57<=6,'前提'!$B$76,IF(57<=12,'前提'!$B$77,IF(57<=18,'前提'!$B$78,IF(57<=24,'前提'!$B$79,IF(57<=36,'前提'!$B$80,IF(57<=48,'前提'!$B$81,'前提'!$B$82)))))) | BG49: =IF(58<=6,'前提'!$B$76,IF(58<=12,'前提'!$B$77,IF(58<=18,'前提'!$B$78,IF(58<=24,'前提'!$B$79,IF(58<=36,'前提'!$B$80,IF(58<=48,'前提'!$B$81,'前提'!$B$82)))))) | BH49: =IF(59<=6,'前提'!$B$76,IF(59<=12,'前提'!$B$77,IF(59<=18,'前提'!$B$78,IF(59<=24,'前提'!$B$79,IF(59<=36,'前提'!$B$80,IF(59<=48,'前提'!$B$81,'前提'!$B$82)))))) | BI49: =IF(60<=6,'前提'!$B$76,IF(60<=12,'前提'!$B$77,IF(60<=18,'前提'!$B$78,IF(60<=24,'前提'!$B$79,IF(60<=36,'前提'!$B$80,IF(60<=48,'前提'!$B$81,'前提'!$B$82))))))
A50: その他固定費 | B50: ='前提'!$B$55 | C50: ='前提'!$B$55 | D50: ='前提'!$B$55 | E50: ='前提'!$B$55 | F50: ='前提'!$B$55 | G50: ='前提'!$B$55 | H50: ='前提'!$B$55 | I50: ='前提'!$B$55 | ... BI50: ='前提'!$B$55
A51: 固定費合計 | B51: =SUM(B43:B50) | C51: =SUM(C43:C50) | D51: =SUM(D43:D50) | E51: =SUM(E43:E50) | F51: =SUM(F43:F50) | G51: =SUM(G43:G50) | H51: =SUM(H43:H50) | I51: =SUM(I43:I50) | ... BI51: =SUM(BI43:BI50)
A53: コスト合計 | B53: =SUM(B25:B29)+B40+B51 | C53: =SUM(C25:C29)+C40+C51 | D53: =SUM(D25:D29)+D40+D51 | E53: =SUM(E25:E29)+E40+E51 | F53: =SUM(F25:F29)+F40+F51 | G53: =SUM(G25:G29)+G40+G51 | H53: =SUM(H25:H29)+H40+H51 | I53: =SUM(I25:I29)+I40+I51 | ... BI53: =SUM(BI25:BI29)+BI40+BI51
A55: 【損益】
A56: 粗利（売上-直接原価-BPO/CS人件費） | B56: =B22-SUM(B25:B29)-(B35+B36+B37) | C56: =C22-SUM(C25:C29)-(C35+C36+C37) | D56: =D22-SUM(D25:D29)-(D35+D36+D37) | E56: =E22-SUM(E25:E29)-(E35+E36+E37) | F56: =F22-SUM(F25:F29)-(F35+F36+F37) | G56: =G22-SUM(G25:G29)-(G35+G36+G37) | H56: =H22-SUM(H25:H29)-(H35+H36+H37) | I56: =I22-SUM(I25:I29)-(I35+I36+I37) | ... BI56: =BI22-SUM(BI25:BI29)-(BI35+BI36+BI37)
A57: 粗利率 | B57: =IF(B22<>0,B56/B22,0) | C57: =IF(C22<>0,C56/C22,0) | D57: =IF(D22<>0,D56/D22,0) | E57: =IF(E22<>0,E56/E22,0) | F57: =IF(F22<>0,F56/F22,0) | G57: =IF(G22<>0,G56/G22,0) | H57: =IF(H22<>0,H56/H22,0) | I57: =IF(I22<>0,I56/I22,0) | ... BI57: =IF(BI22<>0,BI56/BI22,0)
A58: 営業利益 | B58: =B22-B53 | C58: =C22-C53 | D58: =D22-D53 | E58: =E22-E53 | F58: =F22-F53 | G58: =G22-G53 | H58: =H22-H53 | I58: =I22-I53 | ... BI58: =BI22-BI53
A59: 営業利益率 | B59: =IF(B22<>0,B58/B22,0) | C59: =IF(C22<>0,C58/C22,0) | D59: =IF(D22<>0,D58/D22,0) | E59: =IF(E22<>0,E58/E22,0) | F59: =IF(F22<>0,F58/F22,0) | G59: =IF(G22<>0,G58/G22,0) | H59: =IF(H22<>0,H58/H22,0) | I59: =IF(I22<>0,I58/I22,0) | ... BI59: =IF(BI22<>0,BI58/BI22,0)
A60: 累積営業利益 | B60: =B58 | C60: =B60+C58 | D60: =C60+D58 | E60: =D60+E58 | F60: =E60+F58 | G60: =F60+G58 | H60: =G60+H58 | I60: =H60+I58 | J60: =I60+J58 | ... BI60: =BH60+BI58
A62: 【KPI】
A63: 総顧客数（SD+BPO） | B63: =B10+B14 | C63: =C10+C14 | D63: =D10+D14 | E63: =E10+E14 | F63: =F10+F14 | G63: =G10+G14 | H63: =H10+H14 | I63: =I10+I14 | ... BI63: =BI10+BI14
A64: 平均ARPA（MRR/総顧客） | B64: =IF(B63>0,B21/B63,0) | C64: =IF(C63>0,C21/C63,0) | D64: =IF(D63>0,D21/D63,0) | E64: =IF(E63>0,E21/E63,0) | F64: =IF(F63>0,F21/F63,0) | G64: =IF(G63>0,G21/G63,0) | H64: =IF(H63>0,H21/H63,0) | I64: =IF(I63>0,I21/I63,0) | ... BI64: =IF(BI63>0,BI21/BI63,0)
A65: 高ARPA顧客数（BPO） | B65: =B14 | C65: =C14 | D65: =D14 | E65: =E14 | F65: =F14 | G65: =G14 | H65: =H14 | I65: =I14 | ... BI65: =BI14
A66: ARR | B66: =B21*12 | C66: =C21*12 | D66: =D21*12 | E66: =E21*12 | F66: =F21*12 | G66: =G21*12 | H66: =H21*12 | I66: =I21*12 | ... BI66: =BI21*12
A68: 【キャッシュフロー】
A69: 調達資金（シード/公庫/SeriesA） | B69: =IF(1=1,'前提'!$B$106+'前提'!$B$107+'前提'!$B$108+'前提'!$B$109,0)+IF(1='前提'!$B$116,'前提'!$B$114,0) | C69: =IF(2=1,'前提'!$B$106+'前提'!$B$107+'前提'!$B$108+'前提'!$B$109,0)+IF(2='前提'!$B$116,'前提'!$B$114,0) | D69: =IF(3=1,'前提'!$B$106+'前提'!$B$107+'前提'!$B$108+'前提'!$B$109,0)+IF(3='前提'!$B$116,'前提'!$B$114,0) | E69: =IF(4=1,'前提'!$B$106+'前提'!$B$107+'前提'!$B$108+'前提'!$B$109,0)+IF(4='前提'!$B$116,'前提'!$B$114,0) | F69: =IF(5=1,'前提'!$B$106+'前提'!$B$107+'前提'!$B$108+'前提'!$B$109,0)+IF(5='前提'!$B$116,'前提'!$B$114,0) | G69: =IF(6=1,'前提'!$B$106+'前提'!$B$107+'前提'!$B$108+'前提'!$B$109,0)+IF(6='前提'!$B$116,'前提'!$B$114,0) | H69: =IF(7=1,'前提'!$B$106+'前提'!$B$107+'前提'!$B$108+'前提'!$B$109,0)+IF(7='前提'!$B$116,'前提'!$B$114,0) | I69: =IF(8=1,'前提'!$B$106+'前提'!$B$107+'前提'!$B$108+'前提'!$B$109,0)+IF(8='前提'!$B$116,'前提'!$B$114,0) | J69: =IF(9=1,'前提'!$B$106+'前提'!$B$107+'前提'!$B$108+'前提'!$B$109,0)+IF(9='前提'!$B$116,'前提'!$B$114,0) | K69: =IF(10=1,'前提'!$B$106+'前提'!$B$107+'前提'!$B$108+'前提'!$B$109,0)+IF(10='前提'!$B$116,'前提'!$B$114,0) | L69: =IF(11=1,'前提'!$B$106+'前提'!$B$107+'前提'!$B$108+'前提'!$B$109,0)+IF(11='前提'!$B$116,'前提'!$B$114,0) | M69: =IF(12=1,'前提'!$B$106+'前提'!$B$107+'前提'!$B$108+'前提'!$B$109,0)+IF(12='前提'!$B$116,'前提'!$B$114,0) | N69: =IF(13=1,'前提'!$B$106+'前提'!$B$107+'前提'!$B$108+'前提'!$B$109,0)+IF(13='前提'!$B$116,'前提'!$B$114,0) | O69: =IF(14=1,'前提'!$B$106+'前提'!$B$107+'前提'!$B$108+'前提'!$B$109,0)+IF(14='前提'!$B$116,'前提'!$B$114,0) | P69: =IF(15=1,'前提'!$B$106+'前提'!$B$107+'前提'!$B$108+'前提'!$B$109,0)+IF(15='前提'!$B$116,'前提'!$B$114,0) | Q69: =IF(16=1,'前提'!$B$106+'前提'!$B$107+'前提'!$B$108+'前提'!$B$109,0)+IF(16='前提'!$B$116,'前提'!$B$114,0) | R69: =IF(17=1,'前提'!$B$106+'前提'!$B$107+'前提'!$B$108+'前提'!$B$109,0)+IF(17='前提'!$B$116,'前提'!$B$114,0) | S69: =IF(18=1,'前提'!$B$106+'前提'!$B$107+'前提'!$B$108+'前提'!$B$109,0)+IF(18='前提'!$B$116,'前提'!$B$114,0) | T69: =IF(19=1,'前提'!$B$106+'前提'!$B$107+'前提'!$B$108+'前提'!$B$109,0)+IF(19='前提'!$B$116,'前提'!$B$114,0) | U69: =IF(20=1,'前提'!$B$106+'前提'!$B$107+'前提'!$B$108+'前提'!$B$109,0)+IF(20='前提'!$B$116,'前提'!$B$114,0) | V69: =IF(21=1,'前提'!$B$106+'前提'!$B$107+'前提'!$B$108+'前提'!$B$109,0)+IF(21='前提'!$B$116,'前提'!$B$114,0) | W69: =IF(22=1,'前提'!$B$106+'前提'!$B$107+'前提'!$B$108+'前提'!$B$109,0)+IF(22='前提'!$B$116,'前提'!$B$114,0) | X69: =IF(23=1,'前提'!$B$106+'前提'!$B$107+'前提'!$B$108+'前提'!$B$109,0)+IF(23='前提'!$B$116,'前提'!$B$114,0) | Y69: =IF(24=1,'前提'!$B$106+'前提'!$B$107+'前提'!$B$108+'前提'!$B$109,0)+IF(24='前提'!$B$116,'前提'!$B$114,0) | Z69: =IF(25=1,'前提'!$B$106+'前提'!$B$107+'前提'!$B$108+'前提'!$B$109,0)+IF(25='前提'!$B$116,'前提'!$B$114,0) | AA69: =IF(26=1,'前提'!$B$106+'前提'!$B$107+'前提'!$B$108+'前提'!$B$109,0)+IF(26='前提'!$B$116,'前提'!$B$114,0) | AB69: =IF(27=1,'前提'!$B$106+'前提'!$B$107+'前提'!$B$108+'前提'!$B$109,0)+IF(27='前提'!$B$116,'前提'!$B$114,0) | AC69: =IF(28=1,'前提'!$B$106+'前提'!$B$107+'前提'!$B$108+'前提'!$B$109,0)+IF(28='前提'!$B$116,'前提'!$B$114,0) | AD69: =IF(29=1,'前提'!$B$106+'前提'!$B$107+'前提'!$B$108+'前提'!$B$109,0)+IF(29='前提'!$B$116,'前提'!$B$114,0) | AE69: =IF(30=1,'前提'!$B$106+'前提'!$B$107+'前提'!$B$108+'前提'!$B$109,0)+IF(30='前提'!$B$116,'前提'!$B$114,0) | AF69: =IF(31=1,'前提'!$B$106+'前提'!$B$107+'前提'!$B$108+'前提'!$B$109,0)+IF(31='前提'!$B$116,'前提'!$B$114,0) | AG69: =IF(32=1,'前提'!$B$106+'前提'!$B$107+'前提'!$B$108+'前提'!$B$109,0)+IF(32='前提'!$B$116,'前提'!$B$114,0) | AH69: =IF(33=1,'前提'!$B$106+'前提'!$B$107+'前提'!$B$108+'前提'!$B$109,0)+IF(33='前提'!$B$116,'前提'!$B$114,0) | AI69: =IF(34=1,'前提'!$B$106+'前提'!$B$107+'前提'!$B$108+'前提'!$B$109,0)+IF(34='前提'!$B$116,'前提'!$B$114,0) | AJ69: =IF(35=1,'前提'!$B$106+'前提'!$B$107+'前提'!$B$108+'前提'!$B$109,0)+IF(35='前提'!$B$116,'前提'!$B$114,0) | AK69: =IF(36=1,'前提'!$B$106+'前提'!$B$107+'前提'!$B$108+'前提'!$B$109,0)+IF(36='前提'!$B$116,'前提'!$B$114,0) | AL69: =IF(37=1,'前提'!$B$106+'前提'!$B$107+'前提'!$B$108+'前提'!$B$109,0)+IF(37='前提'!$B$116,'前提'!$B$114,0) | AM69: =IF(38=1,'前提'!$B$106+'前提'!$B$107+'前提'!$B$108+'前提'!$B$109,0)+IF(38='前提'!$B$116,'前提'!$B$114,0) | AN69: =IF(39=1,'前提'!$B$106+'前提'!$B$107+'前提'!$B$108+'前提'!$B$109,0)+IF(39='前提'!$B$116,'前提'!$B$114,0) | AO69: =IF(40=1,'前提'!$B$106+'前提'!$B$107+'前提'!$B$108+'前提'!$B$109,0)+IF(40='前提'!$B$116,'前提'!$B$114,0) | AP69: =IF(41=1,'前提'!$B$106+'前提'!$B$107+'前提'!$B$108+'前提'!$B$109,0)+IF(41='前提'!$B$116,'前提'!$B$114,0) | AQ69: =IF(42=1,'前提'!$B$106+'前提'!$B$107+'前提'!$B$108+'前提'!$B$109,0)+IF(42='前提'!$B$116,'前提'!$B$114,0) | AR69: =IF(43=1,'前提'!$B$106+'前提'!$B$107+'前提'!$B$108+'前提'!$B$109,0)+IF(43='前提'!$B$116,'前提'!$B$114,0) | AS69: =IF(44=1,'前提'!$B$106+'前提'!$B$107+'前提'!$B$108+'前提'!$B$109,0)+IF(44='前提'!$B$116,'前提'!$B$114,0) | AT69: =IF(45=1,'前提'!$B$106+'前提'!$B$107+'前提'!$B$108+'前提'!$B$109,0)+IF(45='前提'!$B$116,'前提'!$B$114,0) | AU69: =IF(46=1,'前提'!$B$106+'前提'!$B$107+'前提'!$B$108+'前提'!$B$109,0)+IF(46='前提'!$B$116,'前提'!$B$114,0) | AV69: =IF(47=1,'前提'!$B$106+'前提'!$B$107+'前提'!$B$108+'前提'!$B$109,0)+IF(47='前提'!$B$116,'前提'!$B$114,0) | AW69: =IF(48=1,'前提'!$B$106+'前提'!$B$107+'前提'!$B$108+'前提'!$B$109,0)+IF(48='前提'!$B$116,'前提'!$B$114,0) | AX69: =IF(49=1,'前提'!$B$106+'前提'!$B$107+'前提'!$B$108+'前提'!$B$109,0)+IF(49='前提'!$B$116,'前提'!$B$114,0) | AY69: =IF(50=1,'前提'!$B$106+'前提'!$B$107+'前提'!$B$108+'前提'!$B$109,0)+IF(50='前提'!$B$116,'前提'!$B$114,0) | AZ69: =IF(51=1,'前提'!$B$106+'前提'!$B$107+'前提'!$B$108+'前提'!$B$109,0)+IF(51='前提'!$B$116,'前提'!$B$114,0) | BA69: =IF(52=1,'前提'!$B$106+'前提'!$B$107+'前提'!$B$108+'前提'!$B$109,0)+IF(52='前提'!$B$116,'前提'!$B$114,0) | BB69: =IF(53=1,'前提'!$B$106+'前提'!$B$107+'前提'!$B$108+'前提'!$B$109,0)+IF(53='前提'!$B$116,'前提'!$B$114,0) | BC69: =IF(54=1,'前提'!$B$106+'前提'!$B$107+'前提'!$B$108+'前提'!$B$109,0)+IF(54='前提'!$B$116,'前提'!$B$114,0) | BD69: =IF(55=1,'前提'!$B$106+'前提'!$B$107+'前提'!$B$108+'前提'!$B$109,0)+IF(55='前提'!$B$116,'前提'!$B$114,0) | BE69: =IF(56=1,'前提'!$B$106+'前提'!$B$107+'前提'!$B$108+'前提'!$B$109,0)+IF(56='前提'!$B$116,'前提'!$B$114,0) | BF69: =IF(57=1,'前提'!$B$106+'前提'!$B$107+'前提'!$B$108+'前提'!$B$109,0)+IF(57='前提'!$B$116,'前提'!$B$114,0) | BG69: =IF(58=1,'前提'!$B$106+'前提'!$B$107+'前提'!$B$108+'前提'!$B$109,0)+IF(58='前提'!$B$116,'前提'!$B$114,0) | BH69: =IF(59=1,'前提'!$B$106+'前提'!$B$107+'前提'!$B$108+'前提'!$B$109,0)+IF(59='前提'!$B$116,'前提'!$B$114,0) | BI69: =IF(60=1,'前提'!$B$106+'前提'!$B$107+'前提'!$B$108+'前提'!$B$109,0)+IF(60='前提'!$B$116,'前提'!$B$114,0)
A70: 公庫利息 | B70: =IF(1<='前提'!$B$111,'前提'!$B$109*'前提'!$B$110/12,'前提'!$B$109*'前提'!$B$110/12) | C70: =IF(2<='前提'!$B$111,'前提'!$B$109*'前提'!$B$110/12,'前提'!$B$109*'前提'!$B$110/12) | D70: =IF(3<='前提'!$B$111,'前提'!$B$109*'前提'!$B$110/12,'前提'!$B$109*'前提'!$B$110/12) | E70: =IF(4<='前提'!$B$111,'前提'!$B$109*'前提'!$B$110/12,'前提'!$B$109*'前提'!$B$110/12) | F70: =IF(5<='前提'!$B$111,'前提'!$B$109*'前提'!$B$110/12,'前提'!$B$109*'前提'!$B$110/12) | G70: =IF(6<='前提'!$B$111,'前提'!$B$109*'前提'!$B$110/12,'前提'!$B$109*'前提'!$B$110/12) | H70: =IF(7<='前提'!$B$111,'前提'!$B$109*'前提'!$B$110/12,'前提'!$B$109*'前提'!$B$110/12) | I70: =IF(8<='前提'!$B$111,'前提'!$B$109*'前提'!$B$110/12,'前提'!$B$109*'前提'!$B$110/12) | J70: =IF(9<='前提'!$B$111,'前提'!$B$109*'前提'!$B$110/12,'前提'!$B$109*'前提'!$B$110/12) | K70: =IF(10<='前提'!$B$111,'前提'!$B$109*'前提'!$B$110/12,'前提'!$B$109*'前提'!$B$110/12) | L70: =IF(11<='前提'!$B$111,'前提'!$B$109*'前提'!$B$110/12,'前提'!$B$109*'前提'!$B$110/12) | M70: =IF(12<='前提'!$B$111,'前提'!$B$109*'前提'!$B$110/12,'前提'!$B$109*'前提'!$B$110/12) | N70: =IF(13<='前提'!$B$111,'前提'!$B$109*'前提'!$B$110/12,'前提'!$B$109*'前提'!$B$110/12) | O70: =IF(14<='前提'!$B$111,'前提'!$B$109*'前提'!$B$110/12,'前提'!$B$109*'前提'!$B$110/12) | P70: =IF(15<='前提'!$B$111,'前提'!$B$109*'前提'!$B$110/12,'前提'!$B$109*'前提'!$B$110/12) | Q70: =IF(16<='前提'!$B$111,'前提'!$B$109*'前提'!$B$110/12,'前提'!$B$109*'前提'!$B$110/12) | R70: =IF(17<='前提'!$B$111,'前提'!$B$109*'前提'!$B$110/12,'前提'!$B$109*'前提'!$B$110/12) | S70: =IF(18<='前提'!$B$111,'前提'!$B$109*'前提'!$B$110/12,'前提'!$B$109*'前提'!$B$110/12) | T70: =IF(19<='前提'!$B$111,'前提'!$B$109*'前提'!$B$110/12,'前提'!$B$109*'前提'!$B$110/12) | U70: =IF(20<='前提'!$B$111,'前提'!$B$109*'前提'!$B$110/12,'前提'!$B$109*'前提'!$B$110/12) | V70: =IF(21<='前提'!$B$111,'前提'!$B$109*'前提'!$B$110/12,'前提'!$B$109*'前提'!$B$110/12) | W70: =IF(22<='前提'!$B$111,'前提'!$B$109*'前提'!$B$110/12,'前提'!$B$109*'前提'!$B$110/12) | X70: =IF(23<='前提'!$B$111,'前提'!$B$109*'前提'!$B$110/12,'前提'!$B$109*'前提'!$B$110/12) | Y70: =IF(24<='前提'!$B$111,'前提'!$B$109*'前提'!$B$110/12,'前提'!$B$109*'前提'!$B$110/12) | Z70: =IF(25<='前提'!$B$111,'前提'!$B$109*'前提'!$B$110/12,'前提'!$B$109*'前提'!$B$110/12) | AA70: =IF(26<='前提'!$B$111,'前提'!$B$109*'前提'!$B$110/12,'前提'!$B$109*'前提'!$B$110/12) | AB70: =IF(27<='前提'!$B$111,'前提'!$B$109*'前提'!$B$110/12,'前提'!$B$109*'前提'!$B$110/12) | AC70: =IF(28<='前提'!$B$111,'前提'!$B$109*'前提'!$B$110/12,'前提'!$B$109*'前提'!$B$110/12) | AD70: =IF(29<='前提'!$B$111,'前提'!$B$109*'前提'!$B$110/12,'前提'!$B$109*'前提'!$B$110/12) | AE70: =IF(30<='前提'!$B$111,'前提'!$B$109*'前提'!$B$110/12,'前提'!$B$109*'前提'!$B$110/12) | AF70: =IF(31<='前提'!$B$111,'前提'!$B$109*'前提'!$B$110/12,'前提'!$B$109*'前提'!$B$110/12) | AG70: =IF(32<='前提'!$B$111,'前提'!$B$109*'前提'!$B$110/12,'前提'!$B$109*'前提'!$B$110/12) | AH70: =IF(33<='前提'!$B$111,'前提'!$B$109*'前提'!$B$110/12,'前提'!$B$109*'前提'!$B$110/12) | AI70: =IF(34<='前提'!$B$111,'前提'!$B$109*'前提'!$B$110/12,'前提'!$B$109*'前提'!$B$110/12) | AJ70: =IF(35<='前提'!$B$111,'前提'!$B$109*'前提'!$B$110/12,'前提'!$B$109*'前提'!$B$110/12) | AK70: =IF(36<='前提'!$B$111,'前提'!$B$109*'前提'!$B$110/12,'前提'!$B$109*'前提'!$B$110/12) | AL70: =IF(37<='前提'!$B$111,'前提'!$B$109*'前提'!$B$110/12,'前提'!$B$109*'前提'!$B$110/12) | AM70: =IF(38<='前提'!$B$111,'前提'!$B$109*'前提'!$B$110/12,'前提'!$B$109*'前提'!$B$110/12) | AN70: =IF(39<='前提'!$B$111,'前提'!$B$109*'前提'!$B$110/12,'前提'!$B$109*'前提'!$B$110/12) | AO70: =IF(40<='前提'!$B$111,'前提'!$B$109*'前提'!$B$110/12,'前提'!$B$109*'前提'!$B$110/12) | AP70: =IF(41<='前提'!$B$111,'前提'!$B$109*'前提'!$B$110/12,'前提'!$B$109*'前提'!$B$110/12) | AQ70: =IF(42<='前提'!$B$111,'前提'!$B$109*'前提'!$B$110/12,'前提'!$B$109*'前提'!$B$110/12) | AR70: =IF(43<='前提'!$B$111,'前提'!$B$109*'前提'!$B$110/12,'前提'!$B$109*'前提'!$B$110/12) | AS70: =IF(44<='前提'!$B$111,'前提'!$B$109*'前提'!$B$110/12,'前提'!$B$109*'前提'!$B$110/12) | AT70: =IF(45<='前提'!$B$111,'前提'!$B$109*'前提'!$B$110/12,'前提'!$B$109*'前提'!$B$110/12) | AU70: =IF(46<='前提'!$B$111,'前提'!$B$109*'前提'!$B$110/12,'前提'!$B$109*'前提'!$B$110/12) | AV70: =IF(47<='前提'!$B$111,'前提'!$B$109*'前提'!$B$110/12,'前提'!$B$109*'前提'!$B$110/12) | AW70: =IF(48<='前提'!$B$111,'前提'!$B$109*'前提'!$B$110/12,'前提'!$B$109*'前提'!$B$110/12) | AX70: =IF(49<='前提'!$B$111,'前提'!$B$109*'前提'!$B$110/12,'前提'!$B$109*'前提'!$B$110/12) | AY70: =IF(50<='前提'!$B$111,'前提'!$B$109*'前提'!$B$110/12,'前提'!$B$109*'前提'!$B$110/12) | AZ70: =IF(51<='前提'!$B$111,'前提'!$B$109*'前提'!$B$110/12,'前提'!$B$109*'前提'!$B$110/12) | BA70: =IF(52<='前提'!$B$111,'前提'!$B$109*'前提'!$B$110/12,'前提'!$B$109*'前提'!$B$110/12) | BB70: =IF(53<='前提'!$B$111,'前提'!$B$109*'前提'!$B$110/12,'前提'!$B$109*'前提'!$B$110/12) | BC70: =IF(54<='前提'!$B$111,'前提'!$B$109*'前提'!$B$110/12,'前提'!$B$109*'前提'!$B$110/12) | BD70: =IF(55<='前提'!$B$111,'前提'!$B$109*'前提'!$B$110/12,'前提'!$B$109*'前提'!$B$110/12) | BE70: =IF(56<='前提'!$B$111,'前提'!$B$109*'前提'!$B$110/12,'前提'!$B$109*'前提'!$B$110/12) | BF70: =IF(57<='前提'!$B$111,'前提'!$B$109*'前提'!$B$110/12,'前提'!$B$109*'前提'!$B$110/12) | BG70: =IF(58<='前提'!$B$111,'前提'!$B$109*'前提'!$B$110/12,'前提'!$B$109*'前提'!$B$110/12) | BH70: =IF(59<='前提'!$B$111,'前提'!$B$109*'前提'!$B$110/12,'前提'!$B$109*'前提'!$B$110/12) | BI70: =IF(60<='前提'!$B$111,'前提'!$B$109*'前提'!$B$110/12,'前提'!$B$109*'前提'!$B$110/12)
A71: キャッシュ残高 | B71: =B69+B58-B70 | C71: =B71+C69+C58-C70 | D71: =C71+D69+D58-D70 | E71: =D71+E69+E58-E70 | F71: =E71+F69+F58-F70 | G71: =F71+G69+G58-G70 | H71: =G71+H69+H58-H70 | I71: =H71+I69+I58-I70 | J71: =I71+J69+J58-J70 | ... BI71: =BH71+BI69+BI58-BI70
A72: ランウェイ（月） | B72: =IF(B71>0,IF(B53>0,B71/B53,999),0) | C72: =IF(C71>0,IF(C53>0,C71/C53,999),0) | D72: =IF(D71>0,IF(D53>0,D71/D53,999),0) | E72: =IF(E71>0,IF(E53>0,E71/E53,999),0) | F72: =IF(F71>0,IF(F53>0,F71/F53,999),0) | G72: =IF(G71>0,IF(G53>0,G71/G53,999),0) | H72: =IF(H71>0,IF(H53>0,H71/H53,999),0) | I72: =IF(I71>0,IF(I53>0,I71/I53,999),0) | ... BI72: =IF(BI71>0,IF(BI53>0,BI71/BI53,999),0)

Sheet 年次事業計画
A1: 年次事業計画（5年）
A3: 年度 | B3: Y1 (M1-12) | C3: Y2 (M13-24) | D3: Y3 (M25-36) | E3: Y4 (M37-48) | F3: Y5 (M49-60)
A5: 【顧客数（期末）】
A6: SuguDesk期末 | B6: ='月次事業計画'!M10 | C6: ='月次事業計画'!Y10 | D6: ='月次事業計画'!AK10 | E6: ='月次事業計画'!AW10 | F6: ='月次事業計画'!BI10
A7: BPO期末 | B7: ='月次事業計画'!M14 | C7: ='月次事業計画'!Y14 | D7: ='月次事業計画'!AK14 | E7: ='月次事業計画'!AW14 | F7: ='月次事業計画'!BI14
A8: 総顧客数 | B8: ='月次事業計画'!M63 | C8: ='月次事業計画'!Y63 | D8: ='月次事業計画'!AK63 | E8: ='月次事業計画'!AW63 | F8: ='月次事業計画'!BI63
A10: 【売上】
A11: SuguDesk月額 | B11: =SUM('月次事業計画'!B17:M17) | C11: =SUM('月次事業計画'!N17:Y17) | D11: =SUM('月次事業計画'!Z17:AK17) | E11: =SUM('月次事業計画'!AL17:AW17) | F11: =SUM('月次事業計画'!AX17:BI17)
A12: BPO事務長代行 | B12: =SUM('月次事業計画'!B18:M18) | C12: =SUM('月次事業計画'!N18:Y18) | D12: =SUM('月次事業計画'!Z18:AK18) | E12: =SUM('月次事業計画'!AL18:AW18) | F12: =SUM('月次事業計画'!AX18:BI18)
A13: BPO採用/集患 | B13: =SUM('月次事業計画'!B19:M19) | C13: =SUM('月次事業計画'!N19:Y19) | D13: =SUM('月次事業計画'!Z19:AK19) | E13: =SUM('月次事業計画'!AL19:AW19) | F13: =SUM('月次事業計画'!AX19:BI19)
A14: 導入費用 | B14: =SUM('月次事業計画'!B20:M20) | C14: =SUM('月次事業計画'!N20:Y20) | D14: =SUM('月次事業計画'!Z20:AK20) | E14: =SUM('月次事業計画'!AL20:AW20) | F14: =SUM('月次事業計画'!AX20:BI20)
A15: MRR合計（年間） | B15: =SUM('月次事業計画'!B21:M21) | C15: =SUM('月次事業計画'!N21:Y21) | D15: =SUM('月次事業計画'!Z21:AK21) | E15: =SUM('月次事業計画'!AL21:AW21) | F15: =SUM('月次事業計画'!AX21:BI21)
A16: 売上合計 | B16: =SUM('月次事業計画'!B22:M22) | C16: =SUM('月次事業計画'!N22:Y22) | D16: =SUM('月次事業計画'!Z22:AK22) | E16: =SUM('月次事業計画'!AL22:AW22) | F16: =SUM('月次事業計画'!AX22:BI22)
A18: 【コスト】
A19: 直接原価 | B19: =SUM('月次事業計画'!B25:M29) | C19: =SUM('月次事業計画'!N25:Y29) | D19: =SUM('月次事業計画'!Z25:AK29) | E19: =SUM('月次事業計画'!AL25:AW29) | F19: =SUM('月次事業計画'!AX25:BI29)
A20: 人件費 | B20: =SUM('月次事業計画'!B40:M40) | C20: =SUM('月次事業計画'!N40:Y40) | D20: =SUM('月次事業計画'!Z40:AK40) | E20: =SUM('月次事業計画'!AL40:AW40) | F20: =SUM('月次事業計画'!AX40:BI40)
A21: 固定費・販管費 | B21: =SUM('月次事業計画'!B51:M51) | C21: =SUM('月次事業計画'!N51:Y51) | D21: =SUM('月次事業計画'!Z51:AK51) | E21: =SUM('月次事業計画'!AL51:AW51) | F21: =SUM('月次事業計画'!AX51:BI51)
A22: コスト合計 | B22: =SUM('月次事業計画'!B53:M53) | C22: =SUM('月次事業計画'!N53:Y53) | D22: =SUM('月次事業計画'!Z53:AK53) | E22: =SUM('月次事業計画'!AL53:AW53) | F22: =SUM('月次事業計画'!AX53:BI53)
A24: 【損益】
A25: 粗利 | B25: =SUM('月次事業計画'!B56:M56) | C25: =SUM('月次事業計画'!N56:Y56) | D25: =SUM('月次事業計画'!Z56:AK56) | E25: =SUM('月次事業計画'!AL56:AW56) | F25: =SUM('月次事業計画'!AX56:BI56)
A26: 粗利率 | B26: =IF(B16<>0,B25/B16,0) | C26: =IF(C16<>0,C25/C16,0) | D26: =IF(D16<>0,D25/D16,0) | E26: =IF(E16<>0,E25/E16,0) | F26: =IF(F16<>0,F25/F16,0)
A27: 営業利益 | B27: =B16-B22 | C27: =C16-C22 | D27: =D16-D22 | E27: =E16-E22 | F27: =F16-F22
A28: 営業利益率 | B28: =IF(B16<>0,B27/B16,0) | C28: =IF(C16<>0,C27/C16,0) | D28: =IF(D16<>0,D27/D16,0) | E28: =IF(E16<>0,E27/E16,0) | F28: =IF(F16<>0,F27/F16,0)
A29: 累積営業利益（期末） | B29: ='月次事業計画'!M60 | C29: ='月次事業計画'!Y60 | D29: ='月次事業計画'!AK60 | E29: ='月次事業計画'!AW60 | F29: ='月次事業計画'!BI60
A31: 【KPI（期末）】
A32: 期末MRR | B32: ='月次事業計画'!M21 | C32: ='月次事業計画'!Y21 | D32: ='月次事業計画'!AK21 | E32: ='月次事業計画'!AW21 | F32: ='月次事業計画'!BI21
A33: ARR | B33: ='月次事業計画'!M66 | C33: ='月次事業計画'!Y66 | D33: ='月次事業計画'!AK66 | E33: ='月次事業計画'!AW66 | F33: ='月次事業計画'!BI66
A34: 平均ARPA | B34: ='月次事業計画'!M64 | C34: ='月次事業計画'!Y64 | D34: ='月次事業計画'!AK64 | E34: ='月次事業計画'!AW64 | F34: ='月次事業計画'!BI64
A35: 期末キャッシュ | B35: ='月次事業計画'!M71 | C35: ='月次事業計画'!Y71 | D35: ='月次事業計画'!AK71 | E35: ='月次事業計画'!AW71 | F35: ='月次事業計画'!BI71
A36: ランウェイ（月） | B36: ='月次事業計画'!M72 | C36: ='月次事業計画'!Y72 | D36: ='月次事業計画'!AK72 | E36: ='月次事業計画'!AW72 | F36: ='月次事業計画'!BI72

Sheet 資本政策表
A1: 資本政策表（Misuzu条件反映）
A3: 【ラウンド別】 | B3: 設立 | C3: シード | D3: Series A
A4: プレバリュー | C4: ='前提'!B105 | D4: ='前提'!B113
A5: エクイティ調達額 | B5: ='前提'!B104 | C5: ='前提'!B106+'前提'!B107+'前提'!B108 | D5: ='前提'!B114
A6: デット（公庫） | C6: ='前提'!B109
A7: ポストバリュー | C7: =C4+C5 | D7: =D4+D5
A8: 希薄化 | C8: =C5/C7 | D8: =D5/D7
A10: 【株式数】
A11: シード株価（円/株） | C11: ='前提'!B105/'前提'!B103
A12: Oikaze 新規株数 | C12: =ROUNDDOWN('前提'!B106/C11,0)
A13: 佐藤 新規株数 | C13: =ROUNDDOWN('前提'!B107/C11,0)
A14: 洋介 新規株数 | C14: =ROUNDDOWN('前提'!B108/C11,0)
A15: シード後 発行済株数 | C15: ='前提'!B103+C12+C13+C14
A16: Series A 株価 | D16: ='前提'!B113/C15
A17: Series A 新規株数 | D17: =ROUNDDOWN('前提'!B114/D16,0)
A18: SOPプール | D18: =ROUNDDOWN((C15+D17)*'前提'!B115/(1-'前提'!B115),0)
A19: Series A後 発行済株数 | D19: =C15+D17+D18
A21: 【Cap Table 持分比率】 | B21: 設立 | C21: シード後 | D21: Series A後
A22: CEO（根来杏奈） | B22: ='前提'!B103/'前提'!B103 | C22: ='前提'!B103/C15 | D22: ='前提'!B103/D19
A23: Oikaze（みなし優先株） | C23: =C12/C15 | D23: =C12/D19
A24: 佐藤さん | C24: =C13/C15 | D24: =C13/D19
A25: 洋介さん | C25: =C14/C15 | D25: =C14/D19
A26: Series A投資家 | D26: =D17/D19
A27: SOPプール | D27: =D18/D19
A28: 合計（検算） | B28: =B22 | C28: =SUM(C22:C25) | D28: =SUM(D22:D27)
A31: 【Series Aプレバリュー別 Founder持分感度】 | B31: Pre 3億 | C31: Pre 5億 | D31: Pre 7億 | E31: Pre 10億
A32: Series A新規株数 | B32: =ROUNDDOWN('前提'!B114/(300000000/C15),0) | C32: =ROUNDDOWN('前提'!B114/(500000000/C15),0) | D32: =ROUNDDOWN('前提'!B114/(700000000/C15),0) | E32: =ROUNDDOWN('前提'!B114/(1000000000/C15),0)
A33: SOPプール | B33: =ROUNDDOWN((C15+B32)*'前提'!B115/(1-'前提'!B115),0) | C33: =ROUNDDOWN((C15+C32)*'前提'!B115/(1-'前提'!B115),0) | D33: =ROUNDDOWN((C15+D32)*'前提'!B115/(1-'前提'!B115),0) | E33: =ROUNDDOWN((C15+E32)*'前提'!B115/(1-'前提'!B115),0)
A34: SA後 発行済 | B34: =C15+B32+B33 | C34: =C15+C32+C33 | D34: =C15+D32+D33 | E34: =C15+E32+E33
A35: CEO持分 | B35: ='前提'!B103/B34 | C35: ='前提'!B103/C34 | D35: ='前提'!B103/D34 | E35: ='前提'!B103/E34
A38: 【Series A プレバリュー別必要ARR（マルチプル）】 | B38: 10x | C38: 15x | D38: 20x | E38: 30x
A39: Pre 3億 → 必要ARR | B39: =300000000/10 | C39: =300000000/15 | D39: =300000000/20 | E39: =300000000/30
A40: Pre 5億 → 必要ARR | B40: =500000000/10 | C40: =500000000/15 | D40: =500000000/20 | E40: =500000000/30
A41: Pre 7億 → 必要ARR | B41: =700000000/10 | C41: =700000000/15 | D41: =700000000/20 | E41: =700000000/30
A42: Pre 10億 → 必要ARR | B42: =1000000000/10 | C42: =1000000000/15 | D42: =1000000000/20 | E42: =1000000000/30
A44: 参考：M24 ARR（想定） | B44: ='月次事業計画'!Y66
A45: 参考：M36 ARR | B45: ='月次事業計画'!AK66

Sheet 資金使途
A1: 資金使途（シード18ヶ月）
A3: 項目 | B3: 18ヶ月合計 | C3: 比率 | D3: 備考
A4: CEO人件費 | B4: =SUM('月次事業計画'!B32:S32) | C4: =B4/$B$21
A5: エンジニア（開発） | B5: =SUM('月次事業計画'!B33:S33) | C5: =B5/$B$21
A6: 営業サポート | B6: =SUM('月次事業計画'!B34:S34) | C6: =B6/$B$21
A7: BPO人材（事務長+オペ） | B7: =SUM('月次事業計画'!B35:S35)+SUM('月次事業計画'!B36:S36) | C7: =B7/$B$21 | D7: SUM2つ
A8: CS人件費 | B8: =SUM('月次事業計画'!B37:S37) | C8: =B8/$B$21
A9: 社会保険料 | B9: =SUM('月次事業計画'!B38:S38) | C9: =B9/$B$21
A10: 福利厚生 | B10: =SUM('月次事業計画'!B39:S39) | C10: =B10/$B$21
A11: FAQ構築原価 | B11: =SUM('月次事業計画'!B25:S25) | C11: =B11/$B$21
A12: 月額メンテ原価 | B12: =SUM('月次事業計画'!B26:S26) | C12: =B12/$B$21
A13: LLM API | B13: =SUM('月次事業計画'!B27:S27) | C13: =B13/$B$21
A14: インフラ（GCP） | B14: =SUM('月次事業計画'!B28:S28) | C14: =B14/$B$21
A15: 決済手数料 | B15: =SUM('月次事業計画'!B29:S29) | C15: =B15/$B$21
A16: 広告宣伝費 | B16: =SUM('月次事業計画'!B49:S49) | C16: =B16/$B$21
A17: オフィス家賃 | B17: =SUM('月次事業計画'!B43:S43) | C17: =B17/$B$21
A18: SaaS費用 | B18: =SUM('月次事業計画'!B44:S44) | C18: =B18/$B$21
A19: 通信・会計・法務・保険 | B19: =SUM('月次事業計画'!B45:S45)+SUM('月次事業計画'!B46:S46)+SUM('月次事業計画'!B47:S47)+SUM('月次事業計画'!B48:S48) | C19: =B19/$B$21 | D19: 4項目合算
A20: その他固定費 | B20: =SUM('月次事業計画'!B50:S50) | C20: =B20/$B$21
A21: 合計 | B21: =SUM(B4:B20) | C21: =100%
A24: 【ランウェイ試算】
A25: 調達額合計（シード＋公庫） | B25: ='前提'!B106+'前提'!B107+'前提'!B108+'前提'!B109
A26: 18ヶ月バーン（コスト合計） | B26: =B21
A27: Phase1平均バーン（M1-6） | B27: =AVERAGE('月次事業計画'!B53:G53)
A28: Phase2平均バーン（M7-12） | B28: =AVERAGE('月次事業計画'!H53:M53)
A29: M12末キャッシュ | B29: ='月次事業計画'!M71
A30: M18末キャッシュ | B30: ='月次事業計画'!S71
A31: M24末キャッシュ（SeriesA前） | B31: ='月次事業計画'!Y71
