Workbook

Sheet 前提
A1: SuguDesk 事業計画 前提条件
A3: 【価格前提】
A4: 導入費用（初期） | B4: 400000 | C4: 1院あたり
A5: 月額ENTRY | B5: 25000 | C5: チャットボット基本
A6: 月額EXPAND | B6: 75000 | C6: FAQ+運用サポート
A7: 月額DEEPEN | B7: 250000 | C7: BPO込み
A8: 月次チャーン率 | B8: 0.03
A9: EXPANDアップセル率（月次） | B9: 0.15 | C9: 平均6.7ヶ月でEXPANDアップセル
A10: DEEPENアップセル率（月次） | B10: 0.05 | C10: EXPAND 20院で月1件アップセル
A12: 【営業前提（月間新規契約数）】
A13: Phase1（M1-M6） | B13: 2
A14: Phase2（M7-M12） | B14: 3
A15: Phase3（M13-M18） | B15: 8
A16: Phase4（M19-M36） | B16: 15
A17: Phase5（M37-M60） | B17: 25
A19: 【コスト前提（月額）】
A20: 代表報酬 | B20: 350000
A21: エンジニア（正社員） | B21: 700000 | C21: CTO / フルスタック
A22: CS（業務委託） | B22: 200000 | C22: FAQ構築・クライアント対応
A23: 営業人件費/人 | B23: 400000 | C23: 外注で検討
A24: LLM API変動費/院 | B24: 2000 | C24: Claude API等
A25: インフラ・ツール | B25: 100000 | C25: Dify API, AWS, SaaS
A26: その他固定費 | B26: 50000 | C26: 法務・会計・雑費
A27: 事務長 単価/人（月額） | B27: 300000 | C27: 提案・設計担当（業務委託）
A28: BPOオペ 単価/人（月額） | B28: 150000 | C28: 標準化業務の実行担当
A29: 【人員計画（人数）】
B30: エンジニア正社員 | C30: CS | D30: 営業
A31: Phase1（M1-M6） | B31: 0.5 | C31: 0 | D31: 0
A32: Phase2（M7-M12） | B32: 1 | C32: 1 | D32: 1
A33: Phase3（M13-M18） | B33: 1 | C33: 1 | D33: 1
A34: Phase4（M19-M36） | B34: 1 | C34: 2 | D34: 2
A35: Phase5（M37-M60） | B35: 1 | C35: 4 | D35: 4
A36: ※営業はPhase1内M7から1名開始
A38: 【営業ファネル前提】
A39: 商談→契約率（受注率） | B39: 0.25
A40: アプローチ→商談化率（アウトバウンド） | B40: 0.01
A41: アプローチ→商談化率（紹介） | B41: 0.3
A43: チャネル比率 | B43: Phase1 | C43: Phase2 | D43: Phase3以降
A44: 紹介比率 | B44: 0.5 | C44: 0.3 | D44: 0.2
A45: アウトバウンド比率 | B45: 0.5 | C45: 0.7 | D45: 0.8
A46: 加重平均商談化率 | B46: =B44*$B$41+B45*$B$40 -> 0.155 | C46: =C44*$B$41+C45*$B$40 -> 0.097 | D46: =D44*$B$41+D45*$B$40 -> 0.068
A48: 外注営業 月間アプローチ数/人 | B48: 120
A49: 外注営業 単価/人月 | B49: 400000
A51: 【CSキャパシティ前提】
A52: オンボーディング工数/院（時間） | B52: 30
A53: 月次運用工数/院（時間） | B53: 3
A54: CS 1名 月間稼働時間 | B54: 160
A56: AI自動化による工数削減率 | B56: Phase1 | C56: Phase2 | D56: Phase3以降
A57: AI自動化率 | B57: 0 | C57: 0.2 | D57: 0.4
A59: 【資本政策前提】
A60: 設立時株数 | B60: 1000000
A61: 設立時資本金 | B61: 1000000
A62: J-KISSキャップ | B62: 100000000 | C62: ¥1億
A63: 佐藤さん出資額 | B63: 2000000 | C63: STORES CEO
A64: ようすけさん出資額 | B64: 500000 | C64: 元リクルート役員
A65: シードプレバリュー | B65: 170000000 | C65: FIXED
A66: シード調達額 | B66: 30000000
A67: シード取得比率 | B67: 0.15 | C67: 原則15%以上
A68: 公庫借入 | C68: デット
A69: シリーズAプレバリュー | B69: 500000000 | C69: 想定
A70: シリーズA調達額 | B70: 50000000 | C70: 想定
A71: SOPプール比率 | B71: 0.067 | C71: シリーズA時に設定
A72: シリーズA調達月 | B72: 24 | C72: M24（Y2末）想定
A74: 【デッド返済前提】
A75: 公庫据置期間（月） | B75: 12 | C75: 元本返済なし、利息のみ
A76: 公庫返済期間（月） | B76: 60 | C76: 5年（元利均等）
A77: 公庫金利（年率） | B77: 0.015 | C77: 日本政策金融公庫 標準
A79: 【事務長3段階モデル】 | C79: M1-12: Anna兼務（コスト0） | D79: M13-24: 兼務@15万 段階採用 | E79: M25-36: 分業化アップセル（固定段階増） | F79: M37~: AI数式ドリブン
A80: 【事務長キャパシティ前提（M37~数式ドリブン：担当可能院数/人）】
B81: AI導入期(M37-48) | C81: AI成熟期(M49-60)
A82: ENTRY（自動提案+月1レビュー） | B82: 60 | C82: 100 | D82: AI提案書自動生成で大幅効率化
A83: EXPAND（AI分析+進捗管理） | B83: 30 | C83: 50
A84: DEEPEN（設計+品質管理） | B84: 15 | C84: 25
A85: ※ M25-36は固定段階増、M37以降で数式ドリブン
A87: 【BPOオペレーターキャパシティ前提（M37~実務：担当可能院数/人）】
B88: AI導入期(M37-48) | C88: AI成熟期(M49-60)
A89: EXPAND（AI+標準化BPO） | B89: 20 | C89: 35 | D89: AI自動入力・自動レポートで効率化
A90: DEEPEN（バックオフィス実務） | B90: 10 | C90: 18
A91: ※ M25-36は固定段階増。標準化+AI自動化で段階的効率向上

Sheet 月次事業計画
A1: SuguDesk 月次事業計画
A2: フェーズ | B2: Phase1 | C2: Phase1 | D2: Phase1 | E2: Phase1 | F2: Phase1 | G2: Phase1 | H2: Phase1 | I2: Phase1 | J2: Phase1 | K2: Phase1 | L2: Phase1 | M2: Phase1 | N2: Phase2 | O2: Phase2 | P2: Phase2 | Q2: Phase2 | R2: Phase2 | S2: Phase2 | T2: Phase2 | U2: Phase2 | V2: Phase2 | W2: Phase2 | X2: Phase2 | Y2: Phase2 | Z2: Phase3 | AA2: Phase3 | AB2: Phase3 | AC2: Phase3 | AD2: Phase3 | AE2: Phase3 | AF2: Phase3 | AG2: Phase3 | AH2: Phase3 | AI2: Phase3 | AJ2: Phase3 | AK2: Phase3 | AL2: Phase4 | AM2: Phase4 | AN2: Phase4 | AO2: Phase4 | AP2: Phase4 | AQ2: Phase4 | AR2: Phase4 | AS2: Phase4 | AT2: Phase4 | AU2: Phase4 | AV2: Phase4 | AW2: Phase4 | AX2: Phase5 | AY2: Phase5 | AZ2: Phase5 | BA2: Phase5 | BB2: Phase5 | BC2: Phase5 | BD2: Phase5 | BE2: Phase5 | BF2: Phase5 | BG2: Phase5 | BH2: Phase5 | BI2: Phase5
A3: 月 | B3: M1 | C3: M2 | D3: M3 | E3: M4 | F3: M5 | G3: M6 | H3: M7 | I3: M8 | J3: M9 | K3: M10 | L3: M11 | M3: M12 | N3: M13 | O3: M14 | P3: M15 | Q3: M16 | R3: M17 | S3: M18 | T3: M19 | U3: M20 | V3: M21 | W3: M22 | X3: M23 | Y3: M24 | Z3: M25 | AA3: M26 | AB3: M27 | AC3: M28 | AD3: M29 | AE3: M30 | AF3: M31 | AG3: M32 | AH3: M33 | AI3: M34 | AJ3: M35 | AK3: M36 | AL3: M37 | AM3: M38 | AN3: M39 | AO3: M40 | AP3: M41 | AQ3: M42 | AR3: M43 | AS3: M44 | AT3: M45 | AU3: M46 | AV3: M47 | AW3: M48 | AX3: M49 | AY3: M50 | AZ3: M51 | BA3: M52 | BB3: M53 | BC3: M54 | BD3: M55 | BE3: M56 | BF3: M57 | BG3: M58 | BH3: M59 | BI3: M60
A4: 【営業活動】
A5: 月間必要契約数 | B5: ='前提'!$B$13 -> 2 | C5: ='前提'!$B$13 -> 2 | D5: ='前提'!$B$13 -> 2 | E5: ='前提'!$B$13 -> 2 | F5: ='前提'!$B$13 -> 2 | G5: ='前提'!$B$13 -> 2 | H5: ='前提'!$B$14 -> 3 | I5: ='前提'!$B$14 -> 3 | J5: ='前提'!$B$14 -> 3 | K5: ='前提'!$B$14 -> 3 | L5: ='前提'!$B$14 -> 3 | M5: ='前提'!$B$14 -> 3 | N5: ='前提'!$B$15 -> 8 | O5: ='前提'!$B$15 -> 8 | P5: ='前提'!$B$15 -> 8 | Q5: ='前提'!$B$15 -> 8 | R5: ='前提'!$B$15 -> 8 | S5: ='前提'!$B$15 -> 8 | T5: ='前提'!$B$16 -> 15 | U5: ='前提'!$B$16 -> 15 | V5: ='前提'!$B$16 -> 15 | W5: ='前提'!$B$16 -> 15 | X5: ='前提'!$B$16 -> 15 | Y5: ='前提'!$B$16 -> 15 | Z5: ='前提'!$B$16 -> 15 | AA5: ='前提'!$B$16 -> 15 | ... AK5: ='前提'!$B$16 -> 15 | AL5: ='前提'!$B$17 -> 25 | AM5: ='前提'!$B$17 -> 25 | AN5: ='前提'!$B$17 -> 25 | AO5: ='前提'!$B$17 -> 25 | AP5: ='前提'!$B$17 -> 25 | AQ5: ='前提'!$B$17 -> 25 | AR5: ='前提'!$B$17 -> 25 | AS5: ='前提'!$B$17 -> 25 | ... BI5: ='前提'!$B$17 -> 25
A6: 必要商談数 | B6: =ROUNDUP(B5/'前提'!$B$39,0) -> 8 | C6: =ROUNDUP(C5/'前提'!$B$39,0) -> 8 | D6: =ROUNDUP(D5/'前提'!$B$39,0) -> 8 | E6: =ROUNDUP(E5/'前提'!$B$39,0) -> 8 | F6: =ROUNDUP(F5/'前提'!$B$39,0) -> 8 | G6: =ROUNDUP(G5/'前提'!$B$39,0) -> 8 | H6: =ROUNDUP(H5/'前提'!$B$39,0) -> 12 | I6: =ROUNDUP(I5/'前提'!$B$39,0) -> 12 | ... BI6: =ROUNDUP(BI5/'前提'!$B$39,0) -> 100
A7: 必要アプローチ数 | B7: =IF('前提'!$B$46>0,ROUNDUP(B6/'前提'!$B$46,0),0) -> 52 | C7: =IF('前提'!$B$46>0,ROUNDUP(C6/'前提'!$B$46,0),0) -> 52 | D7: =IF('前提'!$B$46>0,ROUNDUP(D6/'前提'!$B$46,0),0) -> 52 | E7: =IF('前提'!$B$46>0,ROUNDUP(E6/'前提'!$B$46,0),0) -> 52 | F7: =IF('前提'!$B$46>0,ROUNDUP(F6/'前提'!$B$46,0),0) -> 52 | G7: =IF('前提'!$B$46>0,ROUNDUP(G6/'前提'!$B$46,0),0) -> 52 | H7: =IF('前提'!$B$46>0,ROUNDUP(H6/'前提'!$B$46,0),0) -> 78 | I7: =IF('前提'!$B$46>0,ROUNDUP(I6/'前提'!$B$46,0),0) -> 78 | ... S7: =IF('前提'!$B$46>0,ROUNDUP(S6/'前提'!$B$46,0),0) -> 207 | T7: =IF('前提'!$C$46>0,ROUNDUP(T6/'前提'!$C$46,0),0) -> 619 | U7: =IF('前提'!$C$46>0,ROUNDUP(U6/'前提'!$C$46,0),0) -> 619 | V7: =IF('前提'!$C$46>0,ROUNDUP(V6/'前提'!$C$46,0),0) -> 619 | W7: =IF('前提'!$C$46>0,ROUNDUP(W6/'前提'!$C$46,0),0) -> 619 | X7: =IF('前提'!$C$46>0,ROUNDUP(X6/'前提'!$C$46,0),0) -> 619 | Y7: =IF('前提'!$C$46>0,ROUNDUP(Y6/'前提'!$C$46,0),0) -> 619 | Z7: =IF('前提'!$C$46>0,ROUNDUP(Z6/'前提'!$C$46,0),0) -> 619 | AA7: =IF('前提'!$C$46>0,ROUNDUP(AA6/'前提'!$C$46,0),0) -> 619 | ... AK7: =IF('前提'!$C$46>0,ROUNDUP(AK6/'前提'!$C$46,0),0) -> 619 | AL7: =IF('前提'!$D$46>0,ROUNDUP(AL6/'前提'!$D$46,0),0) -> 1471 | AM7: =IF('前提'!$D$46>0,ROUNDUP(AM6/'前提'!$D$46,0),0) -> 1471 | AN7: =IF('前提'!$D$46>0,ROUNDUP(AN6/'前提'!$D$46,0),0) -> 1471 | AO7: =IF('前提'!$D$46>0,ROUNDUP(AO6/'前提'!$D$46,0),0) -> 1471 | AP7: =IF('前提'!$D$46>0,ROUNDUP(AP6/'前提'!$D$46,0),0) -> 1471 | AQ7: =IF('前提'!$D$46>0,ROUNDUP(AQ6/'前提'!$D$46,0),0) -> 1471 | AR7: =IF('前提'!$D$46>0,ROUNDUP(AR6/'前提'!$D$46,0),0) -> 1471 | AS7: =IF('前提'!$D$46>0,ROUNDUP(AS6/'前提'!$D$46,0),0) -> 1471 | ... BI7: =IF('前提'!$D$46>0,ROUNDUP(BI6/'前提'!$D$46,0),0) -> 1471
A8: 必要外注営業人月 | B8: =IF('前提'!$B$48>0,B7/'前提'!$B$48,0) -> 0.43333333 | C8: =IF('前提'!$B$48>0,C7/'前提'!$B$48,0) -> 0.43333333 | D8: =IF('前提'!$B$48>0,D7/'前提'!$B$48,0) -> 0.43333333 | E8: =IF('前提'!$B$48>0,E7/'前提'!$B$48,0) -> 0.43333333 | F8: =IF('前提'!$B$48>0,F7/'前提'!$B$48,0) -> 0.43333333 | G8: =IF('前提'!$B$48>0,G7/'前提'!$B$48,0) -> 0.43333333 | H8: =IF('前提'!$B$48>0,H7/'前提'!$B$48,0) -> 0.65 | I8: =IF('前提'!$B$48>0,I7/'前提'!$B$48,0) -> 0.65 | ... BI8: =IF('前提'!$B$48>0,BI7/'前提'!$B$48,0) -> 12.258333
A9: 営業外注コスト | B9: =ROUNDUP(B8,0)*'前提'!$B$49 -> 400000 | C9: =ROUNDUP(C8,0)*'前提'!$B$49 -> 400000 | D9: =ROUNDUP(D8,0)*'前提'!$B$49 -> 400000 | E9: =ROUNDUP(E8,0)*'前提'!$B$49 -> 400000 | F9: =ROUNDUP(F8,0)*'前提'!$B$49 -> 400000 | G9: =ROUNDUP(G8,0)*'前提'!$B$49 -> 400000 | H9: =ROUNDUP(H8,0)*'前提'!$B$49 -> 400000 | I9: =ROUNDUP(I8,0)*'前提'!$B$49 -> 400000 | ... BI9: =ROUNDUP(BI8,0)*'前提'!$B$49 -> 5200000
A11: 【顧客数】
A12: 新規契約数 | B12: ='前提'!$B$13 -> 2 | C12: ='前提'!$B$13 -> 2 | D12: ='前提'!$B$13 -> 2 | E12: ='前提'!$B$13 -> 2 | F12: ='前提'!$B$13 -> 2 | G12: ='前提'!$B$13 -> 2 | H12: ='前提'!$B$14 -> 3 | I12: ='前提'!$B$14 -> 3 | J12: ='前提'!$B$14 -> 3 | K12: ='前提'!$B$14 -> 3 | L12: ='前提'!$B$14 -> 3 | M12: ='前提'!$B$14 -> 3 | N12: ='前提'!$B$15 -> 8 | O12: ='前提'!$B$15 -> 8 | P12: ='前提'!$B$15 -> 8 | Q12: ='前提'!$B$15 -> 8 | R12: ='前提'!$B$15 -> 8 | S12: ='前提'!$B$15 -> 8 | T12: ='前提'!$B$16 -> 15 | U12: ='前提'!$B$16 -> 15 | V12: ='前提'!$B$16 -> 15 | W12: ='前提'!$B$16 -> 15 | X12: ='前提'!$B$16 -> 15 | Y12: ='前提'!$B$16 -> 15 | Z12: ='前提'!$B$16 -> 15 | AA12: ='前提'!$B$16 -> 15 | ... AK12: ='前提'!$B$16 -> 15 | AL12: ='前提'!$B$17 -> 25 | AM12: ='前提'!$B$17 -> 25 | AN12: ='前提'!$B$17 -> 25 | AO12: ='前提'!$B$17 -> 25 | AP12: ='前提'!$B$17 -> 25 | AQ12: ='前提'!$B$17 -> 25 | AR12: ='前提'!$B$17 -> 25 | AS12: ='前提'!$B$17 -> 25 | ... BI12: ='前提'!$B$17 -> 25
A13: 解約数 | B13: =ROUNDDOWN(B14*'前提'!$B$8,0) -> 0 | C13: =ROUNDDOWN(C14*'前提'!$B$8,0) -> 0 | D13: =ROUNDDOWN(D14*'前提'!$B$8,0) -> 0 | E13: =ROUNDDOWN(E14*'前提'!$B$8,0) -> 0 | F13: =ROUNDDOWN(F14*'前提'!$B$8,0) -> 0 | G13: =ROUNDDOWN(G14*'前提'!$B$8,0) -> 0 | H13: =ROUNDDOWN(H14*'前提'!$B$8,0) -> 0 | I13: =ROUNDDOWN(I14*'前提'!$B$8,0) -> 0 | ... BI13: =ROUNDDOWN(BI14*'前提'!$B$8,0) -> 16
A14: 期首顧客数 | B14: 1 | C14: =B15 -> 3 | D14: =C15 -> 5 | E14: =D15 -> 7 | F14: =E15 -> 9 | G14: =F15 -> 11 | H14: =G15 -> 13 | I14: =H15 -> 16 | J14: =I15 -> 19 | ... BI14: =BH15 -> 558
A15: 期末顧客数 | B15: =B14+B12-B13 -> 3 | C15: =C14+C12-C13 -> 5 | D15: =D14+D12-D13 -> 7 | E15: =E14+E12-E13 -> 9 | F15: =F14+F12-F13 -> 11 | G15: =G14+G12-G13 -> 13 | H15: =H14+H12-H13 -> 16 | I15: =I14+I12-I13 -> 19 | ... BI15: =BI14+BI12-BI13 -> 567
A16: ENTRY | B16: =B15 -> 3 | C16: =MAX(0,B16+C12-ROUNDDOWN(B16*'前提'!$B$8,0)-ROUNDDOWN(B16*'前提'!$B$9,0)) -> 5 | D16: =MAX(0,C16+D12-ROUNDDOWN(C16*'前提'!$B$8,0)-ROUNDDOWN(C16*'前提'!$B$9,0)) -> 7 | E16: =MAX(0,D16+E12-ROUNDDOWN(D16*'前提'!$B$8,0)-ROUNDDOWN(D16*'前提'!$B$9,0)) -> 8 | F16: =MAX(0,E16+F12-ROUNDDOWN(E16*'前提'!$B$8,0)-ROUNDDOWN(E16*'前提'!$B$9,0)) -> 9 | G16: =MAX(0,F16+G12-ROUNDDOWN(F16*'前提'!$B$8,0)-ROUNDDOWN(F16*'前提'!$B$9,0)) -> 10 | H16: =MAX(0,G16+H12-ROUNDDOWN(G16*'前提'!$B$8,0)-ROUNDDOWN(G16*'前提'!$B$9,0)) -> 12 | I16: =MAX(0,H16+I12-ROUNDDOWN(H16*'前提'!$B$8,0)-ROUNDDOWN(H16*'前提'!$B$9,0)) -> 14 | J16: =MAX(0,I16+J12-ROUNDDOWN(I16*'前提'!$B$8,0)-ROUNDDOWN(I16*'前提'!$B$9,0)) -> 15 | ... BI16: =MAX(0,BH16+BI12-ROUNDDOWN(BH16*'前提'!$B$8,0)-ROUNDDOWN(BH16*'前提'!$B$9,0)) -> 140
A17: EXPAND | B17: 0 | C17: =MAX(0,B17+ROUNDDOWN(B16*'前提'!$B$9,0)-ROUNDDOWN(B17*'前提'!$B$8,0)-ROUNDDOWN(B17*'前提'!$B$10,0)) -> 0 | D17: =MAX(0,C17+ROUNDDOWN(C16*'前提'!$B$9,0)-ROUNDDOWN(C17*'前提'!$B$8,0)-ROUNDDOWN(C17*'前提'!$B$10,0)) -> 0 | E17: =MAX(0,D17+ROUNDDOWN(D16*'前提'!$B$9,0)-ROUNDDOWN(D17*'前提'!$B$8,0)-ROUNDDOWN(D17*'前提'!$B$10,0)) -> 1 | F17: =MAX(0,E17+ROUNDDOWN(E16*'前提'!$B$9,0)-ROUNDDOWN(E17*'前提'!$B$8,0)-ROUNDDOWN(E17*'前提'!$B$10,0)) -> 2 | G17: =MAX(0,F17+ROUNDDOWN(F16*'前提'!$B$9,0)-ROUNDDOWN(F17*'前提'!$B$8,0)-ROUNDDOWN(F17*'前提'!$B$10,0)) -> 3 | H17: =MAX(0,G17+ROUNDDOWN(G16*'前提'!$B$9,0)-ROUNDDOWN(G17*'前提'!$B$8,0)-ROUNDDOWN(G17*'前提'!$B$10,0)) -> 4 | I17: =MAX(0,H17+ROUNDDOWN(H16*'前提'!$B$9,0)-ROUNDDOWN(H17*'前提'!$B$8,0)-ROUNDDOWN(H17*'前提'!$B$10,0)) -> 5 | J17: =MAX(0,I17+ROUNDDOWN(I16*'前提'!$B$9,0)-ROUNDDOWN(I17*'前提'!$B$8,0)-ROUNDDOWN(I17*'前提'!$B$10,0)) -> 7 | ... BI17: =MAX(0,BH17+ROUNDDOWN(BH16*'前提'!$B$9,0)-ROUNDDOWN(BH17*'前提'!$B$8,0)-ROUNDDOWN(BH17*'前提'!$B$10,0)) -> 245
A18: DEEPEN | B18: 0 | C18: =MAX(0,B18+ROUNDDOWN(B17*'前提'!$B$10,0)-ROUNDDOWN(B18*'前提'!$B$8,0)) -> 0 | D18: =MAX(0,C18+ROUNDDOWN(C17*'前提'!$B$10,0)-ROUNDDOWN(C18*'前提'!$B$8,0)) -> 0 | E18: =MAX(0,D18+ROUNDDOWN(D17*'前提'!$B$10,0)-ROUNDDOWN(D18*'前提'!$B$8,0)) -> 0 | F18: =MAX(0,E18+ROUNDDOWN(E17*'前提'!$B$10,0)-ROUNDDOWN(E18*'前提'!$B$8,0)) -> 0 | G18: =MAX(0,F18+ROUNDDOWN(F17*'前提'!$B$10,0)-ROUNDDOWN(F18*'前提'!$B$8,0)) -> 0 | H18: =MAX(0,G18+ROUNDDOWN(G17*'前提'!$B$10,0)-ROUNDDOWN(G18*'前提'!$B$8,0)) -> 0 | I18: =MAX(0,H18+ROUNDDOWN(H17*'前提'!$B$10,0)-ROUNDDOWN(H18*'前提'!$B$8,0)) -> 0 | J18: =MAX(0,I18+ROUNDDOWN(I17*'前提'!$B$10,0)-ROUNDDOWN(I18*'前提'!$B$8,0)) -> 0 | ... BI18: =MAX(0,BH18+ROUNDDOWN(BH17*'前提'!$B$10,0)-ROUNDDOWN(BH18*'前提'!$B$8,0)) -> 200
A20: 【売上】
A21: ENTRY月額売上 | B21: =B16*'前提'!$B$5 -> 75000 | C21: =C16*'前提'!$B$5 -> 125000 | D21: =D16*'前提'!$B$5 -> 175000 | E21: =E16*'前提'!$B$5 -> 200000 | F21: =F16*'前提'!$B$5 -> 225000 | G21: =G16*'前提'!$B$5 -> 250000 | H21: =H16*'前提'!$B$5 -> 300000 | I21: =I16*'前提'!$B$5 -> 350000 | ... BI21: =BI16*'前提'!$B$5 -> 3500000
A22: EXPAND月額売上 | B22: =B17*'前提'!$B$6 -> 0 | C22: =C17*'前提'!$B$6 -> 0 | D22: =D17*'前提'!$B$6 -> 0 | E22: =E17*'前提'!$B$6 -> 75000 | F22: =F17*'前提'!$B$6 -> 150000 | G22: =G17*'前提'!$B$6 -> 225000 | H22: =H17*'前提'!$B$6 -> 300000 | I22: =I17*'前提'!$B$6 -> 375000 | ... BI22: =BI17*'前提'!$B$6 -> 18375000
A23: DEEPEN月額売上 | B23: =B18*'前提'!$B$7 -> 0 | C23: =C18*'前提'!$B$7 -> 0 | D23: =D18*'前提'!$B$7 -> 0 | E23: =E18*'前提'!$B$7 -> 0 | F23: =F18*'前提'!$B$7 -> 0 | G23: =G18*'前提'!$B$7 -> 0 | H23: =H18*'前提'!$B$7 -> 0 | I23: =I18*'前提'!$B$7 -> 0 | ... BI23: =BI18*'前提'!$B$7 -> 50000000
A24: 月額売上小計 | B24: =B21+B22+B23 -> 75000 | C24: =C21+C22+C23 -> 125000 | D24: =D21+D22+D23 -> 175000 | E24: =E21+E22+E23 -> 275000 | F24: =F21+F22+F23 -> 375000 | G24: =G21+G22+G23 -> 475000 | H24: =H21+H22+H23 -> 600000 | I24: =I21+I22+I23 -> 725000 | ... BI24: =BI21+BI22+BI23 -> 71875000
A25: 導入費用 | B25: =B12*'前提'!$B$4 -> 800000 | C25: =C12*'前提'!$B$4 -> 800000 | D25: =D12*'前提'!$B$4 -> 800000 | E25: =E12*'前提'!$B$4 -> 800000 | F25: =F12*'前提'!$B$4 -> 800000 | G25: =G12*'前提'!$B$4 -> 800000 | H25: =H12*'前提'!$B$4 -> 1200000 | I25: =I12*'前提'!$B$4 -> 1200000 | ... BI25: =BI12*'前提'!$B$4 -> 10000000
A26: 売上合計 | B26: =B24+B25 -> 875000 | C26: =C24+C25 -> 925000 | D26: =D24+D25 -> 975000 | E26: =E24+E25 -> 1075000 | F26: =F24+F25 -> 1175000 | G26: =G24+G25 -> 1275000 | H26: =H24+H25 -> 1800000 | I26: =I24+I25 -> 1925000 | ... BI26: =BI24+BI25 -> 81875000
A27: MRR | B27: =B24 -> 75000 | C27: =C24 -> 125000 | D27: =D24 -> 175000 | E27: =E24 -> 275000 | F27: =F24 -> 375000 | G27: =G24 -> 475000 | H27: =H24 -> 600000 | I27: =I24 -> 725000 | ... BI27: =BI24 -> 71875000
A29: 【コスト】
A30: 代表報酬 | B30: ='前提'!$B$20 -> 350000 | C30: ='前提'!$B$20 -> 350000 | D30: ='前提'!$B$20 -> 350000 | E30: ='前提'!$B$20 -> 350000 | F30: ='前提'!$B$20 -> 350000 | G30: ='前提'!$B$20 -> 350000 | H30: ='前提'!$B$20 -> 350000 | I30: ='前提'!$B$20 -> 350000 | ... BI30: ='前提'!$B$20 -> 350000
A31: エンジニア（正社員） | B31: ='前提'!$B$21*'前提'!$B$31 -> 350000 | C31: ='前提'!$B$21*'前提'!$B$31 -> 350000 | D31: ='前提'!$B$21*'前提'!$B$31 -> 350000 | E31: ='前提'!$B$21*'前提'!$B$31 -> 350000 | F31: ='前提'!$B$21*'前提'!$B$31 -> 350000 | G31: ='前提'!$B$21*'前提'!$B$31 -> 350000 | H31: ='前提'!$B$21*'前提'!$B$32 -> 700000 | I31: ='前提'!$B$21*'前提'!$B$32 -> 700000 | J31: ='前提'!$B$21*'前提'!$B$32 -> 700000 | K31: ='前提'!$B$21*'前提'!$B$32 -> 700000 | L31: ='前提'!$B$21*'前提'!$B$32 -> 700000 | M31: ='前提'!$B$21*'前提'!$B$32 -> 700000 | N31: ='前提'!$B$21*'前提'!$B$33 -> 700000 | O31: ='前提'!$B$21*'前提'!$B$33 -> 700000 | P31: ='前提'!$B$21*'前提'!$B$33 -> 700000 | Q31: ='前提'!$B$21*'前提'!$B$33 -> 700000 | R31: ='前提'!$B$21*'前提'!$B$33 -> 700000 | S31: ='前提'!$B$21*'前提'!$B$33 -> 700000 | T31: ='前提'!$B$21*'前提'!$B$34 -> 700000 | U31: ='前提'!$B$21*'前提'!$B$34 -> 700000 | V31: ='前提'!$B$21*'前提'!$B$34 -> 700000 | W31: ='前提'!$B$21*'前提'!$B$34 -> 700000 | X31: ='前提'!$B$21*'前提'!$B$34 -> 700000 | Y31: ='前提'!$B$21*'前提'!$B$34 -> 700000 | Z31: ='前提'!$B$21*'前提'!$B$34 -> 700000 | AA31: ='前提'!$B$21*'前提'!$B$34 -> 700000 | ... AK31: ='前提'!$B$21*'前提'!$B$34 -> 700000 | AL31: ='前提'!$B$21*'前提'!$B$35 -> 700000 | AM31: ='前提'!$B$21*'前提'!$B$35 -> 700000 | AN31: ='前提'!$B$21*'前提'!$B$35 -> 700000 | AO31: ='前提'!$B$21*'前提'!$B$35 -> 700000 | AP31: ='前提'!$B$21*'前提'!$B$35 -> 700000 | AQ31: ='前提'!$B$21*'前提'!$B$35 -> 700000 | AR31: ='前提'!$B$21*'前提'!$B$35 -> 700000 | AS31: ='前提'!$B$21*'前提'!$B$35 -> 700000 | ... BI31: ='前提'!$B$21*'前提'!$B$35 -> 700000
A32: 開発外注 | B32: 0 | C32: 0 | D32: 0 | E32: 0 | F32: 0 | G32: 0 | H32: 0 | I32: 0 | J32: 0 | K32: 0 | L32: 0 | M32: 0 | N32: 0 | O32: 0 | P32: 0 | Q32: 0 | R32: 0 | S32: 0 | T32: 300000 | U32: 300000 | V32: 300000 | W32: 300000 | X32: 300000 | Y32: 300000 | Z32: 300000 | AA32: 300000 | AB32: 300000 | AC32: 300000 | AD32: 300000 | AE32: 300000 | AF32: 300000 | AG32: 300000 | AH32: 300000 | AI32: 300000 | AJ32: 300000 | AK32: 300000 | AL32: 500000 | AM32: 500000 | AN32: 500000 | AO32: 500000 | AP32: 500000 | AQ32: 500000 | AR32: 500000 | AS32: 500000 | AT32: 500000 | AU32: 500000 | AV32: 500000 | AW32: 500000 | AX32: 500000 | AY32: 500000 | AZ32: 500000 | BA32: 500000 | BB32: 500000 | BC32: 500000 | BD32: 500000 | BE32: 500000 | BF32: 500000 | BG32: 500000 | BH32: 500000 | BI32: 500000
A33: CS人件費 | B33: 0 | C33: 0 | D33: 0 | E33: 0 | F33: 0 | G33: 0 | H33: ='前提'!$B$22*'前提'!$C$32 -> 200000 | I33: ='前提'!$B$22*'前提'!$C$32 -> 200000 | J33: ='前提'!$B$22*'前提'!$C$32 -> 200000 | K33: ='前提'!$B$22*'前提'!$C$32 -> 200000 | L33: ='前提'!$B$22*'前提'!$C$32 -> 200000 | M33: ='前提'!$B$22*'前提'!$C$32 -> 200000 | N33: ='前提'!$B$22*'前提'!$C$33 -> 200000 | O33: ='前提'!$B$22*'前提'!$C$33 -> 200000 | P33: ='前提'!$B$22*'前提'!$C$33 -> 200000 | Q33: ='前提'!$B$22*'前提'!$C$33 -> 200000 | R33: ='前提'!$B$22*'前提'!$C$33 -> 200000 | S33: ='前提'!$B$22*'前提'!$C$33 -> 200000 | T33: ='前提'!$B$22*'前提'!$C$34 -> 400000 | U33: ='前提'!$B$22*'前提'!$C$34 -> 400000 | V33: ='前提'!$B$22*'前提'!$C$34 -> 400000 | W33: ='前提'!$B$22*'前提'!$C$34 -> 400000 | X33: ='前提'!$B$22*'前提'!$C$34 -> 400000 | Y33: ='前提'!$B$22*'前提'!$C$34 -> 400000 | Z33: ='前提'!$B$22*'前提'!$C$34 -> 400000 | AA33: ='前提'!$B$22*'前提'!$C$34 -> 400000 | ... AK33: ='前提'!$B$22*'前提'!$C$34 -> 400000 | AL33: ='前提'!$B$22*'前提'!$C$35 -> 800000 | AM33: ='前提'!$B$22*'前提'!$C$35 -> 800000 | AN33: ='前提'!$B$22*'前提'!$C$35 -> 800000 | AO33: ='前提'!$B$22*'前提'!$C$35 -> 800000 | AP33: ='前提'!$B$22*'前提'!$C$35 -> 800000 | AQ33: ='前提'!$B$22*'前提'!$C$35 -> 800000 | AR33: ='前提'!$B$22*'前提'!$C$35 -> 800000 | AS33: ='前提'!$B$22*'前提'!$C$35 -> 800000 | ... BI33: ='前提'!$B$22*'前提'!$C$35 -> 800000
A34: 営業人件費（社員） | B34: 0 | C34: 0 | D34: 0 | E34: 0 | F34: 0 | G34: 0 | H34: ='前提'!$B$23*'前提'!$D$32 -> 400000 | I34: ='前提'!$B$23*'前提'!$D$32 -> 400000 | J34: ='前提'!$B$23*'前提'!$D$32 -> 400000 | K34: ='前提'!$B$23*'前提'!$D$32 -> 400000 | L34: ='前提'!$B$23*'前提'!$D$32 -> 400000 | M34: ='前提'!$B$23*'前提'!$D$32 -> 400000 | N34: ='前提'!$B$23*'前提'!$D$33 -> 400000 | O34: ='前提'!$B$23*'前提'!$D$33 -> 400000 | P34: ='前提'!$B$23*'前提'!$D$33 -> 400000 | Q34: ='前提'!$B$23*'前提'!$D$33 -> 400000 | R34: ='前提'!$B$23*'前提'!$D$33 -> 400000 | S34: ='前提'!$B$23*'前提'!$D$33 -> 400000 | T34: ='前提'!$B$23*'前提'!$D$34 -> 800000 | U34: ='前提'!$B$23*'前提'!$D$34 -> 800000 | V34: ='前提'!$B$23*'前提'!$D$34 -> 800000 | W34: ='前提'!$B$23*'前提'!$D$34 -> 800000 | X34: ='前提'!$B$23*'前提'!$D$34 -> 800000 | Y34: ='前提'!$B$23*'前提'!$D$34 -> 800000 | Z34: ='前提'!$B$23*'前提'!$D$34 -> 800000 | AA34: ='前提'!$B$23*'前提'!$D$34 -> 800000 | ... AK34: ='前提'!$B$23*'前提'!$D$34 -> 800000 | AL34: ='前提'!$B$23*'前提'!$D$35 -> 1600000 | AM34: ='前提'!$B$23*'前提'!$D$35 -> 1600000 | AN34: ='前提'!$B$23*'前提'!$D$35 -> 1600000 | AO34: ='前提'!$B$23*'前提'!$D$35 -> 1600000 | AP34: ='前提'!$B$23*'前提'!$D$35 -> 1600000 | AQ34: ='前提'!$B$23*'前提'!$D$35 -> 1600000 | AR34: ='前提'!$B$23*'前提'!$D$35 -> 1600000 | AS34: ='前提'!$B$23*'前提'!$D$35 -> 1600000 | ... BI34: ='前提'!$B$23*'前提'!$D$35 -> 1600000
A35: 営業外注費 | B35: =B9 -> 400000 | C35: =C9 -> 400000 | D35: =D9 -> 400000 | E35: =E9 -> 400000 | F35: =F9 -> 400000 | G35: =G9 -> 400000 | H35: =H9 -> 400000 | I35: =I9 -> 400000 | ... BI35: =BI9 -> 5200000
A36: LLM API変動費 | B36: =B15*'前提'!$B$24 -> 6000 | C36: =C15*'前提'!$B$24 -> 10000 | D36: =D15*'前提'!$B$24 -> 14000 | E36: =E15*'前提'!$B$24 -> 18000 | F36: =F15*'前提'!$B$24 -> 22000 | G36: =G15*'前提'!$B$24 -> 26000 | H36: =H15*'前提'!$B$24 -> 32000 | I36: =I15*'前提'!$B$24 -> 38000 | ... BI36: =BI15*'前提'!$B$24 -> 1134000
A37: 事務長（提案・設計） | B37: 0 | C37: 0 | D37: 0 | E37: 0 | F37: 0 | G37: 0 | H37: 0 | I37: 0 | J37: 0 | K37: 0 | L37: 0 | M37: 0 | N37: 300000 | O37: 300000 | P37: 300000 | Q37: 450000 | R37: 450000 | S37: 450000 | T37: 600000 | U37: 600000 | V37: 600000 | W37: 750000 | X37: 750000 | Y37: 750000 | Z37: 1800000 | AA37: 2100000 | AB37: 2400000 | AC37: 2700000 | AD37: 3000000 | AE37: 3300000 | AF37: 3600000 | AG37: 3900000 | AH37: 4200000 | AI37: 4500000 | AJ37: 4800000 | AK37: 5100000 | AL37: =ROUNDUP(AL16/'前提'!$B$82+AL17/'前提'!$B$83+AL18/'前提'!$B$84,0)*'前提'!$B$27 -> 3300000 | AM37: =ROUNDUP(AM16/'前提'!$B$82+AM17/'前提'!$B$83+AM18/'前提'!$B$84,0)*'前提'!$B$27 -> 3300000 | AN37: =ROUNDUP(AN16/'前提'!$B$82+AN17/'前提'!$B$83+AN18/'前提'!$B$84,0)*'前提'!$B$27 -> 3600000 | AO37: =ROUNDUP(AO16/'前提'!$B$82+AO17/'前提'!$B$83+AO18/'前提'!$B$84,0)*'前提'!$B$27 -> 3900000 | AP37: =ROUNDUP(AP16/'前提'!$B$82+AP17/'前提'!$B$83+AP18/'前提'!$B$84,0)*'前提'!$B$27 -> 3900000 | AQ37: =ROUNDUP(AQ16/'前提'!$B$82+AQ17/'前提'!$B$83+AQ18/'前提'!$B$84,0)*'前提'!$B$27 -> 4200000 | AR37: =ROUNDUP(AR16/'前提'!$B$82+AR17/'前提'!$B$83+AR18/'前提'!$B$84,0)*'前提'!$B$27 -> 4500000 | AS37: =ROUNDUP(AS16/'前提'!$B$82+AS17/'前提'!$B$83+AS18/'前提'!$B$84,0)*'前提'!$B$27 -> 4500000 | ... AW37: =ROUNDUP(AW16/'前提'!$B$82+AW17/'前提'!$B$83+AW18/'前提'!$B$84,0)*'前提'!$B$27 -> 5400000 | AX37: =ROUNDUP(AX16/'前提'!$C$82+AX17/'前提'!$C$83+AX18/'前提'!$C$84,0)*'前提'!$B$27 -> 3300000 | AY37: =ROUNDUP(AY16/'前提'!$C$82+AY17/'前提'!$C$83+AY18/'前提'!$C$84,0)*'前提'!$B$27 -> 3300000 | AZ37: =ROUNDUP(AZ16/'前提'!$C$82+AZ17/'前提'!$C$83+AZ18/'前提'!$C$84,0)*'前提'!$B$27 -> 3600000 | BA37: =ROUNDUP(BA16/'前提'!$C$82+BA17/'前提'!$C$83+BA18/'前提'!$C$84,0)*'前提'!$B$27 -> 3600000 | BB37: =ROUNDUP(BB16/'前提'!$C$82+BB17/'前提'!$C$83+BB18/'前提'!$C$84,0)*'前提'!$B$27 -> 3900000 | BC37: =ROUNDUP(BC16/'前提'!$C$82+BC17/'前提'!$C$83+BC18/'前提'!$C$84,0)*'前提'!$B$27 -> 3900000 | BD37: =ROUNDUP(BD16/'前提'!$C$82+BD17/'前提'!$C$83+BD18/'前提'!$C$84,0)*'前提'!$B$27 -> 3900000 | BE37: =ROUNDUP(BE16/'前提'!$C$82+BE17/'前提'!$C$83+BE18/'前提'!$C$84,0)*'前提'!$B$27 -> 4200000 | ... BI37: =ROUNDUP(BI16/'前提'!$C$82+BI17/'前提'!$C$83+BI18/'前提'!$C$84,0)*'前提'!$B$27 -> 4500000
A38: BPOオペレーター | B38: 0 | C38: 0 | D38: 0 | E38: 0 | F38: 0 | G38: 0 | H38: 0 | I38: 0 | J38: 0 | K38: 0 | L38: 0 | M38: 0 | N38: 0 | O38: 0 | P38: 0 | Q38: 0 | R38: 0 | S38: 0 | T38: 0 | U38: 0 | V38: 0 | W38: 0 | X38: 0 | Y38: 0 | Z38: 450000 | AA38: 600000 | AB38: 750000 | AC38: 900000 | AD38: 1050000 | AE38: 1200000 | AF38: 1350000 | AG38: 1500000 | AH38: 1650000 | AI38: 1800000 | AJ38: 1950000 | AK38: 2100000 | AL38: =IF(AL17+AL18>0,ROUNDUP(AL17/'前提'!$B$89+AL18/'前提'!$B$90,0)*'前提'!$B$28,0) -> 2100000 | AM38: =IF(AM17+AM18>0,ROUNDUP(AM17/'前提'!$B$89+AM18/'前提'!$B$90,0)*'前提'!$B$28,0) -> 2100000 | AN38: =IF(AN17+AN18>0,ROUNDUP(AN17/'前提'!$B$89+AN18/'前提'!$B$90,0)*'前提'!$B$28,0) -> 2250000 | AO38: =IF(AO17+AO18>0,ROUNDUP(AO17/'前提'!$B$89+AO18/'前提'!$B$90,0)*'前提'!$B$28,0) -> 2400000 | AP38: =IF(AP17+AP18>0,ROUNDUP(AP17/'前提'!$B$89+AP18/'前提'!$B$90,0)*'前提'!$B$28,0) -> 2400000 | AQ38: =IF(AQ17+AQ18>0,ROUNDUP(AQ17/'前提'!$B$89+AQ18/'前提'!$B$90,0)*'前提'!$B$28,0) -> 2550000 | AR38: =IF(AR17+AR18>0,ROUNDUP(AR17/'前提'!$B$89+AR18/'前提'!$B$90,0)*'前提'!$B$28,0) -> 2700000 | AS38: =IF(AS17+AS18>0,ROUNDUP(AS17/'前提'!$B$89+AS18/'前提'!$B$90,0)*'前提'!$B$28,0) -> 2850000 | ... AW38: =IF(AW17+AW18>0,ROUNDUP(AW17/'前提'!$B$89+AW18/'前提'!$B$90,0)*'前提'!$B$28,0) -> 3450000 | AX38: =IF(AX17+AX18>0,ROUNDUP(AX17/'前提'!$C$89+AX18/'前提'!$C$90,0)*'前提'!$B$28,0) -> 1950000 | AY38: =IF(AY17+AY18>0,ROUNDUP(AY17/'前提'!$C$89+AY18/'前提'!$C$90,0)*'前提'!$B$28,0) -> 2100000 | AZ38: =IF(AZ17+AZ18>0,ROUNDUP(AZ17/'前提'!$C$89+AZ18/'前提'!$C$90,0)*'前提'!$B$28,0) -> 2100000 | BA38: =IF(BA17+BA18>0,ROUNDUP(BA17/'前提'!$C$89+BA18/'前提'!$C$90,0)*'前提'!$B$28,0) -> 2250000 | BB38: =IF(BB17+BB18>0,ROUNDUP(BB17/'前提'!$C$89+BB18/'前提'!$C$90,0)*'前提'!$B$28,0) -> 2250000 | BC38: =IF(BC17+BC18>0,ROUNDUP(BC17/'前提'!$C$89+BC18/'前提'!$C$90,0)*'前提'!$B$28,0) -> 2400000 | BD38: =IF(BD17+BD18>0,ROUNDUP(BD17/'前提'!$C$89+BD18/'前提'!$C$90,0)*'前提'!$B$28,0) -> 2400000 | BE38: =IF(BE17+BE18>0,ROUNDUP(BE17/'前提'!$C$89+BE18/'前提'!$C$90,0)*'前提'!$B$28,0) -> 2550000 | ... BI38: =IF(BI17+BI18>0,ROUNDUP(BI17/'前提'!$C$89+BI18/'前提'!$C$90,0)*'前提'!$B$28,0) -> 2850000
A39: インフラ・ツール | B39: ='前提'!$B$25 -> 100000 | C39: ='前提'!$B$25 -> 100000 | D39: ='前提'!$B$25 -> 100000 | E39: ='前提'!$B$25 -> 100000 | F39: ='前提'!$B$25 -> 100000 | G39: ='前提'!$B$25 -> 100000 | H39: ='前提'!$B$25 -> 100000 | I39: ='前提'!$B$25 -> 100000 | ... BI39: ='前提'!$B$25 -> 100000
A40: その他固定費 | B40: ='前提'!$B$26 -> 50000 | C40: ='前提'!$B$26 -> 50000 | D40: ='前提'!$B$26 -> 50000 | E40: ='前提'!$B$26 -> 50000 | F40: ='前提'!$B$26 -> 50000 | G40: ='前提'!$B$26 -> 50000 | H40: ='前提'!$B$26 -> 50000 | I40: ='前提'!$B$26 -> 50000 | ... BI40: ='前提'!$B$26 -> 50000
A42: コスト合計 | B42: =B30+B31+B32+B33+B34+B35+B36+B37+B38+B39+B40 -> 1256000 | C42: =C30+C31+C32+C33+C34+C35+C36+C37+C38+C39+C40 -> 1260000 | D42: =D30+D31+D32+D33+D34+D35+D36+D37+D38+D39+D40 -> 1264000 | E42: =E30+E31+E32+E33+E34+E35+E36+E37+E38+E39+E40 -> 1268000 | F42: =F30+F31+F32+F33+F34+F35+F36+F37+F38+F39+F40 -> 1272000 | G42: =G30+G31+G32+G33+G34+G35+G36+G37+G38+G39+G40 -> 1276000 | H42: =H30+H31+H32+H33+H34+H35+H36+H37+H38+H39+H40 -> 2232000 | I42: =I30+I31+I32+I33+I34+I35+I36+I37+I38+I39+I40 -> 2238000 | ... BI42: =BI30+BI31+BI32+BI33+BI34+BI35+BI36+BI37+BI38+BI39+BI40 -> 17784000
A44: 【CS工数試算】
A45: オンボーディング工数 | B45: =B12*'前提'!$B$52 -> 60 | C45: =C12*'前提'!$B$52 -> 60 | D45: =D12*'前提'!$B$52 -> 60 | E45: =E12*'前提'!$B$52 -> 60 | F45: =F12*'前提'!$B$52 -> 60 | G45: =G12*'前提'!$B$52 -> 60 | H45: =H12*'前提'!$B$52 -> 90 | I45: =I12*'前提'!$B$52 -> 90 | ... BI45: =BI12*'前提'!$B$52 -> 750
A46: 月次運用工数 | B46: =B15*'前提'!$B$53 -> 9 | C46: =C15*'前提'!$B$53 -> 15 | D46: =D15*'前提'!$B$53 -> 21 | E46: =E15*'前提'!$B$53 -> 27 | F46: =F15*'前提'!$B$53 -> 33 | G46: =G15*'前提'!$B$53 -> 39 | H46: =H15*'前提'!$B$53 -> 48 | I46: =I15*'前提'!$B$53 -> 57 | ... BI46: =BI15*'前提'!$B$53 -> 1701
A47: 合計必要工数 | B47: =B45+B46 -> 69 | C47: =C45+C46 -> 75 | D47: =D45+D46 -> 81 | E47: =E45+E46 -> 87 | F47: =F45+F46 -> 93 | G47: =G45+G46 -> 99 | H47: =H45+H46 -> 138 | I47: =I45+I46 -> 147 | ... BI47: =BI45+BI46 -> 2451
A48: AI自動化率 | B48: ='前提'!$B$57 -> 0 | C48: ='前提'!$B$57 -> 0 | D48: ='前提'!$B$57 -> 0 | E48: ='前提'!$B$57 -> 0 | F48: ='前提'!$B$57 -> 0 | G48: ='前提'!$B$57 -> 0 | H48: ='前提'!$B$57 -> 0 | I48: ='前提'!$B$57 -> 0 | ... S48: ='前提'!$B$57 -> 0 | T48: ='前提'!$C$57 -> 0.2 | U48: ='前提'!$C$57 -> 0.2 | V48: ='前提'!$C$57 -> 0.2 | W48: ='前提'!$C$57 -> 0.2 | X48: ='前提'!$C$57 -> 0.2 | Y48: ='前提'!$C$57 -> 0.2 | Z48: ='前提'!$C$57 -> 0.2 | AA48: ='前提'!$C$57 -> 0.2 | ... AK48: ='前提'!$C$57 -> 0.2 | AL48: ='前提'!$D$57 -> 0.4 | AM48: ='前提'!$D$57 -> 0.4 | AN48: ='前提'!$D$57 -> 0.4 | AO48: ='前提'!$D$57 -> 0.4 | AP48: ='前提'!$D$57 -> 0.4 | AQ48: ='前提'!$D$57 -> 0.4 | AR48: ='前提'!$D$57 -> 0.4 | AS48: ='前提'!$D$57 -> 0.4 | ... BI48: ='前提'!$D$57 -> 0.4
A49: 自動化後工数 | B49: =B47*(1-B48) -> 69 | C49: =C47*(1-C48) -> 75 | D49: =D47*(1-D48) -> 81 | E49: =E47*(1-E48) -> 87 | F49: =F47*(1-F48) -> 93 | G49: =G47*(1-G48) -> 99 | H49: =H47*(1-H48) -> 138 | I49: =I47*(1-I48) -> 147 | ... BI49: =BI47*(1-BI48) -> 1470.6
A50: 必要CS人数（理論値） | B50: =ROUNDUP(B49/'前提'!$B$54,1) -> 0.5 | C50: =ROUNDUP(C49/'前提'!$B$54,1) -> 0.5 | D50: =ROUNDUP(D49/'前提'!$B$54,1) -> 0.6 | E50: =ROUNDUP(E49/'前提'!$B$54,1) -> 0.6 | F50: =ROUNDUP(F49/'前提'!$B$54,1) -> 0.6 | G50: =ROUNDUP(G49/'前提'!$B$54,1) -> 0.7 | H50: =ROUNDUP(H49/'前提'!$B$54,1) -> 0.9 | I50: =ROUNDUP(I49/'前提'!$B$54,1) -> 1 | ... BI50: =ROUNDUP(BI49/'前提'!$B$54,1) -> 9.2
A52: 【損益】
A53: 売上合計(再掲) | B53: =B26 -> 875000 | C53: =C26 -> 925000 | D53: =D26 -> 975000 | E53: =E26 -> 1075000 | F53: =F26 -> 1175000 | G53: =G26 -> 1275000 | H53: =H26 -> 1800000 | I53: =I26 -> 1925000 | ... BI53: =BI26 -> 81875000
A54: コスト合計(再掲) | B54: =B42 -> 1256000 | C54: =C42 -> 1260000 | D54: =D42 -> 1264000 | E54: =E42 -> 1268000 | F54: =F42 -> 1272000 | G54: =G42 -> 1276000 | H54: =H42 -> 2232000 | I54: =I42 -> 2238000 | ... BI54: =BI42 -> 17784000
A55: 営業利益 | B55: =B53-B54 -> -381000 | C55: =C53-C54 -> -335000 | D55: =D53-D54 -> -289000 | E55: =E53-E54 -> -193000 | F55: =F53-F54 -> -97000 | G55: =G53-G54 -> -1000 | H55: =H53-H54 -> -432000 | I55: =I53-I54 -> -313000 | ... BI55: =BI53-BI54 -> 64091000
A56: 営業利益率 | B56: =IF(B53<>0,B55/B53,0) -> -0.43542857 | C56: =IF(C53<>0,C55/C53,0) -> -0.36216216 | D56: =IF(D53<>0,D55/D53,0) -> -0.29641026 | E56: =IF(E53<>0,E55/E53,0) -> -0.17953488 | F56: =IF(F53<>0,F55/F53,0) -> -0.082553191 | G56: =IF(G53<>0,G55/G53,0) -> -0.00078431373 | H56: =IF(H53<>0,H55/H53,0) -> -0.24 | I56: =IF(I53<>0,I55/I53,0) -> -0.1625974 | ... BI56: =IF(BI53<>0,BI55/BI53,0) -> 0.78279084
A57: MRRベース利益 | B57: =B27-B42 -> -1181000 | C57: =C27-C42 -> -1135000 | D57: =D27-D42 -> -1089000 | E57: =E27-E42 -> -993000 | F57: =F27-F42 -> -897000 | G57: =G27-G42 -> -801000 | H57: =H27-H42 -> -1632000 | I57: =I27-I42 -> -1513000 | ... BI57: =BI27-BI42 -> 54091000
A58: 累積損益 | B58: =B55 -> -381000 | C58: =B58+C55 -> -716000 | D58: =C58+D55 -> -1005000 | E58: =D58+E55 -> -1198000 | F58: =E58+F55 -> -1295000 | G58: =F58+G55 -> -1296000 | H58: =G58+H55 -> -1728000 | I58: =H58+I55 -> -2041000 | J58: =I58+J55 -> -2185000 | ... BI58: =BH58+BI55 -> 1276968000
A60: 【バーンレート・キャッシュ】
A61: 月間ネットバーン | B61: =B42-B26 -> 381000 | C61: =C42-C26 -> 335000 | D61: =D42-D26 -> 289000 | E61: =E42-E26 -> 193000 | F61: =F42-F26 -> 97000 | G61: =G42-G26 -> 1000 | H61: =H42-H26 -> 432000 | I61: =I42-I26 -> 313000 | ... BI61: =BI42-BI26 -> -64091000
A62: 月間売上 | B62: =B26 -> 875000 | C62: =C26 -> 925000 | D62: =D26 -> 975000 | E62: =E26 -> 1075000 | F62: =F26 -> 1175000 | G62: =G26 -> 1275000 | H62: =H26 -> 1800000 | I62: =I26 -> 1925000 | ... BI62: =BI26 -> 81875000
A63: 月間コスト | B63: =B42 -> 1256000 | C63: =C42 -> 1260000 | D63: =D42 -> 1264000 | E63: =E42 -> 1268000 | F63: =F42 -> 1272000 | G63: =G42 -> 1276000 | H63: =H42 -> 2232000 | I63: =I42 -> 2238000 | ... BI63: =BI42 -> 17784000
A64: 調達資金（初期） | B64: ='前提'!$B$63+'前提'!$B$64+#REF!+'前提'!$B$66+'前提'!$B$68 -> #REF! | C64: 0 | D64: 0 | E64: 0 | F64: 0 | G64: 0 | H64: 0 | I64: 0 | J64: 0 | K64: 0 | L64: 0 | M64: 0 | N64: 0 | O64: 0 | P64: 0 | Q64: 0 | R64: 0 | S64: 0 | T64: 0 | U64: 0 | V64: 0 | W64: 0 | X64: 0 | Y64: 0 | Z64: 0 | AA64: 0 | AB64: 0 | AC64: 0 | AD64: 0 | AE64: 0 | AF64: 0 | AG64: 0 | AH64: 0 | AI64: 0 | AJ64: 0 | AK64: 0 | AL64: 0 | AM64: 0 | AN64: 0 | AO64: 0 | AP64: 0 | AQ64: 0 | AR64: 0 | AS64: 0 | AT64: 0 | AU64: 0 | AV64: 0 | AW64: 0 | AX64: 0 | AY64: 0 | AZ64: 0 | BA64: 0 | BB64: 0 | BC64: 0 | BD64: 0 | BE64: 0 | BF64: 0 | BG64: 0 | BH64: 0 | BI64: 0
A65: シリーズA入金 | B65: =IF(COLUMN()-1='前提'!$B$72,'前提'!$B$70,0) -> 0 | C65: =IF(COLUMN()-1='前提'!$B$72,'前提'!$B$70,0) -> 0 | D65: =IF(COLUMN()-1='前提'!$B$72,'前提'!$B$70,0) -> 0 | E65: =IF(COLUMN()-1='前提'!$B$72,'前提'!$B$70,0) -> 0 | F65: =IF(COLUMN()-1='前提'!$B$72,'前提'!$B$70,0) -> 0 | G65: =IF(COLUMN()-1='前提'!$B$72,'前提'!$B$70,0) -> 0 | H65: =IF(COLUMN()-1='前提'!$B$72,'前提'!$B$70,0) -> 0 | I65: =IF(COLUMN()-1='前提'!$B$72,'前提'!$B$70,0) -> 0 | ... BI65: =IF(COLUMN()-1='前提'!$B$72,'前提'!$B$70,0) -> 0
A66: 公庫返済 | B66: =IF(COLUMN()-1<='前提'!$B$75,'前提'!$B$68*'前提'!$B$77/12,IF(COLUMN()-1<='前提'!$B$75+'前提'!$B$76,PMT('前提'!$B$77/12,'前提'!$B$76,-'前提'!$B$68),0)) -> 0 | C66: =IF(COLUMN()-1<='前提'!$B$75,'前提'!$B$68*'前提'!$B$77/12,IF(COLUMN()-1<='前提'!$B$75+'前提'!$B$76,PMT('前提'!$B$77/12,'前提'!$B$76,-'前提'!$B$68),0)) -> 0 | D66: =IF(COLUMN()-1<='前提'!$B$75,'前提'!$B$68*'前提'!$B$77/12,IF(COLUMN()-1<='前提'!$B$75+'前提'!$B$76,PMT('前提'!$B$77/12,'前提'!$B$76,-'前提'!$B$68),0)) -> 0 | E66: =IF(COLUMN()-1<='前提'!$B$75,'前提'!$B$68*'前提'!$B$77/12,IF(COLUMN()-1<='前提'!$B$75+'前提'!$B$76,PMT('前提'!$B$77/12,'前提'!$B$76,-'前提'!$B$68),0)) -> 0 | F66: =IF(COLUMN()-1<='前提'!$B$75,'前提'!$B$68*'前提'!$B$77/12,IF(COLUMN()-1<='前提'!$B$75+'前提'!$B$76,PMT('前提'!$B$77/12,'前提'!$B$76,-'前提'!$B$68),0)) -> 0 | G66: =IF(COLUMN()-1<='前提'!$B$75,'前提'!$B$68*'前提'!$B$77/12,IF(COLUMN()-1<='前提'!$B$75+'前提'!$B$76,PMT('前提'!$B$77/12,'前提'!$B$76,-'前提'!$B$68),0)) -> 0 | H66: =IF(COLUMN()-1<='前提'!$B$75,'前提'!$B$68*'前提'!$B$77/12,IF(COLUMN()-1<='前提'!$B$75+'前提'!$B$76,PMT('前提'!$B$77/12,'前提'!$B$76,-'前提'!$B$68),0)) -> 0 | I66: =IF(COLUMN()-1<='前提'!$B$75,'前提'!$B$68*'前提'!$B$77/12,IF(COLUMN()-1<='前提'!$B$75+'前提'!$B$76,PMT('前提'!$B$77/12,'前提'!$B$76,-'前提'!$B$68),0)) -> 0 | ... BI66: =IF(COLUMN()-1<='前提'!$B$75,'前提'!$B$68*'前提'!$B$77/12,IF(COLUMN()-1<='前提'!$B$75+'前提'!$B$76,PMT('前提'!$B$77/12,'前提'!$B$76,-'前提'!$B$68),0)) -> 0
A67: キャッシュ残高 | B67: =B64+B65-B61-B66 -> #REF! | C67: =B67+C64+C65-C61-C66 -> #REF! | D67: =C67+D64+D65-D61-D66 -> #REF! | E67: =D67+E64+E65-E61-E66 -> #REF! | F67: =E67+F64+F65-F61-F66 -> #REF! | G67: =F67+G64+G65-G61-G66 -> #REF! | H67: =G67+H64+H65-H61-H66 -> #REF! | I67: =H67+I64+I65-I61-I66 -> #REF! | J67: =I67+J64+J65-J61-J66 -> #REF! | ... BI67: =BH67+BI64+BI65-BI61-BI66 -> #REF!
A68: ランウェイ（月） | B68: =IF(B67<=0,0,IF(B63>0,B67/B63,"")) -> #REF! | C68: =IF(C67<=0,0,IF(C63>0,C67/C63,"")) -> #REF! | D68: =IF(D67<=0,0,IF(D63>0,D67/D63,"")) -> #REF! | E68: =IF(E67<=0,0,IF(E63>0,E67/E63,"")) -> #REF! | F68: =IF(F67<=0,0,IF(F63>0,F67/F63,"")) -> #REF! | G68: =IF(G67<=0,0,IF(G63>0,G67/G63,"")) -> #REF! | H68: =IF(H67<=0,0,IF(H63>0,H67/H63,"")) -> #REF! | I68: =IF(I67<=0,0,IF(I63>0,I67/I63,"")) -> #REF! | ... BI68: =IF(BI67<=0,0,IF(BI63>0,BI67/BI63,"")) -> #REF!
A70: 【人員数】
A71: 代表 | B71: 1 | C71: 1 | D71: 1 | E71: 1 | F71: 1 | G71: 1 | H71: 1 | I71: 1 | J71: 1 | K71: 1 | L71: 1 | M71: 1 | N71: 1 | O71: 1 | P71: 1 | Q71: 1 | R71: 1 | S71: 1 | T71: 1 | U71: 1 | V71: 1 | W71: 1 | X71: 1 | Y71: 1 | Z71: 1 | AA71: 1 | AB71: 1 | AC71: 1 | AD71: 1 | AE71: 1 | AF71: 1 | AG71: 1 | AH71: 1 | AI71: 1 | AJ71: 1 | AK71: 1 | AL71: 1 | AM71: 1 | AN71: 1 | AO71: 1 | AP71: 1 | AQ71: 1 | AR71: 1 | AS71: 1 | AT71: 1 | AU71: 1 | AV71: 1 | AW71: 1 | AX71: 1 | AY71: 1 | AZ71: 1 | BA71: 1 | BB71: 1 | BC71: 1 | BD71: 1 | BE71: 1 | BF71: 1 | BG71: 1 | BH71: 1 | BI71: 1
A72: エンジニア正社員 | B72: ='前提'!$B$31 -> 0.5 | C72: ='前提'!$B$31 -> 0.5 | D72: ='前提'!$B$31 -> 0.5 | E72: ='前提'!$B$31 -> 0.5 | F72: ='前提'!$B$31 -> 0.5 | G72: ='前提'!$B$31 -> 0.5 | H72: ='前提'!$B$32 -> 1 | I72: ='前提'!$B$32 -> 1 | J72: ='前提'!$B$32 -> 1 | K72: ='前提'!$B$32 -> 1 | L72: ='前提'!$B$32 -> 1 | M72: ='前提'!$B$32 -> 1 | N72: ='前提'!$B$33 -> 1 | O72: ='前提'!$B$33 -> 1 | P72: ='前提'!$B$33 -> 1 | Q72: ='前提'!$B$33 -> 1 | R72: ='前提'!$B$33 -> 1 | S72: ='前提'!$B$33 -> 1 | T72: ='前提'!$B$34 -> 1 | U72: ='前提'!$B$34 -> 1 | V72: ='前提'!$B$34 -> 1 | W72: ='前提'!$B$34 -> 1 | X72: ='前提'!$B$34 -> 1 | Y72: ='前提'!$B$34 -> 1 | Z72: ='前提'!$B$34 -> 1 | AA72: ='前提'!$B$34 -> 1 | ... AK72: ='前提'!$B$34 -> 1 | AL72: ='前提'!$B$35 -> 1 | AM72: ='前提'!$B$35 -> 1 | AN72: ='前提'!$B$35 -> 1 | AO72: ='前提'!$B$35 -> 1 | AP72: ='前提'!$B$35 -> 1 | AQ72: ='前提'!$B$35 -> 1 | AR72: ='前提'!$B$35 -> 1 | AS72: ='前提'!$B$35 -> 1 | ... BI72: ='前提'!$B$35 -> 1
A73: 開発外注（人月換算） | B73: 0 | C73: 0 | D73: 0 | E73: 0 | F73: 0 | G73: 0 | H73: 0 | I73: 0 | J73: 0 | K73: 0 | L73: 0 | M73: 0 | N73: 0 | O73: 0 | P73: 0 | Q73: 0 | R73: 0 | S73: 0 | T73: =T32/'前提'!$B$21 -> 0.42857143 | U73: =U32/'前提'!$B$21 -> 0.42857143 | V73: =V32/'前提'!$B$21 -> 0.42857143 | W73: =W32/'前提'!$B$21 -> 0.42857143 | X73: =X32/'前提'!$B$21 -> 0.42857143 | Y73: =Y32/'前提'!$B$21 -> 0.42857143 | Z73: =Z32/'前提'!$B$21 -> 0.42857143 | AA73: =AA32/'前提'!$B$21 -> 0.42857143 | ... BI73: =BI32/'前提'!$B$21 -> 0.71428571
A74: CS | B74: ='前提'!$C$31 -> 0 | C74: ='前提'!$C$31 -> 0 | D74: ='前提'!$C$31 -> 0 | E74: ='前提'!$C$31 -> 0 | F74: ='前提'!$C$31 -> 0 | G74: ='前提'!$C$31 -> 0 | H74: ='前提'!$C$32 -> 1 | I74: ='前提'!$C$32 -> 1 | J74: ='前提'!$C$32 -> 1 | K74: ='前提'!$C$32 -> 1 | L74: ='前提'!$C$32 -> 1 | M74: ='前提'!$C$32 -> 1 | N74: ='前提'!$C$33 -> 1 | O74: ='前提'!$C$33 -> 1 | P74: ='前提'!$C$33 -> 1 | Q74: ='前提'!$C$33 -> 1 | R74: ='前提'!$C$33 -> 1 | S74: ='前提'!$C$33 -> 1 | T74: ='前提'!$C$34 -> 2 | U74: ='前提'!$C$34 -> 2 | V74: ='前提'!$C$34 -> 2 | W74: ='前提'!$C$34 -> 2 | X74: ='前提'!$C$34 -> 2 | Y74: ='前提'!$C$34 -> 2 | Z74: ='前提'!$C$34 -> 2 | AA74: ='前提'!$C$34 -> 2 | ... AK74: ='前提'!$C$34 -> 2 | AL74: ='前提'!$C$35 -> 4 | AM74: ='前提'!$C$35 -> 4 | AN74: ='前提'!$C$35 -> 4 | AO74: ='前提'!$C$35 -> 4 | AP74: ='前提'!$C$35 -> 4 | AQ74: ='前提'!$C$35 -> 4 | AR74: ='前提'!$C$35 -> 4 | AS74: ='前提'!$C$35 -> 4 | ... BI74: ='前提'!$C$35 -> 4
A75: 営業（社員） | B75: ='前提'!$D$31 -> 0 | C75: ='前提'!$D$31 -> 0 | D75: ='前提'!$D$31 -> 0 | E75: ='前提'!$D$31 -> 0 | F75: ='前提'!$D$31 -> 0 | G75: ='前提'!$D$31 -> 0 | H75: ='前提'!$D$32 -> 1 | I75: ='前提'!$D$32 -> 1 | J75: ='前提'!$D$32 -> 1 | K75: ='前提'!$D$32 -> 1 | L75: ='前提'!$D$32 -> 1 | M75: ='前提'!$D$32 -> 1 | N75: ='前提'!$D$33 -> 1 | O75: ='前提'!$D$33 -> 1 | P75: ='前提'!$D$33 -> 1 | Q75: ='前提'!$D$33 -> 1 | R75: ='前提'!$D$33 -> 1 | S75: ='前提'!$D$33 -> 1 | T75: ='前提'!$D$34 -> 2 | U75: ='前提'!$D$34 -> 2 | V75: ='前提'!$D$34 -> 2 | W75: ='前提'!$D$34 -> 2 | X75: ='前提'!$D$34 -> 2 | Y75: ='前提'!$D$34 -> 2 | Z75: ='前提'!$D$34 -> 2 | AA75: ='前提'!$D$34 -> 2 | ... AK75: ='前提'!$D$34 -> 2 | AL75: ='前提'!$D$35 -> 4 | AM75: ='前提'!$D$35 -> 4 | AN75: ='前提'!$D$35 -> 4 | AO75: ='前提'!$D$35 -> 4 | AP75: ='前提'!$D$35 -> 4 | AQ75: ='前提'!$D$35 -> 4 | AR75: ='前提'!$D$35 -> 4 | AS75: ='前提'!$D$35 -> 4 | ... BI75: ='前提'!$D$35 -> 4
A76: 営業（外注換算） | B76: =IF(B35>0,B35/'前提'!$B$23,0) -> 1 | C76: =IF(C35>0,C35/'前提'!$B$23,0) -> 1 | D76: =IF(D35>0,D35/'前提'!$B$23,0) -> 1 | E76: =IF(E35>0,E35/'前提'!$B$23,0) -> 1 | F76: =IF(F35>0,F35/'前提'!$B$23,0) -> 1 | G76: =IF(G35>0,G35/'前提'!$B$23,0) -> 1 | H76: =IF(H35>0,H35/'前提'!$B$23,0) -> 1 | I76: =IF(I35>0,I35/'前提'!$B$23,0) -> 1 | ... BI76: =IF(BI35>0,BI35/'前提'!$B$23,0) -> 13
A77: 事務長/兼務 | B77: 0 | C77: 0 | D77: 0 | E77: 0 | F77: 0 | G77: 0 | H77: 0 | I77: 0 | J77: 0 | K77: 0 | L77: 0 | M77: 0 | N77: 2 | O77: 2 | P77: 2 | Q77: 3 | R77: 3 | S77: 3 | T77: 4 | U77: 4 | V77: 4 | W77: 5 | X77: 5 | Y77: 5 | Z77: 6 | AA77: 7 | AB77: 8 | AC77: 9 | AD77: 10 | AE77: 11 | AF77: 12 | AG77: 13 | AH77: 14 | AI77: 15 | AJ77: 16 | AK77: 17 | AL77: =AL37/'前提'!$B$27 -> 11 | AM77: =AM37/'前提'!$B$27 -> 11 | AN77: =AN37/'前提'!$B$27 -> 12 | AO77: =AO37/'前提'!$B$27 -> 13 | AP77: =AP37/'前提'!$B$27 -> 13 | AQ77: =AQ37/'前提'!$B$27 -> 14 | AR77: =AR37/'前提'!$B$27 -> 15 | AS77: =AS37/'前提'!$B$27 -> 15 | ... BI77: =BI37/'前提'!$B$27 -> 15
A78: BPOオペレーター（人数） | B78: 0 | C78: 0 | D78: 0 | E78: 0 | F78: 0 | G78: 0 | H78: 0 | I78: 0 | J78: 0 | K78: 0 | L78: 0 | M78: 0 | N78: 0 | O78: 0 | P78: 0 | Q78: 0 | R78: 0 | S78: 0 | T78: 0 | U78: 0 | V78: 0 | W78: 0 | X78: 0 | Y78: 0 | Z78: 3 | AA78: 4 | AB78: 5 | AC78: 6 | AD78: 7 | AE78: 8 | AF78: 9 | AG78: 10 | AH78: 11 | AI78: 12 | AJ78: 13 | AK78: 14 | AL78: =IF(AL38>0,AL38/'前提'!$B$28,0) -> 14 | AM78: =IF(AM38>0,AM38/'前提'!$B$28,0) -> 14 | AN78: =IF(AN38>0,AN38/'前提'!$B$28,0) -> 15 | AO78: =IF(AO38>0,AO38/'前提'!$B$28,0) -> 16 | AP78: =IF(AP38>0,AP38/'前提'!$B$28,0) -> 16 | AQ78: =IF(AQ38>0,AQ38/'前提'!$B$28,0) -> 17 | AR78: =IF(AR38>0,AR38/'前提'!$B$28,0) -> 18 | AS78: =IF(AS38>0,AS38/'前提'!$B$28,0) -> 19 | ... BI78: =IF(BI38>0,BI38/'前提'!$B$28,0) -> 19
A80: 合計人数 | B80: =B71+B72+B73+B74+B75+B76+B77+B78 -> 2.5 | C80: =C71+C72+C73+C74+C75+C76+C77+C78 -> 2.5 | D80: =D71+D72+D73+D74+D75+D76+D77+D78 -> 2.5 | E80: =E71+E72+E73+E74+E75+E76+E77+E78 -> 2.5 | F80: =F71+F72+F73+F74+F75+F76+F77+F78 -> 2.5 | G80: =G71+G72+G73+G74+G75+G76+G77+G78 -> 2.5 | H80: =H71+H72+H73+H74+H75+H76+H77+H78 -> 5 | I80: =I71+I72+I73+I74+I75+I76+I77+I78 -> 5 | ... BI80: =BI71+BI72+BI73+BI74+BI75+BI76+BI77+BI78 -> 57.714286

Sheet 年次事業計画
A1: SuguDesk 年次事業計画
B3: 1年目 | C3: 2年目 | D3: 3年目 | E3: 4年目 | F3: 5年目
A4: 【顧客数】
A5: 期末顧客数 | B5: ='月次事業計画'!M15 -> 31 | C5: ='月次事業計画'!Y15 -> 147 | D5: ='月次事業計画'!AK15 -> 260 | E5: ='月次事業計画'!AW15 -> 441 | F5: ='月次事業計画'!BI15 -> 567
A6: ENTRY | B6: ='月次事業計画'!M16 -> 18 | C6: ='月次事業計画'!Y16 -> 73 | D6: ='月次事業計画'!AK16 -> 87 | E6: ='月次事業計画'!AW16 -> 138 | F6: ='月次事業計画'!BI16 -> 140
A7: EXPAND | B7: ='月次事業計画'!M17 -> 13 | C7: ='月次事業計画'!Y17 -> 67 | D7: ='月次事業計画'!AK17 -> 127 | E7: ='月次事業計画'!AW17 -> 198 | F7: ='月次事業計画'!BI17 -> 245
A8: DEEPEN | B8: ='月次事業計画'!M18 -> 0 | C8: ='月次事業計画'!Y18 -> 14 | D8: ='月次事業計画'!AK18 -> 60 | E8: ='月次事業計画'!AW18 -> 123 | F8: ='月次事業計画'!BI18 -> 200
A10: 【売上】
A11: MRR（期末） | B11: ='月次事業計画'!M27 -> 1425000 | C11: ='月次事業計画'!Y27 -> 10350000 | D11: ='月次事業計画'!AK27 -> 26700000 | E11: ='月次事業計画'!AW27 -> 49050000 | F11: ='月次事業計画'!BI27 -> 71875000
A12: ARR（期末） | B12: ='月次事業計画'!M27*12 -> 17100000 | C12: ='月次事業計画'!Y27*12 -> 124200000 | D12: ='月次事業計画'!AK27*12 -> 320400000 | E12: ='月次事業計画'!AW27*12 -> 588600000 | F12: ='月次事業計画'!BI27*12 -> 862500000
A13: 年間売上合計 | B13: =SUM('月次事業計画'!B26:M26) -> 19475000 | C13: =SUM('月次事業計画'!N26:Y26) -> 117675000 | D13: =SUM('月次事業計画'!Z26:AK26) -> 300400000 | E13: =SUM('月次事業計画'!AL26:AW26) -> 582275000 | F13: =SUM('月次事業計画'!AX26:BI26) -> 859175000
A14: 月額売上 | B14: =SUM('月次事業計画'!B24:M24) -> 7475000 | C14: =SUM('月次事業計画'!N24:Y24) -> 62475000 | D14: =SUM('月次事業計画'!Z24:AK24) -> 228400000 | E14: =SUM('月次事業計画'!AL24:AW24) -> 462275000 | F14: =SUM('月次事業計画'!AX24:BI24) -> 739175000
A15: 導入費用 | B15: =SUM('月次事業計画'!B25:M25) -> 12000000 | C15: =SUM('月次事業計画'!N25:Y25) -> 55200000 | D15: =SUM('月次事業計画'!Z25:AK25) -> 72000000 | E15: =SUM('月次事業計画'!AL25:AW25) -> 120000000 | F15: =SUM('月次事業計画'!AX25:BI25) -> 120000000
A17: 【コスト】
A18: 年間コスト合計 | B18: =SUM('月次事業計画'!B42:M42) -> 21078000 | C18: =SUM('月次事業計画'!N42:Y42) -> 54584000 | D18: =SUM('月次事業計画'!Z42:AK42) -> 122980000 | E18: =SUM('月次事業計画'!AL42:AW42) -> 203878000 | F18: =SUM('月次事業計画'!AX42:BI42) -> 199512000
A19: 代表報酬 | B19: =SUM('月次事業計画'!B30:M30) -> 4200000 | C19: =SUM('月次事業計画'!N30:Y30) -> 4200000 | D19: =SUM('月次事業計画'!Z30:AK30) -> 4200000 | E19: =SUM('月次事業計画'!AL30:AW30) -> 4200000 | F19: =SUM('月次事業計画'!AX30:BI30) -> 4200000
A20: エンジニア（正社員） | B20: =SUM('月次事業計画'!B31:M31) -> 6300000 | C20: =SUM('月次事業計画'!N31:Y31) -> 8400000 | D20: =SUM('月次事業計画'!Z31:AK31) -> 8400000 | E20: =SUM('月次事業計画'!AL31:AW31) -> 8400000 | F20: =SUM('月次事業計画'!AX31:BI31) -> 8400000
A21: 開発外注 | B21: =SUM('月次事業計画'!B32:M32) -> 0 | C21: =SUM('月次事業計画'!N32:Y32) -> 1800000 | D21: =SUM('月次事業計画'!Z32:AK32) -> 3600000 | E21: =SUM('月次事業計画'!AL32:AW32) -> 6000000 | F21: =SUM('月次事業計画'!AX32:BI32) -> 6000000
A22: CS人件費 | B22: =SUM('月次事業計画'!B33:M33) -> 1200000 | C22: =SUM('月次事業計画'!N33:Y33) -> 3600000 | D22: =SUM('月次事業計画'!Z33:AK33) -> 4800000 | E22: =SUM('月次事業計画'!AL33:AW33) -> 9600000 | F22: =SUM('月次事業計画'!AX33:BI33) -> 9600000
A23: 営業人件費（社員） | B23: =SUM('月次事業計画'!B34:M34) -> 2400000 | C23: =SUM('月次事業計画'!N34:Y34) -> 7200000 | D23: =SUM('月次事業計画'!Z34:AK34) -> 9600000 | E23: =SUM('月次事業計画'!AL34:AW34) -> 19200000 | F23: =SUM('月次事業計画'!AX34:BI34) -> 19200000
A24: 営業外注費 | B24: =SUM('月次事業計画'!B35:M35) -> 4800000 | C24: =SUM('月次事業計画'!N35:Y35) -> 19200000 | D24: =SUM('月次事業計画'!Z35:AK35) -> 28800000 | E24: =SUM('月次事業計画'!AL35:AW35) -> 62400000 | F24: =SUM('月次事業計画'!AX35:BI35) -> 62400000
A25: LLM API変動費 | B25: =SUM('月次事業計画'!B36:M36) -> 378000 | C25: =SUM('月次事業計画'!N36:Y36) -> 2084000 | D25: =SUM('月次事業計画'!Z36:AK36) -> 5080000 | E25: =SUM('月次事業計画'!AL36:AW36) -> 8728000 | F25: =SUM('月次事業計画'!AX36:BI36) -> 12312000
A26: 事務長（提案・設計） | B26: =SUM('月次事業計画'!B37:M37) -> 0 | C26: =SUM('月次事業計画'!N37:Y37) -> 6300000 | D26: =SUM('月次事業計画'!Z37:AK37) -> 41400000 | E26: =SUM('月次事業計画'!AL37:AW37) -> 51300000 | F26: =SUM('月次事業計画'!AX37:BI37) -> 46800000
A27: BPOオペレーター | B27: =SUM('月次事業計画'!B38:M38) -> 0 | C27: =SUM('月次事業計画'!N38:Y38) -> 0 | D27: =SUM('月次事業計画'!Z38:AK38) -> 15300000 | E27: =SUM('月次事業計画'!AL38:AW38) -> 32250000 | F27: =SUM('月次事業計画'!AX38:BI38) -> 28800000
A28: インフラ・ツール | B28: =SUM('月次事業計画'!B39:M39) -> 1200000 | C28: =SUM('月次事業計画'!N39:Y39) -> 1200000 | D28: =SUM('月次事業計画'!Z39:AK39) -> 1200000 | E28: =SUM('月次事業計画'!AL39:AW39) -> 1200000 | F28: =SUM('月次事業計画'!AX39:BI39) -> 1200000
A29: その他固定費 | B29: =SUM('月次事業計画'!B40:M40) -> 600000 | C29: =SUM('月次事業計画'!N40:Y40) -> 600000 | D29: =SUM('月次事業計画'!Z40:AK40) -> 600000 | E29: =SUM('月次事業計画'!AL40:AW40) -> 600000 | F29: =SUM('月次事業計画'!AX40:BI40) -> 600000
A31: 【損益】
A32: 年間営業利益 | B32: =SUM('月次事業計画'!B55:M55) -> -1603000 | C32: =SUM('月次事業計画'!N55:Y55) -> 63091000 | D32: =SUM('月次事業計画'!Z55:AK55) -> 177420000 | E32: =SUM('月次事業計画'!AL55:AW55) -> 378397000 | F32: =SUM('月次事業計画'!AX55:BI55) -> 659663000
A33: 営業利益率 | B33: =IF(B13<>0,B32/B13,0) -> -0.082310655 | C33: =IF(C13<>0,C32/C13,0) -> 0.53614617 | D33: =IF(D13<>0,D32/D13,0) -> 0.59061252 | E33: =IF(E13<>0,E32/E13,0) -> 0.6498596 | F33: =IF(F13<>0,F32/F13,0) -> 0.76778654
A34: 累積損益 | B34: ='月次事業計画'!M58 -> -1603000 | C34: ='月次事業計画'!Y58 -> 61488000 | D34: ='月次事業計画'!AK58 -> 238908000 | E34: ='月次事業計画'!AW58 -> 617305000 | F34: ='月次事業計画'!BI58 -> 1276968000
A36: 【バーンレート】
A37: シリーズA入金 | B37: =SUM('月次事業計画'!B65:M65) -> 0 | C37: =SUM('月次事業計画'!N65:Y65) -> 50000000 | D37: =SUM('月次事業計画'!Z65:AK65) -> 0 | E37: =SUM('月次事業計画'!AL65:AW65) -> 0 | F37: =SUM('月次事業計画'!AX65:BI65) -> 0
A38: 公庫返済合計 | B38: =SUM('月次事業計画'!B66:M66) -> 0 | C38: =SUM('月次事業計画'!N66:Y66) -> 0 | D38: =SUM('月次事業計画'!Z66:AK66) -> 0 | E38: =SUM('月次事業計画'!AL66:AW66) -> 0 | F38: =SUM('月次事業計画'!AX66:BI66) -> 0
A39: 年間ネットバーン | B39: =SUM('月次事業計画'!B61:M61) -> 1603000 | C39: =SUM('月次事業計画'!N61:Y61) -> -63091000 | D39: =SUM('月次事業計画'!Z61:AK61) -> -177420000 | E39: =SUM('月次事業計画'!AL61:AW61) -> -378397000 | F39: =SUM('月次事業計画'!AX61:BI61) -> -659663000
A40: 月平均ネットバーン | B40: =AVERAGE('月次事業計画'!B61:M61) -> 133583.33 | C40: =AVERAGE('月次事業計画'!N61:Y61) -> -5257583.3 | D40: =AVERAGE('月次事業計画'!Z61:AK61) -> -14785000 | E40: =AVERAGE('月次事業計画'!AL61:AW61) -> -31533083 | F40: =AVERAGE('月次事業計画'!AX61:BI61) -> -54971917
A41: 期末キャッシュ残高 | B41: ='月次事業計画'!M67 -> #REF! | C41: ='月次事業計画'!Y67 -> #REF! | D41: ='月次事業計画'!AK67 -> #REF! | E41: ='月次事業計画'!AW67 -> #REF! | F41: ='月次事業計画'!BI67 -> #REF!
A42: 期末ランウェイ（月） | B42: ='月次事業計画'!M68 -> #REF! | C42: ='月次事業計画'!Y68 -> #REF! | D42: ='月次事業計画'!AK68 -> #REF! | E42: ='月次事業計画'!AW68 -> #REF! | F42: ='月次事業計画'!BI68 -> #REF!
A44: 【期末人員数】
A45: 期末合計人数 | B45: ='月次事業計画'!M80 -> 5 | C45: ='月次事業計画'!Y80 -> 17.428571 | D45: ='月次事業計画'!AK80 -> 43.428571 | E45: ='月次事業計画'!AW80 -> 64.714286 | F45: ='月次事業計画'!BI80 -> 57.714286
A46: 代表 | B46: ='月次事業計画'!M71 -> 1 | C46: ='月次事業計画'!Y71 -> 1 | D46: ='月次事業計画'!AK71 -> 1 | E46: ='月次事業計画'!AW71 -> 1 | F46: ='月次事業計画'!BI71 -> 1
A47: エンジニア正社員 | B47: ='月次事業計画'!M72 -> 1 | C47: ='月次事業計画'!Y72 -> 1 | D47: ='月次事業計画'!AK72 -> 1 | E47: ='月次事業計画'!AW72 -> 1 | F47: ='月次事業計画'!BI72 -> 1
A48: 開発外注（人月換算） | B48: ='月次事業計画'!M73 -> 0 | C48: ='月次事業計画'!Y73 -> 0.42857143 | D48: ='月次事業計画'!AK73 -> 0.42857143 | E48: ='月次事業計画'!AW73 -> 0.71428571 | F48: ='月次事業計画'!BI73 -> 0.71428571
A49: CS | B49: ='月次事業計画'!M74 -> 1 | C49: ='月次事業計画'!Y74 -> 2 | D49: ='月次事業計画'!AK74 -> 2 | E49: ='月次事業計画'!AW74 -> 4 | F49: ='月次事業計画'!BI74 -> 4
A50: 営業（社員） | B50: ='月次事業計画'!M75 -> 1 | C50: ='月次事業計画'!Y75 -> 2 | D50: ='月次事業計画'!AK75 -> 2 | E50: ='月次事業計画'!AW75 -> 4 | F50: ='月次事業計画'!BI75 -> 4
A51: 営業（外注換算） | B51: ='月次事業計画'!M76 -> 1 | C51: ='月次事業計画'!Y76 -> 6 | D51: ='月次事業計画'!AK76 -> 6 | E51: ='月次事業計画'!AW76 -> 13 | F51: ='月次事業計画'!BI76 -> 13
A52: 事務長/兼務 | B52: ='月次事業計画'!M77 -> 0 | C52: ='月次事業計画'!Y77 -> 5 | D52: ='月次事業計画'!AK77 -> 17 | E52: ='月次事業計画'!AW77 -> 18 | F52: ='月次事業計画'!BI77 -> 15
A53: BPOオペレーター（人数） | B53: ='月次事業計画'!M78 -> 0 | C53: ='月次事業計画'!Y78 -> 0 | D53: ='月次事業計画'!AK78 -> 14 | E53: ='月次事業計画'!AW78 -> 23 | F53: ='月次事業計画'!BI78 -> 19

Sheet 資本政策表
A1: SuguDesk 資本政策表
B3: 設立 | C3: J-KISS | D3: Seed（シード） | E3: Series A
A4: プレバリュー | B4: - | C4: - | D4: ='前提'!$B$65 -> 170000000 | E4: ='前提'!$B$69 -> 500000000
A5: 調達額 | B5: ='前提'!$B$61 -> 1000000 | C5: ='前提'!$B$63+'前提'!$B$64 -> 2500000 | D5: ='前提'!$B$66 -> 30000000 | E5: ='前提'!$B$70 -> 50000000
A6: ポストバリュー | B6: - | C6: - | D6: =D4+D5 -> 200000000 | E6: =E4+E5 -> 550000000
A7: 公庫借入（デット） | D7: ='前提'!$B$68
A9: 【株式数】
A10: J-KISS転換株価 | C10: ='前提'!$B$62/'前提'!$B$60 -> 100
A11: J-KISS転換株数 | C11: =ROUNDDOWN(C5/C10,0) -> 25000
A12: J-KISS転換後 発行済株数 | C12: ='前提'!$B$60+C11 -> 1025000
A13: Seed株価 | D13: =D4/C12 -> 165.85366
A14: Seed新規発行株数 | D14: =ROUNDDOWN(D5/D13,0) -> 180882
A15: Seed後 発行済株数 | D15: =C12+D14 -> 1205882
A16: Series A 株価 | E16: =E4/D15 -> 414.63427
A17: Series A 新規発行株数 | E17: =ROUNDDOWN(E5/E16,0) -> 120588
A18: SOPプール株数 | E18: =ROUNDDOWN((D15+E17)*'前提'!$B$71/(1-'前提'!$B$71),0) -> 95255
A19: Series A後 発行済株数 | E19: =D15+E17+E18 -> 1421725
A21: 【持分比率】
A22: Anna（代表） | B22: 100.0% | C22: ='前提'!$B$60/C12 -> 0.97560976 | D22: ='前提'!$B$60/D15 -> 0.82926854 | E22: ='前提'!$B$60/E19 -> 0.70337091
A23: J-KISS投資家 | B23: - | C23: =C11/C12 -> 0.024390244 | D23: =C11/D15 -> 0.020731713 | E23: =C11/E19 -> 0.017584273
A24: 佐藤さん | C24: =ROUNDDOWN('前提'!$B$63/C10,0)/C12 -> 0.019512195 | D24: =ROUNDDOWN('前提'!$B$63/C10,0)/D15 -> 0.016585371 | E24: =ROUNDDOWN('前提'!$B$63/C10,0)/E19 -> 0.014067418
A25: ようすけさん | C25: =ROUNDDOWN('前提'!$B$64/C10,0)/C12 -> 0.0048780488 | D25: =ROUNDDOWN('前提'!$B$64/C10,0)/D15 -> 0.0041463427 | E25: =ROUNDDOWN('前提'!$B$64/C10,0)/E19 -> 0.0035168545
A26: シード | B26: - | C26: - | D26: =D14/D15 -> 0.14999975 | E26: =D14/E19 -> 0.12722714
A27: SOPプール | B27: - | C27: - | D27: - | E27: =E18/E19 -> 0.066999596
A28: Series A 投資家 | B28: - | C28: - | D28: - | E28: =E17/E19 -> 0.084818091
A30: 合計チェック | E30: =E22+E23+E26+E27+E28 -> 1
A32: 【感度分析】Series Aプレバリュー別 Founder持分
B33: 保守的 ¥3億 | C33: 現実的 ¥5億 | D33: 中間 ¥7億 | E33: 現計画 ¥10億 | F33: 強気 ¥15億
A34: Series A プレバリュー | B34: 300000000 | C34: 500000000 | D34: 700000000 | E34: 1000000000 | F34: 1500000000
A35: 調達額（固定） | B35: ='前提'!$B$70 -> 50000000 | C35: ='前提'!$B$70 -> 50000000 | D35: ='前提'!$B$70 -> 50000000 | E35: ='前提'!$B$70 -> 50000000 | F35: ='前提'!$B$70 -> 50000000
A36: Series A 株価 | B36: =B34/$D$15 -> 248.78056 | C36: =C34/$D$15 -> 414.63427 | D36: =D34/$D$15 -> 580.48797 | E36: =E34/$D$15 -> 829.26854 | F36: =F34/$D$15 -> 1243.9028
A37: 新規発行株数 | B37: =ROUNDDOWN(B35/B36,0) -> 200980 | C37: =ROUNDDOWN(C35/C36,0) -> 120588 | D37: =ROUNDDOWN(D35/D36,0) -> 86134 | E37: =ROUNDDOWN(E35/E36,0) -> 60294 | F37: =ROUNDDOWN(F35/F36,0) -> 40196
A38: SOPプール株数 | B38: =ROUNDDOWN(($D$15+B37)*'前提'!$B$71/(1-'前提'!$B$71),0) -> 101028 | C38: =ROUNDDOWN(($D$15+C37)*'前提'!$B$71/(1-'前提'!$B$71),0) -> 95255 | D38: =ROUNDDOWN(($D$15+D37)*'前提'!$B$71/(1-'前提'!$B$71),0) -> 92781 | E38: =ROUNDDOWN(($D$15+E37)*'前提'!$B$71/(1-'前提'!$B$71),0) -> 90925 | F38: =ROUNDDOWN(($D$15+F37)*'前提'!$B$71/(1-'前提'!$B$71),0) -> 89482
A39: 発行済株数合計 | B39: =$D$15+B37+B38 -> 1507890 | C39: =$D$15+C37+C38 -> 1421725 | D39: =$D$15+D37+D38 -> 1384797 | E39: =$D$15+E37+E38 -> 1357101 | F39: =$D$15+F37+F38 -> 1335560
A41: Anna持分 | B41: ='前提'!$B$60/B39 -> 0.66317835 | C41: ='前提'!$B$60/C39 -> 0.70337091 | D41: ='前提'!$B$60/D39 -> 0.7221275 | E41: ='前提'!$B$60/E39 -> 0.73686483 | F41: ='前提'!$B$60/F39 -> 0.74874959
A42: J-KISS投資家 | B42: =$C$11/B39 -> 0.016579459 | C42: =$C$11/C39 -> 0.017584273 | D42: =$C$11/D39 -> 0.018053188 | E42: =$C$11/E39 -> 0.018421621 | F42: =$C$11/F39 -> 0.01871874
A43: シード | B43: =$D$14/B39 -> 0.11995703 | C43: =$D$14/C39 -> 0.12722714 | D43: =$D$14/D39 -> 0.13061987 | E43: =$D$14/E39 -> 0.13328558 | F43: =$D$14/F39 -> 0.13543532
A44: SOPプール | B44: =B38/B39 -> 0.066999582 | C44: =C38/C39 -> 0.066999596 | D44: =D38/D39 -> 0.066999712 | E44: =E38/E39 -> 0.066999435 | F44: =F38/F39 -> 0.066999611
A45: Series A 投資家 | B45: =B37/B39 -> 0.13328558 | C45: =C37/C39 -> 0.084818091 | D45: =D37/D39 -> 0.06219973 | E45: =E37/E39 -> 0.044428528 | F45: =F37/F39 -> 0.030096738
A47: Founder 50%超? | B47: =IF(B41>=0.5,"OK","NG") -> OK | C47: =IF(C41>=0.5,"OK","NG") -> OK | D47: =IF(D41>=0.5,"OK","NG") -> OK | E47: =IF(E41>=0.5,"OK","NG") -> OK | F47: =IF(F41>=0.5,"OK","NG") -> OK
A49: 【ARR逆算】プレバリューに必要なARR
B50: 10x | C50: 15x | D50: 20x | E50: 30x | F50: 40x
A51: ARRマルチプル | B51: 10 | C51: 15 | D51: 20 | E51: 30 | F51: 40
A52: プレ ¥3億 に必要なARR | B52: =300000000/B51 -> 30000000 | C52: =300000000/C51 -> 20000000 | D52: =300000000/D51 -> 15000000 | E52: =300000000/E51 -> 10000000 | F52: =300000000/F51 -> 7500000
A53: プレ ¥5億 に必要なARR | B53: =500000000/B51 -> 50000000 | C53: =500000000/C51 -> 33333333 | D53: =500000000/D51 -> 25000000 | E53: =500000000/E51 -> 16666667 | F53: =500000000/F51 -> 12500000
A54: プレ ¥7億 に必要なARR | B54: =700000000/B51 -> 70000000 | C54: =700000000/C51 -> 46666667 | D54: =700000000/D51 -> 35000000 | E54: =700000000/E51 -> 23333333 | F54: =700000000/F51 -> 17500000
A55: プレ ¥10億 に必要なARR | B55: =1000000000/B51 -> 100000000 | C55: =1000000000/C51 -> 66666667 | D55: =1000000000/D51 -> 50000000 | E55: =1000000000/E51 -> 33333333 | F55: =1000000000/F51 -> 25000000
A57: 【現計画のARR推移（参照）】
B58: 1年目 | C58: 2年目 | D58: 3年目 | E58: 4年目 | F58: 5年目
A59: 現計画 ARR | B59: ='月次事業計画'!M27*12 -> 17100000 | C59: ='月次事業計画'!Y27*12 -> 124200000 | D59: ='月次事業計画'!AK27*12 -> 320400000 | E59: ='月次事業計画'!AW27*12 -> 588600000 | F59: ='月次事業計画'!BI27*12 -> 862500000
A60: 現計画 MRR | B60: ='月次事業計画'!M27 -> 1425000 | C60: ='月次事業計画'!Y27 -> 10350000 | D60: ='月次事業計画'!AK27 -> 26700000 | E60: ='月次事業計画'!AW27 -> 49050000 | F60: ='月次事業計画'!BI27 -> 71875000
A61: プレ ¥3億 の場合の倍率 | B61: =IF(B59>0,300000000/B59,"-") -> 17.54386 | C61: =IF(C59>0,300000000/C59,"-") -> 2.4154589 | D61: =IF(D59>0,300000000/D59,"-") -> 0.93632959 | E61: =IF(E59>0,300000000/E59,"-") -> 0.509684 | F61: =IF(F59>0,300000000/F59,"-") -> 0.34782609
A62: プレ ¥5億 の場合の倍率 | B62: =IF(B59>0,500000000/B59,"-") -> 29.239766 | C62: =IF(C59>0,500000000/C59,"-") -> 4.0257649 | D62: =IF(D59>0,500000000/D59,"-") -> 1.5605493 | E62: =IF(E59>0,500000000/E59,"-") -> 0.84947333 | F62: =IF(F59>0,500000000/F59,"-") -> 0.57971014
A63: プレ ¥10億 の場合の倍率 | B63: =IF(B59>0,1000000000/B59,"-") -> 58.479532 | C63: =IF(C59>0,1000000000/C59,"-") -> 8.0515298 | D63: =IF(D59>0,1000000000/D59,"-") -> 3.1210986 | E63: =IF(E59>0,1000000000/E59,"-") -> 1.6989467 | F63: =IF(F59>0,1000000000/F59,"-") -> 1.1594203
A65: 読み方：
A66: 倍率が15x以下なら投資家に説明しやすい。
A67: ARRを上げるほど同じプレバリューを低い倍率で正当化できる。
A68: → Series A前にARRをどこまで積めるかが交渉力を決める。
A70: 【EXITシナリオ分析】投資家リターン × プレバリュー感度
A71: 現計画ベース（プレ=E4, 調達=E5）
B72: EXIT ¥10億 | C72: EXIT ¥15億 | D72: EXIT ¥20億 | E72: EXIT ¥30億 | F72: EXIT ¥50億
A73: EXIT時企業価値 | B73: 1000000000 | C73: 1500000000 | D73: 2000000000 | E73: 3000000000 | F73: 5000000000
A74: Anna リターン | B74: =B73*$E$22 -> 7.0337091e+08 | C74: =C73*$E$22 -> 1055056358 | D74: =D73*$E$22 -> 1406741810 | E74: =E73*$E$22 -> 2110112715 | F74: =F73*$E$22 -> 3516854525
A75: Series A 投資家リターン | B75: =B73*$E$28 -> 84818091 | C75: =C73*$E$28 -> 127227136 | D75: =D73*$E$28 -> 1.6963618e+08 | E75: =E73*$E$28 -> 2.5445427e+08 | F75: =F73*$E$28 -> 4.2409045e+08
A76: Series A 投資倍率 | B76: =IF($E$5>0,B75/$E$5,0) -> 1.6963618 | C76: =IF($E$5>0,C75/$E$5,0) -> 2.5445427 | D76: =IF($E$5>0,D75/$E$5,0) -> 3.3927236 | E76: =IF($E$5>0,E75/$E$5,0) -> 5.0890854 | F76: =IF($E$5>0,F75/$E$5,0) -> 8.4818091
A77: 1x LP（最低保証） | B77: =$E$5 -> 50000000 | C77: =$E$5 -> 50000000 | D77: =$E$5 -> 50000000 | E77: =$E$5 -> 50000000 | F77: =$E$5 -> 50000000
A78: SA実取り分（LP適用後） | B78: =MAX($E$5,B75) -> 84818091 | C78: =MAX($E$5,C75) -> 127227136 | D78: =MAX($E$5,D75) -> 1.6963618e+08 | E78: =MAX($E$5,E75) -> 2.5445427e+08 | F78: =MAX($E$5,F75) -> 4.2409045e+08
A79: Anna 実取り分（LP適用後） | B79: =B73-B78-B73*($E$23+$E$26+$E$27) -> 7.0337091e+08 | C79: =C73-C78-C73*($E$23+$E$26+$E$27) -> 1055056358 | D79: =D73-D78-D73*($E$23+$E$26+$E$27) -> 1406741810 | E79: =E73-E78-E73*($E$23+$E$26+$E$27) -> 2110112715 | F79: =F73-F78-F73*($E$23+$E$26+$E$27) -> 3516854525
A81: 【調達額の感度分析】プレ¥5億固定、調達額を変えた場合
B82: 調達 ¥3000万 | C82: 調達 ¥5000万 | D82: 調達 ¥8000万 | E82: 調達 ¥1億 | F82: 調達 ¥1.5億
A83: 調達額 | B83: 30000000 | C83: 50000000 | D83: 80000000 | E83: 100000000 | F83: 150000000
A84: プレバリュー（固定¥5億） | B84: 500000000 | C84: 500000000 | D84: 500000000 | E84: 500000000 | F84: 500000000
A85: Series A 株価 | B85: =B84/$D$15 -> 414.63427 | C85: =C84/$D$15 -> 414.63427 | D85: =D84/$D$15 -> 414.63427 | E85: =E84/$D$15 -> 414.63427 | F85: =F84/$D$15 -> 414.63427
A86: 新規発行株数 | B86: =ROUNDDOWN(B83/B85,0) -> 72352 | C86: =ROUNDDOWN(C83/C85,0) -> 120588 | D86: =ROUNDDOWN(D83/D85,0) -> 192941 | E86: =ROUNDDOWN(E83/E85,0) -> 241176 | F86: =ROUNDDOWN(F83/F85,0) -> 361764
A87: SOPプール株数 | B87: =ROUNDDOWN(($D$15+B86)*'前提'!$B$71/(1-'前提'!$B$71),0) -> 91791 | C87: =ROUNDDOWN(($D$15+C86)*'前提'!$B$71/(1-'前提'!$B$71),0) -> 95255 | D87: =ROUNDDOWN(($D$15+D86)*'前提'!$B$71/(1-'前提'!$B$71),0) -> 100451 | E87: =ROUNDDOWN(($D$15+E86)*'前提'!$B$71/(1-'前提'!$B$71),0) -> 103915 | F87: =ROUNDDOWN(($D$15+F86)*'前提'!$B$71/(1-'前提'!$B$71),0) -> 112574
A88: 発行済株数合計 | B88: =$D$15+B86+B87 -> 1370025 | C88: =$D$15+C86+C87 -> 1421725 | D88: =$D$15+D86+D87 -> 1499274 | E88: =$D$15+E86+E87 -> 1550973 | F88: =$D$15+F86+F87 -> 1680220
A90: Anna持分 | B90: ='前提'!$B$60/B88 -> 0.72991369 | C90: ='前提'!$B$60/C88 -> 0.70337091 | D90: ='前提'!$B$60/D88 -> 0.66698949 | E90: ='前提'!$B$60/E88 -> 0.64475655 | F90: ='前提'!$B$60/F88 -> 0.59516016
A91: Series A 投資家持分 | B91: =B86/B88 -> 0.052810715 | C91: =C86/C88 -> 0.084818091 | D91: =D86/D88 -> 0.12868962 | E91: =E86/E88 -> 0.15549981 | F91: =F86/F88 -> 0.21530752
A92: EXIT¥20億時 SA倍率 | B92: =IF(B83>0,2000000000*B91/B83,0) -> 3.5207143 | C92: =IF(C83>0,2000000000*C91/C83,0) -> 3.3927236 | D92: =IF(D83>0,2000000000*D91/D83,0) -> 3.2172405 | E92: =IF(E83>0,2000000000*E91/E83,0) -> 3.1099961 | F92: =IF(F83>0,2000000000*F91/F83,0) -> 2.8707669
A93: EXIT¥30億時 SA倍率 | B93: =IF(B83>0,3000000000*B91/B83,0) -> 5.2810715 | C93: =IF(C83>0,3000000000*C91/C83,0) -> 5.0890854 | D93: =IF(D83>0,3000000000*D91/D83,0) -> 4.8258607 | E93: =IF(E83>0,3000000000*E91/E83,0) -> 4.6649942 | F93: =IF(F83>0,3000000000*F91/F83,0) -> 4.3061504
A95: 読み方：
A96: 調達額を減らすほどAnna持分は守れるが、ランウェイが短くなる。
A97: SA投資家は¥5000万投資でEXIT¥20億なら十分なリターン（数十x）。
A98: → 調達額を絞ってもEXITさえ出れば投資家は満足する構造。

Sheet 資金使途
A1: シードラウンド 資金使途
A2: 調達額合計 | B2: ='前提'!B63+'前提'!B64+#REF!+'前提'!B66+'前提'!B68 -> #REF! | C2: （J-KISS+エクイティ+デット）
A4: 【やりたいこと → 資金使途】
A5: 項目 | B5: 月額 | C5: 年額（想定） | D5: 備考
A6: エンジニア正社員（AI駆動開発） | B6: ='前提'!B21 -> 700000 | C6: =B6*12 -> 8400000 | D6: Dify APIアップセル・基盤開発・BPO検証・チャットUI改善
A7: CS（業務委託） | B7: ='前提'!B22 -> 200000 | C7: =B7*12 -> 2400000 | D7: FAQ構築・クライアント対応
A8: Anna代表報酬 | B8: ='前提'!B20 -> 350000 | C8: =B8*12 -> 4200000 | D8: 営業・経営・資金調達に集中
A9: 営業（M7以降） | B9: ='前提'!B23 -> 400000 | C9: =B9*6 -> 2400000 | D9: M7から採用（年の半分）
A10: 営業外注費（平均） | B10: =AVERAGE('月次事業計画'!B9:'月次事業計画'!M9) -> 400000 | C10: =B10*12 -> 4800000 | D10: ファネル逆算に基づく外注費
A11: インフラ・ツール | B11: ='前提'!B25 -> 100000 | C11: =B11*12 -> 1200000 | D11: Dify API, AWS, Claude, SaaS等
A12: その他固定費 | B12: ='前提'!B26 -> 50000 | C12: =B12*12 -> 600000 | D12: 法務・会計・雑費
A13: デザイン（スポット） | B13: - | C13: 400000 | D13: チャットUI/UXデザイン改善
A14: 年間合計 | B14: =SUM(B6:B13) -> 2200000 | C14: =SUM(C6:C13) -> 24400000
A16: 【ランウェイ試算】
A17: Phase1 前半バーンレート（月） | B17: =AVERAGE('月次事業計画'!B42:'月次事業計画'!G42) -> 1266000 | C17: M1-M6平均コスト
A18: Phase1 後半バーンレート（月） | B18: =AVERAGE('月次事業計画'!H42:'月次事業計画'!M42) -> 2247000 | C18: M7-M12平均コスト
A19: Phase1 月間コスト平均 | B19: =AVERAGE('月次事業計画'!B63:'月次事業計画'!M63) -> 1756500 | C19: M1-M12平均コスト（売上無視）
A21: 初期キャッシュ | B21: ='前提'!$B$63+'前提'!$B$64+#REF!+'前提'!$B$66+'前提'!$B$68 -> #REF!
A22: ランウェイ（コスト基準） | B22: =IF(B19>0,B21/B19,"") -> #REF! | C22: 月（売上ゼロでも持つ期間）
A23: M12末キャッシュ残高 | B23: ='月次事業計画'!M67 -> #REF!
A24: M24末キャッシュ残高 | B24: ='月次事業計画'!Y67 -> #REF!
